Workbook

Sheet COMPARISON
B2: OASIS AT SAN MARCO
B3: CBRE UNDERWRITING AND HISTORICAL OVERVIEW - COMPARISON
D5: OCTOBER | G5: NOVEMBER | J5: VARIANCE
D6: Amount | E6: Per Unit | G6: Amount | H6: Per Unit | J6: Amount | K6: Per Unit | N6: Underwriting Notes
B7: Economic Occupancy (Vacancy Loss only) | D7: 0.94775996 | G7: =+PROFORMA!S7 -> 0.95 | J7: =+G7-D7 -> 0.0022400421
B8: Physical Occupancy | D8: 0.95275591 | G8: =+PROFORMA!S8 -> 0.96062992 | J8: =+G8-D8 -> 0.0078740157 | M8: Growth Factor
B10: REVENUE
A11: 1 | B11: Gross Potential Rent (net of LTL) | D11: 1666308 | E11: =+D11/$D$77 -> 13120.535 | G11: =+PROFORMA!S11 -> 1655436 | H11: =+G11/$D$77 -> 13034.929 | J11: =+G11-D11 -> -10872 | K11: =+J11/$D$77 -> -85.606299 | N11: OCT = 11/4/25 RR, NOV = 12/16/25 RR
A12: 2 | B12: Vacancy Loss | D12: -87048 | E12: =+D12/$D$77 -> -685.41732 | G12: =+PROFORMA!S12 -> -82771.8 | H12: =+G12/$D$77 -> -651.74646 | J12: =+G12-D12 -> 4276.2 | K12: =+J12/$D$77 -> 33.670866 | N12: OCT = 11/4/25 RR, NOV = 5%
A13: 3 | B13: Concessions | D13: 0 | E13: =+D13/$D$77 -> 0 | G13: =+PROFORMA!S13 -> 0 | H13: =+G13/$D$77 -> 0 | J13: =+G13-D13 -> 0 | K13: =+J13/$D$77 -> 0 | N13: 0
A14: 4 | B14: Delinquency/Bad Debt | D14: -49989.24 | E14: =+D14/$D$77 -> -393.61606 | G14: =+PROFORMA!S14 -> -49663.08 | H14: =+G14/$D$77 -> -391.04787 | J14: =+G14-D14 -> 326.16 | K14: =+J14/$D$77 -> 2.568189 | N14: 0.03
A15: 5 | B15: Model/Down Units | D15: 0 | E15: =+D15/$D$77 -> 0 | G15: =+PROFORMA!S15 -> 0 | H15: =+G15/$D$77 -> 0 | J15: =+G15-D15 -> 0 | K15: =+J15/$D$77 -> 0 | N15: T12
B16: Total Rental Income | D16: 1529260 | E16: =+D16/$D$77 -> 12041.417 | G16: =+PROFORMA!S16 -> 1523001.1 | H16: =+G16/$D$77 -> 11992.135 | J16: =+G16-D16 -> -6258.88 | K16: =+J16/$D$77 -> -49.28252
A17: 6 | B17: Utility Reimbursements | D17: 85773.847 | E17: =+D17/$D$77 -> 675.38463 | G17: =+PROFORMA!S17 -> 87122.56 | H17: =+G17/$D$77 -> 686.00441 | J17: =+G17-D17 -> 1348.7129 | K17: =+J17/$D$77 -> 10.619787 | M17: 0.03 | N17: T12
A18: 7 | B18: Miscellaneous Income | D18: 133870.98 | E18: =+D18/$D$77 -> 1054.1022 | G18: =+PROFORMA!S18 -> 124901.74 | H18: =+G18/$D$77 -> 983.47831 | J18: =+G18-D18 -> -8969.24 | K18: =+J18/$D$77 -> -70.623937 | M18: 0.03 | N18: T12
B19: Effective Gross Income | D19: 1748904.8 | E19: =+D19/$D$77 -> 13770.904 | G19: =+PROFORMA!S19 -> 1735025.4 | H19: =+G19/$D$77 -> 13661.618 | J19: =+G19-D19 -> -13879.407 | K19: =+J19/$D$77 -> -109.28667
B21: EXPENSES
A22: 8 | B22: Payroll | D22: 88011.461 | E22: =+D22/$D$77 -> 693.00363 | G22: =+PROFORMA!S22 -> 103654.23 | H22: =+G22/$D$77 -> 816.175 | J22: =+G22-D22 -> 15642.765 | K22: =+J22/$D$77 -> 123.17137 | M22: 0.03 | N22: T12
A23: 9 | B23: General & Administrative | D23: 61873.872 | E23: =+D23/$D$77 -> 487.19584 | G23: =+PROFORMA!S23 -> 59070.706 | H23: =+G23/$D$77 -> 465.12367 | J23: =+G23-D23 -> -2803.1656 | K23: =+J23/$D$77 -> -22.07217 | M23: 0.03 | N23: T12
A24: 10 | B24: Advertising | D24: 29015.285 | E24: =+D24/$D$77 -> 228.46681 | G24: =+PROFORMA!S24 -> 32334.502 | H24: =+G24/$D$77 -> 254.60237 | J24: =+G24-D24 -> 3319.2162 | K24: =+J24/$D$77 -> 26.135561 | M24: 0.03 | N24: T12
A25: 11 | B25: Repairs & Maintenance | D25: 66435.082 | E25: =+D25/$D$77 -> 523.11089 | G25: =+PROFORMA!S25 -> 64927.42 | H25: =+G25/$D$77 -> 511.23953 | J25: =+G25-D25 -> -1507.6625 | K25: =+J25/$D$77 -> -11.871358 | M25: 0.03 | N25: T12
A26: 12 | B26: Contract Services | D26: 68126.373 | E26: =+D26/$D$77 -> 536.42814 | G26: =+PROFORMA!S26 -> 66526.639 | H26: =+G26/$D$77 -> 523.8318 | J26: =+G26-D26 -> -1599.7342 | K26: =+J26/$D$77 -> -12.596332 | M26: 0.03 | N26: T12
A27: 13 | B27: Turnover/Cleaning | D27: 51694.691 | E27: =+D27/$D$77 -> 407.04481 | G27: =+PROFORMA!S27 -> 47022.981 | H27: =+G27/$D$77 -> 370.2597 | J27: =+G27-D27 -> -4671.7092 | K27: =+J27/$D$77 -> -36.785112 | M27: 0.03 | N27: T12
A28: 14 | B28: Utilities | D28: 78048.487 | E28: =+D28/$D$77 -> 614.55501 | G28: =+PROFORMA!S28 -> 77975.563 | H28: =+G28/$D$77 -> 613.98081 | J28: =+G28-D28 -> -72.924 | K28: =+J28/$D$77 -> -0.57420472 | M28: 0.03 | N28: T12
A29: 15 | B29: Property Taxes | D29: 163732.42 | E29: =+D29/$D$77 -> 1289.2316 | G29: =+PROFORMA!S29 -> 163732.42 | H29: =+G29/$D$77 -> 1289.2316 | J29: =+G29-D29 -> 0 | K29: =+J29/$D$77 -> 0 | M29: 0.03 | N29: 2025 Bill
A30: 16 | B30: Property Insurance | D30: 160000 | E30: =+D30/$D$77 -> 1259.8425 | G30: =+PROFORMA!S30 -> 160000 | H30: =+G30/$D$77 -> 1259.8425 | J30: =+G30-D30 -> 0 | K30: =+J30/$D$77 -> 0 | N30: Insurance Renewal
A31: 17 | B31: Management Fee | D31: 61211.669 | E31: =+D31/$D$77 -> 481.98165 | G31: =+PROFORMA!S31 -> 60725.89 | H31: =+G31/$D$77 -> 478.15661 | J31: =+G31-D31 -> -485.77925 | K31: =+J31/$D$77 -> -3.8250335 | N31: 0.035
B32: Reserves | D32: 38100 | E32: =+D32/$D$77 -> 300 | G32: =+PROFORMA!S32 -> 38100 | H32: =+G32/$D$77 -> 300 | J32: =+G32-D32 -> 0 | K32: =+J32/$D$77 -> 0 | N32: 300
B33: Total Operating Expenses | D33: 866249.34 | E33: =+D33/$D$77 -> 6820.8609 | G33: =+PROFORMA!S33 -> 874070.34 | H33: =+G33/$D$77 -> 6882.4436 | J33: =+G33-D33 -> 7821.006 | K33: =+J33/$D$77 -> 61.582724
B34: Expense Ratio | D34: 0.49530959 | G34: =+PROFORMA!S34 -> 0.50377956 | J34: =+G34-D34 -> 0.0084699678
B36: NET OPERATING INCOME | D36: 882655.5 | E36: =+D36/$D$77 -> 6950.0433 | G36: =+PROFORMA!S36 -> 860955.08 | H36: =+G36/$D$77 -> 6779.1739 | J36: =+G36-D36 -> -21700.413 | K36: =+J36/$D$77 -> -170.86939
B38: Footnotes: | P38: PROPERTY TAX CALC | W38: 2026 | AA38: 2025 | AE38: 2024 | AI38: 2023 | AM38: 2022
R39: Re-Assessed Value | U39: Taxable Values
P40: Market Value | R40: 11000000 | U40: Non-School | W40: =+(1+AVERAGE(AA44:AE44))*AA40 -> 9442061 | AA40: 9143000 | AE40: 8958200 | AI40: 8574168 | AM40: 7794699
P41: Taxable Value | Q41: 0.8 | R41: =+Q41*R40 -> 8800000 | U41: School | W41: =+(1+$AA45)*AA41 -> 9331612.3 | AA41: 9143000 | AE41: 8958200 | AI41: 9103200 | AM41: 8947800
P42: Millage Rate | Q42: =+$X$59 -> 17.7412 | R42: =+(Q42/1000)*R41 -> 156122.56
B43: LOAN METRICS | P43: Non-Ad Valorem | R43: =+Y64 -> 3379.2 | U43: YoY Increases
E44: Per Unit | H44: Per Unit | K44: Per Unit | P44: Taxes | R44: =+SUM(R42:R43) -> 159501.76 | U44: Non-School | W44: =+W40/AA40-1 -> 0.032709281 | AA44: =+AA40/AE40-1 -> 0.020629144 | AE44: =+AE40/AI40-1 -> 0.044789419 | AI44: =+AI40/AM40-1 -> 0.099999885
B45: Value at | C45: 0.0575 | D45: =+ROUND(D36/$C45,-4) -> 15350000 | E45: =+ROUND(D45/$G$77,-3) -> 121000 | G45: =+ROUND(G36/$C45,-4) -> 14970000 | H45: =+ROUND(G45/$G$77,-3) -> 118000 | J45: =+G45-D45 -> -380000 | K45: =+ROUND(J45/$G$77,-3) -> -3000 | P45: Prepay | Q45: -0.04 | R45: =+Q45*R44 -> -6380.0704 | U45: School | W45: =+W41/AA41-1 -> 0.020629144 | AA45: =+AA41/AE41-1 -> 0.020629144 | AE45: =+AE41/AI41-1 -> -0.015928465 | AI45: =+AI41/AM41-1 -> 0.017367398
B46: Loan Size | D46: 10500000 | E46: =+ROUND(D46/$G$77,-3) -> 83000 | G46: 10500000 | H46: =+ROUND(G46/$G$77,-3) -> 83000 | J46: =+G46-D46 -> 0 | K46: =+ROUND(J46/$G$77,-3) -> 0 | P46: Taxes net of Prepay | R46: =+SUM(R44:R45) -> 153121.69
B47: LTV | D47: =+D46/D45 -> 0.68403909 | G47: =+G46/G45 -> 0.70140281 | J47: =+G47-D47 -> 0.017363718
B49: Index | D49: 3-YR UST | G49: 3-YR UST | W49: Taxable Value | X49: Millage | Y49: Taxes | AA49: Taxable Value | AB49: Millage | AC49: Taxes | AE49: Taxable Value | AF49: Millage | AG49: Taxes | AI49: Taxable Value | AJ49: Millage | AK49: Taxes | AM49: Taxable Value | AN49: Millage | AO49: Taxes
B50: Index Rate Date | D50: 45972 | G50: 46008
B51: Index Rate at the Time | D51: 0.0355 | G51: 0.03543 | U51: COJ | W51: =+W$40 -> 9442061 | X51: 11.1919 | Y51: =+(X51/1000)*W51 -> 105674.6 | AA51: =+AA$40 -> 9143000 | AB51: 11.1919 | AC51: =+(AB51/1000)*AA51 -> 102327.54 | AE51: =+AE$40 -> 8958200 | AF51: 11.3169 | AG51: =+(AF51/1000)*AE51 -> 101379.05 | AI51: =+AI$40 -> 8574168 | AJ51: 11.3169 | AK51: =+(AJ51/1000)*AI51 -> 97033.002 | AM51: =+AM$40 -> 7794699 | AN51: 11.3169 | AO51: =+(AN51/1000)*AM51 -> 88211.829
B52: Spread | D52: 0.02 | G52: =+D52 -> 0.02 | P52: INDEX RATES (as of 12/16/2025) | U52: SJRWMD | W52: =+W$40 -> 9442061 | X52: 0.1793 | Y52: =+(X52/1000)*W52 -> 1692.9615 | AA52: =+AA$40 -> 9143000 | AB52: 0.1793 | AC52: =+(AB52/1000)*AA52 -> 1639.3399 | AE52: =+AE$40 -> 8958200 | AF52: 0.1793 | AG52: =+(AF52/1000)*AE52 -> 1606.2053 | AI52: =+AI$40 -> 8574168 | AJ52: 0.1793 | AK52: =+(AJ52/1000)*AI52 -> 1537.3483 | AM52: =+AM$40 -> 7794699 | AN52: 0.1974 | AO52: =+(AN52/1000)*AM52 -> 1538.6736
B53: Face Rate at the Time | D53: =+SUM(D51:D52) -> 0.0555 | G53: =+SUM(G51:G52) -> 0.05543 | P53: 3-YR UST | Q53: 0.03532 | U53: FL Inland Navigation | W53: =+W$40 -> 9442061 | X53: 0.027 | Y53: =+(X53/1000)*W53 -> 254.93565 | AA53: =+AA$40 -> 9143000 | AB53: 0.027 | AC53: =+(AB53/1000)*AA53 -> 246.861 | AE53: =+AE$40 -> 8958200 | AF53: 0.0288 | AG53: =+(AF53/1000)*AE53 -> 257.99616 | AI53: =+AI$40 -> 8574168 | AJ53: 0.0288 | AK53: =+(AJ53/1000)*AI53 -> 246.93604 | AM53: =+AM$40 -> 7794699 | AN53: 0.032 | AO53: =+(AN53/1000)*AM53 -> 249.43037
P54: 5-YR UST | Q54: 0.03699 | U54: School - State | W54: =+W$41 -> 9331612.3 | X54: 0.748 | Y54: =+(X54/1000)*W54 -> 6980.046 | AA54: =+AA$41 -> 9143000 | AB54: 0.748 | AC54: =+(AB54/1000)*AA54 -> 6838.964 | AE54: =+AE$41 -> 8958200 | AF54: 0.748 | AG54: =+(AF54/1000)*AE54 -> 6700.7336 | AI54: =+AI$41 -> 9103200 | AJ54: 0.748 | AK54: =+(AJ54/1000)*AI54 -> 6809.1936 | AM54: =+AM$41 -> 8947800 | AN54: 0.748 | AO54: =+(AN54/1000)*AM54 -> 6692.9544
B55: IO DSCR | D55: =+D36/(D53*D46) -> 1.5146383 | G55: =+G36/(G53*G46) -> 1.4792661 | J55: =+G55-D55 -> -0.035372205 | P55: 7-YR UST | Q55: 0.03904 | U55: School - Capital Outlay | W55: =+W$41 -> 9331612.3 | X55: 1.5 | Y55: =+(X55/1000)*W55 -> 13997.418 | AA55: =+AA$41 -> 9143000 | AB55: 1.5 | AC55: =+(AB55/1000)*AA55 -> 13714.5 | AE55: =+AE$41 -> 8958200 | AF55: 1.5 | AG55: =+(AF55/1000)*AE55 -> 13437.3 | AI55: =+AI$41 -> 9103200 | AJ55: 1.5 | AK55: =+(AJ55/1000)*AI55 -> 13654.8 | AM55: =+AM$41 -> 8947800 | AN55: 1.5 | AO55: =+(AN55/1000)*AM55 -> 13421.7
P56: 10-YR UST | Q56: 0.04148 | U56: School - Local Board | W56: =+W$41 -> 9331612.3 | X56: 3.095 | Y56: =+(X56/1000)*W56 -> 28881.34 | AA56: =+AA$41 -> 9143000 | AB56: 3.095 | AC56: =+(AB56/1000)*AA56 -> 28297.585 | AE56: =+AE$41 -> 8958200 | AF56: 3.092 | AG56: =+(AF56/1000)*AE56 -> 27698.754 | AI56: =+AI$41 -> 9103200 | AJ56: 3.183 | AK56: =+(AJ56/1000)*AI56 -> 28975.486 | AM56: =+AM$41 -> 8947800 | AN56: 3.236 | AO56: =+(AN56/1000)*AM56 -> 28955.081
B57: DSCR | P57: 1-MO TERM SOFR | Q57: 0.037356 | U57: School - Voter Approved | W57: =+W$41 -> 9331612.3 | X57: 1 | Y57: =+(X57/1000)*W57 -> 9331.6123 | AA57: =+AA$41 -> 9143000 | AB57: 1 | AC57: =+(AB57/1000)*AA57 -> 9143 | AE57: =+AE$41 -> 8958200 | AF57: 1 | AG57: =+(AF57/1000)*AE57 -> 8958.2 | AI57: =+AI$41 -> 9103200 | AJ57: 1 | AK57: =+(AJ57/1000)*AI57 -> 9103.2
B58: 25 | D58: =+D$36/(-PMT(D$53/12,$B58*12,D$46,0,1)*12) -> 1.1404737 | G58: =+G$36/(-PMT(G$53/12,$B58*12,G$46,0,1)*12) -> 1.1131841 | J58: =+G58-D58 -> -0.027289628
B59: 30 | D59: =+D$36/(-PMT(D$53/12,$B59*12,D$46,0,1)*12) -> 1.2326557 | G59: =+G$36/(-PMT(G$53/12,$B59*12,G$46,0,1)*12) -> 1.2032712 | J59: =+G59-D59 -> -0.029384483 | U59: Total Ad Valorem | X59: =+SUM(X51:X58) -> 17.7412 | Y59: =+SUM(Y51:Y58) -> 166812.92 | AB59: =+SUM(AB51:AB58) -> 17.7412 | AC59: =+SUM(AC51:AC58) -> 162207.79 | AF59: =+SUM(AF51:AF58) -> 17.865 | AG59: =+SUM(AG51:AG58) -> 160038.24 | AJ59: =+SUM(AJ51:AJ58) -> 17.956 | AK59: =+SUM(AK51:AK58) -> 157359.97 | AN59: =+SUM(AN51:AN58) -> 17.0303 | AO59: =+SUM(AO51:AO58) -> 139069.67
B61: Debt Yield | D61: =+D36/D46 -> 0.084062428 | G61: =+G36/G46 -> 0.081995722 | J61: =+G61-D61 -> -0.002066706 | U61: COJ Solid Waste | Y61: 0 | AC61: 0 | AG61: 0 | AK61: 0 | AO61: 0
U62: COJ Stormwater | Y62: 3379.2 | AC62: 3379.2 | AG62: 3379.2 | AK62: 3379.2 | AO62: 3379.2
U64: Total Non-Ad Valorem | Y64: =+SUM(Y61:Y63) -> 3379.2 | AC64: =+SUM(AC61:AC63) -> 3379.2 | AG64: =+SUM(AG61:AG63) -> 3379.2 | AK64: =+SUM(AK61:AK63) -> 3379.2 | AO64: =+SUM(AO61:AO63) -> 3379.2
U67: TOTAL TAXES | Y67: =+Y59+Y64 -> 170192.12 | AC67: =+AC59+AC64 -> 165586.99 | AG67: =+AG59+AG64 -> 163417.44 | AK67: =+AK59+AK64 -> 160739.17 | AO67: =+AO59+AO64 -> 142448.87
U69: Less: 4% Prepay Discount | Y69: =+-4%*Y67 -> -6807.6846 | AC69: =+-4%*AC67 -> -6623.4797 | AG69: =+-4%*AG67 -> -6536.6977 | AK69: =+-4%*AK67 -> -6429.5666 | AO69: =+-4%*AO67 -> -5697.9547
D71: PROPERTY INFO | G71: PROPERTY INFO | J71: PROPERTY INFO | U71: TOTAL DISCOUNTED TAXES | Y71: =+SUM(Y67:Y70) -> 163384.43 | AC71: =+SUM(AC67:AC70) -> 158963.51 | AG71: =+SUM(AG67:AG70) -> 156880.75 | AK71: =+SUM(AK67:AK70) -> 154309.6 | AO71: =+SUM(AO67:AO70) -> 136750.91
D73: https://paopropertysearch.coj.net/Basic/Detail.aspx?RE=1294960000 | G73: https://paopropertysearch.coj.net/Basic/Detail.aspx?RE=1294960000 | J73: https://paopropertysearch.coj.net/Basic/Detail.aspx?RE=1294960000 | U73: Year-over-Year | Y73: =+Y71/AC71-1 -> 0.027810906 | AC73: =+AC71/AG71-1 -> 0.013276114 | AG73: =+AG71/AK71-1 -> 0.016662259 | AK73: =+AK71/AO71-1 -> 0.12839903
D75: 8.32 | E75: Acres | G75: 8.32 | H75: Acres | J75: 8.32 | K75: Acres
D76: 1963 | E76: Years Built | G76: 1963 | H76: Years Built | J76: 1963 | K76: Years Built
D77: =+'RR 11-4-25'!$G$152 -> 127 | E77: # Units | G77: =+'RR 11-4-25'!$G$152 -> 127 | H77: # Units | J77: =+'RR 11-4-25'!$G$152 -> 127 | K77: # Units
D78: 129496-0000 | E78: Parcel ID | G78: 129496-0000 | H78: Parcel ID | J78: 129496-0000 | K78: Parcel ID
D79: 11370000 | E79: Last Purchase Price | G79: 11370000 | H79: Last Purchase Price | J79: 11370000 | K79: Last Purchase Price
D80: 45313 | E80: Last Purchase Date | G80: 45313 | H80: Last Purchase Date | J80: 45313 | K80: Last Purchase Date
D81: 4800 Atlantic Blvd | E81: Address | G81: 4800 Atlantic Blvd | H81: Address | J81: 4800 Atlantic Blvd | K81: Address

Sheet PROFORMA
B2: OASIS AT SAN MARCO
B3: CBRE UNDERWRITING AND HISTORICAL OVERVIEW
D5: 2022 | G5: 2023 | J5: 2024 | M5: T12 | N5: T6 | O5: T3 | P5: T2 | Q5: T1 | S5: PROFORMA
D6: Amount | E6: Per Unit | G6: Amount | H6: Per Unit | J6: Amount | K6: Per Unit | S6: Amount | T6: Per Unit | W6: Underwriting Notes
B7: Economic Occupancy (Vacancy Loss only) | D7: =IFERROR(1-(-D12/D11),"NA") -> NA | G7: =IFERROR(1-(-G12/G11),"NA") -> NA | J7: =IFERROR(1-(-J12/J11),"NA") -> NA | M7: =IFERROR(1-(-M12/M11),"NA") -> 0.82460883 | N7: =IFERROR(1-(-N12/N11),"NA") -> 0.83204828 | O7: =IFERROR(1-(-O12/O11),"NA") -> 0.91508542 | P7: =IFERROR(1-(-P12/P11),"NA") -> 0.94388776 | Q7: =IFERROR(1-(-Q12/Q11),"NA") -> 0.93297484 | S7: =IFERROR(1-(-S12/S11),"NA") -> 0.95
B8: Physical Occupancy | S8: =+'RR 12-16-25'!$H$150 -> 0.96062992 | V8: Growth Factor
B10: REVENUE
A11: 1 | B11: Gross Potential Rent (net of LTL) | D11: =+SUMIFS('IS 2022'!$V:$V,'IS 2022'!$A:$A,$A11) -> 0 | E11: =+D11/'RR 11-4-25'!$G$152 -> 0 | G11: =+SUMIFS('IS 2023'!$V:$V,'IS 2023'!$A:$A,$A11) -> 0 | H11: =+G11/'RR 11-4-25'!$G$152 -> 0 | J11: =+SUMIFS('IS 2024'!$V:$V,'IS 2024'!$A:$A,$A11) -> 0 | K11: =+J11/'RR 11-4-25'!$G$152 -> 0 | M11: =+SUMIFS('TTM Nov-25'!U:U,'TTM Nov-25'!$A:$A,$A11) -> 1617029 | N11: =+SUMIFS('TTM Nov-25'!T:T,'TTM Nov-25'!$A:$A,$A11) -> 1584657.8 | O11: =+SUMIFS('TTM Nov-25'!S:S,'TTM Nov-25'!$A:$A,$A11) -> 1481992.8 | P11: =+SUMIFS('TTM Nov-25'!R:R,'TTM Nov-25'!$A:$A,$A11) -> 1502837.9 | Q11: =+SUMIFS('TTM Nov-25'!Q:Q,'TTM Nov-25'!$A:$A,$A11) -> 1560859.3 | S11: =+'RR 12-16-25'!$K$152*12 -> 1655436 | T11: =+S11/'RR 11-4-25'!$G$152 -> 13034.929 | W11: Rent Roll as of 11/4/2025
A12: 2 | B12: Vacancy Loss | D12: =+SUMIFS('IS 2022'!$V:$V,'IS 2022'!$A:$A,$A12) -> 0 | E12: =+D12/'RR 11-4-25'!$G$152 -> 0 | G12: =+SUMIFS('IS 2023'!$V:$V,'IS 2023'!$A:$A,$A12) -> 0 | H12: =+G12/'RR 11-4-25'!$G$152 -> 0 | J12: =+SUMIFS('IS 2024'!$V:$V,'IS 2024'!$A:$A,$A12) -> 0 | K12: =+J12/'RR 11-4-25'!$G$152 -> 0 | M12: =+SUMIFS('TTM Nov-25'!U:U,'TTM Nov-25'!$A:$A,$A12) -> -283612.62 | N12: =+SUMIFS('TTM Nov-25'!T:T,'TTM Nov-25'!$A:$A,$A12) -> -266146 | O12: =+SUMIFS('TTM Nov-25'!S:S,'TTM Nov-25'!$A:$A,$A12) -> -125842.8 | P12: =+SUMIFS('TTM Nov-25'!R:R,'TTM Nov-25'!$A:$A,$A12) -> -84327.6 | Q12: =+SUMIFS('TTM Nov-25'!Q:Q,'TTM Nov-25'!$A:$A,$A12) -> -104616.84 | S12: =+-W12*S11 -> -82771.8 | T12: =+S12/'RR 11-4-25'!$G$152 -> -651.74646 | W12: 0.05
A13: 3 | B13: Concessions | D13: =+SUMIFS('IS 2022'!$V:$V,'IS 2022'!$A:$A,$A13) -> 0 | E13: =+D13/'RR 11-4-25'!$G$152 -> 0 | G13: =+SUMIFS('IS 2023'!$V:$V,'IS 2023'!$A:$A,$A13) -> 0 | H13: =+G13/'RR 11-4-25'!$G$152 -> 0 | J13: =+SUMIFS('IS 2024'!$V:$V,'IS 2024'!$A:$A,$A13) -> 0 | K13: =+J13/'RR 11-4-25'!$G$152 -> 0 | M13: =+SUMIFS('TTM Nov-25'!U:U,'TTM Nov-25'!$A:$A,$A13) -> -1730 | N13: =+SUMIFS('TTM Nov-25'!T:T,'TTM Nov-25'!$A:$A,$A13) -> -3460 | O13: =+SUMIFS('TTM Nov-25'!S:S,'TTM Nov-25'!$A:$A,$A13) -> -4520 | P13: =+SUMIFS('TTM Nov-25'!R:R,'TTM Nov-25'!$A:$A,$A13) -> -4320 | Q13: =+SUMIFS('TTM Nov-25'!Q:Q,'TTM Nov-25'!$A:$A,$A13) -> -3720 | S13: =+-W13*S10 -> 0 | T13: =+S13/'RR 11-4-25'!$G$152 -> 0 | W13: 0
A14: 4 | B14: Delinquency/Bad Debt | D14: =+SUMIFS('IS 2022'!$V:$V,'IS 2022'!$A:$A,$A14) -> 0 | E14: =+D14/'RR 11-4-25'!$G$152 -> 0 | G14: =+SUMIFS('IS 2023'!$V:$V,'IS 2023'!$A:$A,$A14) -> 0 | H14: =+G14/'RR 11-4-25'!$G$152 -> 0 | J14: =+SUMIFS('IS 2024'!$V:$V,'IS 2024'!$A:$A,$A14) -> 0 | K14: =+J14/'RR 11-4-25'!$G$152 -> 0 | M14: =+SUMIFS('TTM Nov-25'!U:U,'TTM Nov-25'!$A:$A,$A14) -> -103089.13 | N14: =+SUMIFS('TTM Nov-25'!T:T,'TTM Nov-25'!$A:$A,$A14) -> -64606.52 | O14: =+SUMIFS('TTM Nov-25'!S:S,'TTM Nov-25'!$A:$A,$A14) -> -113341.04 | P14: =+SUMIFS('TTM Nov-25'!R:R,'TTM Nov-25'!$A:$A,$A14) -> -70044.42 | Q14: =+SUMIFS('TTM Nov-25'!Q:Q,'TTM Nov-25'!$A:$A,$A14) -> 0 | S14: =+-W14*S11 -> -49663.08 | T14: =+S14/'RR 11-4-25'!$G$152 -> -391.04787 | W14: 0.03
A15: 5 | B15: Model/Down Units | D15: =+SUMIFS('IS 2022'!$V:$V,'IS 2022'!$A:$A,$A15) -> 0 | E15: =+D15/'RR 11-4-25'!$G$152 -> 0 | G15: =+SUMIFS('IS 2023'!$V:$V,'IS 2023'!$A:$A,$A15) -> 0 | H15: =+G15/'RR 11-4-25'!$G$152 -> 0 | J15: =+SUMIFS('IS 2024'!$V:$V,'IS 2024'!$A:$A,$A15) -> 0 | K15: =+J15/'RR 11-4-25'!$G$152 -> 0 | M15: =+SUMIFS('TTM Nov-25'!U:U,'TTM Nov-25'!$A:$A,$A15) -> 0 | N15: =+SUMIFS('TTM Nov-25'!T:T,'TTM Nov-25'!$A:$A,$A15) -> 0 | O15: =+SUMIFS('TTM Nov-25'!S:S,'TTM Nov-25'!$A:$A,$A15) -> 0 | P15: =+SUMIFS('TTM Nov-25'!R:R,'TTM Nov-25'!$A:$A,$A15) -> 0 | Q15: =+SUMIFS('TTM Nov-25'!Q:Q,'TTM Nov-25'!$A:$A,$A15) -> 0 | S15: =+SUMIFS($M15:$Q15,$M$5:$Q$5,$W15)*(1+$V15) -> 0 | T15: =+S15/'RR 11-4-25'!$G$152 -> 0 | W15: T12
B16: Total Rental Income | D16: =+SUM(D11:D15) -> 0 | E16: =+D16/'RR 11-4-25'!$G$152 -> 0 | G16: =+SUM(G11:G15) -> 0 | H16: =+G16/'RR 11-4-25'!$G$152 -> 0 | J16: =+SUM(J11:J15) -> 0 | K16: =+J16/'RR 11-4-25'!$G$152 -> 0 | M16: =+SUM(M11:M15) -> 1228597.3 | N16: =+SUM(N11:N15) -> 1250445.3 | O16: =+SUM(O11:O15) -> 1238289 | P16: =+SUM(P11:P15) -> 1344145.9 | Q16: =+SUM(Q11:Q15) -> 1452522.5 | S16: =+SUM(S11:S15) -> 1523001.1 | T16: =+S16/'RR 11-4-25'!$G$152 -> 11992.135
A17: 6 | B17: Utility Reimbursements | D17: =+SUMIFS('IS 2022'!$V:$V,'IS 2022'!$A:$A,$A17) -> 0 | E17: =+D17/'RR 11-4-25'!$G$152 -> 0 | G17: =+SUMIFS('IS 2023'!$V:$V,'IS 2023'!$A:$A,$A17) -> 0 | H17: =+G17/'RR 11-4-25'!$G$152 -> 0 | J17: =+SUMIFS('IS 2024'!$V:$V,'IS 2024'!$A:$A,$A17) -> 0 | K17: =+J17/'RR 11-4-25'!$G$152 -> 0 | M17: =+SUMIFS('TTM Nov-25'!U:U,'TTM Nov-25'!$A:$A,$A17) -> 84585.01 | N17: =+SUMIFS('TTM Nov-25'!T:T,'TTM Nov-25'!$A:$A,$A17) -> 82450.02 | O17: =+SUMIFS('TTM Nov-25'!S:S,'TTM Nov-25'!$A:$A,$A17) -> 90137.28 | P17: =+SUMIFS('TTM Nov-25'!R:R,'TTM Nov-25'!$A:$A,$A17) -> 93177.96 | Q17: =+SUMIFS('TTM Nov-25'!Q:Q,'TTM Nov-25'!$A:$A,$A17) -> 93227.52 | S17: =+SUMIFS($M17:$Q17,$M$5:$Q$5,$W17)*(1+$V17) -> 87122.56 | T17: =+S17/'RR 11-4-25'!$G$152 -> 686.00441 | V17: 0.03 | W17: T12
A18: 7 | B18: Miscellaneous Income | D18: =+SUMIFS('IS 2022'!$V:$V,'IS 2022'!$A:$A,$A18) -> 0 | E18: =+D18/'RR 11-4-25'!$G$152 -> 0 | G18: =+SUMIFS('IS 2023'!$V:$V,'IS 2023'!$A:$A,$A18) -> 0 | H18: =+G18/'RR 11-4-25'!$G$152 -> 0 | J18: =+SUMIFS('IS 2024'!$V:$V,'IS 2024'!$A:$A,$A18) -> 0 | K18: =+J18/'RR 11-4-25'!$G$152 -> 0 | M18: =+SUMIFS('TTM Nov-25'!U:U,'TTM Nov-25'!$A:$A,$A18) -> 121263.83 | N18: =+SUMIFS('TTM Nov-25'!T:T,'TTM Nov-25'!$A:$A,$A18) -> 91409.54 | O18: =+SUMIFS('TTM Nov-25'!S:S,'TTM Nov-25'!$A:$A,$A18) -> 88093.56 | P18: =+SUMIFS('TTM Nov-25'!R:R,'TTM Nov-25'!$A:$A,$A18) -> 95491.5 | Q18: =+SUMIFS('TTM Nov-25'!Q:Q,'TTM Nov-25'!$A:$A,$A18) -> 116246.76 | S18: =+SUMIFS($M18:$Q18,$M$5:$Q$5,$W18)*(1+$V18) -> 124901.74 | T18: =+S18/'RR 11-4-25'!$G$152 -> 983.47831 | V18: 0.03 | W18: T12
B19: Effective Gross Income | D19: =+SUM(D16:D18) -> 0 | E19: =+D19/'RR 11-4-25'!$G$152 -> 0 | G19: =+SUM(G16:G18) -> 0 | H19: =+G19/'RR 11-4-25'!$G$152 -> 0 | J19: =+SUM(J16:J18) -> 0 | K19: =+J19/'RR 11-4-25'!$G$152 -> 0 | M19: =+SUM(M16:M18) -> 1434446.1 | N19: =+SUM(N16:N18) -> 1424304.9 | O19: =+SUM(O16:O18) -> 1416519.8 | P19: =+SUM(P16:P18) -> 1532815.4 | Q19: =+SUM(Q16:Q18) -> 1661996.8 | S19: =+SUM(S16:S18) -> 1735025.4 | T19: =+S19/'RR 11-4-25'!$G$152 -> 13661.618
B21: EXPENSES
A22: 8 | B22: Payroll | D22: =+SUMIFS('IS 2022'!$V:$V,'IS 2022'!$A:$A,$A22) -> 0 | E22: =+D22/'RR 11-4-25'!$G$152 -> 0 | G22: =+SUMIFS('IS 2023'!$V:$V,'IS 2023'!$A:$A,$A22) -> 0 | H22: =+G22/'RR 11-4-25'!$G$152 -> 0 | J22: =+SUMIFS('IS 2024'!$V:$V,'IS 2024'!$A:$A,$A22) -> 0 | K22: =+J22/'RR 11-4-25'!$G$152 -> 0 | M22: =+SUMIFS('TTM Nov-25'!U:U,'TTM Nov-25'!$A:$A,$A22) -> 100635.17 | N22: =+SUMIFS('TTM Nov-25'!T:T,'TTM Nov-25'!$A:$A,$A22) -> 186164.24 | O22: =+SUMIFS('TTM Nov-25'!S:S,'TTM Nov-25'!$A:$A,$A22) -> 158930.56 | P22: =+SUMIFS('TTM Nov-25'!R:R,'TTM Nov-25'!$A:$A,$A22) -> 163955.64 | Q22: =+SUMIFS('TTM Nov-25'!Q:Q,'TTM Nov-25'!$A:$A,$A22) -> 146188.08 | S22: =+SUMIFS($M22:$Q22,$M$5:$Q$5,$W22)*(1+$V22) -> 103654.23 | T22: =+S22/'RR 11-4-25'!$G$152 -> 816.175 | V22: 0.03 | W22: T12
A23: 9 | B23: General & Administrative | D23: =+SUMIFS('IS 2022'!$V:$V,'IS 2022'!$A:$A,$A23) -> 0 | E23: =+D23/'RR 11-4-25'!$G$152 -> 0 | G23: =+SUMIFS('IS 2023'!$V:$V,'IS 2023'!$A:$A,$A23) -> 0 | H23: =+G23/'RR 11-4-25'!$G$152 -> 0 | J23: =+SUMIFS('IS 2024'!$V:$V,'IS 2024'!$A:$A,$A23) -> 0 | K23: =+J23/'RR 11-4-25'!$G$152 -> 0 | M23: =+SUMIFS('TTM Nov-25'!U:U,'TTM Nov-25'!$A:$A,$A23) -> 57350.2 | N23: =+SUMIFS('TTM Nov-25'!T:T,'TTM Nov-25'!$A:$A,$A23) -> 42387.04 | O23: =+SUMIFS('TTM Nov-25'!S:S,'TTM Nov-25'!$A:$A,$A23) -> 25765.2 | P23: =+SUMIFS('TTM Nov-25'!R:R,'TTM Nov-25'!$A:$A,$A23) -> 27994.2 | Q23: =+SUMIFS('TTM Nov-25'!Q:Q,'TTM Nov-25'!$A:$A,$A23) -> 21189.12 | S23: =+SUMIFS($M23:$Q23,$M$5:$Q$5,$W23)*(1+$V23) -> 59070.706 | T23: =+S23/'RR 11-4-25'!$G$152 -> 465.12367 | V23: 0.03 | W23: T12
A24: 10 | B24: Advertising | D24: =+SUMIFS('IS 2022'!$V:$V,'IS 2022'!$A:$A,$A24) -> 0 | E24: =+D24/'RR 11-4-25'!$G$152 -> 0 | G24: =+SUMIFS('IS 2023'!$V:$V,'IS 2023'!$A:$A,$A24) -> 0 | H24: =+G24/'RR 11-4-25'!$G$152 -> 0 | J24: =+SUMIFS('IS 2024'!$V:$V,'IS 2024'!$A:$A,$A24) -> 0 | K24: =+J24/'RR 11-4-25'!$G$152 -> 0 | M24: =+SUMIFS('TTM Nov-25'!U:U,'TTM Nov-25'!$A:$A,$A24) -> 31392.72 | N24: =+SUMIFS('TTM Nov-25'!T:T,'TTM Nov-25'!$A:$A,$A24) -> 51515.14 | O24: =+SUMIFS('TTM Nov-25'!S:S,'TTM Nov-25'!$A:$A,$A24) -> 47359.68 | P24: =+SUMIFS('TTM Nov-25'!R:R,'TTM Nov-25'!$A:$A,$A24) -> 44658 | Q24: =+SUMIFS('TTM Nov-25'!Q:Q,'TTM Nov-25'!$A:$A,$A24) -> 45744 | S24: =+SUMIFS($M24:$Q24,$M$5:$Q$5,$W24)*(1+$V24) -> 32334.502 | T24: =+S24/'RR 11-4-25'!$G$152 -> 254.60237 | V24: 0.03 | W24: T12
A25: 11 | B25: Repairs & Maintenance | D25: =+SUMIFS('IS 2022'!$V:$V,'IS 2022'!$A:$A,$A25) -> 0 | E25: =+D25/'RR 11-4-25'!$G$152 -> 0 | G25: =+SUMIFS('IS 2023'!$V:$V,'IS 2023'!$A:$A,$A25) -> 0 | H25: =+G25/'RR 11-4-25'!$G$152 -> 0 | J25: =+SUMIFS('IS 2024'!$V:$V,'IS 2024'!$A:$A,$A25) -> 0 | K25: =+J25/'RR 11-4-25'!$G$152 -> 0 | M25: =+SUMIFS('TTM Nov-25'!U:U,'TTM Nov-25'!$A:$A,$A25) -> 63036.33 | N25: =+SUMIFS('TTM Nov-25'!T:T,'TTM Nov-25'!$A:$A,$A25) -> 57352.92 | O25: =+SUMIFS('TTM Nov-25'!S:S,'TTM Nov-25'!$A:$A,$A25) -> 68108.68 | P25: =+SUMIFS('TTM Nov-25'!R:R,'TTM Nov-25'!$A:$A,$A25) -> 70273.2 | Q25: =+SUMIFS('TTM Nov-25'!Q:Q,'TTM Nov-25'!$A:$A,$A25) -> 80229.6 | S25: =+SUMIFS($M25:$Q25,$M$5:$Q$5,$W25)*(1+$V25) -> 64927.42 | T25: =+S25/'RR 11-4-25'!$G$152 -> 511.23953 | V25: 0.03 | W25: T12
A26: 12 | B26: Contract Services | D26: =+SUMIFS('IS 2022'!$V:$V,'IS 2022'!$A:$A,$A26) -> 0 | E26: =+D26/'RR 11-4-25'!$G$152 -> 0 | G26: =+SUMIFS('IS 2023'!$V:$V,'IS 2023'!$A:$A,$A26) -> 0 | H26: =+G26/'RR 11-4-25'!$G$152 -> 0 | J26: =+SUMIFS('IS 2024'!$V:$V,'IS 2024'!$A:$A,$A26) -> 0 | K26: =+J26/'RR 11-4-25'!$G$152 -> 0 | M26: =+SUMIFS('TTM Nov-25'!U:U,'TTM Nov-25'!$A:$A,$A26) -> 64588.97 | N26: =+SUMIFS('TTM Nov-25'!T:T,'TTM Nov-25'!$A:$A,$A26) -> 64074.82 | O26: =+SUMIFS('TTM Nov-25'!S:S,'TTM Nov-25'!$A:$A,$A26) -> 70707.72 | P26: =+SUMIFS('TTM Nov-25'!R:R,'TTM Nov-25'!$A:$A,$A26) -> 76203.42 | Q26: =+SUMIFS('TTM Nov-25'!Q:Q,'TTM Nov-25'!$A:$A,$A26) -> 88183.2 | S26: =+SUMIFS($M26:$Q26,$M$5:$Q$5,$W26)*(1+$V26) -> 66526.639 | T26: =+S26/'RR 11-4-25'!$G$152 -> 523.8318 | V26: 0.03 | W26: T12
A27: 13 | B27: Turnover/Cleaning | D27: =+SUMIFS('IS 2022'!$V:$V,'IS 2022'!$A:$A,$A27) -> 0 | E27: =+D27/'RR 11-4-25'!$G$152 -> 0 | G27: =+SUMIFS('IS 2023'!$V:$V,'IS 2023'!$A:$A,$A27) -> 0 | H27: =+G27/'RR 11-4-25'!$G$152 -> 0 | J27: =+SUMIFS('IS 2024'!$V:$V,'IS 2024'!$A:$A,$A27) -> 0 | K27: =+J27/'RR 11-4-25'!$G$152 -> 0 | M27: =+SUMIFS('TTM Nov-25'!U:U,'TTM Nov-25'!$A:$A,$A27) -> 45653.38 | N27: =+SUMIFS('TTM Nov-25'!T:T,'TTM Nov-25'!$A:$A,$A27) -> 32028.48 | O27: =+SUMIFS('TTM Nov-25'!S:S,'TTM Nov-25'!$A:$A,$A27) -> 50841.76 | P27: =+SUMIFS('TTM Nov-25'!R:R,'TTM Nov-25'!$A:$A,$A27) -> 24147.96 | Q27: =+SUMIFS('TTM Nov-25'!Q:Q,'TTM Nov-25'!$A:$A,$A27) -> 15101.52 | S27: =+SUMIFS($M27:$Q27,$M$5:$Q$5,$W27)*(1+$V27) -> 47022.981 | T27: =+S27/'RR 11-4-25'!$G$152 -> 370.2597 | V27: 0.03 | W27: T12
A28: 14 | B28: Utilities | D28: =+SUMIFS('IS 2022'!$V:$V,'IS 2022'!$A:$A,$A28) -> 0 | E28: =+D28/'RR 11-4-25'!$G$152 -> 0 | G28: =+SUMIFS('IS 2023'!$V:$V,'IS 2023'!$A:$A,$A28) -> 0 | H28: =+G28/'RR 11-4-25'!$G$152 -> 0 | J28: =+SUMIFS('IS 2024'!$V:$V,'IS 2024'!$A:$A,$A28) -> 0 | K28: =+J28/'RR 11-4-25'!$G$152 -> 0 | M28: =+SUMIFS('TTM Nov-25'!U:U,'TTM Nov-25'!$A:$A,$A28) -> 75704.43 | N28: =+SUMIFS('TTM Nov-25'!T:T,'TTM Nov-25'!$A:$A,$A28) -> 79541.56 | O28: =+SUMIFS('TTM Nov-25'!S:S,'TTM Nov-25'!$A:$A,$A28) -> 76849.04 | P28: =+SUMIFS('TTM Nov-25'!R:R,'TTM Nov-25'!$A:$A,$A28) -> 73728 | Q28: =+SUMIFS('TTM Nov-25'!Q:Q,'TTM Nov-25'!$A:$A,$A28) -> 75841.44 | S28: =+SUMIFS($M28:$Q28,$M$5:$Q$5,$W28)*(1+$V28) -> 77975.563 | T28: =+S28/'RR 11-4-25'!$G$152 -> 613.98081 | V28: 0.03 | W28: T12
A29: 15 | B29: Property Taxes | D29: =+SUMIFS('IS 2022'!$V:$V,'IS 2022'!$A:$A,$A29) -> 0 | E29: =+D29/'RR 11-4-25'!$G$152 -> 0 | G29: =+SUMIFS('IS 2023'!$V:$V,'IS 2023'!$A:$A,$A29) -> 0 | H29: =+G29/'RR 11-4-25'!$G$152 -> 0 | J29: =+SUMIFS('IS 2024'!$V:$V,'IS 2024'!$A:$A,$A29) -> 0 | K29: =+J29/'RR 11-4-25'!$G$152 -> 0 | M29: =+SUMIFS('TTM Nov-25'!U:U,'TTM Nov-25'!$A:$A,$A29) -> 164042.76 | N29: =+SUMIFS('TTM Nov-25'!T:T,'TTM Nov-25'!$A:$A,$A29) -> 165073.2 | O29: =+SUMIFS('TTM Nov-25'!S:S,'TTM Nov-25'!$A:$A,$A29) -> 158173.16 | P29: =+SUMIFS('TTM Nov-25'!R:R,'TTM Nov-25'!$A:$A,$A29) -> 143126.88 | Q29: =+SUMIFS('TTM Nov-25'!Q:Q,'TTM Nov-25'!$A:$A,$A29) -> 97988.04 | S29: =+IF($W29=AA$39,$AA$46,(1+$V29)*$AL$69) -> 163732.42 | T29: =+S29/'RR 11-4-25'!$G$152 -> 1289.2316 | V29: 0.03 | W29: 2025 Bill
A30: 16 | B30: Property Insurance | D30: =+SUMIFS('IS 2022'!$V:$V,'IS 2022'!$A:$A,$A30) -> 0 | E30: =+D30/'RR 11-4-25'!$G$152 -> 0 | G30: =+SUMIFS('IS 2023'!$V:$V,'IS 2023'!$A:$A,$A30) -> 0 | H30: =+G30/'RR 11-4-25'!$G$152 -> 0 | J30: =+SUMIFS('IS 2024'!$V:$V,'IS 2024'!$A:$A,$A30) -> 0 | K30: =+J30/'RR 11-4-25'!$G$152 -> 0 | M30: =+SUMIFS('TTM Nov-25'!U:U,'TTM Nov-25'!$A:$A,$A30) -> 206902.04 | N30: =+SUMIFS('TTM Nov-25'!T:T,'TTM Nov-25'!$A:$A,$A30) -> 228812.92 | O30: =+SUMIFS('TTM Nov-25'!S:S,'TTM Nov-25'!$A:$A,$A30) -> 244238.28 | P30: =+SUMIFS('TTM Nov-25'!R:R,'TTM Nov-25'!$A:$A,$A30) -> 244238.28 | Q30: =+SUMIFS('TTM Nov-25'!Q:Q,'TTM Nov-25'!$A:$A,$A30) -> 244238.28 | S30: 160000 | T30: =+S30/'RR 11-4-25'!$G$152 -> 1259.8425 | W30: Insurance Renewal
A31: 17 | B31: Management Fee | D31: =+SUMIFS('IS 2022'!$V:$V,'IS 2022'!$A:$A,$A31) -> 0 | E31: =+D31/'RR 11-4-25'!$G$152 -> 0 | G31: =+SUMIFS('IS 2023'!$V:$V,'IS 2023'!$A:$A,$A31) -> 0 | H31: =+G31/'RR 11-4-25'!$G$152 -> 0 | J31: =+SUMIFS('IS 2024'!$V:$V,'IS 2024'!$A:$A,$A31) -> 0 | K31: =+J31/'RR 11-4-25'!$G$152 -> 0 | M31: =+SUMIFS('TTM Nov-25'!U:U,'TTM Nov-25'!$A:$A,$A31) -> 121532.18 | N31: =+SUMIFS('TTM Nov-25'!T:T,'TTM Nov-25'!$A:$A,$A31) -> 54000 | O31: =+SUMIFS('TTM Nov-25'!S:S,'TTM Nov-25'!$A:$A,$A31) -> 54000 | P31: =+SUMIFS('TTM Nov-25'!R:R,'TTM Nov-25'!$A:$A,$A31) -> 54000 | Q31: =+SUMIFS('TTM Nov-25'!Q:Q,'TTM Nov-25'!$A:$A,$A31) -> 54000 | S31: =+W31*S19 -> 60725.89 | T31: =+S31/'RR 11-4-25'!$G$152 -> 478.15661 | W31: 0.035
B32: Reserves | D32: =+SUMIFS('IS 2022'!$V:$V,'IS 2022'!$A:$A,$A32) -> 0 | E32: =+D32/'RR 11-4-25'!$G$152 -> 0 | G32: =+SUMIFS('IS 2023'!$V:$V,'IS 2023'!$A:$A,$A32) -> 0 | H32: =+G32/'RR 11-4-25'!$G$152 -> 0 | J32: =+SUMIFS('IS 2024'!$V:$V,'IS 2024'!$A:$A,$A32) -> 0 | K32: =+J32/'RR 11-4-25'!$G$152 -> 0 | S32: =+$W32*'RR 11-4-25'!$G$152 -> 38100 | T32: =+S32/'RR 11-4-25'!$G$152 -> 300 | W32: 300
B33: Total Operating Expenses | D33: =+SUM(D22:D32) -> 0 | E33: =+D33/'RR 11-4-25'!$G$152 -> 0 | G33: =+SUM(G22:G32) -> 0 | H33: =+G33/'RR 11-4-25'!$G$152 -> 0 | J33: =+SUM(J22:J32) -> 0 | K33: =+J33/'RR 11-4-25'!$G$152 -> 0 | M33: =+SUM(M22:M32) -> 930838.18 | N33: =+SUM(N22:N32) -> 960950.32 | O33: =+SUM(O22:O32) -> 954974.08 | P33: =+SUM(P22:P32) -> 922325.58 | Q33: =+SUM(Q22:Q32) -> 868703.28 | S33: =+SUM(S22:S32) -> 874070.34 | T33: =+S33/'RR 11-4-25'!$G$152 -> 6882.4436
B34: Expense Ratio | D34: =+IFERROR(D33/D19,"NA") -> NA | G34: =+IFERROR(G33/G19,"NA") -> NA | J34: =+IFERROR(J33/J19,"NA") -> NA | S34: =+S33/S19 -> 0.50377956
B36: NET OPERATING INCOME | D36: =+D19-D33 -> 0 | E36: =+E19-E33 -> 0 | G36: =+G19-G33 -> 0 | H36: =+H19-H33 -> 0 | J36: =+J19-J33 -> 0 | K36: =+K19-K33 -> 0 | M36: =+M19-M33 -> 503607.95 | N36: =+N19-N33 -> 463354.54 | O36: =+O19-O33 -> 461545.76 | P36: =+P19-P33 -> 610489.8 | Q36: =+Q19-Q33 -> 793293.48 | S36: =+S19-S33 -> 860955.08 | T36: =+T19-T33 -> 6779.1739
B38: Footnotes: | Y38: PROPERTY TAX CALC | AF38: 2026 | AJ38: 2025 | AN38: 2024 | AR38: 2023 | AV38: 2022
AA39: Re-Assessed Value | AD39: Taxable Values
Y40: Market Value | AA40: 11000000 | AD40: Non-School | AF40: =+(1+AVERAGE(AJ44:AN44))*AJ40 -> 9442061 | AJ40: 9143000 | AN40: 8958200 | AR40: 8574168 | AV40: 7794699
Y41: Taxable Value | Z41: 0.8 | AA41: =+Z41*AA40 -> 8800000 | AD41: School | AF41: =+(1+$AJ45)*AJ41 -> 9331612.3 | AJ41: 9143000 | AN41: 8958200 | AR41: 9103200 | AV41: 8947800
Y42: Millage Rate | Z42: =+$AG$57 -> 17.7412 | AA42: =+(Z42/1000)*AA41 -> 156122.56
P43: LOAN METRICS | Y43: Non-Ad Valorem | AA43: =+AH62 -> 3379.2 | AD43: YoY Increases
T44: Per Unit | Y44: Taxes | AA44: =+SUM(AA42:AA43) -> 159501.76 | AD44: Non-School | AF44: =+AF40/AJ40-1 -> 0.032709281 | AJ44: =+AJ40/AN40-1 -> 0.020629144 | AN44: =+AN40/AR40-1 -> 0.044789419 | AR44: =+AR40/AV40-1 -> 0.099999885
P45: Cap Rate | Q45: 0.0575 | S45: =+ROUND(S36/Q45,-4) -> 14970000 | T45: =+ROUND(S45/'RR 11-4-25'!$G$152,-3) -> 118000 | Y45: Prepay | Z45: -0.04 | AA45: =+Z45*AA44 -> -6380.0704 | AD45: School | AF45: =+AF41/AJ41-1 -> 0.020629144 | AJ45: =+AJ41/AN41-1 -> 0.020629144 | AN45: =+AN41/AR41-1 -> -0.015928465 | AR45: =+AR41/AV41-1 -> 0.017367398
P46: LTV | Q46: =+S46/S45 -> 0.70140281 | S46: 10500000 | T46: =+ROUND(S46/'RR 11-4-25'!$G$152,-3) -> 83000 | Y46: Taxes net of Prepay | AA46: =+SUM(AA44:AA45) -> 153121.69
P48: Index | S48: 3-YR UST | AF48: Taxable Value | AG48: Millage | AH48: Taxes | AJ48: Taxable Value | AK48: Millage | AL48: Taxes | AN48: Taxable Value | AO48: Millage | AP48: Taxes | AR48: Taxable Value | AS48: Millage | AT48: Taxes | AV48: Taxable Value | AW48: Millage | AX48: Taxes
P49: Index Rate as of 11/11/2025 | S49: =+SUMIFS($Z$51:$Z$55,$Y$51:$Y$55,$S$48) -> 0.0355 | AD49: COJ | AF49: =+AF$40 -> 9442061 | AG49: 11.1919 | AH49: =+(AG49/1000)*AF49 -> 105674.6 | AJ49: =+AJ$40 -> 9143000 | AK49: 11.1919 | AL49: =+(AK49/1000)*AJ49 -> 102327.54 | AN49: =+AN$40 -> 8958200 | AO49: 11.3169 | AP49: =+(AO49/1000)*AN49 -> 101379.05 | AR49: =+AR$40 -> 8574168 | AS49: 11.3169 | AT49: =+(AS49/1000)*AR49 -> 97033.002 | AV49: =+AV$40 -> 7794699 | AW49: 11.3169 | AX49: =+(AW49/1000)*AV49 -> 88211.829
P50: Spread | S50: 0.02 | Y50: INDEX RATES (as of 11/11/2025) | AD50: SJRWMD | AF50: =+AF$40 -> 9442061 | AG50: 0.1793 | AH50: =+(AG50/1000)*AF50 -> 1692.9615 | AJ50: =+AJ$40 -> 9143000 | AK50: 0.1793 | AL50: =+(AK50/1000)*AJ50 -> 1639.3399 | AN50: =+AN$40 -> 8958200 | AO50: 0.1793 | AP50: =+(AO50/1000)*AN50 -> 1606.2053 | AR50: =+AR$40 -> 8574168 | AS50: 0.1793 | AT50: =+(AS50/1000)*AR50 -> 1537.3483 | AV50: =+AV$40 -> 7794699 | AW50: 0.1974 | AX50: =+(AW50/1000)*AV50 -> 1538.6736
P51: Face Rate as of 11/11/2025 | S51: =+SUM(S49:S50) -> 0.0555 | Y51: 3-YR UST | Z51: 0.0355 | AD51: FL Inland Navigation | AF51: =+AF$40 -> 9442061 | AG51: 0.027 | AH51: =+(AG51/1000)*AF51 -> 254.93565 | AJ51: =+AJ$40 -> 9143000 | AK51: 0.027 | AL51: =+(AK51/1000)*AJ51 -> 246.861 | AN51: =+AN$40 -> 8958200 | AO51: 0.0288 | AP51: =+(AO51/1000)*AN51 -> 257.99616 | AR51: =+AR$40 -> 8574168 | AS51: 0.0288 | AT51: =+(AS51/1000)*AR51 -> 246.93604 | AV51: =+AV$40 -> 7794699 | AW51: 0.032 | AX51: =+(AW51/1000)*AV51 -> 249.43037
Y52: 5-YR UST | Z52: 0.03714 | AD52: School - State | AF52: =+AF$41 -> 9331612.3 | AG52: 0.748 | AH52: =+(AG52/1000)*AF52 -> 6980.046 | AJ52: =+AJ$41 -> 9143000 | AK52: 0.748 | AL52: =+(AK52/1000)*AJ52 -> 6838.964 | AN52: =+AN$41 -> 8958200 | AO52: 0.748 | AP52: =+(AO52/1000)*AN52 -> 6700.7336 | AR52: =+AR$41 -> 9103200 | AS52: 0.748 | AT52: =+(AS52/1000)*AR52 -> 6809.1936 | AV52: =+AV$41 -> 8947800 | AW52: 0.748 | AX52: =+(AW52/1000)*AV52 -> 6692.9544
P53: IO DSCR | S53: =+S36/(S51*S46) -> 1.4774004 | Y53: 7-YR UST | Z53: 0.03901 | AD53: School - Capital Outlay | AF53: =+AF$41 -> 9331612.3 | AG53: 1.5 | AH53: =+(AG53/1000)*AF53 -> 13997.418 | AJ53: =+AJ$41 -> 9143000 | AK53: 1.5 | AL53: =+(AK53/1000)*AJ53 -> 13714.5 | AN53: =+AN$41 -> 8958200 | AO53: 1.5 | AP53: =+(AO53/1000)*AN53 -> 13437.3 | AR53: =+AR$41 -> 9103200 | AS53: 1.5 | AT53: =+(AS53/1000)*AR53 -> 13654.8 | AV53: =+AV$41 -> 8947800 | AW53: 1.5 | AX53: =+(AW53/1000)*AV53 -> 13421.7
Y54: 10-YR UST | Z54: 0.04117 | AD54: School - Local Board | AF54: =+AF$41 -> 9331612.3 | AG54: 3.095 | AH54: =+(AG54/1000)*AF54 -> 28881.34 | AJ54: =+AJ$41 -> 9143000 | AK54: 3.095 | AL54: =+(AK54/1000)*AJ54 -> 28297.585 | AN54: =+AN$41 -> 8958200 | AO54: 3.092 | AP54: =+(AO54/1000)*AN54 -> 27698.754 | AR54: =+AR$41 -> 9103200 | AS54: 3.183 | AT54: =+(AS54/1000)*AR54 -> 28975.486 | AV54: =+AV$41 -> 8947800 | AW54: 3.236 | AX54: =+(AW54/1000)*AV54 -> 28955.081
P55: DSCR | Y55: 1-MO TERM SOFR | Z55: 0.039479 | AD55: School - Voter Approved | AF55: =+AF$41 -> 9331612.3 | AG55: 1 | AH55: =+(AG55/1000)*AF55 -> 9331.6123 | AJ55: =+AJ$41 -> 9143000 | AK55: 1 | AL55: =+(AK55/1000)*AJ55 -> 9143 | AN55: =+AN$41 -> 8958200 | AO55: 1 | AP55: =+(AO55/1000)*AN55 -> 8958.2 | AR55: =+AR$41 -> 9103200 | AS55: 1 | AT55: =+(AS55/1000)*AR55 -> 9103.2
P56: 25 | S56: =+S$36/(-PMT(S$51/12,$P56*12,S$46,0,1)*12) -> 1.1124347
P57: 30 | S57: =+S$36/(-PMT(S$51/12,$P57*12,S$46,0,1)*12) -> 1.2023504 | AD57: Total Ad Valorem | AG57: =+SUM(AG49:AG56) -> 17.7412 | AH57: =+SUM(AH49:AH56) -> 166812.92 | AK57: =+SUM(AK49:AK56) -> 17.7412 | AL57: =+SUM(AL49:AL56) -> 162207.79 | AO57: =+SUM(AO49:AO56) -> 17.865 | AP57: =+SUM(AP49:AP56) -> 160038.24 | AS57: =+SUM(AS49:AS56) -> 17.956 | AT57: =+SUM(AT49:AT56) -> 157359.97 | AW57: =+SUM(AW49:AW56) -> 17.0303 | AX57: =+SUM(AX49:AX56) -> 139069.67
P59: Debt Yield | S59: =+S36/S46 -> 0.081995722 | AD59: COJ Solid Waste | AH59: 0 | AL59: 0 | AP59: 0 | AT59: 0 | AX59: 0
AD60: COJ Stormwater | AH60: 3379.2 | AL60: 3379.2 | AP60: 3379.2 | AT60: 3379.2 | AX60: 3379.2
AD62: Total Non-Ad Valorem | AH62: =+SUM(AH59:AH61) -> 3379.2 | AL62: =+SUM(AL59:AL61) -> 3379.2 | AP62: =+SUM(AP59:AP61) -> 3379.2 | AT62: =+SUM(AT59:AT61) -> 3379.2 | AX62: =+SUM(AX59:AX61) -> 3379.2
AD65: TOTAL TAXES | AH65: =+AH57+AH62 -> 170192.12 | AL65: =+AL57+AL62 -> 165586.99 | AP65: =+AP57+AP62 -> 163417.44 | AT65: =+AT57+AT62 -> 160739.17 | AX65: =+AX57+AX62 -> 142448.87
AD67: Less: 4% Prepay Discount | AH67: =+-4%*AH65 -> -6807.6846 | AL67: =+-4%*AL65 -> -6623.4797 | AP67: =+-4%*AP65 -> -6536.6977 | AT67: =+-4%*AT65 -> -6429.5666 | AX67: =+-4%*AX65 -> -5697.9547
S69: PROPERTY INFO | AD69: TOTAL DISCOUNTED TAXES | AH69: =+SUM(AH65:AH68) -> 163384.43 | AL69: =+SUM(AL65:AL68) -> 158963.51 | AP69: =+SUM(AP65:AP68) -> 156880.75 | AT69: =+SUM(AT65:AT68) -> 154309.6 | AX69: =+SUM(AX65:AX68) -> 136750.91
S71: https://paopropertysearch.coj.net/Basic/Detail.aspx?RE=1294960000 | AD71: Year-over-Year | AH71: =+AH69/AL69-1 -> 0.027810906 | AL71: =+AL69/AP69-1 -> 0.013276114 | AP71: =+AP69/AT69-1 -> 0.016662259 | AT71: =+AT69/AX69-1 -> 0.12839903
S73: 8.32 | T73: Acres
S74: 1963 | T74: Years Built
S75: =+'RR 11-4-25'!$G$152 -> 127 | T75: # Units
S76: 129496-0000 | T76: Parcel ID
S77: 11370000 | T77: Last Purchase Price
S78: 45313 | T78: Last Purchase Date
S79: 4800 Atlantic Blvd | T79: Address

Sheet Sources & Uses
B2: OASIS AT SAN MARCO
B3: LOAN REQUEST AND SOURCES & USES
B6: Loan Sizing | F6: Sources and Uses
B10: On Cost | D10: Per Unit | F10: SOURCES
B11: =+"Value at "&TEXT(PROFORMA!$Q$45,"#.0%")&" cap rate on Proforma NOI" -> Value at 5.8% cap rate on Proforma NOI | C11: =+PROFORMA!$S$45 -> 14970000 | D11: =+ROUND(C11/'RR 11-4-25'!$G$152,-3) -> 118000 | F11: Debt | H11: =+C12 -> 10500000 | I11: =+H11/$H$12 -> 1
B12: Loan Size | C12: =+PROFORMA!$S$46 -> 10500000 | D12: =+ROUND(C12/'RR 11-4-25'!$G$152,-3) -> 83000 | F12: TOTAL SOURCES | H12: =+H11 -> 10500000 | I12: =+H12/$H$12 -> 1
B13: Loan to Value | C13: =+C12/C11 -> 0.70140281
F14: USES
B15: On Proforma | F15: Payoff Existing Loan | H15: 10300000 | I15: =+H15/$H$19 -> 0.98095238
B16: Market Cap Rate | C16: =+PROFORMA!$Q$45 -> 0.0575 | F16: Recoup Previously Expended Capital (see schedule page 6) | I16: =+H16/$H$19 -> 0
B17: Proforma NOI (CBRE UW) | C17: =+PROFORMA!$S$36 -> 860955.08 | F17: Closing Costs | H17: =+$I$61 -> 224675 | I17: 0.02
B18: Index | C18: =+PROFORMA!$S$48 -> 3-YR UST | F18: Equity Recapture | H18: =+H19-SUM(H15:H17) -> -24675 | I18: =+H18/$H$19 -> -0.00235
B19: =+PROFORMA!$P$49 -> Index Rate as of 11/11/2025 | C19: =+PROFORMA!S49 -> 0.0355 | F19: TOTAL USES | H19: =+H12 -> 10500000 | I19: =+H19/$H$19 -> 1
B20: Spread | C20: =+PROFORMA!S50 -> 0.02
B21: =+PROFORMA!$P$51 -> Face Rate as of 11/11/2025 | C21: =+SUM(C19:C20) -> 0.0555 | F21: BASIS
B22: IO DSCR at current Face Rate | C22: =+C17/(C21*C12) -> 1.4774004 | F22: Purchase Price (1/22/2024) | H22: 11370000 | I22: =+H22/$H$25 -> 0.98039216 | K22: =+H22/'RR 11-4-25'!$G$152 -> 89527.559
B23: 25-Year Amortizing DSCR at current Face Rate | C23: =+PROFORMA!S56 -> 1.1124347 | F23: Closing Costs & Due Diligence | H23: =2%*H22 -> 227400 | I23: =+H23/$H$25 -> 0.019607843 | K23: =+H23/'RR 11-4-25'!$G$152 -> 1790.5512
B24: 30-Year Amortizing DSCR at current Face Rate | C24: =+PROFORMA!S57 -> 1.2023504 | F24: Additional Capital Expenditures (see schedule page 6) | I24: =+H24/$H$25 -> 0 | K24: =+H24/'RR 11-4-25'!$G$152 -> 0
B25: Stabilized Yield on Cost | C25: =+C17/C12 -> 0.081995722 | F25: TOTAL BASIS | H25: =+SUM(H22:H24) -> 11597400 | I25: =+H25/$H$25 -> 1 | K25: =+C11/H25-1 -> 0.29080656
F28: Loan Closing Costs
F32: Loan Request | I32: =+H11 -> 10500000
F37: Origination Fees
F38: Lender Fee | H38: 0.0025 | I38: =+H38*$I$32 -> 26250
F39: CBRE Fee | H39: 0.01 | I39: =+H39*$I$32 -> 105000
H40: =+SUBTOTAL(9,H38:H39) -> 0.0125 | I40: =+SUBTOTAL(9,I38:I39) -> 131250
F41: Legal Fees
F42: Lender Legal | H42: =+I42/$I$32 -> 0.0019047619 | I42: 20000
F43: Borrower Legal | H43: =+I43/$I$32 -> 0.0019047619 | I43: 20000
H44: =+SUBTOTAL(9,H42:H43) -> 0.0038095238 | I44: =+SUBTOTAL(9,I42:I43) -> 40000
F45: Taxes / Government Fees
F46: FL Documentary Stamp Tax | G46: 0.35 | H46: =+I46/$I$32 -> 6.6666667e-05 | I46: =+G46*(($I$32-$H$15)/100) -> 700 | L46: Title Insurance Sizer | N46: =+SUM(N47:N51) -> 27325
F47: FL Intangible Tax | G47: 2 | H47: =+I47/$I$32 -> 3.8095238e-05 | I47: =+G47*(($I$32-$H$15)/1000) -> 400 | L47: 100000 | M47: 0.00575 | N47: =+M47*L47 -> 575
F48: Recording and Filing Fees | H48: =+I48/$I$32 -> 0.00047619048 | I48: 5000 | L48: 1000000 | M48: 0.005 | N48: =+M48*(L48-L47) -> 4500
H49: =+SUBTOTAL(9,H46:H48) -> 0.00058095238 | I49: =+SUBTOTAL(9,I46:I48) -> 6100 | L49: 5000000 | M49: 0.0025 | N49: =+M49*(L49-L48) -> 10000
L50: 10000000 | M50: 0.00225 | N50: =+M50*(L50-L49) -> 11250
F51: Title Insurance Policy | H51: =+I51/$I$32 -> 0.002602381 | I51: =+N46 -> 27325 | L51: =+H11 -> 10500000 | M51: 0.002 | N51: =+M51*(L51-L50) -> 1000
F53: Due Diligence / Third Party Reports
F54: Survey | H54: =+I54/$I$32 -> 0.00052380952 | I54: 5500
F55: ESA | H55: =+I55/$I$32 -> 0.00033333333 | I55: 3500
F56: PCA | H56: =+I56/$I$32 -> 0.00038095238 | I56: 4000
F57: Appraisal Fee | H57: =+I57/$I$32 -> 0.00042857143 | I57: 4500
F58: Zoning Report | H58: =+I58/$I$32 -> 0.00023809524 | I58: 2500
H59: =+SUBTOTAL(9,H54:H58) -> 0.0019047619 | I59: =+SUBTOTAL(9,I54:I58) -> 20000
F61: Total Closing Costs | H61: =+I61/$I$32 -> 0.021397619 | I61: =+SUBTOTAL(9,I34:I60) -> 224675

Sheet CapEx
B2: TOPAZ VILLAGE
B3: HISTORICAL CAPITAL EXPENDITURES UNDER CURRENT OWNERSHIP
B5: CapEx Schedule | D5: 2018 | E5: 2019 | F5: 2020 | G5: 2021 | H5: 2022 | I5: 2023 | J5: 2024 | K5: YTD thru 7/31/25 | L5: Total
B9: COMMON ITEMS
B10: Water Heaters | D10: 5977 | E10: 8712 | F10: 5624 | G10: 5519 | H10: 2514 | I10: 4370 | J10: 1964 | K10: 4218 | L10: =+SUM(D10:K10) -> 38898
B11: Plumbing | D11: 111 | E11: 23463 | F11: 2132 | G11: 14401 | H11: 1100 | I11: 16645 | J11: 12500 | K11: 5275 | L11: =+SUM(D11:K11) -> 75627
B12: Electrical | D12: 5757 | E12: 5696 | F12: 4378 | G12: 1716 | H12: 1686 | I12: 2241 | J12: 3406 | K12: 0 | L12: =+SUM(D12:K12) -> 24880
D13: =+SUBTOTAL(9,D10:D12) -> 11845 | E13: =+SUBTOTAL(9,E10:E12) -> 37871 | F13: =+SUBTOTAL(9,F10:F12) -> 12134 | G13: =+SUBTOTAL(9,G10:G12) -> 21636 | H13: =+SUBTOTAL(9,H10:H12) -> 5300 | I13: =+SUBTOTAL(9,I10:I12) -> 23256 | J13: =+SUBTOTAL(9,J10:J12) -> 17870 | K13: =+SUBTOTAL(9,K10:K12) -> 9493 | L13: =+SUBTOTAL(9,L10:L12) -> 139405
B15: COMMON AREA ITEMS
B16: Common Area Improvements | D16: 35465 | E16: 43825 | F16: 5919 | G16: 12525 | H16: 27267 | I16: 37031 | J16: 22923 | K16: 9453 | L16: =+SUM(D16:K16) -> 194408
B17: Trees and Landscaping | D17: 28754 | E17: 10350 | F17: 0 | G17: 4700 | H17: 16055 | I17: 19255 | J17: 5845 | K17: 0 | L17: =+SUM(D17:K17) -> 84959
B18: Asphalt | D18: 0 | E18: 41820 | F18: 0 | G18: 0 | H18: 0 | I18: 2296 | J18: 0 | K18: 8750 | L18: =+SUM(D18:K18) -> 52866
B19: Approved Capital Projects | D19: 4906 | E19: 19041 | F19: 0 | G19: 1772 | H19: 0 | I19: 0 | J19: 0 | K19: 0 | L19: =+SUM(D19:K19) -> 25719
B20: Laundry Room Equipment | D20: 0 | E20: 29000 | F20: 0 | G20: 0 | H20: 0 | I20: 0 | J20: 0 | K20: 0 | L20: =+SUM(D20:K20) -> 29000
B21: Fitness Room | D21: 0 | E21: 0 | F21: 13881 | G21: 0 | H21: 0 | I21: 0 | J21: 0 | K21: 0 | L21: =+SUM(D21:K21) -> 13881
B22: Amenities | D22: 0 | E22: 0 | F22: 0 | G22: 0 | H22: 2308 | I22: 4850 | J22: 1666 | K22: 0 | L22: =+SUM(D22:K22) -> 8824
B23: Clubhouse Renovation | D23: 11833 | E23: 0 | F23: 0 | G23: 0 | H23: 6589 | I23: 0 | J23: 0 | K23: 0 | L23: =+SUM(D23:K23) -> 18422
D24: =+SUBTOTAL(9,D16:D23) -> 80958 | E24: =+SUBTOTAL(9,E16:E23) -> 144036 | F24: =+SUBTOTAL(9,F16:F23) -> 19800 | G24: =+SUBTOTAL(9,G16:G23) -> 18997 | H24: =+SUBTOTAL(9,H16:H23) -> 52219 | I24: =+SUBTOTAL(9,I16:I23) -> 63432 | J24: =+SUBTOTAL(9,J16:J23) -> 30434 | K24: =+SUBTOTAL(9,K16:K23) -> 18203 | L24: =+SUBTOTAL(9,L16:L23) -> 428079
B26: BIG TICKET ITEMS
B27: HVAC Replacement | D27: 51911 | E27: 19582 | F27: 44356 | G27: 24958 | H27: 43503 | I27: 59832 | J27: 67875 | K27: 23721 | L27: =+SUM(D27:K27) -> 335738
B28: Roof Replacement | D28: 0 | E28: 0 | F28: 0 | G28: 0 | H28: 7100 | I28: 6000 | J28: 18361 | K28: 5000 | L28: =+SUM(D28:K28) -> 36461
D29: =+SUBTOTAL(9,D27:D28) -> 51911 | E29: =+SUBTOTAL(9,E27:E28) -> 19582 | F29: =+SUBTOTAL(9,F27:F28) -> 44356 | G29: =+SUBTOTAL(9,G27:G28) -> 24958 | H29: =+SUBTOTAL(9,H27:H28) -> 50603 | I29: =+SUBTOTAL(9,I27:I28) -> 65832 | J29: =+SUBTOTAL(9,J27:J28) -> 86236 | K29: =+SUBTOTAL(9,K27:K28) -> 28721 | L29: =+SUBTOTAL(9,L27:L28) -> 372199
B31: UNIT RENOVATIONS AND UPGRADES
B32: Unit Upgrade Capital - Appliances | D32: 22002 | E32: 47467 | F32: 34343 | G32: 24175 | H32: 35747 | I32: 31534 | J32: 16390 | K32: 19354 | L32: =+SUM(D32:K32) -> 231012
B33: Unit Upgrade Capital - General | D33: 75191 | E33: 434939 | F33: 127351 | G33: 3523 | H33: 4394 | I33: 1061 | J33: 3166 | K33: 9488 | L33: =+SUM(D33:K33) -> 659113
B34: Unit Upgrade Capital - Flooring | D34: 98983 | E34: 260132 | F34: 105365 | G34: 57498 | H34: 29279 | I34: 38116 | J34: 23809 | K34: 48748 | L34: =+SUM(D34:K34) -> 661930
D35: =+SUBTOTAL(9,D32:D34) -> 196176 | E35: =+SUBTOTAL(9,E32:E34) -> 742538 | F35: =+SUBTOTAL(9,F32:F34) -> 267059 | G35: =+SUBTOTAL(9,G32:G34) -> 85196 | H35: =+SUBTOTAL(9,H32:H34) -> 69420 | I35: =+SUBTOTAL(9,I32:I34) -> 70711 | J35: =+SUBTOTAL(9,J32:J34) -> 43365 | K35: =+SUBTOTAL(9,K32:K34) -> 77590 | L35: =+SUBTOTAL(9,L32:L34) -> 1552055
B37: Total | D37: =+SUBTOTAL(9,D10:D36) -> 340890 | E37: =+SUBTOTAL(9,E10:E36) -> 944027 | F37: =+SUBTOTAL(9,F10:F36) -> 343349 | G37: =+SUBTOTAL(9,G10:G36) -> 150787 | H37: =+SUBTOTAL(9,H10:H36) -> 177542 | I37: =+SUBTOTAL(9,I10:I36) -> 223231 | J37: =+SUBTOTAL(9,J10:J36) -> 177905 | K37: =+SUBTOTAL(9,K10:K36) -> 134007 | L37: =+SUBTOTAL(9,L10:L36) -> 2491738

Sheet Unit Mix
B3: Unit Mix
B8: Floorplan | C8: Average SQFT | D8: # Units | E8: # Occupied Units | F8: Occupancy % | G8: Average Market Rent | H8: Market Rent PSF | I8: Average In-Place Rent | J8: In-Place Rent PSF
B9: 1x1a | C9: 645 | D9: 62 | E9: 57 | F9: 0.9194 | G9: 1132.18 | H9: 1.76 | I9: 936.33 | J9: 1.45
B10: 1x1L | C10: 745 | D10: 44 | E10: 41 | F10: 0.9318 | G10: 1209.89 | H10: 1.62 | I10: 1016.39 | J10: 1.36
B11: 1x1L-C | C11: 745 | D11: 36 | E11: 33 | F11: 0.9167 | G11: 1222.08 | H11: 1.64 | I11: 1044.39 | J11: 1.4
B12: 2x1 | C12: 996 | D12: 2 | E12: 2 | F12: 1 | G12: 1335 | H12: 1.34 | I12: 1102.5 | J12: 1.11
B13: 2x1-C | C13: 996 | D13: 30 | E13: 30 | F13: 1 | G13: 1414 | H13: 1.42 | I13: 1197.37 | J13: 1.2
B14: 2x2 | C14: 1024 | D14: 1 | E14: 1 | F14: 1 | G14: 1440 | H14: 1.41 | I14: 1185 | J14: 1.16
B15: 2x2-C | C15: 1024 | D15: 51 | E15: 50 | F15: 0.9804 | G15: 1485.1 | H15: 1.45 | I15: 1242.56 | J15: 1.21
B16: 3x2 | C16: 1320 | D16: 32 | E16: 31 | F16: 0.9688 | G16: 1611.88 | H16: 1.22 | I16: 1422.77 | J16: 1.08
B17: Totals / Averages: | C17: 880 | D17: 258 | E17: 245 | F17: 0.9496 | G17: 1322.77 | H17: 1.5 | I17: 1122.67 | J17: 1.27

Sheet Sales Comps
C3: Sales Comps
I4: Transaction Details
C5: Property | D5: Address | E5: Distance to Subject (mi) | F5: Built/ Renovated | G5: Units | I5: Date | J5: Price | K5: Per Unit
C6: Lakewood Oaks | D6: 3534 Smithfield Rd | E6: 8.5 | F6: 1974 | G6: 138 | I6: 45323 | J6: 13370000 | K6: =+ROUND(J6/G6,-3) -> 97000
C7: Oasis Club | D7: 5800 University Blvd W | E7: 7.5 | F7: 1972/2000 | G7: 242 | I7: 45323 | J7: 26030000 | K7: =+ROUND(J7/G7,-3) -> 108000
C8: Magnolia Point | D8: 7507 Beach Blvd | E8: 6.37 | F8: 1973/1980 | G8: 227 | I8: 45323 | J8: 25830000 | K8: =+ROUND(J8/G8,-3) -> 114000
C9: Oakview Landing | D9: 7350 Blanding Blvd | E9: 13.95 | F9: 1974/2021 | G9: 216 | I9: 45658 | J9: 20300000 | K9: =+ROUND(J9/G9,-3) -> 94000
C10: Renaissance Strawberry Creek | D10: 7557 Arlington Expwy | E10: 3.76 | F10: 1969/2017 | G10: 195 | I10: 45778 | J10: 23358000 | K10: =+ROUND(J10/G10,-3) -> 120000
C11: Edenfield Shores | D11: 5885 Edenfield Rd | E11: 0.27 | F11: 1975/2017 | G11: 332 | I11: 45870 | J11: 37000000 | K11: =+ROUND(J11/G11,-3) -> 111000
C13: Total / Wtd Average | G13: =+SUM(G6:G12) -> 1350 | J13: =+SUM(J6:J12) -> 145888000 | K13: =+ROUND(J13/G13,-3) -> 108000
C15: SUBJECT* | D15: 5501 University Club Blvd N | E15: 0 | F15: 1975/2024 | G15: 258 | J15: =+'Sources & Uses'!C11 -> 14970000 | K15: =+ROUND(J15/G15,-3) -> 58000
C17: *Value based on proforma NOI using a market 6.2% cap rate

Sheet Rent Comps
C3: Rent Comps
C5: Property | D5: Address | E5: Distance to Subject (mi) | F5: Built/ Renovated | G5: Units | H5: Avg Unit Size (SF) | I5: Market Rent | J5: Market Rent PSF | K5: In-Place Rent | L5: In-Place Rent PSF | M5: Current Occupancy
C6: Townsend | D6: 3501 Townsend Blvd | E6: 2.03 | F6: 1970 | G6: 396 | H6: 1000 | I6: 1094 | J6: 1.09 | K6: 1094 | L6: 1.09 | M6: 0.91
C7: The Square at 59 Caroline | D7: 5959 Fort Caroline Rd | E7: =4791/5280 -> 0.90738636 | F7: 1972 | G7: 356 | H7: 960 | I7: 1107 | J7: 1.15 | K7: 1022 | L7: 1.06 | M7: 0.92
C8: Edenfield Shores | D8: 5885 Edenfield Rd | E8: 0.27 | F8: 1975/2017 | G8: 332 | H8: 983 | I8: 1233 | J8: 1.25 | K8: 1233 | L8: 1.25 | M8: 0.79
C9: Casa Bella | D9: 5791 University Club Blvd N | E9: =669/5280 -> 0.12670455 | F9: 1986 | G9: 168 | H9: 893 | I9: 1048 | J9: 1.17 | K9: 1048 | L9: 1.17 | M9: 0.99
C11: Total / Wtd Average | G11: =+SUM(G6:G10) -> 1252 | H11: =+SUMPRODUCT($G$6:$G$10,H$6:H$10)/$G11 -> 969.76038 | I11: =+SUMPRODUCT($G$6:$G$10,I$6:I$10)/$G11 -> 1128.3834 | J11: =+SUMPRODUCT($G$6:$G$10,J$6:J$10)/$G11 -> 1.1602236 | K11: =+SUMPRODUCT($G$6:$G$10,K$6:K$10)/$G11 -> 1104.2141 | L11: =+SUMPRODUCT($G$6:$G$10,L$6:L$10)/$G11 -> 1.1346326 | M11: =+SUMPRODUCT($G$6:$G$10,M$6:M$10)/$G11 -> 0.89175719
C13: SUBJECT | D13: 5501 University Club Blvd N | E13: 0 | F13: 1975/2024 | G13: 258 | H13: 880 | I13: 1323 | J13: 1.5 | K13: 1123 | L13: 1.27 | M13: 0.95

Sheet TTM Nov-25
B1: Income Statement - 12 Month
B2: Exported On: 12/10/2025 03:27 PM
B4: Atrium Management Company
B5: Properties: Oasis at San Marco - 4800 Atlantic Blvd Jacksonville, FL 32207
B6: Fund Type: All
B7: Period Range: Dec 2024 to Nov 2025 (Trailing 12 Months)
B8: Accounting Basis: Accrual
B9: GL Account Map: None - use master chart of accounts
B10: Level of Detail: Detail View
B11: Include Zero Balance GL Accounts: No
B13: Account Name | C13: Dec 2024 | D13: Jan 2025 | E13: Feb 2025 | F13: Mar 2025 | G13: Apr 2025 | H13: May 2025 | I13: Jun 2025 | J13: Jul 2025 | K13: Aug 2025 | L13: Sep 2025 | M13: Oct 2025 | N13: Nov 2025 | O13: Total | Q13: T1 | R13: T2 | S13: T3 | T13: T6 | U13: T12
B14: Operating Income & Expense
B15: Income
B16: Rental Income
A17: 1 | B17: Gross Potential Rent | C17: 144721.55 | D17: 146896.53 | E17: 147357.5 | F17: 147078 | G17: 147078 | H17: 147078 | I17: 154421 | J17: 155067.12 | K17: 142265.39 | L17: 136185.3 | M17: 139780.78 | N17: 143362 | O17: 1751291.2 | Q17: =+N17*12 -> 1720344 | R17: =+SUM(M17:N17)*6 -> 1698856.7 | S17: =+SUM(L17:N17)*4 -> 1677312.3 | T17: =+SUM(I17:N17)*2 -> 1742163.2 | U17: =+SUM(C17:N17) -> 1751291.2
A18: 1 | B18: Loss/Gain to Market | C18: -7553.26 | D18: -9302.88 | E18: -7219.92 | F18: -11409.39 | G18: -7196.23 | H18: -8458.77 | I18: -15965.57 | J18: -3498.54 | K18: -1535.7 | L18: 856.42 | M18: -158.9 | N18: -1700.4 | O18: -73143.14 | Q18: =+N18*12 -> -20404.8 | R18: =+SUM(M18:N18)*6 -> -11155.8 | S18: =+SUM(L18:N18)*4 -> -4011.52 | T18: =+SUM(I18:N18)*2 -> -44005.38 | U18: =+SUM(C18:N18) -> -73143.14
A19: 1 | B19: Concessions | C19: -100 | D19: -700 | E19: -1200 | F19: -320 | G19: -200 | H19: -1849 | I19: -1659 | J19: -1409 | K19: -5855 | L19: -17016.5 | M19: -19220.5 | N19: -11589.99 | O19: -61118.99 | Q19: =+N19*12 -> -139079.88 | R19: =+SUM(M19:N19)*6 -> -184862.94 | S19: =+SUM(L19:N19)*4 -> -191307.96 | T19: =+SUM(I19:N19)*2 -> -113499.98 | U19: =+SUM(C19:N19) -> -61118.99
A20: 3 | B20: Concessions - Recurring | C20: 0 | D20: 0 | E20: 0 | F20: 0 | G20: 0 | H20: 0 | I20: -200 | J20: -200 | K20: -200 | L20: -200 | M20: -200 | N20: -100 | O20: -1100 | Q20: =+N20*12 -> -1200 | R20: =+SUM(M20:N20)*6 -> -1800 | S20: =+SUM(L20:N20)*4 -> -2000 | T20: =+SUM(I20:N20)*2 -> -2200 | U20: =+SUM(C20:N20) -> -1100
A21: 3 | B21: Concessions - Employee Unit | C21: 0 | D21: 0 | E21: 0 | F21: 0 | G21: 0 | H21: 0 | I21: 0 | J21: 0 | K21: 0 | L21: -210 | M21: -210 | N21: -210 | O21: -630 | Q21: =+N21*12 -> -2520 | R21: =+SUM(M21:N21)*6 -> -2520 | S21: =+SUM(L21:N21)*4 -> -2520 | T21: =+SUM(I21:N21)*2 -> -1260 | U21: =+SUM(C21:N21) -> -630
A22: 2 | B22: Vacancy | C22: -29499.93 | D22: -25913.5 | E22: -24560.58 | F22: -19223.61 | G22: -25112.77 | H22: -26229.23 | I22: -29901.46 | J22: -37429.9 | K22: -34280.94 | L22: -17406.1 | M22: -5336.53 | N22: -8718.07 | O22: -283612.62 | Q22: =+N22*12 -> -104616.84 | R22: =+SUM(M22:N22)*6 -> -84327.6 | S22: =+SUM(L22:N22)*4 -> -125842.8 | T22: =+SUM(I22:N22)*2 -> -266146 | U22: =+SUM(C22:N22) -> -283612.62
A23: 4 | B23: Bad Debt - Contra | C23: -400 | D23: -22098.2 | E23: -1006 | F23: -20742.65 | G23: -26539.02 | H23: 0 | I23: 0 | J23: -3968 | K23: 0 | L23: -16661.19 | M23: -11674.07 | N23: 0 | O23: -103089.13 | Q23: =+N23*12 -> 0 | R23: =+SUM(M23:N23)*6 -> -70044.42 | S23: =+SUM(L23:N23)*4 -> -113341.04 | T23: =+SUM(I23:N23)*2 -> -64606.52 | U23: =+SUM(C23:N23) -> -103089.13
B24: Total Rental Income | C24: 107168.36 | D24: 88881.95 | E24: 113371 | F24: 95382.35 | G24: 88029.98 | H24: 110541 | I24: 106694.97 | J24: 108561.68 | K24: 100393.75 | L24: 85547.93 | M24: 102980.78 | N24: 121043.54 | O24: 1228597.3 | Q24: =+N24*12 -> 1452522.5 | R24: =+SUM(M24:N24)*6 -> 1344145.9 | S24: =+SUM(L24:N24)*4 -> 1238289 | T24: =+SUM(I24:N24)*2 -> 1250445.3 | U24: =+SUM(C24:N24) -> 1228597.3
B25: Other Income | Q25: =+N25*12 -> 0 | R25: =+SUM(M25:N25)*6 -> 0 | S25: =+SUM(L25:N25)*4 -> 0 | T25: =+SUM(I25:N25)*2 -> 0 | U25: =+SUM(C25:N25) -> 0
A26: 7 | B26: Lease Lock | C26: 1274 | D26: 1218 | E26: 0 | F26: 0 | G26: 0 | H26: 0 | I26: 0 | J26: 0 | K26: 0 | L26: 0 | M26: 0 | N26: 0 | O26: 2492 | Q26: =+N26*12 -> 0 | R26: =+SUM(M26:N26)*6 -> 0 | S26: =+SUM(L26:N26)*4 -> 0 | T26: =+SUM(I26:N26)*2 -> 0 | U26: =+SUM(C26:N26) -> 2492
A27: 7 | B27: NSF Fees Collected | C27: 0 | D27: 165 | E27: 275 | F27: 385 | G27: 55 | H27: 55 | I27: 0 | J27: 150 | K27: 0 | L27: -75 | M27: -75 | N27: 80 | O27: 1015 | Q27: =+N27*12 -> 960 | R27: =+SUM(M27:N27)*6 -> 30 | S27: =+SUM(L27:N27)*4 -> -280 | T27: =+SUM(I27:N27)*2 -> 160 | U27: =+SUM(C27:N27) -> 1015
A28: 7 | B28: Late Fee | C28: 2414.8 | D28: 2981 | E28: 3381.7 | F28: 3761.8 | G28: 3081.7 | H28: 3111.8 | I28: 4980.4 | J28: 250 | K28: 2429.16 | L28: 1850.19 | M28: 2271.56 | N28: 2299.95 | O28: 32814.06 | Q28: =+N28*12 -> 27599.4 | R28: =+SUM(M28:N28)*6 -> 27429.06 | S28: =+SUM(L28:N28)*4 -> 25686.8 | T28: =+SUM(I28:N28)*2 -> 28162.52 | U28: =+SUM(C28:N28) -> 32814.06
A29: 6 | B29: Utility Income | C29: 0 | D29: 0 | E29: 0 | F29: 0 | G29: 0 | H29: 0 | I29: 0 | J29: 0 | K29: 9.03 | L29: -9.03 | M29: 0 | N29: 0 | O29: 0 | Q29: =+N29*12 -> 0 | R29: =+SUM(M29:N29)*6 -> 0 | S29: =+SUM(L29:N29)*4 -> -36.12 | T29: =+SUM(I29:N29)*2 -> 0 | U29: =+SUM(C29:N29) -> 0
A30: 6 | B30: Electricity Income | C30: 95 | D30: 95 | E30: 95 | F30: 95 | G30: 95 | H30: 95 | I30: 0 | J30: 0 | K30: 0 | L30: 0 | M30: 0 | N30: 0 | O30: 570 | Q30: =+N30*12 -> 0 | R30: =+SUM(M30:N30)*6 -> 0 | S30: =+SUM(L30:N30)*4 -> 0 | T30: =+SUM(I30:N30)*2 -> 0 | U30: =+SUM(C30:N30) -> 570
A31: 6 | B31: Utility Reimbursements | C31: 6794 | D31: 7216 | E31: 7099 | F31: 7482 | G31: 7122 | H31: 7077 | I31: 6398.33 | J31: 6302.77 | K31: 5980.56 | L31: 7009.03 | M31: 7576.96 | N31: 7558.96 | O31: 83616.61 | Q31: =+N31*12 -> 90707.52 | R31: =+SUM(M31:N31)*6 -> 90815.52 | S31: =+SUM(L31:N31)*4 -> 88579.8 | T31: =+SUM(I31:N31)*2 -> 81653.22 | U31: =+SUM(C31:N31) -> 83616.61
A32: 7 | B32: Resident Liability & Contents Coverage | C32: 588 | D32: 661.5 | E32: 735 | F32: 756 | G32: 766.5 | H32: 724.5 | I32: -15.5 | J32: 258.5 | K32: 161 | L32: -107.92 | M32: -58.08 | N32: 263.22 | O32: 4732.72 | Q32: =+N32*12 -> 3158.64 | R32: =+SUM(M32:N32)*6 -> 1230.84 | S32: =+SUM(L32:N32)*4 -> 388.88 | T32: =+SUM(I32:N32)*2 -> 1002.44 | U32: =+SUM(C32:N32) -> 4732.72
A33: 7 | B33: 1st month - Resident Liability & Contents Coverage | C33: 0 | D33: 0 | E33: 0 | F33: 0 | G33: 0 | H33: 0 | I33: 26.52 | J33: -13.52 | K33: -13 | L33: -13 | M33: 0 | N33: 0 | O33: -13 | Q33: =+N33*12 -> 0 | R33: =+SUM(M33:N33)*6 -> 0 | S33: =+SUM(L33:N33)*4 -> -52 | T33: =+SUM(I33:N33)*2 -> -26 | U33: =+SUM(C33:N33) -> -13
A34: 7 | B34: AppFolio Insurance Admin Fee | C34: -382.5 | D34: -428 | E34: -505 | F34: -563 | G34: -581.5 | H34: -1366 | I34: 0 | J34: 0 | K34: 0 | L34: 0 | M34: 0 | N34: 0 | O34: -3826 | Q34: =+N34*12 -> 0 | R34: =+SUM(M34:N34)*6 -> 0 | S34: =+SUM(L34:N34)*4 -> 0 | T34: =+SUM(I34:N34)*2 -> 0 | U34: =+SUM(C34:N34) -> -3826
A35: 7 | B35: Pet Fee - Non Refundable | C35: 0 | D35: 0 | E35: 0 | F35: 0 | G35: 300 | H35: 0 | I35: 0 | J35: 0 | K35: 0 | L35: 0 | M35: 0 | N35: 0 | O35: 300 | Q35: =+N35*12 -> 0 | R35: =+SUM(M35:N35)*6 -> 0 | S35: =+SUM(L35:N35)*4 -> 0 | T35: =+SUM(I35:N35)*2 -> 0 | U35: =+SUM(C35:N35) -> 300
A36: 7 | B36: Bad Debt Recovery | C36: 0 | D36: 0 | E36: 0 | F36: 0 | G36: 162.71 | H36: 14.55 | I36: 0 | J36: 0 | K36: 0 | L36: 0 | M36: 0 | N36: 0 | O36: 177.26 | Q36: =+N36*12 -> 0 | R36: =+SUM(M36:N36)*6 -> 0 | S36: =+SUM(L36:N36)*4 -> 0 | T36: =+SUM(I36:N36)*2 -> 0 | U36: =+SUM(C36:N36) -> 177.26
A37: 7 | B37: Pet Application Fee | C37: 0 | D37: 0 | E37: 0 | F37: 0 | G37: 0 | H37: 222 | I37: 0 | J37: 0 | K37: 0 | L37: 0 | M37: 0 | N37: 0 | O37: 222 | Q37: =+N37*12 -> 0 | R37: =+SUM(M37:N37)*6 -> 0 | S37: =+SUM(L37:N37)*4 -> 0 | T37: =+SUM(I37:N37)*2 -> 0 | U37: =+SUM(C37:N37) -> 222
... A58: 7 | B58: Bad Debt - Contra Other Income | C58: 0 | D58: 0 | E58: 0 | F58: 0 | G58: 0 | H58: 0 | I58: 0 | J58: -727 | K58: 0 | L58: -2964 | M58: -3628 | N58: -6 | O58: -7325 | Q58: =+N58*12 -> -72 | R58: =+SUM(M58:N58)*6 -> -21804 | S58: =+SUM(L58:N58)*4 -> -26392 | T58: =+SUM(I58:N58)*2 -> -14650 | U58: =+SUM(C58:N58) -> -7325
B59: Total Other Income | C59: 17493.8 | D59: 19106.8 | E59: 15144.7 | F59: 21278.91 | G59: 27756.41 | H59: 18138.44 | I59: 16538.85 | J59: 11410.24 | K59: 14422.98 | L59: 13112.8 | M59: 13988.72 | N59: 17456.19 | O59: 205848.84 | Q59: =+N59*12 -> 209474.28 | R59: =+SUM(M59:N59)*6 -> 188669.46 | S59: =+SUM(L59:N59)*4 -> 178230.84 | T59: =+SUM(I59:N59)*2 -> 173859.56 | U59: =+SUM(C59:N59) -> 205848.84
B60: Total Operating Income | C60: 124662.16 | D60: 107988.75 | E60: 128515.7 | F60: 116661.26 | G60: 115786.39 | H60: 128679.44 | I60: 123233.82 | J60: 119971.92 | K60: 114816.73 | L60: 98660.73 | M60: 116969.5 | N60: 138499.73 | O60: 1434446.1 | Q60: =+N60*12 -> 1661996.8 | R60: =+SUM(M60:N60)*6 -> 1532815.4 | S60: =+SUM(L60:N60)*4 -> 1416519.8 | T60: =+SUM(I60:N60)*2 -> 1424304.9 | U60: =+SUM(C60:N60) -> 1434446.1
B61: Expense | Q61: =+N61*12 -> 0 | R61: =+SUM(M61:N61)*6 -> 0 | S61: =+SUM(L61:N61)*4 -> 0 | T61: =+SUM(I61:N61)*2 -> 0 | U61: =+SUM(C61:N61) -> 0
B62: Management Fee Expenses | Q62: =+N62*12 -> 0 | R62: =+SUM(M62:N62)*6 -> 0 | S62: =+SUM(L62:N62)*4 -> 0 | T62: =+SUM(I62:N62)*2 -> 0 | U62: =+SUM(C62:N62) -> 0
A63: 17 | B63: Management Fees | C63: 15433 | D63: 16178 | E63: 16327 | F63: 16625 | G63: 16923 | H63: 13046.18 | I63: 0 | J63: 0 | K63: 0 | L63: 0 | M63: 0 | N63: 0 | O63: 94532.18 | Q63: =+N63*12 -> 0 | R63: =+SUM(M63:N63)*6 -> 0 | S63: =+SUM(L63:N63)*4 -> 0 | T63: =+SUM(I63:N63)*2 -> 0 | U63: =+SUM(C63:N63) -> 94532.18
A64: 8 | B64: Lease Renewal Fee | C64: 450 | D64: 900 | E64: 1200 | F64: 450 | G64: 0 | H64: 1050 | I64: 0 | J64: 0 | K64: 0 | L64: 0 | M64: 0 | N64: 0 | O64: 4050 | Q64: =+N64*12 -> 0 | R64: =+SUM(M64:N64)*6 -> 0 | S64: =+SUM(L64:N64)*4 -> 0 | T64: =+SUM(I64:N64)*2 -> 0 | U64: =+SUM(C64:N64) -> 4050
A65: 17 | B65: Management Fee - Multifamily | C65: 0 | D65: 0 | E65: 0 | F65: 0 | G65: 0 | H65: 0 | I65: 4500 | J65: 4500 | K65: 4500 | L65: 4500 | M65: 4500 | N65: 4500 | O65: 27000 | Q65: =+N65*12 -> 54000 | R65: =+SUM(M65:N65)*6 -> 54000 | S65: =+SUM(L65:N65)*4 -> 54000 | T65: =+SUM(I65:N65)*2 -> 54000 | U65: =+SUM(C65:N65) -> 27000
B66: Total Management Fee Expenses | C66: 15883 | D66: 17078 | E66: 17527 | F66: 17075 | G66: 16923 | H66: 14096.18 | I66: 4500 | J66: 4500 | K66: 4500 | L66: 4500 | M66: 4500 | N66: 4500 | O66: 125582.18 | Q66: =+N66*12 -> 54000 | R66: =+SUM(M66:N66)*6 -> 54000 | S66: =+SUM(L66:N66)*4 -> 54000 | T66: =+SUM(I66:N66)*2 -> 54000 | U66: =+SUM(C66:N66) -> 125582.18
B67: Admin Expenses | Q67: =+N67*12 -> 0 | R67: =+SUM(M67:N67)*6 -> 0 | S67: =+SUM(L67:N67)*4 -> 0 | T67: =+SUM(I67:N67)*2 -> 0 | U67: =+SUM(C67:N67) -> 0
B68: Property Inspections | C68: 45 | D68: 0 | E68: 0 | F68: 0 | G68: 0 | H68: 0 | I68: 0 | J68: 0 | K68: 0 | L68: 0 | M68: 0 | N68: 0 | O68: 45 | Q68: =+N68*12 -> 0 | R68: =+SUM(M68:N68)*6 -> 0 | S68: =+SUM(L68:N68)*4 -> 0 | T68: =+SUM(I68:N68)*2 -> 0 | U68: =+SUM(C68:N68) -> 45
B69: Payment Processing Fees | C69: 0 | D69: 0 | E69: 0 | F69: 0 | G69: 0 | H69: 0 | I69: 0 | J69: 1430.6 | K69: 0 | L69: 0 | M69: 0 | N69: 0 | O69: 1430.6 | Q69: =+N69*12 -> 0 | R69: =+SUM(M69:N69)*6 -> 0 | S69: =+SUM(L69:N69)*4 -> 0 | T69: =+SUM(I69:N69)*2 -> 2861.2 | U69: =+SUM(C69:N69) -> 1430.6
B70: Telephone Expense | C70: 133.84 | D70: 398.15 | E70: 138.15 | F70: 138.15 | G70: 138.01 | H70: 138 | I70: 138.01 | J70: 133 | K70: 158.07 | L70: 145.58 | M70: 138.36 | N70: 138.36 | O70: 1935.68 | Q70: =+N70*12 -> 1660.32 | R70: =+SUM(M70:N70)*6 -> 1660.32 | S70: =+SUM(L70:N70)*4 -> 1689.2 | T70: =+SUM(I70:N70)*2 -> 1702.76 | U70: =+SUM(C70:N70) -> 1935.68
B71: Memberships/Professional Organizations | C71: 0 | D71: 0 | E71: 0 | F71: 0 | G71: 0 | H71: 0 | I71: 264.32 | J71: 0 | K71: 0 | L71: 0 | M71: 0 | N71: 0 | O71: 264.32 | Q71: =+N71*12 -> 0 | R71: =+SUM(M71:N71)*6 -> 0 | S71: =+SUM(L71:N71)*4 -> 0 | T71: =+SUM(I71:N71)*2 -> 528.64 | U71: =+SUM(C71:N71) -> 264.32
B72: Uniforms | C72: 0 | D72: 0 | E72: 0 | F72: 0 | G72: 0 | H72: 0 | I72: 0 | J72: 300 | K72: 0 | L72: 0 | M72: 0 | N72: 0 | O72: 300 | Q72: =+N72*12 -> 0 | R72: =+SUM(M72:N72)*6 -> 0 | S72: =+SUM(L72:N72)*4 -> 0 | T72: =+SUM(I72:N72)*2 -> 600 | U72: =+SUM(C72:N72) -> 300
B73: Legal Fees - Retail | C73: 438.5 | D73: 354 | E73: 0 | F73: 0 | G73: 0 | H73: 926 | I73: 0 | J73: 0 | K73: 0 | L73: 0 | M73: 0 | N73: 0 | O73: 1718.5 | Q73: =+N73*12 -> 0 | R73: =+SUM(M73:N73)*6 -> 0 | S73: =+SUM(L73:N73)*4 -> 0 | T73: =+SUM(I73:N73)*2 -> 0 | U73: =+SUM(C73:N73) -> 1718.5
B74: Office Rent | C74: 0 | D74: 0 | E74: 0 | F74: 0 | G74: 0 | H74: 0 | I74: 0 | J74: 0 | K74: 0 | L74: 0 | M74: 32.87 | N74: 0 | O74: 32.87 | Q74: =+N74*12 -> 0 | R74: =+SUM(M74:N74)*6 -> 197.22 | S74: =+SUM(L74:N74)*4 -> 131.48 | T74: =+SUM(I74:N74)*2 -> 65.74 | U74: =+SUM(C74:N74) -> 32.87
B75: Office Supplies | C75: 200 | D75: 0 | E75: 0 | F75: 0 | G75: 80.6 | H75: 0 | I75: 253.43 | J75: 47.92 | K75: 64.49 | L75: 0 | M75: 90.33 | N75: 0 | O75: 736.77 | Q75: =+N75*12 -> 0 | R75: =+SUM(M75:N75)*6 -> 541.98 | S75: =+SUM(L75:N75)*4 -> 361.32 | T75: =+SUM(I75:N75)*2 -> 912.34 | U75: =+SUM(C75:N75) -> 736.77
B76: Marketing - Entertainment | C76: 0 | D76: 0 | E76: 0 | F76: 0 | G76: 0 | H76: 0 | I76: 0 | J76: 0 | K76: 0 | L76: 0 | M76: 277.36 | N76: 0 | O76: 277.36 | Q76: =+N76*12 -> 0 | R76: =+SUM(M76:N76)*6 -> 1664.16 | S76: =+SUM(L76:N76)*4 -> 1109.44 | T76: =+SUM(I76:N76)*2 -> 554.72 | U76: =+SUM(C76:N76) -> 277.36
B77: Bank Fees | C77: 0 | D77: 0 | E77: 195 | F77: 0 | G77: 0 | H77: 0 | I77: 0 | J77: 0 | K77: 0 | L77: 0 | M77: 0 | N77: 0 | O77: 195 | Q77: =+N77*12 -> 0 | R77: =+SUM(M77:N77)*6 -> 0 | S77: =+SUM(L77:N77)*4 -> 0 | T77: =+SUM(I77:N77)*2 -> 0 | U77: =+SUM(C77:N77) -> 195
B78: Office Miscellaneous Expenses | C78: 0 | D78: 0 | E78: 0 | F78: 0 | G78: 0 | H78: 0 | I78: 0 | J78: 483.64 | K78: 0 | L78: 0 | M78: 0 | N78: 48.58 | O78: 532.22 | Q78: =+N78*12 -> 582.96 | R78: =+SUM(M78:N78)*6 -> 291.48 | S78: =+SUM(L78:N78)*4 -> 194.32 | T78: =+SUM(I78:N78)*2 -> 1064.44 | U78: =+SUM(C78:N78) -> 532.22
B79: Legal Expenses | C79: 0 | D79: 0 | E79: 0 | F79: 0 | G79: 0 | H79: 0 | I79: 204 | J79: 926 | K79: 1001 | L79: 0 | M79: 102 | N79: 0 | O79: 2233 | Q79: =+N79*12 -> 0 | R79: =+SUM(M79:N79)*6 -> 612 | S79: =+SUM(L79:N79)*4 -> 408 | T79: =+SUM(I79:N79)*2 -> 4466 | U79: =+SUM(C79:N79) -> 2233
... B91: Staff-Meals/Entertainment | C91: 2.84 | D91: 0 | E91: 0 | F91: 0 | G91: 0 | H91: 0 | I91: 75.23 | J91: 0 | K91: 0 | L91: 0 | M91: 0 | N91: 0 | O91: 78.07 | Q91: =+N91*12 -> 0 | R91: =+SUM(M91:N91)*6 -> 0 | S91: =+SUM(L91:N91)*4 -> 0 | T91: =+SUM(I91:N91)*2 -> 150.46 | U91: =+SUM(C91:N91) -> 78.07
A92: 9 | B92: Total Admin Expenses | C92: 15475.18 | D92: 2053.87 | E92: 3083.15 | F92: 1202.65 | G92: 6798.96 | H92: 7542.87 | I92: 1458.99 | J92: 9822.95 | K92: 3470.28 | L92: 1775.6 | M92: 2899.94 | N92: 1765.76 | O92: 57350.2 | Q92: =+N92*12 -> 21189.12 | R92: =+SUM(M92:N92)*6 -> 27994.2 | S92: =+SUM(L92:N92)*4 -> 25765.2 | T92: =+SUM(I92:N92)*2 -> 42387.04 | U92: =+SUM(C92:N92) -> 57350.2
B93: Turn Costs | Q93: =+N93*12 -> 0 | R93: =+SUM(M93:N93)*6 -> 0 | S93: =+SUM(L93:N93)*4 -> 0 | T93: =+SUM(I93:N93)*2 -> 0 | U93: =+SUM(C93:N93) -> 0
B94: Carpet/ Floor Replacement - Turns | C94: 0 | D94: 0 | E94: 0 | F94: 0 | G94: 0 | H94: 0 | I94: 0 | J94: 0 | K94: 0 | L94: 1715.42 | M94: 0 | N94: 514.16 | O94: 2229.58 | Q94: =+N94*12 -> 6169.92 | R94: =+SUM(M94:N94)*6 -> 3084.96 | S94: =+SUM(L94:N94)*4 -> 8918.32 | T94: =+SUM(I94:N94)*2 -> 4459.16 | U94: =+SUM(C94:N94) -> 2229.58
B95: Painting Turn | C95: 1720.67 | D95: 4650 | E95: 1333.7 | F95: 1558.63 | G95: 0 | H95: 0 | I95: 0 | J95: 0 | K95: 670.77 | L95: 290 | M95: 0 | N95: 509.3 | O95: 10733.07 | Q95: =+N95*12 -> 6111.6 | R95: =+SUM(M95:N95)*6 -> 3055.8 | S95: =+SUM(L95:N95)*4 -> 3197.2 | T95: =+SUM(I95:N95)*2 -> 2940.14 | U95: =+SUM(C95:N95) -> 10733.07
B96: Cleaning/Janitorial Turn | C96: 1160 | D96: 1261.33 | E96: 386.54 | F96: 985 | G96: 1870 | H96: 2420 | I96: 0 | J96: 0 | K96: 236.03 | L96: 1540.36 | M96: 2190.01 | N96: 235 | O96: 12284.27 | Q96: =+N96*12 -> 2820 | R96: =+SUM(M96:N96)*6 -> 14550.06 | S96: =+SUM(L96:N96)*4 -> 15861.48 | T96: =+SUM(I96:N96)*2 -> 8402.8 | U96: =+SUM(C96:N96) -> 12284.27
B97: Key/Lock Turn | C97: 19.95 | D97: 0 | E97: 80.3 | F97: 0 | G97: 0 | H97: -31.98 | I97: 0 | J97: 0 | K97: 0 | L97: 0 | M97: 0 | N97: 0 | O97: 68.27 | Q97: =+N97*12 -> 0 | R97: =+SUM(M97:N97)*6 -> 0 | S97: =+SUM(L97:N97)*4 -> 0 | T97: =+SUM(I97:N97)*2 -> 0 | U97: =+SUM(C97:N97) -> 68.27
B98: Carpet/Tile Cleaning - Turns | C98: 200 | D98: 0 | E98: 0 | F98: 0 | G98: 125 | H98: 980 | I98: 0 | J98: 0 | K98: 0 | L98: 0 | M98: 515 | N98: 0 | O98: 1820 | Q98: =+N98*12 -> 0 | R98: =+SUM(M98:N98)*6 -> 3090 | S98: =+SUM(L98:N98)*4 -> 2060 | T98: =+SUM(I98:N98)*2 -> 1030 | U98: =+SUM(C98:N98) -> 1820
B99: Turn Repairs R&M | C99: 0 | D99: 0 | E99: 0 | F99: 0 | G99: 0 | H99: 0 | I99: 0 | J99: 0 | K99: 152 | L99: 5140 | M99: 61.19 | N99: 0 | O99: 5353.19 | Q99: =+N99*12 -> 0 | R99: =+SUM(M99:N99)*6 -> 367.14 | S99: =+SUM(L99:N99)*4 -> 20804.76 | T99: =+SUM(I99:N99)*2 -> 10706.38 | U99: =+SUM(C99:N99) -> 5353.19
B100: Tub/Shower Resurfacing - Turns | C100: 0 | D100: 0 | E100: 560 | F100: 4100 | G100: 0 | H100: 6260 | I100: 0 | J100: 0 | K100: 2245 | L100: 0 | M100: 0 | N100: 0 | O100: 13165 | Q100: =+N100*12 -> 0 | R100: =+SUM(M100:N100)*6 -> 0 | S100: =+SUM(L100:N100)*4 -> 0 | T100: =+SUM(I100:N100)*2 -> 4490 | U100: =+SUM(C100:N100) -> 13165
A101: 13 | B101: Total Turn Costs | C101: 3100.62 | D101: 5911.33 | E101: 2360.54 | F101: 6643.63 | G101: 1995 | H101: 9628.02 | I101: 0 | J101: 0 | K101: 3303.8 | L101: 8685.78 | M101: 2766.2 | N101: 1258.46 | O101: 45653.38 | Q101: =+N101*12 -> 15101.52 | R101: =+SUM(M101:N101)*6 -> 24147.96 | S101: =+SUM(L101:N101)*4 -> 50841.76 | T101: =+SUM(I101:N101)*2 -> 32028.48 | U101: =+SUM(C101:N101) -> 45653.38
B102: Advertising | Q102: =+N102*12 -> 0 | R102: =+SUM(M102:N102)*6 -> 0 | S102: =+SUM(L102:N102)*4 -> 0 | T102: =+SUM(I102:N102)*2 -> 0 | U102: =+SUM(C102:N102) -> 0
B103: Advertising - General | C103: 645 | D103: 645 | E103: 667.17 | F103: 682.98 | G103: 1175 | H103: 1820 | I103: 0 | J103: 0 | K103: 0 | L103: 0 | M103: 0 | N103: 0 | O103: 5635.15 | Q103: =+N103*12 -> 0 | R103: =+SUM(M103:N103)*6 -> 0 | S103: =+SUM(L103:N103)*4 -> 0 | T103: =+SUM(I103:N103)*2 -> 0 | U103: =+SUM(C103:N103) -> 5635.15
B104: Website | C104: 0 | D104: 0 | E104: 0 | F104: 0 | G104: 0 | H104: 0 | I104: 1950 | J104: 0 | K104: 0 | L104: 0 | M104: 0 | N104: 0 | O104: 1950 | Q104: =+N104*12 -> 0 | R104: =+SUM(M104:N104)*6 -> 0 | S104: =+SUM(L104:N104)*4 -> 0 | T104: =+SUM(I104:N104)*2 -> 3900 | U104: =+SUM(C104:N104) -> 1950
B105: Resident Referral Fees | C105: 0 | D105: 0 | E105: 0 | F105: 0 | G105: 0 | H105: 0 | I105: 0 | J105: 0 | K105: 600 | L105: 750 | M105: 0 | N105: 250 | O105: 1600 | Q105: =+N105*12 -> 3000 | R105: =+SUM(M105:N105)*6 -> 1500 | S105: =+SUM(L105:N105)*4 -> 4000 | T105: =+SUM(I105:N105)*2 -> 3200 | U105: =+SUM(C105:N105) -> 1600
B106: Marketing / Promotions | C106: 0 | D106: 0 | E106: 0 | F106: 0 | G106: 0 | H106: 0 | I106: 0 | J106: 429.38 | K106: 0 | L106: -79.03 | M106: 69 | N106: 0 | O106: 419.35 | Q106: =+N106*12 -> 0 | R106: =+SUM(M106:N106)*6 -> 414 | S106: =+SUM(L106:N106)*4 -> -40.12 | T106: =+SUM(I106:N106)*2 -> 838.7 | U106: =+SUM(C106:N106) -> 419.35
B107: Resident Refreshments and Events | C107: 0 | D107: 0 | E107: 0 | F107: 0 | G107: 0 | H107: 0 | I107: 0 | J107: 0 | K107: 373.23 | L107: 0 | M107: 0 | N107: 0 | O107: 373.23 | Q107: =+N107*12 -> 0 | R107: =+SUM(M107:N107)*6 -> 0 | S107: =+SUM(L107:N107)*4 -> 0 | T107: =+SUM(I107:N107)*2 -> 746.46 | U107: =+SUM(C107:N107) -> 373.23
B108: Model Expense | C108: 0 | D108: 0 | E108: 0 | F108: 0 | G108: 0 | H108: 0 | I108: 0 | J108: 0 | K108: 0 | L108: 163.95 | M108: 0 | N108: 0 | O108: 163.95 | Q108: =+N108*12 -> 0 | R108: =+SUM(M108:N108)*6 -> 0 | S108: =+SUM(L108:N108)*4 -> 655.8 | T108: =+SUM(I108:N108)*2 -> 327.9 | U108: =+SUM(C108:N108) -> 163.95
B109: Apartments.com | C109: 0 | D109: 0 | E109: 0 | F109: 0 | G109: 0 | H109: 0 | I109: 2940.39 | J109: 2532 | K109: 2832 | L109: 2832 | M109: 2832 | N109: 2832 | O109: 16800.39 | Q109: =+N109*12 -> 33984 | R109: =+SUM(M109:N109)*6 -> 33984 | S109: =+SUM(L109:N109)*4 -> 33984 | T109: =+SUM(I109:N109)*2 -> 33600.78 | U109: =+SUM(C109:N109) -> 16800.39
B110: Zillow | C110: 0 | D110: 0 | E110: 0 | F110: 0 | G110: 0 | H110: 0 | I110: 800.65 | J110: 730 | K110: 730 | L110: 730 | M110: 730 | N110: 730 | O110: 4450.65 | Q110: =+N110*12 -> 8760 | R110: =+SUM(M110:N110)*6 -> 8760 | S110: =+SUM(L110:N110)*4 -> 8760 | T110: =+SUM(I110:N110)*2 -> 8901.3 | U110: =+SUM(C110:N110) -> 4450.65
A111: 10 | B111: Total Advertising | C111: 645 | D111: 645 | E111: 667.17 | F111: 682.98 | G111: 1175 | H111: 1820 | I111: 5691.04 | J111: 3691.38 | K111: 4535.23 | L111: 4396.92 | M111: 3631 | N111: 3812 | O111: 31392.72 | Q111: =+N111*12 -> 45744 | R111: =+SUM(M111:N111)*6 -> 44658 | S111: =+SUM(L111:N111)*4 -> 47359.68 | T111: =+SUM(I111:N111)*2 -> 51515.14 | U111: =+SUM(C111:N111) -> 31392.72
B112: Repairs and Maintenance | Q112: =+N112*12 -> 0 | R112: =+SUM(M112:N112)*6 -> 0 | S112: =+SUM(L112:N112)*4 -> 0 | T112: =+SUM(I112:N112)*2 -> 0 | U112: =+SUM(C112:N112) -> 0
B113: HVAC (Heat, Ventilation, Air) R&M | C113: 776.97 | D113: 704.69 | E113: 234.76 | F113: 960 | G113: 0 | H113: 1475.28 | I113: 1205.79 | J113: 502.98 | K113: 2330 | L113: 818.79 | M113: 2001.93 | N113: 45.12 | O113: 11056.31 | Q113: =+N113*12 -> 541.44 | R113: =+SUM(M113:N113)*6 -> 12282.3 | S113: =+SUM(L113:N113)*4 -> 11463.36 | T113: =+SUM(I113:N113)*2 -> 13809.22 | U113: =+SUM(C113:N113) -> 11056.31
B114: Plumbing R&M | C114: 3414.03 | D114: 532.35 | E114: 511.46 | F114: 2075.99 | G114: 0 | H114: 861.56 | I114: 2205.25 | J114: 0 | K114: 1872.8 | L114: 2179.47 | M114: 601.88 | N114: 3883.34 | O114: 18138.13 | Q114: =+N114*12 -> 46600.08 | R114: =+SUM(M114:N114)*6 -> 26911.32 | S114: =+SUM(L114:N114)*4 -> 26658.76 | T114: =+SUM(I114:N114)*2 -> 21485.48 | U114: =+SUM(C114:N114) -> 18138.13
B115: Electrical R&M | C115: 610 | D115: 775 | E115: 205.3 | F115: 0 | G115: 650 | H115: 0 | I115: 309.3 | J115: 0 | K115: 0 | L115: 0 | M115: 0 | N115: 0 | O115: 2549.6 | Q115: =+N115*12 -> 0 | R115: =+SUM(M115:N115)*6 -> 0 | S115: =+SUM(L115:N115)*4 -> 0 | T115: =+SUM(I115:N115)*2 -> 618.6 | U115: =+SUM(C115:N115) -> 2549.6
B116: Roof R&M | C116: 1500 | D116: 1500 | E116: 750 | F116: 0 | G116: 0 | H116: 800 | I116: 0 | J116: 0 | K116: 645 | L116: 0 | M116: 396.41 | N116: 0 | O116: 5591.41 | Q116: =+N116*12 -> 0 | R116: =+SUM(M116:N116)*6 -> 2378.46 | S116: =+SUM(L116:N116)*4 -> 1585.64 | T116: =+SUM(I116:N116)*2 -> 2082.82 | U116: =+SUM(C116:N116) -> 5591.41
B117: Supplies R&M | C117: 1009.81 | D117: 510.19 | E117: 1369.28 | F117: 1819.9 | G117: 674.13 | H117: 4162.29 | I117: 857 | J117: 0 | K117: 0 | L117: 0 | M117: 0 | N117: 209.99 | O117: 10612.59 | Q117: =+N117*12 -> 2519.88 | R117: =+SUM(M117:N117)*6 -> 1259.94 | S117: =+SUM(L117:N117)*4 -> 839.96 | T117: =+SUM(I117:N117)*2 -> 2133.98 | U117: =+SUM(C117:N117) -> 10612.59
B118: Window and Screen R&M | C118: 0 | D118: 0 | E118: 0 | F118: 0 | G118: 1405 | H118: 954.6 | I118: 0 | J118: 0 | K118: 0 | L118: 633.25 | M118: 0 | N118: 1225 | O118: 4217.85 | Q118: =+N118*12 -> 14700 | R118: =+SUM(M118:N118)*6 -> 7350 | S118: =+SUM(L118:N118)*4 -> 7433 | T118: =+SUM(I118:N118)*2 -> 3716.5 | U118: =+SUM(C118:N118) -> 4217.85
B119: Repair R&M | C119: 266.61 | D119: 0 | E119: 125 | F119: -105 | G119: 0 | H119: 0 | I119: 1123.32 | J119: 161.49 | K119: 397.86 | L119: 953.46 | M119: 1018.7 | N119: 1322.35 | O119: 5263.79 | Q119: =+N119*12 -> 15868.2 | R119: =+SUM(M119:N119)*6 -> 14046.3 | S119: =+SUM(L119:N119)*4 -> 13178.04 | T119: =+SUM(I119:N119)*2 -> 9954.36 | U119: =+SUM(C119:N119) -> 5263.79
B120: Equipment/Tools R&M | C120: 0 | D120: 0 | E120: -118 | F120: 0 | G120: 0 | H120: 128.99 | I120: 0 | J120: 0 | K120: 0 | L120: 0 | M120: 107.48 | N120: 0 | O120: 118.47 | Q120: =+N120*12 -> 0 | R120: =+SUM(M120:N120)*6 -> 644.88 | S120: =+SUM(L120:N120)*4 -> 429.92 | T120: =+SUM(I120:N120)*2 -> 214.96 | U120: =+SUM(C120:N120) -> 118.47
B121: Maintenance Services Request | C121: 0 | D121: 75 | E121: 0 | F121: 50 | G121: 50 | H121: 25 | I121: 0 | J121: 0 | K121: 0 | L121: 0 | M121: 0 | N121: 0 | O121: 200 | Q121: =+N121*12 -> 0 | R121: =+SUM(M121:N121)*6 -> 0 | S121: =+SUM(L121:N121)*4 -> 0 | T121: =+SUM(I121:N121)*2 -> 0 | U121: =+SUM(C121:N121) -> 200
B122: Trash Cleanup | C122: 0 | D122: 0 | E122: 0 | F122: 0 | G122: 315 | H122: 370 | I122: 0 | J122: 0 | K122: 0 | L122: 0 | M122: 0 | N122: 0 | O122: 685 | Q122: =+N122*12 -> 0 | R122: =+SUM(M122:N122)*6 -> 0 | S122: =+SUM(L122:N122)*4 -> 0 | T122: =+SUM(I122:N122)*2 -> 0 | U122: =+SUM(C122:N122) -> 685
B123: Bulk Trash Pickup | C123: 0 | D123: 445 | E123: 0 | F123: 470 | G123: 1515 | H123: 504.68 | I123: 0 | J123: 0 | K123: 0 | L123: 730 | M123: 900 | N123: 0 | O123: 4564.68 | Q123: =+N123*12 -> 0 | R123: =+SUM(M123:N123)*6 -> 5400 | S123: =+SUM(L123:N123)*4 -> 6520 | T123: =+SUM(I123:N123)*2 -> 3260 | U123: =+SUM(C123:N123) -> 4564.68
B124: Vehicle Maint & Fuel | C124: 0 | D124: 0 | E124: 0 | F124: 0 | G124: 0 | H124: 0 | I124: 0 | J124: 38.5 | K124: 0 | L124: 0 | M124: 0 | N124: 0 | O124: 38.5 | Q124: =+N124*12 -> 0 | R124: =+SUM(M124:N124)*6 -> 0 | S124: =+SUM(L124:N124)*4 -> 0 | T124: =+SUM(I124:N124)*2 -> 77 | U124: =+SUM(C124:N124) -> 38.5
A125: 11 | B125: Total Repairs and Maintenance | C125: 7577.42 | D125: 4542.23 | E125: 3077.8 | F125: 5270.89 | G125: 4609.13 | H125: 9282.4 | I125: 5700.66 | J125: 702.97 | K125: 5245.66 | L125: 5314.97 | M125: 5026.4 | N125: 6685.8 | O125: 63036.33 | Q125: =+N125*12 -> 80229.6 | R125: =+SUM(M125:N125)*6 -> 70273.2 | S125: =+SUM(L125:N125)*4 -> 68108.68 | T125: =+SUM(I125:N125)*2 -> 57352.92 | U125: =+SUM(C125:N125) -> 63036.33
B126: Contract Services | Q126: =+N126*12 -> 0 | R126: =+SUM(M126:N126)*6 -> 0 | S126: =+SUM(L126:N126)*4 -> 0 | T126: =+SUM(I126:N126)*2 -> 0 | U126: =+SUM(C126:N126) -> 0
B127: Pool R&M | C127: 0 | D127: 0 | E127: 0 | F127: 0 | G127: 0 | H127: 0 | I127: 0 | J127: 19.34 | K127: 0 | L127: 169.81 | M127: 0 | N127: 0 | O127: 189.15 | Q127: =+N127*12 -> 0 | R127: =+SUM(M127:N127)*6 -> 0 | S127: =+SUM(L127:N127)*4 -> 679.24 | T127: =+SUM(I127:N127)*2 -> 378.3 | U127: =+SUM(C127:N127) -> 189.15
B128: Security/Fire Alarm R&M | C128: 0 | D128: 0 | E128: 0 | F128: 0 | G128: 0 | H128: 0 | I128: 0 | J128: 0 | K128: 47.57 | L128: 0 | M128: 0 | N128: 1916.73 | O128: 1964.3 | Q128: =+N128*12 -> 23000.76 | R128: =+SUM(M128:N128)*6 -> 11500.38 | S128: =+SUM(L128:N128)*4 -> 7666.92 | T128: =+SUM(I128:N128)*2 -> 3928.6 | U128: =+SUM(C128:N128) -> 1964.3
B129: Lift Station R&M | C129: 0 | D129: 887 | E129: 0 | F129: 1186.18 | G129: 106 | H129: 0 | I129: 523.3 | J129: 0 | K129: 0 | L129: 0 | M129: 0 | N129: 0 | O129: 2702.48 | Q129: =+N129*12 -> 0 | R129: =+SUM(M129:N129)*6 -> 0 | S129: =+SUM(L129:N129)*4 -> 0 | T129: =+SUM(I129:N129)*2 -> 1046.6 | U129: =+SUM(C129:N129) -> 2702.48
B130: Handy Trac Monthly Service | C130: 0 | D130: 24.95 | E130: 24.95 | F130: 24.95 | G130: 0 | H130: 49.9 | I130: 0 | J130: 0 | K130: 0 | L130: 0 | M130: 0 | N130: 0 | O130: 124.75 | Q130: =+N130*12 -> 0 | R130: =+SUM(M130:N130)*6 -> 0 | S130: =+SUM(L130:N130)*4 -> 0 | T130: =+SUM(I130:N130)*2 -> 0 | U130: =+SUM(C130:N130) -> 124.75
B131: Security/Fire Alarm Contract | C131: 107.48 | D131: 0 | E131: 344.33 | F131: 458.25 | G131: 113.92 | H131: 0 | I131: 0 | J131: 0 | K131: 343.47 | L131: 341.76 | M131: 0 | N131: 0 | O131: 1709.21 | Q131: =+N131*12 -> 0 | R131: =+SUM(M131:N131)*6 -> 0 | S131: =+SUM(L131:N131)*4 -> 1367.04 | T131: =+SUM(I131:N131)*2 -> 1370.46 | U131: =+SUM(C131:N131) -> 1709.21
B132: Garbage/Recycling Expense | C132: 3579.82 | D132: 0 | E132: 2473 | F132: 2888.16 | G132: 2662.76 | H132: 3499.83 | I132: 2225.91 | J132: 1604.25 | K132: 1877.54 | L132: 1964.2 | M132: 1660.11 | N132: 2263.51 | O132: 26699.09 | Q132: =+N132*12 -> 27162.12 | R132: =+SUM(M132:N132)*6 -> 23541.72 | S132: =+SUM(L132:N132)*4 -> 23551.28 | T132: =+SUM(I132:N132)*2 -> 23191.04 | U132: =+SUM(C132:N132) -> 26699.09
B133: Landscaping Contract | C133: 1950 | D133: 1950 | E133: 1950 | F133: 0 | G133: 1950 | H133: 3900 | I133: 1950 | J133: 1950 | K133: 1950 | L133: 1950 | M133: 1950 | N133: 1950 | O133: 23400 | Q133: =+N133*12 -> 23400 | R133: =+SUM(M133:N133)*6 -> 23400 | S133: =+SUM(L133:N133)*4 -> 23400 | T133: =+SUM(I133:N133)*2 -> 23400 | U133: =+SUM(C133:N133) -> 23400
...

Sheet TTM Oct-25
B1: Income Statement - 12 Month
B2: Exported On: 11/03/2025 05:33 PM
B4: Atrium Management Company
B5: Properties: Active
B6: Fund Type: All
B7: Period Range: Nov 2024 to Oct 2025
B8: Accounting Basis: Accrual
B9: GL Account Map: None - use master chart of accounts
B10: Level of Detail: Detail View
B11: Include Zero Balance GL Accounts: No
B13: Account Name | C13: Nov 2024 | D13: Dec 2024 | E13: Jan 2025 | F13: Feb 2025 | G13: Mar 2025 | H13: Apr 2025 | I13: May 2025 | J13: Jun 2025 | K13: Jul 2025 | L13: Aug 2025 | M13: Sep 2025 | N13: Oct 2025 | O13: Total | Q13: T1 | R13: T2 | S13: T3 | T13: T6 | U13: T12
B14: Operating Income & Expense
B15: Income
B16: Rental Income
A17: 1 | B17: Rent | C17: 0 | D17: 0 | E17: 0 | F17: 0 | G17: 0 | H17: 0 | I17: 0 | J17: 0 | K17: 0 | L17: 0 | M17: 0 | N17: 132432.35 | O17: 132432.35 | Q17: =+N17*12 -> 1589188.2 | R17: =+SUM(M17:N17)*6 -> 794594.1 | S17: =+SUM(L17:N17)*4 -> 529729.4 | T17: =+SUM(I17:N17)*2 -> 264864.7 | U17: =+SUM(C17:N17) -> 132432.35
A18: 1 | B18: Section-8 Rent | C18: 0 | D18: 0 | E18: 0 | F18: 0 | G18: 0 | H18: 0 | I18: 0 | J18: 0 | K18: 0 | L18: 0 | M18: 0 | N18: 1853 | O18: 1853 | Q18: =+N18*12 -> 22236 | R18: =+SUM(M18:N18)*6 -> 11118 | S18: =+SUM(L18:N18)*4 -> 7412 | T18: =+SUM(I18:N18)*2 -> 3706 | U18: =+SUM(C18:N18) -> 1853
A19: 1 | B19: Gross Potential Rent | C19: 144311 | D19: 144721.55 | E19: 146896.53 | F19: 147357.5 | G19: 147078 | H19: 147078 | I19: 147078 | J19: 154421 | K19: 155067.12 | L19: 142265.39 | M19: 136185.3 | N19: 0 | O19: 1612459.4 | Q19: =+N19*12 -> 0 | R19: =+SUM(M19:N19)*6 -> 817111.8 | S19: =+SUM(L19:N19)*4 -> 1113802.8 | T19: =+SUM(I19:N19)*2 -> 1470033.6 | U19: =+SUM(C19:N19) -> 1612459.4
A20: 1 | B20: Loss/Gain to Market | C20: -5871.9 | D20: -7553.26 | E20: -9302.88 | F20: -7219.92 | G20: -11409.39 | H20: -7196.23 | I20: -8458.77 | J20: -15965.57 | K20: -3498.54 | L20: -1535.7 | M20: 856.42 | N20: 0 | O20: -77155.74 | Q20: =+N20*12 -> 0 | R20: =+SUM(M20:N20)*6 -> 5138.52 | S20: =+SUM(L20:N20)*4 -> -2717.12 | T20: =+SUM(I20:N20)*2 -> -57204.32 | U20: =+SUM(C20:N20) -> -77155.74
A21: 3 | B21: Concessions | C21: -800 | D21: -100 | E21: -700 | F21: -1200 | G21: -320 | H21: -200 | I21: -1849 | J21: -1659 | K21: -1409 | L21: -5855 | M21: -17016.5 | N21: -19220.5 | O21: -50329 | Q21: =+N21*12 -> -230646 | R21: =+SUM(M21:N21)*6 -> -217422 | S21: =+SUM(L21:N21)*4 -> -168368 | T21: =+SUM(I21:N21)*2 -> -94018 | U21: =+SUM(C21:N21) -> -50329
A22: 3 | B22: Concessions - Recurring | C22: 0 | D22: 0 | E22: 0 | F22: 0 | G22: 0 | H22: 0 | I22: 0 | J22: -200 | K22: -200 | L22: -200 | M22: -200 | N22: -200 | O22: -1000 | Q22: =+N22*12 -> -2400 | R22: =+SUM(M22:N22)*6 -> -2400 | S22: =+SUM(L22:N22)*4 -> -2400 | T22: =+SUM(I22:N22)*2 -> -2000 | U22: =+SUM(C22:N22) -> -1000
A23: 3 | B23: Concessions - Employee Unit | C23: 0 | D23: 0 | E23: 0 | F23: 0 | G23: 0 | H23: 0 | I23: 0 | J23: 0 | K23: 0 | L23: 0 | M23: -210 | N23: -210 | O23: -420 | Q23: =+N23*12 -> -2520 | R23: =+SUM(M23:N23)*6 -> -2520 | S23: =+SUM(L23:N23)*4 -> -1680 | T23: =+SUM(I23:N23)*2 -> -840 | U23: =+SUM(C23:N23) -> -420
A24: 2 | B24: Vacancy | C24: -33216.77 | D24: -29499.93 | E24: -25913.5 | F24: -24560.58 | G24: -19223.61 | H24: -25112.77 | I24: -26229.23 | J24: -29901.46 | K24: -37429.9 | L24: -34280.94 | M24: -17406.1 | N24: 0 | O24: -302774.79 | Q24: =+N24*12 -> 0 | R24: =+SUM(M24:N24)*6 -> -104436.6 | S24: =+SUM(L24:N24)*4 -> -206748.16 | T24: =+SUM(I24:N24)*2 -> -290495.26 | U24: =+SUM(C24:N24) -> -302774.79
A25: 4 | B25: Bad Debt - Contra | C25: -41256.8 | D25: -400 | E25: -22098.2 | F25: -1006 | G25: -20742.65 | H25: -26539.02 | I25: 0 | J25: 0 | K25: -3968 | L25: 0 | M25: -16661.19 | N25: 0 | O25: -132671.86 | Q25: =+N25*12 -> 0 | R25: =+SUM(M25:N25)*6 -> -99967.14 | S25: =+SUM(L25:N25)*4 -> -66644.76 | T25: =+SUM(I25:N25)*2 -> -41258.38 | U25: =+SUM(C25:N25) -> -132671.86
B26: Total Rental Income | C26: 63165.53 | D26: 107168.36 | E26: 88881.95 | F26: 113371 | G26: 95382.35 | H26: 88029.98 | I26: 110541 | J26: 106694.97 | K26: 108561.68 | L26: 100393.75 | M26: 85547.93 | N26: 114654.85 | O26: 1182393.4 | Q26: =+N26*12 -> 1375858.2 | R26: =+SUM(M26:N26)*6 -> 1201216.7 | S26: =+SUM(L26:N26)*4 -> 1202386.1 | T26: =+SUM(I26:N26)*2 -> 1252788.4 | U26: =+SUM(C26:N26) -> 1182393.4
B27: Other Income | Q27: =+N27*12 -> 0 | R27: =+SUM(M27:N27)*6 -> 0 | S27: =+SUM(L27:N27)*4 -> 0 | T27: =+SUM(I27:N27)*2 -> 0 | U27: =+SUM(C27:N27) -> 0
A28: 7 | B28: Lease Lock | C28: 1330 | D28: 1274 | E28: 1218 | F28: 0 | G28: 0 | H28: 0 | I28: 0 | J28: 0 | K28: 0 | L28: 0 | M28: 0 | N28: 0 | O28: 3822 | Q28: =+N28*12 -> 0 | R28: =+SUM(M28:N28)*6 -> 0 | S28: =+SUM(L28:N28)*4 -> 0 | T28: =+SUM(I28:N28)*2 -> 0 | U28: =+SUM(C28:N28) -> 3822
A29: 7 | B29: NSF Fees Collected | C29: 0 | D29: 0 | E29: 165 | F29: 275 | G29: 385 | H29: 55 | I29: 55 | J29: 0 | K29: 150 | L29: 0 | M29: -75 | N29: -75 | O29: 935 | Q29: =+N29*12 -> -900 | R29: =+SUM(M29:N29)*6 -> -900 | S29: =+SUM(L29:N29)*4 -> -600 | T29: =+SUM(I29:N29)*2 -> 110 | U29: =+SUM(C29:N29) -> 935
A30: 7 | B30: Late Fee | C30: 2246.5 | D30: 2414.8 | E30: 2981 | F30: 3381.7 | G30: 3761.8 | H30: 3081.7 | I30: 3111.8 | J30: 4980.4 | K30: 250 | L30: 2429.16 | M30: 1850.19 | N30: 2271.56 | O30: 32760.61 | Q30: =+N30*12 -> 27258.72 | R30: =+SUM(M30:N30)*6 -> 24730.5 | S30: =+SUM(L30:N30)*4 -> 26203.64 | T30: =+SUM(I30:N30)*2 -> 29786.22 | U30: =+SUM(C30:N30) -> 32760.61
A31: 6 | B31: Utility Income | C31: 0 | D31: 0 | E31: 0 | F31: 0 | G31: 0 | H31: 0 | I31: 0 | J31: 0 | K31: 0 | L31: 9.03 | M31: -9.03 | N31: 0 | O31: 0 | Q31: =+N31*12 -> 0 | R31: =+SUM(M31:N31)*6 -> -54.18 | S31: =+SUM(L31:N31)*4 -> 0 | T31: =+SUM(I31:N31)*2 -> 0 | U31: =+SUM(C31:N31) -> 0
A32: 6 | B32: Electricity Income | C32: 0 | D32: 95 | E32: 95 | F32: 95 | G32: 95 | H32: 95 | I32: 95 | J32: 0 | K32: 0 | L32: 0 | M32: 0 | N32: 0 | O32: 570 | Q32: =+N32*12 -> 0 | R32: =+SUM(M32:N32)*6 -> 0 | S32: =+SUM(L32:N32)*4 -> 0 | T32: =+SUM(I32:N32)*2 -> 190 | U32: =+SUM(C32:N32) -> 570
A33: 6 | B33: Utility Reimbursements | C33: 6459.53 | D33: 6794 | E33: 7216 | F33: 7099 | G33: 7482 | H33: 7122 | I33: 7077 | J33: 6398.33 | K33: 6302.77 | L33: 5980.56 | M33: 7009.03 | N33: 7576.96 | O33: 82517.18 | Q33: =+N33*12 -> 90923.52 | R33: =+SUM(M33:N33)*6 -> 87515.94 | S33: =+SUM(L33:N33)*4 -> 82266.2 | T33: =+SUM(I33:N33)*2 -> 80689.3 | U33: =+SUM(C33:N33) -> 82517.18
A34: 7 | B34: Resident Liability & Contents Coverage | C34: 493.5 | D34: 588 | E34: 661.5 | F34: 735 | G34: 756 | H34: 766.5 | I34: 724.5 | J34: -15.5 | K34: 258.5 | L34: 161 | M34: -107.92 | N34: 52.92 | O34: 5074 | Q34: =+N34*12 -> 635.04 | R34: =+SUM(M34:N34)*6 -> -330 | S34: =+SUM(L34:N34)*4 -> 424 | T34: =+SUM(I34:N34)*2 -> 2147 | U34: =+SUM(C34:N34) -> 5074
A35: 7 | B35: 1st month - Resident Liability & Contents Coverage | C35: 0 | D35: 0 | E35: 0 | F35: 0 | G35: 0 | H35: 0 | I35: 0 | J35: 26.52 | K35: -13.52 | L35: -13 | M35: -13 | N35: 0 | O35: -13 | Q35: =+N35*12 -> 0 | R35: =+SUM(M35:N35)*6 -> -78 | S35: =+SUM(L35:N35)*4 -> -104 | T35: =+SUM(I35:N35)*2 -> -26 | U35: =+SUM(C35:N35) -> -13
A36: 7 | B36: AppFolio Insurance Admin Fee | C36: -226.5 | D36: -382.5 | E36: -428 | F36: -505 | G36: -563 | H36: -581.5 | I36: -1366 | J36: 0 | K36: 0 | L36: 0 | M36: 0 | N36: 0 | O36: -4052.5 | Q36: =+N36*12 -> 0 | R36: =+SUM(M36:N36)*6 -> 0 | S36: =+SUM(L36:N36)*4 -> 0 | T36: =+SUM(I36:N36)*2 -> -2732 | U36: =+SUM(C36:N36) -> -4052.5
A37: 7 | B37: Pet Fee - Non Refundable | C37: 650 | D37: 0 | E37: 0 | F37: 0 | G37: 0 | H37: 300 | I37: 0 | J37: 0 | K37: 0 | L37: 0 | M37: 0 | N37: 0 | O37: 950 | Q37: =+N37*12 -> 0 | R37: =+SUM(M37:N37)*6 -> 0 | S37: =+SUM(L37:N37)*4 -> 0 | T37: =+SUM(I37:N37)*2 -> 0 | U37: =+SUM(C37:N37) -> 950
A38: 7 | B38: Bad Debt Recovery | C38: 871.84 | D38: 0 | E38: 0 | F38: 0 | G38: 0 | H38: 162.71 | I38: 14.55 | J38: 0 | K38: 0 | L38: 0 | M38: 0 | N38: 0 | O38: 1049.1 | Q38: =+N38*12 -> 0 | R38: =+SUM(M38:N38)*6 -> 0 | S38: =+SUM(L38:N38)*4 -> 0 | T38: =+SUM(I38:N38)*2 -> 29.1 | U38: =+SUM(C38:N38) -> 1049.1
A39: 7 | B39: Pet Application Fee | C39: 0 | D39: 0 | E39: 0 | F39: 0 | G39: 0 | H39: 0 | I39: 222 | J39: 0 | K39: 0 | L39: 0 | M39: 0 | N39: 0 | O39: 222 | Q39: =+N39*12 -> 0 | R39: =+SUM(M39:N39)*6 -> 0 | S39: =+SUM(L39:N39)*4 -> 0 | T39: =+SUM(I39:N39)*2 -> 444 | U39: =+SUM(C39:N39) -> 222
... A59: 7 | B59: Bad Debt - Contra Other Income | C59: 0 | D59: 0 | E59: 0 | F59: 0 | G59: 0 | H59: 0 | I59: 0 | J59: 0 | K59: -727 | L59: 0 | M59: -2964 | N59: 0 | O59: -3691 | Q59: =+N59*12 -> 0 | R59: =+SUM(M59:N59)*6 -> -17784 | S59: =+SUM(L59:N59)*4 -> -11856 | T59: =+SUM(I59:N59)*2 -> -7382 | U59: =+SUM(C59:N59) -> -3691
B60: Total Other Income | C60: 21565.76 | D60: 17493.8 | E60: 19106.8 | F60: 15144.7 | G60: 21278.91 | H60: 27756.41 | I60: 18138.44 | J60: 16538.85 | K60: 11410.24 | L60: 14422.98 | M60: 13112.8 | N60: 17277.72 | O60: 213247.41 | Q60: =+N60*12 -> 207332.64 | R60: =+SUM(M60:N60)*6 -> 182343.12 | S60: =+SUM(L60:N60)*4 -> 179254 | T60: =+SUM(I60:N60)*2 -> 181802.06 | U60: =+SUM(C60:N60) -> 213247.41
B61: Total Operating Income | C61: 84731.29 | D61: 124662.16 | E61: 107988.75 | F61: 128515.7 | G61: 116661.26 | H61: 115786.39 | I61: 128679.44 | J61: 123233.82 | K61: 119971.92 | L61: 114816.73 | M61: 98660.73 | N61: 131932.57 | O61: 1395640.8 | Q61: =+N61*12 -> 1583190.8 | R61: =+SUM(M61:N61)*6 -> 1383559.8 | S61: =+SUM(L61:N61)*4 -> 1381640.1 | T61: =+SUM(I61:N61)*2 -> 1434590.4 | U61: =+SUM(C61:N61) -> 1395640.8
B62: Expense | Q62: =+N62*12 -> 0 | R62: =+SUM(M62:N62)*6 -> 0 | S62: =+SUM(L62:N62)*4 -> 0 | T62: =+SUM(I62:N62)*2 -> 0 | U62: =+SUM(C62:N62) -> 0
B63: Management Fee Expenses | Q63: =+N63*12 -> 0 | R63: =+SUM(M63:N63)*6 -> 0 | S63: =+SUM(L63:N63)*4 -> 0 | T63: =+SUM(I63:N63)*2 -> 0 | U63: =+SUM(C63:N63) -> 0
A64: 17 | B64: Management Fees | C64: 15049 | D64: 15433 | E64: 16178 | F64: 16327 | G64: 16625 | H64: 16923 | I64: 13046.18 | J64: 0 | K64: 0 | L64: 0 | M64: 0 | N64: 0 | O64: 109581.18 | Q64: =+N64*12 -> 0 | R64: =+SUM(M64:N64)*6 -> 0 | S64: =+SUM(L64:N64)*4 -> 0 | T64: =+SUM(I64:N64)*2 -> 26092.36 | U64: =+SUM(C64:N64) -> 109581.18
A65: 8 | B65: Lease Renewal Fee | C65: 750 | D65: 450 | E65: 900 | F65: 1200 | G65: 450 | H65: 0 | I65: 1050 | J65: 0 | K65: 0 | L65: 0 | M65: 0 | N65: 0 | O65: 4800 | Q65: =+N65*12 -> 0 | R65: =+SUM(M65:N65)*6 -> 0 | S65: =+SUM(L65:N65)*4 -> 0 | T65: =+SUM(I65:N65)*2 -> 2100 | U65: =+SUM(C65:N65) -> 4800
A66: 17 | B66: Management Fee - Multifamily | C66: 0 | D66: 0 | E66: 0 | F66: 0 | G66: 0 | H66: 0 | I66: 0 | J66: 4500 | K66: 4500 | L66: 4500 | M66: 4500 | N66: 0 | O66: 18000 | Q66: =+N66*12 -> 0 | R66: =+SUM(M66:N66)*6 -> 27000 | S66: =+SUM(L66:N66)*4 -> 36000 | T66: =+SUM(I66:N66)*2 -> 36000 | U66: =+SUM(C66:N66) -> 18000
B67: Total Management Fee Expenses | C67: 15799 | D67: 15883 | E67: 17078 | F67: 17527 | G67: 17075 | H67: 16923 | I67: 14096.18 | J67: 4500 | K67: 4500 | L67: 4500 | M67: 4500 | N67: 0 | O67: 132381.18 | Q67: =+N67*12 -> 0 | R67: =+SUM(M67:N67)*6 -> 27000 | S67: =+SUM(L67:N67)*4 -> 36000 | T67: =+SUM(I67:N67)*2 -> 64192.36 | U67: =+SUM(C67:N67) -> 132381.18
B68: Admin Expenses | Q68: =+N68*12 -> 0 | R68: =+SUM(M68:N68)*6 -> 0 | S68: =+SUM(L68:N68)*4 -> 0 | T68: =+SUM(I68:N68)*2 -> 0 | U68: =+SUM(C68:N68) -> 0
B69: Property Inspections | C69: 0 | D69: 45 | E69: 0 | F69: 0 | G69: 0 | H69: 0 | I69: 0 | J69: 0 | K69: 0 | L69: 0 | M69: 0 | N69: 0 | O69: 45 | Q69: =+N69*12 -> 0 | R69: =+SUM(M69:N69)*6 -> 0 | S69: =+SUM(L69:N69)*4 -> 0 | T69: =+SUM(I69:N69)*2 -> 0 | U69: =+SUM(C69:N69) -> 45
B70: Payment Processing Fees | C70: 0 | D70: 0 | E70: 0 | F70: 0 | G70: 0 | H70: 0 | I70: 0 | J70: 0 | K70: 1430.6 | L70: 0 | M70: 0 | N70: 0 | O70: 1430.6 | Q70: =+N70*12 -> 0 | R70: =+SUM(M70:N70)*6 -> 0 | S70: =+SUM(L70:N70)*4 -> 0 | T70: =+SUM(I70:N70)*2 -> 2861.2 | U70: =+SUM(C70:N70) -> 1430.6
B71: Telephone Expense | C71: 133.89 | D71: 133.84 | E71: 398.15 | F71: 138.15 | G71: 138.15 | H71: 138.01 | I71: 138 | J71: 138.01 | K71: 133 | L71: 158.07 | M71: 145.58 | N71: -145.58 | O71: 1647.27 | Q71: =+N71*12 -> -1746.96 | R71: =+SUM(M71:N71)*6 -> 0 | S71: =+SUM(L71:N71)*4 -> 632.28 | T71: =+SUM(I71:N71)*2 -> 1134.16 | U71: =+SUM(C71:N71) -> 1647.27
B72: Memberships/Professional Organizations | C72: 0 | D72: 0 | E72: 0 | F72: 0 | G72: 0 | H72: 0 | I72: 0 | J72: 264.32 | K72: 0 | L72: 0 | M72: 0 | N72: 0 | O72: 264.32 | Q72: =+N72*12 -> 0 | R72: =+SUM(M72:N72)*6 -> 0 | S72: =+SUM(L72:N72)*4 -> 0 | T72: =+SUM(I72:N72)*2 -> 528.64 | U72: =+SUM(C72:N72) -> 264.32
B73: Uniforms | C73: 0 | D73: 0 | E73: 0 | F73: 0 | G73: 0 | H73: 0 | I73: 0 | J73: 0 | K73: 300 | L73: 0 | M73: 0 | N73: 0 | O73: 300 | Q73: =+N73*12 -> 0 | R73: =+SUM(M73:N73)*6 -> 0 | S73: =+SUM(L73:N73)*4 -> 0 | T73: =+SUM(I73:N73)*2 -> 600 | U73: =+SUM(C73:N73) -> 300
B74: Legal Fees - Retail | C74: 0 | D74: 438.5 | E74: 354 | F74: 0 | G74: 0 | H74: 0 | I74: 926 | J74: 0 | K74: 0 | L74: 0 | M74: 0 | N74: 0 | O74: 1718.5 | Q74: =+N74*12 -> 0 | R74: =+SUM(M74:N74)*6 -> 0 | S74: =+SUM(L74:N74)*4 -> 0 | T74: =+SUM(I74:N74)*2 -> 1852 | U74: =+SUM(C74:N74) -> 1718.5
B75: Office Supplies | C75: 84.36 | D75: 200 | E75: 0 | F75: 0 | G75: 0 | H75: 80.6 | I75: 0 | J75: 253.43 | K75: 47.92 | L75: 64.49 | M75: 0 | N75: 0 | O75: 730.8 | Q75: =+N75*12 -> 0 | R75: =+SUM(M75:N75)*6 -> 0 | S75: =+SUM(L75:N75)*4 -> 257.96 | T75: =+SUM(I75:N75)*2 -> 731.68 | U75: =+SUM(C75:N75) -> 730.8
B76: Bank Fees | C76: 0 | D76: 0 | E76: 0 | F76: 195 | G76: 0 | H76: 0 | I76: 0 | J76: 0 | K76: 0 | L76: 0 | M76: 0 | N76: 0 | O76: 195 | Q76: =+N76*12 -> 0 | R76: =+SUM(M76:N76)*6 -> 0 | S76: =+SUM(L76:N76)*4 -> 0 | T76: =+SUM(I76:N76)*2 -> 0 | U76: =+SUM(C76:N76) -> 195
B77: Office Miscellaneous Expenses | C77: 29.02 | D77: 0 | E77: 0 | F77: 0 | G77: 0 | H77: 0 | I77: 0 | J77: 0 | K77: 483.64 | L77: 0 | M77: 0 | N77: 0 | O77: 512.66 | Q77: =+N77*12 -> 0 | R77: =+SUM(M77:N77)*6 -> 0 | S77: =+SUM(L77:N77)*4 -> 0 | T77: =+SUM(I77:N77)*2 -> 967.28 | U77: =+SUM(C77:N77) -> 512.66
B78: Legal Expenses | C78: 0 | D78: 0 | E78: 0 | F78: 0 | G78: 0 | H78: 0 | I78: 0 | J78: 204 | K78: 926 | L78: 1001 | M78: 0 | N78: 102 | O78: 2233 | Q78: =+N78*12 -> 1224 | R78: =+SUM(M78:N78)*6 -> 612 | S78: =+SUM(L78:N78)*4 -> 4412 | T78: =+SUM(I78:N78)*2 -> 4466 | U78: =+SUM(C78:N78) -> 2233
B79: Accounting Expenses | C79: 2472 | D79: 0 | E79: 0 | F79: 0 | G79: 150 | H79: 0 | I79: 5633.42 | J79: 0 | K79: 500 | L79: 350 | M79: 350 | N79: 350 | O79: 9805.42 | Q79: =+N79*12 -> 4200 | R79: =+SUM(M79:N79)*6 -> 4200 | S79: =+SUM(L79:N79)*4 -> 4200 | T79: =+SUM(I79:N79)*2 -> 14366.84 | U79: =+SUM(C79:N79) -> 9805.42
B80: Other Professional Fees | C80: 1900 | D80: 14300 | E80: 150 | F80: 2350 | G80: -520.5 | H80: 5300 | I80: 0 | J80: 0 | K80: 0 | L80: 0 | M80: 0 | N80: 0 | O80: 23479.5 | Q80: =+N80*12 -> 0 | R80: =+SUM(M80:N80)*6 -> 0 | S80: =+SUM(L80:N80)*4 -> 0 | T80: =+SUM(I80:N80)*2 -> 0 | U80: =+SUM(C80:N80) -> 23479.5
... B90: Staff-Meals/Entertainment | C90: 165.18 | D90: 2.84 | E90: 0 | F90: 0 | G90: 0 | H90: 0 | I90: 0 | J90: 75.23 | K90: 0 | L90: 0 | M90: 0 | N90: 0 | O90: 243.25 | Q90: =+N90*12 -> 0 | R90: =+SUM(M90:N90)*6 -> 0 | S90: =+SUM(L90:N90)*4 -> 0 | T90: =+SUM(I90:N90)*2 -> 150.46 | U90: =+SUM(C90:N90) -> 243.25
A91: 9 | B91: Total Admin Expenses | C91: 5244.46 | D91: 15475.18 | E91: 2053.87 | F91: 3083.15 | G91: 1202.65 | H91: 6798.96 | I91: 7542.87 | J91: 1458.99 | K91: 9822.95 | L91: 3470.28 | M91: 1775.6 | N91: 2142.76 | O91: 60071.72 | Q91: =+N91*12 -> 25713.12 | R91: =+SUM(M91:N91)*6 -> 23510.16 | S91: =+SUM(L91:N91)*4 -> 29554.56 | T91: =+SUM(I91:N91)*2 -> 52426.9 | U91: =+SUM(C91:N91) -> 60071.72
B92: Turn Costs | Q92: =+N92*12 -> 0 | R92: =+SUM(M92:N92)*6 -> 0 | S92: =+SUM(L92:N92)*4 -> 0 | T92: =+SUM(I92:N92)*2 -> 0 | U92: =+SUM(C92:N92) -> 0
B93: Carpet/ Floor Replacement - Turns | C93: 0 | D93: 0 | E93: 0 | F93: 0 | G93: 0 | H93: 0 | I93: 0 | J93: 0 | K93: 0 | L93: 0 | M93: 1715.42 | N93: 0 | O93: 1715.42 | Q93: =+N93*12 -> 0 | R93: =+SUM(M93:N93)*6 -> 10292.52 | S93: =+SUM(L93:N93)*4 -> 6861.68 | T93: =+SUM(I93:N93)*2 -> 3430.84 | U93: =+SUM(C93:N93) -> 1715.42
B94: Painting Turn | C94: 79.1 | D94: 1720.67 | E94: 4650 | F94: 1333.7 | G94: 1558.63 | H94: 0 | I94: 0 | J94: 0 | K94: 0 | L94: 670.77 | M94: 290 | N94: 3596.19 | O94: 13899.06 | Q94: =+N94*12 -> 43154.28 | R94: =+SUM(M94:N94)*6 -> 23317.14 | S94: =+SUM(L94:N94)*4 -> 18227.84 | T94: =+SUM(I94:N94)*2 -> 9113.92 | U94: =+SUM(C94:N94) -> 13899.06
B95: Cleaning/Janitorial Turn | C95: 0 | D95: 1160 | E95: 1261.33 | F95: 386.54 | G95: 985 | H95: 1870 | I95: 2420 | J95: 0 | K95: 0 | L95: 236.03 | M95: 1540.36 | N95: 2190.01 | O95: 12049.27 | Q95: =+N95*12 -> 26280.12 | R95: =+SUM(M95:N95)*6 -> 22382.22 | S95: =+SUM(L95:N95)*4 -> 15865.6 | T95: =+SUM(I95:N95)*2 -> 12772.8 | U95: =+SUM(C95:N95) -> 12049.27
B96: Key/Lock Turn | C96: 0 | D96: 19.95 | E96: 0 | F96: 80.3 | G96: 0 | H96: 0 | I96: -31.98 | J96: 0 | K96: 0 | L96: 0 | M96: 0 | N96: 0 | O96: 68.27 | Q96: =+N96*12 -> 0 | R96: =+SUM(M96:N96)*6 -> 0 | S96: =+SUM(L96:N96)*4 -> 0 | T96: =+SUM(I96:N96)*2 -> -63.96 | U96: =+SUM(C96:N96) -> 68.27
B97: Carpet/Tile Cleaning - Turns | C97: 0 | D97: 200 | E97: 0 | F97: 0 | G97: 0 | H97: 125 | I97: 980 | J97: 0 | K97: 0 | L97: 0 | M97: 0 | N97: 515 | O97: 1820 | Q97: =+N97*12 -> 6180 | R97: =+SUM(M97:N97)*6 -> 3090 | S97: =+SUM(L97:N97)*4 -> 2060 | T97: =+SUM(I97:N97)*2 -> 2990 | U97: =+SUM(C97:N97) -> 1820
B98: Turn Repairs R&M | C98: 0 | D98: 0 | E98: 0 | F98: 0 | G98: 0 | H98: 0 | I98: 0 | J98: 0 | K98: 0 | L98: 152 | M98: 5140 | N98: 970 | O98: 6262 | Q98: =+N98*12 -> 11640 | R98: =+SUM(M98:N98)*6 -> 36660 | S98: =+SUM(L98:N98)*4 -> 25048 | T98: =+SUM(I98:N98)*2 -> 12524 | U98: =+SUM(C98:N98) -> 6262
B99: Tub/Shower Resurfacing - Turns | C99: 0 | D99: 0 | E99: 0 | F99: 560 | G99: 4100 | H99: 0 | I99: 6260 | J99: 0 | K99: 0 | L99: 2245 | M99: 0 | N99: 1210 | O99: 14375 | Q99: =+N99*12 -> 14520 | R99: =+SUM(M99:N99)*6 -> 7260 | S99: =+SUM(L99:N99)*4 -> 13820 | T99: =+SUM(I99:N99)*2 -> 19430 | U99: =+SUM(C99:N99) -> 14375
A100: 13 | B100: Total Turn Costs | C100: 79.1 | D100: 3100.62 | E100: 5911.33 | F100: 2360.54 | G100: 6643.63 | H100: 1995 | I100: 9628.02 | J100: 0 | K100: 0 | L100: 3303.8 | M100: 8685.78 | N100: 8481.2 | O100: 50189.02 | Q100: =+N100*12 -> 101774.4 | R100: =+SUM(M100:N100)*6 -> 103001.88 | S100: =+SUM(L100:N100)*4 -> 81883.12 | T100: =+SUM(I100:N100)*2 -> 60197.6 | U100: =+SUM(C100:N100) -> 50189.02
B101: Advertising | Q101: =+N101*12 -> 0 | R101: =+SUM(M101:N101)*6 -> 0 | S101: =+SUM(L101:N101)*4 -> 0 | T101: =+SUM(I101:N101)*2 -> 0 | U101: =+SUM(C101:N101) -> 0
B102: Advertising - General | C102: 1319.46 | D102: 645 | E102: 645 | F102: 667.17 | G102: 682.98 | H102: 1175 | I102: 1820 | J102: 0 | K102: 0 | L102: 0 | M102: 0 | N102: 0 | O102: 6954.61 | Q102: =+N102*12 -> 0 | R102: =+SUM(M102:N102)*6 -> 0 | S102: =+SUM(L102:N102)*4 -> 0 | T102: =+SUM(I102:N102)*2 -> 3640 | U102: =+SUM(C102:N102) -> 6954.61
B103: Website | C103: 0 | D103: 0 | E103: 0 | F103: 0 | G103: 0 | H103: 0 | I103: 0 | J103: 1950 | K103: 0 | L103: 0 | M103: 0 | N103: 0 | O103: 1950 | Q103: =+N103*12 -> 0 | R103: =+SUM(M103:N103)*6 -> 0 | S103: =+SUM(L103:N103)*4 -> 0 | T103: =+SUM(I103:N103)*2 -> 3900 | U103: =+SUM(C103:N103) -> 1950
B104: Resident Referral Fees | C104: 0 | D104: 0 | E104: 0 | F104: 0 | G104: 0 | H104: 0 | I104: 0 | J104: 0 | K104: 0 | L104: 600 | M104: 750 | N104: 0 | O104: 1350 | Q104: =+N104*12 -> 0 | R104: =+SUM(M104:N104)*6 -> 4500 | S104: =+SUM(L104:N104)*4 -> 5400 | T104: =+SUM(I104:N104)*2 -> 2700 | U104: =+SUM(C104:N104) -> 1350
B105: Marketing / Promotions | C105: 0 | D105: 0 | E105: 0 | F105: 0 | G105: 0 | H105: 0 | I105: 0 | J105: 0 | K105: 429.38 | L105: 0 | M105: -79.03 | N105: 69 | O105: 419.35 | Q105: =+N105*12 -> 828 | R105: =+SUM(M105:N105)*6 -> -60.18 | S105: =+SUM(L105:N105)*4 -> -40.12 | T105: =+SUM(I105:N105)*2 -> 838.7 | U105: =+SUM(C105:N105) -> 419.35
B106: Resident Refreshments and Events | C106: 0 | D106: 0 | E106: 0 | F106: 0 | G106: 0 | H106: 0 | I106: 0 | J106: 0 | K106: 0 | L106: 373.23 | M106: 0 | N106: 0 | O106: 373.23 | Q106: =+N106*12 -> 0 | R106: =+SUM(M106:N106)*6 -> 0 | S106: =+SUM(L106:N106)*4 -> 1492.92 | T106: =+SUM(I106:N106)*2 -> 746.46 | U106: =+SUM(C106:N106) -> 373.23
B107: Model Expense | C107: 0 | D107: 0 | E107: 0 | F107: 0 | G107: 0 | H107: 0 | I107: 0 | J107: 0 | K107: 0 | L107: 0 | M107: 163.95 | N107: 0 | O107: 163.95 | Q107: =+N107*12 -> 0 | R107: =+SUM(M107:N107)*6 -> 983.7 | S107: =+SUM(L107:N107)*4 -> 655.8 | T107: =+SUM(I107:N107)*2 -> 327.9 | U107: =+SUM(C107:N107) -> 163.95
B108: Apartments.com | C108: 0 | D108: 0 | E108: 0 | F108: 0 | G108: 0 | H108: 0 | I108: 0 | J108: 2940.39 | K108: 2532 | L108: 2832 | M108: 2832 | N108: 2832 | O108: 13968.39 | Q108: =+N108*12 -> 33984 | R108: =+SUM(M108:N108)*6 -> 33984 | S108: =+SUM(L108:N108)*4 -> 33984 | T108: =+SUM(I108:N108)*2 -> 27936.78 | U108: =+SUM(C108:N108) -> 13968.39
B109: Zillow | C109: 0 | D109: 0 | E109: 0 | F109: 0 | G109: 0 | H109: 0 | I109: 0 | J109: 800.65 | K109: 730 | L109: 730 | M109: 730 | N109: 0 | O109: 2990.65 | Q109: =+N109*12 -> 0 | R109: =+SUM(M109:N109)*6 -> 4380 | S109: =+SUM(L109:N109)*4 -> 5840 | T109: =+SUM(I109:N109)*2 -> 5981.3 | U109: =+SUM(C109:N109) -> 2990.65
A110: 10 | B110: Total Advertising | C110: 1319.46 | D110: 645 | E110: 645 | F110: 667.17 | G110: 682.98 | H110: 1175 | I110: 1820 | J110: 5691.04 | K110: 3691.38 | L110: 4535.23 | M110: 4396.92 | N110: 2901 | O110: 28170.18 | Q110: =+N110*12 -> 34812 | R110: =+SUM(M110:N110)*6 -> 43787.52 | S110: =+SUM(L110:N110)*4 -> 47332.6 | T110: =+SUM(I110:N110)*2 -> 46071.14 | U110: =+SUM(C110:N110) -> 28170.18
B111: Repairs and Maintenance | Q111: =+N111*12 -> 0 | R111: =+SUM(M111:N111)*6 -> 0 | S111: =+SUM(L111:N111)*4 -> 0 | T111: =+SUM(I111:N111)*2 -> 0 | U111: =+SUM(C111:N111) -> 0
B112: HVAC (Heat, Ventilation, Air) R&M | C112: 0 | D112: 776.97 | E112: 704.69 | F112: 234.76 | G112: 960 | H112: 0 | I112: 1475.28 | J112: 1205.79 | K112: 502.98 | L112: 2330 | M112: 818.79 | N112: 5860 | O112: 14869.26 | Q112: =+N112*12 -> 70320 | R112: =+SUM(M112:N112)*6 -> 40072.74 | S112: =+SUM(L112:N112)*4 -> 36035.16 | T112: =+SUM(I112:N112)*2 -> 24385.68 | U112: =+SUM(C112:N112) -> 14869.26
B113: Plumbing R&M | C113: 35.06 | D113: 3414.03 | E113: 532.35 | F113: 511.46 | G113: 2075.99 | H113: 0 | I113: 861.56 | J113: 2205.25 | K113: 0 | L113: 1872.8 | M113: 2179.47 | N113: 360 | O113: 14047.97 | Q113: =+N113*12 -> 4320 | R113: =+SUM(M113:N113)*6 -> 15236.82 | S113: =+SUM(L113:N113)*4 -> 17649.08 | T113: =+SUM(I113:N113)*2 -> 14958.16 | U113: =+SUM(C113:N113) -> 14047.97
B114: Electrical R&M | C114: 751 | D114: 610 | E114: 775 | F114: 205.3 | G114: 0 | H114: 650 | I114: 0 | J114: 309.3 | K114: 0 | L114: 0 | M114: 0 | N114: 0 | O114: 3300.6 | Q114: =+N114*12 -> 0 | R114: =+SUM(M114:N114)*6 -> 0 | S114: =+SUM(L114:N114)*4 -> 0 | T114: =+SUM(I114:N114)*2 -> 618.6 | U114: =+SUM(C114:N114) -> 3300.6
B115: Roof R&M | C115: 0 | D115: 1500 | E115: 1500 | F115: 750 | G115: 0 | H115: 0 | I115: 800 | J115: 0 | K115: 0 | L115: 645 | M115: 0 | N115: 396.41 | O115: 5591.41 | Q115: =+N115*12 -> 4756.92 | R115: =+SUM(M115:N115)*6 -> 2378.46 | S115: =+SUM(L115:N115)*4 -> 4165.64 | T115: =+SUM(I115:N115)*2 -> 3682.82 | U115: =+SUM(C115:N115) -> 5591.41
B116: Supplies R&M | C116: 0 | D116: 1009.81 | E116: 510.19 | F116: 1369.28 | G116: 1819.9 | H116: 674.13 | I116: 4162.29 | J116: 857 | K116: 0 | L116: 0 | M116: 0 | N116: 0 | O116: 10402.6 | Q116: =+N116*12 -> 0 | R116: =+SUM(M116:N116)*6 -> 0 | S116: =+SUM(L116:N116)*4 -> 0 | T116: =+SUM(I116:N116)*2 -> 10038.58 | U116: =+SUM(C116:N116) -> 10402.6
B117: Appliance R&M | C117: -62.69 | D117: 0 | E117: 0 | F117: 0 | G117: 0 | H117: 0 | I117: 0 | J117: 0 | K117: 0 | L117: 0 | M117: 0 | N117: 0 | O117: -62.69 | Q117: =+N117*12 -> 0 | R117: =+SUM(M117:N117)*6 -> 0 | S117: =+SUM(L117:N117)*4 -> 0 | T117: =+SUM(I117:N117)*2 -> 0 | U117: =+SUM(C117:N117) -> -62.69
B118: Window and Screen R&M | C118: 0 | D118: 0 | E118: 0 | F118: 0 | G118: 0 | H118: 1405 | I118: 954.6 | J118: 0 | K118: 0 | L118: 0 | M118: 633.25 | N118: 1160 | O118: 4152.85 | Q118: =+N118*12 -> 13920 | R118: =+SUM(M118:N118)*6 -> 10759.5 | S118: =+SUM(L118:N118)*4 -> 7173 | T118: =+SUM(I118:N118)*2 -> 5495.7 | U118: =+SUM(C118:N118) -> 4152.85
B119: Repair R&M | C119: -208.09 | D119: 266.61 | E119: 0 | F119: 125 | G119: -105 | H119: 0 | I119: 0 | J119: 1123.32 | K119: 161.49 | L119: 397.86 | M119: 953.46 | N119: 1175 | O119: 3889.65 | Q119: =+N119*12 -> 14100 | R119: =+SUM(M119:N119)*6 -> 12770.76 | S119: =+SUM(L119:N119)*4 -> 10105.28 | T119: =+SUM(I119:N119)*2 -> 7622.26 | U119: =+SUM(C119:N119) -> 3889.65
B120: Equipment/Tools R&M | C120: 2539.26 | D120: 0 | E120: 0 | F120: -118 | G120: 0 | H120: 0 | I120: 128.99 | J120: 0 | K120: 0 | L120: 0 | M120: 0 | N120: 0 | O120: 2550.25 | Q120: =+N120*12 -> 0 | R120: =+SUM(M120:N120)*6 -> 0 | S120: =+SUM(L120:N120)*4 -> 0 | T120: =+SUM(I120:N120)*2 -> 257.98 | U120: =+SUM(C120:N120) -> 2550.25
B121: Maintenance Services Request | C121: 175 | D121: 0 | E121: 75 | F121: 0 | G121: 50 | H121: 50 | I121: 25 | J121: 0 | K121: 0 | L121: 0 | M121: 0 | N121: 0 | O121: 375 | Q121: =+N121*12 -> 0 | R121: =+SUM(M121:N121)*6 -> 0 | S121: =+SUM(L121:N121)*4 -> 0 | T121: =+SUM(I121:N121)*2 -> 50 | U121: =+SUM(C121:N121) -> 375
B122: Trash Cleanup | C122: 0 | D122: 0 | E122: 0 | F122: 0 | G122: 0 | H122: 315 | I122: 370 | J122: 0 | K122: 0 | L122: 0 | M122: 0 | N122: 0 | O122: 685 | Q122: =+N122*12 -> 0 | R122: =+SUM(M122:N122)*6 -> 0 | S122: =+SUM(L122:N122)*4 -> 0 | T122: =+SUM(I122:N122)*2 -> 740 | U122: =+SUM(C122:N122) -> 685
B123: Bulk Trash Pickup | C123: 545 | D123: 0 | E123: 445 | F123: 0 | G123: 470 | H123: 1515 | I123: 504.68 | J123: 0 | K123: 0 | L123: 0 | M123: 730 | N123: 450 | O123: 4659.68 | Q123: =+N123*12 -> 5400 | R123: =+SUM(M123:N123)*6 -> 7080 | S123: =+SUM(L123:N123)*4 -> 4720 | T123: =+SUM(I123:N123)*2 -> 3369.36 | U123: =+SUM(C123:N123) -> 4659.68
B124: Vehicle Maint & Fuel | C124: 0 | D124: 0 | E124: 0 | F124: 0 | G124: 0 | H124: 0 | I124: 0 | J124: 0 | K124: 38.5 | L124: 0 | M124: 0 | N124: 0 | O124: 38.5 | Q124: =+N124*12 -> 0 | R124: =+SUM(M124:N124)*6 -> 0 | S124: =+SUM(L124:N124)*4 -> 0 | T124: =+SUM(I124:N124)*2 -> 77 | U124: =+SUM(C124:N124) -> 38.5
A125: 11 | B125: Total Repairs and Maintenance | C125: 3774.54 | D125: 7577.42 | E125: 4542.23 | F125: 3077.8 | G125: 5270.89 | H125: 4609.13 | I125: 9282.4 | J125: 5700.66 | K125: 702.97 | L125: 5245.66 | M125: 5314.97 | N125: 9401.41 | O125: 64500.08 | Q125: =+N125*12 -> 112816.92 | R125: =+SUM(M125:N125)*6 -> 88298.28 | S125: =+SUM(L125:N125)*4 -> 79848.16 | T125: =+SUM(I125:N125)*2 -> 71296.14 | U125: =+SUM(C125:N125) -> 64500.08
B126: Contract Services | Q126: =+N126*12 -> 0 | R126: =+SUM(M126:N126)*6 -> 0 | S126: =+SUM(L126:N126)*4 -> 0 | T126: =+SUM(I126:N126)*2 -> 0 | U126: =+SUM(C126:N126) -> 0
B127: Pool R&M | C127: 0 | D127: 0 | E127: 0 | F127: 0 | G127: 0 | H127: 0 | I127: 0 | J127: 0 | K127: 19.34 | L127: 0 | M127: 169.81 | N127: 0 | O127: 189.15 | Q127: =+N127*12 -> 0 | R127: =+SUM(M127:N127)*6 -> 1018.86 | S127: =+SUM(L127:N127)*4 -> 679.24 | T127: =+SUM(I127:N127)*2 -> 378.3 | U127: =+SUM(C127:N127) -> 189.15
B128: Security/Fire Alarm R&M | C128: 0 | D128: 0 | E128: 0 | F128: 0 | G128: 0 | H128: 0 | I128: 0 | J128: 0 | K128: 0 | L128: 47.57 | M128: 0 | N128: 0 | O128: 47.57 | Q128: =+N128*12 -> 0 | R128: =+SUM(M128:N128)*6 -> 0 | S128: =+SUM(L128:N128)*4 -> 190.28 | T128: =+SUM(I128:N128)*2 -> 95.14 | U128: =+SUM(C128:N128) -> 47.57
B129: Lift Station R&M | C129: 212 | D129: 0 | E129: 887 | F129: 0 | G129: 1186.18 | H129: 106 | I129: 0 | J129: 523.3 | K129: 0 | L129: 0 | M129: 0 | N129: 2953.9 | O129: 5868.38 | Q129: =+N129*12 -> 35446.8 | R129: =+SUM(M129:N129)*6 -> 17723.4 | S129: =+SUM(L129:N129)*4 -> 11815.6 | T129: =+SUM(I129:N129)*2 -> 6954.4 | U129: =+SUM(C129:N129) -> 5868.38
B130: Handy Trac Monthly Service | C130: 19.95 | D130: 0 | E130: 24.95 | F130: 24.95 | G130: 24.95 | H130: 0 | I130: 49.9 | J130: 0 | K130: 0 | L130: 0 | M130: 0 | N130: 0 | O130: 144.7 | Q130: =+N130*12 -> 0 | R130: =+SUM(M130:N130)*6 -> 0 | S130: =+SUM(L130:N130)*4 -> 0 | T130: =+SUM(I130:N130)*2 -> 99.8 | U130: =+SUM(C130:N130) -> 144.7
...

Sheet IS 2024
B1: CLUB AT CHARTER POINTE
B2: Twelve Month Trailing Income Statement
B3: 45657
F4: 45322 | G4: 45351 | H4: 45382 | I4: 45412 | J4: 45443 | K4: 45473 | L4: 45504 | M4: 45535 | N4: 45565 | O4: 45596 | P4: 45626 | Q4: 45657 | R4: Total
F5: Actual | G5: Actual | H5: Actual | I5: Actual | J5: Actual | K5: Actual | L5: Actual | M5: Actual | N5: Actual | O5: Actual | P5: Actual | Q5: Actual | T5: T1 | U5: T3 | V5: T12
B6: Income:
B7: Rental Income
B8: 40000 | C8: Gross Potential
B9: 40091 | C9: Income for Renovated Units
B10: 41000 | C10: Rent Below Unit Schedules
B11: 41010 | C11: Rent Exceeding Unit Schedule
A12: 1 | B12: Net Effective Rent
B14: Vacancy , Losses and Concessions
A15: 7 | B15: 40020 | C15: Corporate Suite Income
A16: 7 | B16: 40025 | C16: Retail Income
A17: 7 | B17: 40027 | C17: CAM Income
A18: 2 | B18: 41020 | C18: Vacancies
A19: 5 | B19: 41030 | C19: Models
A20: 5 | B20: 41040 | C20: Rent Due to Down Units
A21: 3 | B21: 41050 | C21: Employee Concessions
A22: 3 | B22: 41070 | C22: Courtesy Officer Concession
A23: 3 | B23: 41080 | C23: New One Time Concessions
A24: 3 | B24: 41090 | C24: Concession Prorated Over Lease
A25: 3 | B25: 41091 | C25: Concession for Renovated Unit
A26: 4 | B26: 41095 | C26: Bad Debt Expense
... A28: 4 | B28: 41097 | C28: COVID-19 Bad Debt Expense
B29: Total Vacancy , Losses and Concessions
B31: Total Rental Income
B33: Other Income
A34: 7 | B34: 42000 | C34: Carport Income
A35: 7 | B35: 42010 | C35: Carport/Valet Concession
A36: 7 | B36: 42100 | C36: Garage/Reserved Income
A37: 7 | B37: 42150 | C37: Parking Permit Income
A38: 7 | B38: 42200 | C38: Valet Parking Income
A39: 7 | B39: 42500 | C39: Non-Refundable Pet Fees
A40: 7 | B40: 42505 | C40: Pet Monthly Rent
A41: 6 | B41: 42800 | C41: Utility Reimbursement Income
A42: 7 | B42: 42810 | C42: Master Meter Electric Reimbursement
A43: 7 | B43: 42900 | C43: Storage Income
A44: 7 | B44: 42905 | C44: Renters Insurance Income
A45: 7 | B45: 43300 | C45: Damages & Other Fees
... A92: 7 | B92: 49999 | C92: Bad Debt-Other Income
B93: Total Other Income
B95: Total Income
B97: Expenses:
B98: Salaries & Employee Costs
B99: 60000 | C99: Salary Expense
B100: 60040 | C100: Other Salaries
B101: 60050 | C101: Employee Overtime
B102: 60055 | C102: Hiring Expense
B103: 60100 | C103: Commissions
B104: 60200 | C104: Bonus
B105: 60210 | C105: Maintenance Stipend
B106: 60250 | C106: Management Bonus
B107: 60300 | C107: 401K Matching
B108: 60310 | C108: Group Healthcare Premium
B109: 60350 | C109: Other Employee Benefit
B110: 60355 | C110: Rent Concession
... B114: 60600 | C114: Payroll Admin Fee
A115: 8 | B115: Total Salaries & Employee Costs
B117: Cleaning & Decorating
B118: 61000 | C118: Paint Supplies
B119: 61005 | C119: Contract Painting
B120: 61010 | C120: Cleaning Supplies
B121: 61015 | C121: Contract Cleaning
B122: 61020 | C122: Carpet Cleaning Supplies
B123: 61025 | C123: Contract Carpet Cleaning
B124: 61026 | C124: Contract General Resurfacing
B125: 61030 | C125: Contract Tub Resurfacing
A126: 13 | B126: Total Cleaning & Decorating
B128: Utilities
B129: 62000 | C129: Electric: House Accounts
B130: 62010 | C130: Electric: Model
B131: 62020 | C131: Electric: Vacants
B132: 62100 | C132: Water
B133: 62200 | C133: Sewer
B134: 62250 | C134: Utility Billing Fees
B135: 62300 | C135: Gas
B136: 62400 | C136: Trash Removal
B137: 62405 | C137: Compactor Rental
B138: 62500 | C138: Telephone
B139: 62505 | C139: Long Distance
B140: 62510 | C140: Answering Service
... B142: 62550 | C142: Cable (Not Contract Service)
A143: 14 | B143: Total Utilities
B145: Management & Professional
B146: 63000 | C146: Management Fee
B147: 63050 | C147: Asset Management Fee
B148: 63100 | C148: Legal Expense
B149: 63200 | C149: Accounting Expense
B150: 63300 | C150: Audit Fee
B151: 63400 | C151: Other Professional Fees
A152: 17 | B152: Total Management & Professional
B154: Contract Services
B155: 63500 | C155: Landscaping
B156: 63501 | C156: Snow Removal
B157: 63510 | C157: Lakes & Canals
B158: 63520 | C158: Pool
B159: 63525 | C159: Fountain Service
B160: 63530 | C160: Exterminating
...

Sheet IS 2023
B1: CLUB AT CHARTER POINTE
B2: Twelve Month Trailing Income Statement
B3: 45291
F4: 44957 | G4: 44985 | H4: 45016 | I4: 45046 | J4: 45077 | K4: 45107 | L4: 45138 | M4: 45169 | N4: 45199 | O4: 45230 | P4: 45260 | Q4: 45291 | R4: Total
F5: Actual | G5: Actual | H5: Actual | I5: Actual | J5: Actual | K5: Actual | L5: Actual | M5: Actual | N5: Actual | O5: Actual | P5: Actual | Q5: Actual | T5: T1 | U5: T3 | V5: T12
B6: Income:
B7: Rental Income
B8: 40000 | C8: Gross Potential
B9: 40091 | C9: Income for Renovated Units
B10: 41000 | C10: Rent Below Unit Schedules
B11: 41010 | C11: Rent Exceeding Unit Schedule
A12: 1 | B12: Net Effective Rent
B14: Vacancy , Losses and Concessions
A15: 7 | B15: 40020 | C15: Corporate Suite Income
A16: 7 | B16: 40025 | C16: Retail Income
A17: 7 | B17: 40027 | C17: CAM Income
A18: 2 | B18: 41020 | C18: Vacancies
A19: 5 | B19: 41030 | C19: Models
A20: 5 | B20: 41040 | C20: Rent Due to Down Units
A21: 3 | B21: 41050 | C21: Employee Concessions
A22: 3 | B22: 41070 | C22: Courtesy Officer Concession
A23: 3 | B23: 41080 | C23: New One Time Concessions
A24: 3 | B24: 41090 | C24: Concession Prorated Over Lease
A25: 3 | B25: 41091 | C25: Concession for Renovated Unit
A26: 4 | B26: 41095 | C26: Bad Debt Expense
... A28: 4 | B28: 41097 | C28: COVID-19 Bad Debt Expense
B29: Total Vacancy , Losses and Concessions
B31: Total Rental Income
B33: Other Income
A34: 7 | B34: 42000 | C34: Carport Income
A35: 7 | B35: 42010 | C35: Carport/Valet Concession
A36: 7 | B36: 42100 | C36: Garage/Reserved Income
A37: 7 | B37: 42150 | C37: Parking Permit Income
A38: 7 | B38: 42200 | C38: Valet Parking Income
A39: 7 | B39: 42500 | C39: Non-Refundable Pet Fees
A40: 7 | B40: 42505 | C40: Pet Monthly Rent
A41: 6 | B41: 42800 | C41: Utility Reimbursement Income
A42: 7 | B42: 42810 | C42: Master Meter Electric Reimbursement
A43: 7 | B43: 42900 | C43: Storage Income
A44: 7 | B44: 42905 | C44: Renters Insurance Income
A45: 7 | B45: 43300 | C45: Damages & Other Fees
... A92: 7 | B92: 49999 | C92: Bad Debt-Other Income
B93: Total Other Income
B95: Total Income
B97: Expenses:
B98: Salaries & Employee Costs
B99: 60000 | C99: Salary Expense
B100: 60040 | C100: Other Salaries
B101: 60050 | C101: Employee Overtime
B102: 60055 | C102: Hiring Expense
B103: 60100 | C103: Commissions
B104: 60200 | C104: Bonus
B105: 60210 | C105: Maintenance Stipend
B106: 60250 | C106: Management Bonus
B107: 60300 | C107: 401K Matching
B108: 60310 | C108: Group Healthcare Premium
B109: 60350 | C109: Other Employee Benefit
B110: 60355 | C110: Rent Concession
... B114: 60600 | C114: Payroll Admin Fee
A115: 8 | B115: Total Salaries & Employee Costs
B117: Cleaning & Decorating
B118: 61000 | C118: Paint Supplies
B119: 61005 | C119: Contract Painting
B120: 61010 | C120: Cleaning Supplies
B121: 61015 | C121: Contract Cleaning
B122: 61020 | C122: Carpet Cleaning Supplies
B123: 61025 | C123: Contract Carpet Cleaning
B124: 61026 | C124: Contract General Resurfacing
B125: 61030 | C125: Contract Tub Resurfacing
A126: 13 | B126: Total Cleaning & Decorating
B128: Utilities
B129: 62000 | C129: Electric: House Accounts
B130: 62010 | C130: Electric: Model
B131: 62020 | C131: Electric: Vacants
B132: 62100 | C132: Water
B133: 62200 | C133: Sewer
B134: 62250 | C134: Utility Billing Fees
B135: 62300 | C135: Gas
B136: 62400 | C136: Trash Removal
B137: 62405 | C137: Compactor Rental
B138: 62500 | C138: Telephone
B139: 62505 | C139: Long Distance
B140: 62510 | C140: Answering Service
... B142: 62550 | C142: Cable (Not Contract Service)
A143: 14 | B143: Total Utilities
B145: Management & Professional
B146: 63000 | C146: Management Fee
B147: 63050 | C147: Asset Management Fee
B148: 63100 | C148: Legal Expense
B149: 63200 | C149: Accounting Expense
B150: 63300 | C150: Audit Fee
B151: 63400 | C151: Other Professional Fees
A152: 17 | B152: Total Management & Professional
B154: Contract Services
B155: 63500 | C155: Landscaping
B156: 63501 | C156: Snow Removal
B157: 63510 | C157: Lakes & Canals
B158: 63520 | C158: Pool
B159: 63525 | C159: Fountain Service
B160: 63530 | C160: Exterminating
...

Sheet IS 2022
B1: CLUB AT CHARTER POINTE
B2: Twelve Month Trailing Income Statement
B3: 44926
F4: 44592 | G4: 44620 | H4: 44651 | I4: 44681 | J4: 44712 | K4: 44742 | L4: 44773 | M4: 44804 | N4: 44834 | O4: 44865 | P4: 44895 | Q4: 44926 | R4: Total
F5: Actual | G5: Actual | H5: Actual | I5: Actual | J5: Actual | K5: Actual | L5: Actual | M5: Actual | N5: Actual | O5: Actual | P5: Actual | Q5: Actual | T5: T1 | U5: T3 | V5: T12
B6: Income:
B7: Rental Income
B8: 40000 | C8: Gross Potential
B9: 40091 | C9: Income for Renovated Units
B10: 41000 | C10: Rent Below Unit Schedules
B11: 41010 | C11: Rent Exceeding Unit Schedule
A12: 1 | B12: Net Effective Rent
B14: Vacancy , Losses and Concessions
A15: 7 | B15: 40020 | C15: Corporate Suite Income
A16: 7 | B16: 40025 | C16: Retail Income
A17: 7 | B17: 40027 | C17: CAM Income
A18: 2 | B18: 41020 | C18: Vacancies
A19: 5 | B19: 41030 | C19: Models
A20: 5 | B20: 41040 | C20: Rent Due to Down Units
A21: 3 | B21: 41050 | C21: Employee Concessions
A22: 3 | B22: 41070 | C22: Courtesy Officer Concession
A23: 3 | B23: 41080 | C23: New One Time Concessions
A24: 3 | B24: 41090 | C24: Concession Prorated Over Lease
A25: 3 | B25: 41091 | C25: Concession for Renovated Unit
A26: 4 | B26: 41095 | C26: Bad Debt Expense
... A28: 4 | B28: 41097 | C28: COVID-19 Bad Debt Expense
B29: Total Vacancy , Losses and Concessions
B31: Total Rental Income
B33: Other Income
A34: 7 | B34: 42000 | C34: Carport Income
A35: 7 | B35: 42010 | C35: Carport/Valet Concession
A36: 7 | B36: 42100 | C36: Garage/Reserved Income
A37: 7 | B37: 42150 | C37: Parking Permit Income
A38: 7 | B38: 42200 | C38: Valet Parking Income
A39: 7 | B39: 42500 | C39: Non-Refundable Pet Fees
A40: 7 | B40: 42505 | C40: Pet Monthly Rent
A41: 6 | B41: 42800 | C41: Utility Reimbursement Income
A42: 7 | B42: 42810 | C42: Master Meter Electric Reimbursement
A43: 7 | B43: 42900 | C43: Storage Income
A44: 7 | B44: 42905 | C44: Renters Insurance Income
A45: 7 | B45: 43300 | C45: Damages & Other Fees
... A91: 7 | B91: 49998 | C91: COVID-19 Bad Debt Other Income
B92: Total Other Income
B94: Total Income
B96: Expenses:
B97: Salaries & Employee Costs
B98: 60000 | C98: Salary Expense
B99: 60040 | C99: Other Salaries
B100: 60050 | C100: Employee Overtime
B101: 60055 | C101: Hiring Expense
B102: 60100 | C102: Commissions
B103: 60200 | C103: Bonus
B104: 60210 | C104: Maintenance Stipend
B105: 60250 | C105: Management Bonus
B106: 60300 | C106: 401K Matching
B107: 60310 | C107: Group Healthcare Premium
B108: 60350 | C108: Other Employee Benefit
B109: 60355 | C109: Rent Concession
... B113: 60600 | C113: Payroll Admin Fee
A114: 8 | B114: Total Salaries & Employee Costs
B116: Cleaning & Decorating
B117: 61000 | C117: Paint Supplies
B118: 61005 | C118: Contract Painting
B119: 61010 | C119: Cleaning Supplies
B120: 61015 | C120: Contract Cleaning
B121: 61020 | C121: Carpet Cleaning Supplies
B122: 61025 | C122: Contract Carpet Cleaning
B123: 61026 | C123: Contract General Resurfacing
B124: 61030 | C124: Contract Tub Resurfacing
A125: 13 | B125: Total Cleaning & Decorating
B127: Utilities
B128: 62000 | C128: Electric: House Accounts
B129: 62010 | C129: Electric: Model
B130: 62020 | C130: Electric: Vacants
B131: 62100 | C131: Water
B132: 62200 | C132: Sewer
B133: 62250 | C133: Utility Billing Fees
B134: 62300 | C134: Gas
B135: 62400 | C135: Trash Removal
B136: 62405 | C136: Compactor Rental
B137: 62500 | C137: Telephone
B138: 62505 | C138: Long Distance
B139: 62510 | C139: Answering Service
... B141: 62550 | C141: Cable (Not Contract Service)
A142: 14 | B142: Total Utilities
B144: Management & Professional
B145: 63000 | C145: Management Fee
B146: 63050 | C146: Asset Management Fee
B147: 63100 | C147: Legal Expense
B148: 63200 | C148: Accounting Expense
B149: 63300 | C149: Audit Fee
B150: 63400 | C150: Other Professional Fees
A151: 17 | B151: Total Management & Professional
B153: Contract Services
B154: 63500 | C154: Landscaping
B155: 63501 | C155: Snow Removal
B156: 63510 | C156: Lakes & Canals
B157: 63520 | C157: Pool
B158: 63525 | C158: Fountain Service
B159: 63530 | C159: Exterminating
...

Sheet RR 12-16-25
A1: Rent Roll
A2: Exported On: 12/16/2025 04:57 PM
A4: Properties: All
A5: Units: Active
A6: As of: 12/16/2025
A7: Include Non-Revenue Units: No
A9: Unit | B9: BD/BA | C9: Sqft | D9: Tenant | E9: Status | G9: Market Rent | H9: Rent | I9: Recurring Charges | J9: Lease From | K9: Lease To | L9: Move-in | M9: Move-out | N9: Past Due | O9: NSF Count | P9: Late Count
A10: Oasis at San Marco - 4800 Atlantic Blvd Jacksonville, FL 32207
A11: B137 | B11: 1/1.00 | C11: 650 | E11: Vacant-Unrented | F11: Vacant | G11: 1029 | I11: 0
A12: G138 | B12: 2/1.50 | C12: 850 | E12: Vacant-Unrented | F12: Vacant | G12: 1199 | I12: 0
A13: G240 | B13: 2/1.50 | C13: 850 | E13: Vacant-Rented | F13: Vacant | G13: 1149 | I13: 0
A14: B132 | B14: 1/1.00 | C14: 650 | D14: Vivian Jenkins | E14: Evict | F14: Vacant | G14: 1029 | H14: 620 | I14: 120.5 | J14: 41694 | K14: 45838 | L14: 41694 | N14: 4344.1 | O14: 0 | P14: 7
A15: B236 | B15: 1/1.00 | C15: 650 | D15: Persharon Jennings | E15: Current | F15: Occupied | G15: 1029 | H15: 632 | I15: 45 | J15: 42307 | K15: 45470 | L15: 42307 | N15: 1410 | O15: 0 | P15: 2
A16: B136 | B16: 1/1.00 | C16: 650 | D16: Arlene Marcellus-Summers | E16: Current | F16: Occupied | G16: 1029 | H16: 905 | I16: 239.5 | J16: 43483 | K16: 45912 | L16: 43483 | N16: 0 | O16: 0 | P16: 0
A17: F213 | B17: 1/1.00 | C17: 650 | D17: Doris Blake | E17: Current | F17: Occupied | G17: 1029 | H17: 925 | I17: 96.5 | J17: 43203 | K17: 46356 | L17: 43203 | N17: 0 | O17: 0 | P17: 0
A18: F113 | B18: 1/1.00 | C18: 650 | D18: Lisa Colon | E18: Current | F18: Occupied | G18: 1029 | H18: 943 | I18: 113.5 | J18: 40764 | K18: 46147 | L18: 40764 | N18: 2571.5 | O18: 0 | P18: 2
A19: B134 | B19: 1/1.00 | C19: 650 | D19: Myia M. Natson-Green | E19: Current | F19: Occupied | G19: 1029 | H19: 949 | I19: 121.5 | J19: 45930 | K19: 46294 | L19: 45930 | N19: 0 | O19: 0 | P19: 0
A20: B232 | B20: 1/1.00 | C20: 650 | D20: Jemuel A. Derla | E20: Current | F20: Occupied | G20: 1029 | H20: 949 | I20: 121.5 | J20: 45891 | K20: 46265 | L20: 45891 | N20: 0 | O20: 0 | P20: 0
A21: B234 | B21: 1/1.00 | C21: 650 | D21: Tavish D. Reynolds | E21: Current | F21: Occupied | G21: 1029 | H21: 949 | I21: 121.5 | J21: 45899 | K21: 46265 | L21: 45899 | N21: 0 | O21: 0 | P21: 1
A22: F111 | B22: 1/1.00 | C22: 650 | D22: Asia R. Lincoln | E22: Current | F22: Occupied | G22: 1029 | H22: 949 | I22: 121.5 | J22: 45910 | K22: 46295 | L22: 45910 | N22: 0 | O22: 0 | P22: 0
A23: F115 | B23: 1/1.00 | C23: 650 | D23: Donnalyn A. Montgomery | E23: Current | F23: Occupied | G23: 1029 | H23: 949 | I23: 106 | J23: 45930 | K23: 46294 | L23: 45930 | N23: 0 | O23: 0 | P23: 0
A24: I156 | B24: 1/1.00 | C24: 650 | D24: Carlos A. Garcia | E24: Current | F24: Occupied | G24: 1029 | H24: 949 | I24: 121.5 | J24: 45910 | K24: 46274 | L24: 45910 | N24: 0 | O24: 0 | P24: 0
A25: I254 | B25: 1/1.00 | C25: 650 | D25: Adriana Pedroso | E25: Current | F25: Occupied | G25: 1029 | H25: 949 | I25: 121.5 | J25: 45912 | K25: 46276 | L25: 45912 | N25: 0 | O25: 0 | P25: 0
... A42: F212 | B42: 1/1.00 | C42: 650 | D42: Shawn Geddes | E42: Current | F42: Occupied | G42: 1029 | H42: 999 | I42: 111.5 | J42: 45582 | K42: 46295 | L42: 45582 | N42: 1721 | O42: 0 | P42: 4
A43: F214 | B43: 1/1.00 | C43: 650 | D43: Wayne Wicker | E43: Current | F43: Occupied | G43: 1029 | H43: 999 | I43: 96.5 | K43: 46326 | L43: 41979 | N43: 0 | O43: 0 | P43: 1
A44: I158 | B44: 1/1.00 | C44: 650 | D44: Kassidy King | E44: Current | F44: Occupied | G44: 1029 | H44: 999 | I44: 113.5 | J44: 45778 | K44: 46142 | L44: 45778 | N44: 0 | O44: 0 | P44: 0
A45: I256 | B45: 1/1.00 | C45: 650 | D45: Nelson Perdomo Alvarez | E45: Current | F45: Occupied | G45: 1029 | H45: 999 | I45: 113.5 | J45: 45383 | K45: 46112 | L45: 45383 | N45: 0 | O45: 0 | P45: 0
A46: J246 | B46: 2/1.00 | C46: 800 | D46: Pashent Robinson | E46: Current | F46: Occupied | G46: 1049 | H46: 999 | J46: 45900 | K46: 46264 | L46: 45900 | N46: 0 | O46: 0 | P46: 1
A47: J247 | B47: 2/1.00 | C47: 800 | D47: Shelly Diallo | E47: Current | F47: Occupied | G47: 1049 | H47: 999 | I47: 118.5 | J47: 45880 | K47: 46244 | L47: 45880 | N47: 2335.9 | O47: 0 | P47: 4
A48: J249 | B48: 2/1.00 | C48: 800 | D48: Aaliyah K. Myers | E48: Current | F48: Occupied | G48: 1049 | H48: 999 | I48: 122 | J48: 45891 | K48: 46265 | L48: 45891 | N48: 0 | O48: 0 | P48: 0
A49: E118 | B49: 2/1.00 | C49: 800 | D49: Miguel Munoz Alvarado | E49: Current | F49: Occupied | G49: 1049 | H49: 1000 | I49: 158.5 | J49: 45055 | K49: 45777 | L49: 45055 | N49: 0 | O49: 0 | P49: 0
A50: C228 | B50: 1/1.00 | C50: 650 | D50: Ability Housing, Inc. | E50: Current | F50: Occupied | G50: 1029 | H50: 1025 | I50: 111.5 | J50: 45618 | K50: 46349 | L50: 45618 | N50: -598 | O50: 0 | P50: 3
A51: F215 | B51: 1/1.00 | C51: 650 | D51: Presbyterian Social Ministries | E51: Current | F51: Occupied | G51: 1029 | H51: 1025 | I51: 111.5 | J51: 45595 | K51: 46326 | L51: 45595 | N51: 0 | O51: 0 | P51: 3
A52: D225 | B52: 2/1.50 | C52: 850 | D52: Omega A. Johnson | E52: Current | F52: Occupied | G52: 1149 | H52: 1029 | I52: 121.5 | J52: 45982 | K52: 46339 | L52: 45975 | N52: 40.5 | O52: 0 | P52: 0
A53: J150 | B53: 2/1.00 | C53: 800 | D53: Lacoria S. Glover | E53: Current | F53: Occupied | G53: 1049 | H53: 1029 | I53: 121.5 | J53: 46003 | K53: 46367 | L53: 46003 | N53: 0 | O53: 0 | P53: 0
A54: D226 | B54: 2/1.50 | C54: 850 | D54: Lisandro Matos | E54: Current | F54: Occupied | G54: 1149 | H54: 1030 | I54: 106.5 | J54: 42620 | K54: 46326 | L54: 42620 | N54: 0 | O54: 0 | P54: 0
A55: C229 | B55: 1/1.00 | C55: 650 | D55: Beryl Davis III | E55: Current | F55: Occupied | G55: 1029 | H55: 1040 | I55: 133.5 | J55: 44968 | K55: 45747 | L55: 44968 | N55: 0 | O55: 0 | P55: 2
A56: B235 | B56: 1/1.00 | C56: 650 | D56: Andre Outlaw | E56: Current | F56: Occupied | G56: 1029 | H56: 1045 | I56: 153 | J56: 45313 | K56: 46053 | L56: 45313 | N56: 0 | O56: 0 | P56: 2
A57: A103 | B57: 2/1.50 | C57: 850 | D57: Nicole J. Rhodes | E57: Current | F57: Occupied | G57: 1199 | H57: 1049 | I57: 121.5 | J57: 45992 | K57: 46356 | L57: 45992 | N57: 0 | O57: 0 | P57: 0
A58: A106 | B58: 2/1.50 | C58: 850 | D58: Darius A. Baldwin | E58: Current | F58: Occupied | G58: 1149 | H58: 1049 | I58: 121.5 | J58: 45930 | K58: 46295 | L58: 45930 | N58: 1342.95 | O58: 0 | P58: 1
... A97: A204 | B97: 2/1.50 | C97: 850 | D97: Yenisel Fernandez | E97: Current | F97: Occupied | G97: 1149 | H97: 1100 | I97: 130.5 | J97: 45383 | K97: 45737 | L97: 45383 | N97: 0 | O97: 0 | P97: 0
A98: G142 | B98: 2/1.50 | C98: 850 | D98: Danier Delagado Sanchez | E98: Notice-Unrented | F98: Occupied | G98: 1149 | H98: 1100 | I98: 119 | J98: 45272 | K98: 46022 | L98: 45272 | M98: 46022 | N98: 0 | O98: 0 | P98: 0
A99: D120 | B99: 1/1.00 | C99: 650 | D99: Najah Mayo | E99: Current | F99: Occupied | G99: 1029 | H99: 1101 | I99: 91 | J99: 43686 | K99: 46265 | L99: 43686 | N99: 0 | O99: 0 | P99: 0
A100: I154 | B100: 1/1.00 | C100: 650 | D100: Cecilio O. Orta-Martinez | E100: Current | F100: Occupied | G100: 1029 | H100: 1108 | I100: -1 | J100: 45809 | K100: 46173 | L100: 45809 | N100: 0 | O100: 0 | P100: 2
A101: G241 | B101: 2/1.50 | C101: 850 | D101: Delia Eslavon | E101: Current | F101: Occupied | G101: 1149 | H101: 1128 | I101: 98.5 | J101: 40634 | K101: 46044 | L101: 40634 | N101: 0 | O101: 0 | P101: 0
A102: A104 | B102: 2/1.50 | C102: 850 | D102: Yisen Montalvo | E102: Current | F102: Occupied | G102: 1149 | H102: 1130 | I102: 139.5 | J102: 45931 | K102: 46295 | L102: 45110 | N102: 0 | O102: 0 | P102: 0
A103: D222 | B103: 2/1.50 | C103: 850 | D103: Ameer Hamza | E103: Current | F103: Occupied | G103: 1199 | H103: 1149 | I103: 121.5 | J103: 45930 | K103: 46295 | L103: 45930 | N103: 1640.5 | O103: 0 | P103: 1
A104: H165 | B104: 2/1.50 | C104: 850 | D104: Deborah L. Anderson | E104: Current | F104: Occupied | G104: 1199 | H104: 1149 | I104: 121.5 | J104: 45941 | K104: 46305 | L104: 45941 | N104: -10.05 | O104: 0 | P104: 1
A105: A107 | B105: 2/1.50 | C105: 850 | D105: Baktash Nawan | E105: Current | F105: Occupied | G105: 1149 | H105: 1150 | I105: 79.5 | J105: 44558 | K105: 46024 | L105: 44558 | N105: 0 | O105: 0 | P105: 1
A106: A109 | B106: 2/1.50 | C106: 850 | D106: Adams Ghaji | E106: Current | F106: Occupied | G106: 1149 | H106: 1150 | I106: 134.5 | J106: 45164 | K106: 46259 | L106: 45164 | N106: 0 | O106: 0 | P106: 0
A107: D122 | B107: 2/1.50 | C107: 850 | D107: Moises Francisco | E107: Current | F107: Occupied | G107: 1149 | H107: 1150 | I107: 179.5 | J107: 45113 | K107: 45869 | L107: 45113 | N107: 0 | O107: 0 | P107: 0
A108: D227 | B108: 2/1.50 | C108: 850 | D108: Antwanette Johnekins | E108: Current | F108: Occupied | G108: 1149 | H108: 1150 | I108: 134.5 | J108: 45243 | K108: 46356 | L108: 45243 | N108: 0 | O108: 0 | P108: 0
A109: J250 | B109: 2/1.00 | C109: 800 | D109: Angel Moya | E109: Current | F109: Occupied | G109: 1049 | H109: 1150 | I109: 149.5 | J109: 45288 | K109: 46018 | L109: 45288 | N109: -50.5 | O109: 0 | P109: 0
A110: G243 | B110: 2/1.50 | C110: 850 | D110: Tilor Correll | E110: Current | F110: Occupied | G110: 1149 | H110: 1157 | I110: 142.5 | J110: 44938 | K110: 46033 | L110: 44938 | N110: 0 | O110: 0 | P110: 0
... A137: I155 | B137: 3/2.00 | C137: 1150 | D137: Abdullah Hassan | E137: Current | F137: Occupied | G137: 1399 | H137: 1425 | I137: 121.5 | J137: 45551 | K137: 46332 | L137: 45551 | N137: 107 | O137: 0 | P137: 2
A138: 127 Units | C138: 100950 | E138: 97.6% Occupied | G138: 142193 | H138: 134193 | I138: 14221 | N138: 34219.6 | O138: 16 | P138: 101
A140: Total 127 Units | C140: 100950 | E140: 97.6% Occupied | G140: 142193 | H140: 134193 | I140: 14221 | N140: 34219.6 | O140: 16 | P140: 101
F147: GPR CALCULATION
F149: Status | G149: Units | H149: Occupancy | I149: Market Rent | J149: In-Place Rent | K149: GPR
F150: Occupied | G150: =+COUNTIFS($F$11:$F$137,$F150) -> 122 | H150: =+G150/$G$152 -> 0.96062992 | I150: =+SUMIFS(G$11:G$137,$F$11:$F$137,$F150) -> 136638 | J150: =+SUMIFS(H$11:H$137,$F$11:$F$137,$F150) -> 132398 | K150: =+J150 -> 132398
F151: Vacant | G151: =+COUNTIFS($F$11:$F$137,$F151) -> 5 | H151: =+G151/$G$152 -> 0.039370079 | I151: =+SUMIFS(G$11:G$137,$F$11:$F$137,$F151) -> 5555 | J151: =+SUMIFS(H$11:H$137,$F$11:$F$137,$F151) -> 1795 | K151: =+I151 -> 5555
F152: Total | G152: =+SUM(G150:G151) -> 127 | H152: =+G152/$G$152 -> 1 | I152: =+SUM(I150:I151) -> 142193 | J152: =+SUM(J150:J151) -> 134193 | K152: =+SUM(K150:K151) -> 137953

Sheet RR 11-4-25
A1: Rent Roll
A2: Exported On: 11/04/2025 01:18 PM
A4: Properties: All
A5: Units: Active
A6: As of: 10/31/2025
A7: Include Non-Revenue Units: No
A9: Unit | B9: BD/BA | C9: Sqft | D9: Tenant | E9: Status | G9: Market Rent | H9: Rent | I9: Recurring Charges | J9: Lease From | K9: Lease To | L9: Move-in | M9: Move-out | N9: Past Due | O9: NSF Count | P9: Late Count
A10: Oasis at San Marco - 4800 Atlantic Blvd Jacksonville, FL 32207
A11: G138 | B11: 2/1.50 | C11: 850 | E11: Vacant-Unrented | F11: Vacant | G11: 1199 | I11: 0
A12: I153 | B12: 3/2.00 | C12: 1150 | E12: Vacant-Unrented | F12: Vacant | G12: 1399 | I12: 0
A13: B132 | B13: 1/1.00 | C13: 650 | D13: Vivian Jenkins | E13: Evict | F13: Vacant | G13: 1029 | H13: 620 | I13: 120.5 | J13: 41694 | K13: 45838 | L13: 41694 | N13: 2839.1 | O13: 0 | P13: 5
A14: B236 | B14: 1/1.00 | C14: 650 | D14: Persharon Jennings | E14: Current | F14: Occupied | G14: 1029 | H14: 632 | I14: 45 | J14: 42307 | K14: 45470 | L14: 42307 | N14: 733 | O14: 0 | P14: 2
A15: F213 | B15: 1/1.00 | C15: 650 | D15: Doris Blake | E15: Current | F15: Occupied | G15: 1029 | H15: 900 | I15: 96.5 | J15: 43203 | K15: 45991 | L15: 43203 | N15: -996.5 | O15: 0 | P15: 0
A16: B136 | B16: 1/1.00 | C16: 650 | D16: Arlene Marcellus-Summers | E16: Current | F16: Occupied | G16: 1029 | H16: 905 | I16: 139.5 | J16: 43483 | K16: 45912 | L16: 43483 | N16: 0 | O16: 0 | P16: 0
A17: F113 | B17: 1/1.00 | C17: 650 | D17: Lisa Colon | E17: Current | F17: Occupied | G17: 1029 | H17: 943 | I17: 113.5 | J17: 40764 | K17: 46147 | L17: 40764 | N17: 1511.5 | O17: 0 | P17: 2
A18: C131 | B18: 1/1.00 | C18: 650 | D18: Victoria Acevedo | E18: Current | F18: Occupied | G18: 1029 | H18: 945 | I18: 124.5 | J18: 44883 | K18: 45991 | L18: 44883 | N18: -1069.5 | O18: 0 | P18: 1
A19: B134 | B19: 1/1.00 | C19: 650 | D19: Myia M. Natson-Green | E19: Current | F19: Occupied | G19: 1029 | H19: 949 | I19: -949 | J19: 45930 | K19: 46294 | L19: 45930 | N19: -570.5 | O19: 0 | P19: 0
A20: B232 | B20: 1/1.00 | C20: 650 | D20: Jemuel A. Derla | E20: Current | F20: Occupied | G20: 1029 | H20: 949 | I20: -378.5 | J20: 45891 | K20: 46265 | L20: 45891 | N20: -25.31 | O20: 0 | P20: 0
A21: B234 | B21: 1/1.00 | C21: 650 | D21: Tavish D. Reynolds | E21: Current | F21: Occupied | G21: 1029 | H21: 949 | I21: 121.5 | J21: 45899 | K21: 46265 | L21: 45899 | N21: -8 | O21: 0 | P21: 0
A22: F111 | B22: 1/1.00 | C22: 650 | D22: Asia R. Lincoln | E22: Current | F22: Occupied | G22: 1029 | H22: 949 | I22: -949 | J22: 45910 | K22: 46295 | L22: 45910 | N22: -570.5 | O22: 0 | P22: 0
A23: F115 | B23: 1/1.00 | C23: 650 | D23: Donnalyn A. Montgomery | E23: Current | F23: Occupied | G23: 1029 | H23: 949 | I23: -964.5 | J23: 45930 | K23: 46294 | L23: 45930 | N23: 0 | O23: 0 | P23: 0
A24: I156 | B24: 1/1.00 | C24: 650 | D24: Carlos A. Garcia | E24: Current | F24: Occupied | G24: 1029 | H24: 949 | I24: -949 | J24: 45910 | K24: 46274 | L24: 45910 | N24: -570.5 | O24: 0 | P24: 0
... A29: B135 | B29: 1/1.00 | C29: 650 | D29: Leslie Montalvo | E29: Current | F29: Occupied | G29: 1029 | H29: 999 | I29: 113.5 | J29: 45744 | K29: 46139 | L29: 45744 | N29: 0 | O29: 4 | P29: 2
A30: B137 | B30: 1/1.00 | C30: 650 | D30: Delrita Richards | E30: Evict | F30: Vacant | G30: 1029 | H30: 999 | I30: 124.5 | J30: 45152 | K30: 45900 | L30: 45152 | M30: 45964 | N30: 2742 | O30: 0 | P30: 5
A31: B237 | B31: 1/1.00 | C31: 650 | D31: Juan Esteban | E31: Current | F31: Occupied | G31: 1029 | H31: 999 | I31: 133.5 | J31: 45666 | K31: 46030 | L31: 45666 | N31: -1132.5 | O31: 0 | P31: 0
A32: C128 | B32: 1/1.00 | C32: 650 | D32: Jasmine Mixson | E32: Current | F32: Occupied | G32: 1029 | H32: 999 | I32: 109 | J32: 43511 | K32: 46234 | L32: 43511 | N32: 0 | O32: 0 | P32: 0
A33: C129 | B33: 1/1.00 | C33: 650 | D33: Julio Galindo Hernandez | E33: Current | F33: Occupied | G33: 1029 | H33: 999 | I33: 129.5 | J33: 45061 | K33: 46234 | L33: 45061 | N33: -1128.5 | O33: 0 | P33: 0
A34: C130 | B34: 1/1.00 | C34: 650 | D34: Leana S. Aldama | E34: Current | F34: Occupied | G34: 1029 | H34: 999 | I34: 121.5 | J34: 45867 | K34: 46234 | L34: 45867 | N34: 0 | O34: 0 | P34: 0
A35: C228 | B35: 1/1.00 | C35: 650 | D35: Ability Housing, Inc. | E35: Current | F35: Occupied | G35: 1029 | H35: 999 | I35: 111.5 | J35: 45618 | K35: 45982 | L35: 45618 | N35: -1629 | O35: 0 | P35: 3
A36: C230 | B36: 1/1.00 | C36: 650 | D36: Yanely Gomez | E36: Current | F36: Occupied | G36: 1029 | H36: 999 | I36: 111.5 | J36: 45601 | K36: 45961 | L36: 45601 | N36: -1110.5 | O36: 0 | P36: 0
A37: C231 | B37: 1/1.00 | C37: 650 | D37: Julianna Martinez | E37: Current | F37: Occupied | G37: 1029 | H37: 999 | I37: 141.5 | J37: 45630 | K37: 45994 | L37: 45630 | N37: -240.5 | O37: 0 | P37: 0
A38: E119 | B38: 2/1.00 | C38: 800 | D38: Michael Hays | E38: Current | F38: Occupied | G38: 1049 | H38: 999 | I38: -378.5 | J38: 45899 | K38: 46263 | L38: 45899 | N38: -1105 | O38: 0 | P38: 0
A39: F110 | B39: 1/1.00 | C39: 650 | D39: Alfredo Raudez Ramos | E39: Current | F39: Occupied | G39: 1029 | H39: 999 | I39: 113.5 | J39: 45772 | K39: 46142 | L39: 45772 | N39: 0 | O39: 0 | P39: 0
A40: F112 | B40: 1/1.00 | C40: 650 | D40: Frantzso Etienne | E40: Current | F40: Occupied | G40: 1029 | H40: 999 | I40: 105.5 | J40: 45710 | K40: 46074 | L40: 45710 | N40: 0 | O40: 2 | P40: 1
A41: F114 | B41: 1/1.00 | C41: 650 | D41: Yerili Rodriguez Chong | E41: Current | F41: Occupied | G41: 1029 | H41: 999 | I41: 118 | J41: 44228 | K41: 46053 | L41: 44228 | N41: -1117 | O41: 0 | P41: 0
A42: F210 | B42: 1/1.00 | C42: 650 | D42: Jose Hernandez | E42: Current | F42: Occupied | G42: 1029 | H42: 999 | I42: 141.5 | J42: 45659 | K42: 46023 | L42: 45659 | N42: -1140.5 | O42: 0 | P42: 2
A43: F212 | B43: 1/1.00 | C43: 650 | D43: Shawn Geddes | E43: Current | F43: Occupied | G43: 1029 | H43: 999 | I43: 111.5 | J43: 45582 | K43: 46295 | L43: 45582 | N43: 0 | O43: 0 | P43: 2
A44: F214 | B44: 1/1.00 | C44: 650 | D44: Wayne Wicker | E44: Current | F44: Occupied | G44: 1029 | H44: 999 | I44: 96.5 | K44: 46326 | L44: 41979 | N44: -1120 | O44: 0 | P44: 1
A45: F215 | B45: 1/1.00 | C45: 650 | D45: Presbyterian Social Ministries | E45: Current | F45: Occupied | G45: 1029 | H45: 999 | I45: 111.5 | J45: 45595 | K45: 45959 | L45: 45595 | N45: -3 | O45: 0 | P45: 3
A46: I158 | B46: 1/1.00 | C46: 650 | D46: Kassidy King | E46: Current | F46: Occupied | G46: 1029 | H46: 999 | I46: 113.5 | J46: 45778 | K46: 46142 | L46: 45778 | N46: 0 | O46: 0 | P46: 0
A47: I256 | B47: 1/1.00 | C47: 650 | D47: Nelson Perdomo Alvarez | E47: Current | F47: Occupied | G47: 1029 | H47: 999 | I47: 113.5 | J47: 45383 | K47: 46112 | L47: 45383 | N47: 0 | O47: 0 | P47: 0
A48: J246 | B48: 2/1.00 | C48: 800 | D48: Pashent Robinson | E48: Current | F48: Occupied | G48: 1049 | H48: 999 | J48: 45900 | K48: 46264 | L48: 45900 | N48: -600 | O48: 0 | P48: 0
A49: J247 | B49: 2/1.00 | C49: 800 | D49: Shelly Diallo | E49: Current | F49: Occupied | G49: 1049 | H49: 999 | I49: 118.5 | J49: 45880 | K49: 46244 | L49: 45880 | N49: 141 | O49: 0 | P49: 2
A50: J249 | B50: 2/1.00 | C50: 800 | D50: Aaliyah K. Myers | E50: Current | F50: Occupied | G50: 1049 | H50: 999 | I50: -378 | J50: 45891 | K50: 46265 | L50: 45891 | N50: -1121 | O50: 0 | P50: 0
A51: D226 | B51: 2/1.50 | C51: 850 | D51: Lisandro Matos | E51: Current | F51: Occupied | G51: 1149 | H51: 1000 | I51: 106.5 | J51: 42620 | K51: 46326 | L51: 42620 | N51: -1136.5 | O51: 0 | P51: 0
A52: E118 | B52: 2/1.00 | C52: 800 | D52: Miguel Munoz Alvarado | E52: Current | F52: Occupied | G52: 1049 | H52: 1000 | I52: 158.5 | J52: 45055 | K52: 45777 | L52: 45055 | N52: 0 | O52: 0 | P52: 0
A53: C229 | B53: 1/1.00 | C53: 650 | D53: Beryl Davis III | E53: Current | F53: Occupied | G53: 1029 | H53: 1040 | I53: 133.5 | J53: 44968 | K53: 45747 | L53: 44968 | N53: -1173.5 | O53: 0 | P53: 2
A54: B235 | B54: 1/1.00 | C54: 650 | D54: Andre Outlaw | E54: Current | F54: Occupied | G54: 1029 | H54: 1045 | I54: 153 | J54: 45313 | K54: 46053 | L54: 45313 | N54: -1198 | O54: 0 | P54: 2
A55: A106 | B55: 2/1.50 | C55: 850 | D55: Darius A. Baldwin | E55: Current | F55: Occupied | G55: 1149 | H55: 1049 | I55: -1049 | J55: 45930 | K55: 46295 | L55: 45930 | N55: 0 | O55: 0 | P55: 0
A56: D126 | B56: 2/1.50 | C56: 850 | D56: SanTonio M. Davis | E56: Current | F56: Occupied | G56: 1149 | H56: 1049 | I56: 121.5 | J56: 45947 | K56: 46326 | L56: 45947 | N56: 0 | O56: 0 | P56: 0
A57: D127 | B57: 2/1.50 | C57: 850 | D57: Genesis Badnegas | E57: Current | F57: Occupied | G57: 1149 | H57: 1049 | I57: 121.5 | J57: 45902 | K57: 46266 | L57: 45902 | N57: 0 | O57: 0 | P57: 0
A58: E116 | B58: 2/1.00 | C58: 800 | D58: Nicole A. Cunningham | E58: Current | F58: Occupied | G58: 1049 | H58: 1049 | I58: -378.5 | J58: 45899 | K58: 46263 | L58: 45899 | N58: 0 | O58: 0 | P58: 0
A59: F211 | B59: 1/1.00 | C59: 650 | D59: Erick Torres Escalera | E59: Current | F59: Occupied | G59: 1029 | H59: 1049 | I59: 133.5 | J59: 45065 | K59: 45748 | L59: 45065 | N59: -1182.5 | O59: 0 | P59: 2
A60: G143 | B60: 2/1.50 | C60: 850 | D60: Temeka R. Stanley | E60: Current | F60: Occupied | G60: 1149 | H60: 1049 | I60: 121.5 | J60: 45897 | K60: 46261 | L60: 45897 | N60: 0 | O60: 0 | P60: 0
... A93: A204 | B93: 2/1.50 | C93: 850 | D93: Yenisel Fernandez | E93: Current | F93: Occupied | G93: 1149 | H93: 1100 | I93: 130.5 | J93: 45383 | K93: 45737 | L93: 45383 | N93: -1230.5 | O93: 0 | P93: 0
A94: G142 | B94: 2/1.50 | C94: 850 | D94: Danier Delagado Sanchez | E94: Notice-Unrented | F94: Occupied | G94: 1149 | H94: 1100 | I94: 119 | J94: 45272 | K94: 46022 | L94: 45272 | M94: 46022 | N94: -1219 | O94: 0 | P94: 0
A95: D120 | B95: 1/1.00 | C95: 650 | D95: Najah Mayo | E95: Current | F95: Occupied | G95: 1029 | H95: 1101 | I95: 91 | J95: 43686 | K95: 46265 | L95: 43686 | N95: 0 | O95: 0 | P95: 0
A96: I154 | B96: 1/1.00 | C96: 650 | D96: Cecilio O. Orta-Martinez | E96: Current | F96: Occupied | G96: 1029 | H96: 1108 | I96: -1 | J96: 45809 | K96: 46173 | L96: 45809 | N96: 0 | O96: 0 | P96: 2
A97: G241 | B97: 2/1.50 | C97: 850 | D97: Delia Eslavon | E97: Current | F97: Occupied | G97: 1149 | H97: 1128 | I97: 98.5 | J97: 40634 | K97: 46044 | L97: 40634 | N97: 0 | O97: 0 | P97: 0
A98: A104 | B98: 2/1.50 | C98: 850 | D98: Yisen Montalvo | E98: Current | F98: Occupied | G98: 1149 | H98: 1130 | I98: 139.5 | J98: 45931 | K98: 46295 | L98: 45110 | N98: -1269.5 | O98: 0 | P98: 0
A99: D222 | B99: 2/1.50 | C99: 850 | D99: Ameer Hamza | E99: Current | F99: Occupied | G99: 1199 | H99: 1149 | I99: -1149 | J99: 45930 | K99: 46295 | L99: 45930 | N99: 0 | O99: 0 | P99: 0
A100: H165 | B100: 2/1.50 | C100: 850 | D100: Deborah L. Anderson | E100: Current | F100: Occupied | G100: 1199 | H100: 1149 | I100: 121.5 | J100: 45941 | K100: 46305 | L100: 45941 | N100: -0.01 | O100: 0 | P100: 0
A101: A107 | B101: 2/1.50 | C101: 850 | D101: Baktash Nawan | E101: Current | F101: Occupied | G101: 1149 | H101: 1150 | I101: 79.5 | J101: 44558 | K101: 46024 | L101: 44558 | N101: 0 | O101: 0 | P101: 0
A102: A109 | B102: 2/1.50 | C102: 850 | D102: Adams Ghaji | E102: Current | F102: Occupied | G102: 1149 | H102: 1150 | I102: 134.5 | J102: 45164 | K102: 46259 | L102: 45164 | N102: -1284.5 | O102: 0 | P102: 0
A103: D122 | B103: 2/1.50 | C103: 850 | D103: Moises Francisco | E103: Current | F103: Occupied | G103: 1149 | H103: 1150 | I103: 179.5 | J103: 45113 | K103: 45869 | L103: 45113 | N103: 0 | O103: 0 | P103: 0
A104: D227 | B104: 2/1.50 | C104: 850 | D104: Antwanette Johnekins | E104: Current | F104: Occupied | G104: 1149 | H104: 1150 | I104: 134.5 | J104: 45243 | K104: 45991 | L104: 45243 | N104: -1284.5 | O104: 0 | P104: 0
A105: J250 | B105: 2/1.00 | C105: 800 | D105: Angel Moya | E105: Current | F105: Occupied | G105: 1049 | H105: 1150 | I105: 149.5 | J105: 45288 | K105: 46018 | L105: 45288 | N105: 0 | O105: 0 | P105: 0
A106: G243 | B106: 2/1.50 | C106: 850 | D106: Tilor Correll | E106: Current | F106: Occupied | G106: 1149 | H106: 1157 | I106: 142.5 | J106: 44938 | K106: 46033 | L106: 44938 | N106: -1299.5 | O106: 0 | P106: 0
... A108: A203 | B108: 2/1.50 | C108: 850 | D108: Scheila Chagas | E108: Current | F108: Occupied | G108: 1149 | H108: 1199 | I108: 151.5 | J108: 45017 | K108: 45747 | L108: 45017 | N108: 0 | O108: 0 | P108: 0
A109: D225 | B109: 2/1.50 | C109: 850 | D109: Jose Perez | E109: Notice-Unrented | F109: Occupied | G109: 1149 | H109: 1199 | I109: 134.5 | J109: 45205 | K109: 45961 | L109: 45205 | M109: 45961 | N109: 0 | O109: 0 | P109: 0
A110: G139 | B110: 2/1.00 | C110: 800 | D110: Alexander Lucas Zapata | E110: Current | F110: Occupied | G110: 1049 | H110: 1199 | I110: 131.5 | J110: 45562 | K110: 46295 | L110: 45562 | N110: -1430.5 | O110: 0 | P110: 3
A111: H261 | B111: 2/1.50 | C111: 850 | D111: Latif Nedimovic | E111: Current | F111: Occupied | G111: 1149 | H111: 1199 | I111: 121.5 | J111: 42749 | K111: 46297 | L111: 42749 | N111: 0 | O111: 0 | P111: 0
A112: I159 | B112: 2/1.50 | C112: 850 | D112: Tantania Burkett | E112: Current | F112: Occupied | G112: 1149 | H112: 1199 | I112: 158.5 | J112: 44778 | K112: 45754 | L112: 44778 | N112: 0 | O112: 0 | P112: 0
A113: I252 | B113: 2/1.50 | C113: 850 | D113: Ana Rodriguez De Garcia | E113: Current | F113: Occupied | G113: 1149 | H113: 1199 | I113: 121.5 | J113: 45536 | K113: 46263 | L113: 45534 | N113: 0 | O113: 0 | P113: 0
A114: D125 | B114: 2/1.50 | C114: 850 | D114: Mary Hale | E114: Current | F114: Occupied | G114: 1199 | H114: 1200 | I114: 106 | J114: 45956 | K114: 46320 | L114: 45591 | N114: -3 | O114: 0 | P114: 0
A115: D221 | B115: 2/1.50 | C115: 850 | D115: Dinia Banegas | E115: Current | F115: Occupied | G115: 1199 | H115: 1200 | I115: 121.5 | J115: 45579 | K115: 45961 | L115: 45579 | N115: 0 | O115: 0 | P115: 0
A116: D224 | B116: 2/1.50 | C116: 850 | D116: Jose Ramos | E116: Current | F116: Occupied | G116: 1149 | H116: 1200 | I116: 121.5 | J116: 45630 | K116: 45994 | L116: 45630 | N116: 0 | O116: 0 | P116: 0
A117: G240 | B117: 2/1.50 | C117: 850 | D117: Sajid Mirazi | E117: Current | F117: Occupied | G117: 1149 | H117: 1200 | I117: 149.5 | J117: 44880 | K117: 45975 | L117: 44880 | N117: -1349.5 | O117: 0 | P117: 0
A118: H160 | B118: 2/1.50 | C118: 850 | D118: Billenia Smith | E118: Current | F118: Occupied | G118: 1199 | H118: 1200 | I118: 121.5 | J118: 45638 | K118: 46002 | L118: 45638 | N118: -1321.5 | O118: 0 | P118: 0
A119: H161 | B119: 2/1.50 | C119: 850 | D119: Yosainer Rodriguez | E119: Current | F119: Occupied | G119: 1199 | H119: 1200 | I119: 108.5 | J119: 45681 | K119: 46045 | L119: 45681 | N119: 0 | O119: 0 | P119: 0
A120: H162 | B120: 2/1.50 | C120: 850 | D120: Andreina Carmen | E120: Current | F120: Occupied | G120: 1199 | H120: 1200 | I120: 138.5 | J120: 45677 | K120: 46041 | L120: 45673 | N120: -1338.5 | O120: 0 | P120: 0
A121: H164 | B121: 2/1.50 | C121: 850 | D121: Chanting Jackson | E121: Current | F121: Occupied | G121: 1199 | H121: 1200 | I121: 121.5 | J121: 45663 | K121: 46027 | L121: 45663 | N121: -7 | O121: 0 | P121: 3
A122: I259 | B122: 2/1.50 | C122: 850 | D122: Jeyner Hernandez | E122: Notice-Unrented | F122: Occupied | G122: 1199 | H122: 1200 | I122: 121.5 | J122: 45595 | K122: 45958 | L122: 45595 | M122: 45961 | N122: 6 | O122: 0 | P122: 0
A123: J147 | B123: 2/1.50 | C123: 850 | D123: Robert Stephens | E123: Current | F123: Occupied | G123: 1149 | H123: 1200 | I123: 106 | J123: 45643 | K123: 46007 | L123: 45643 | N123: -680.5 | O123: 0 | P123: 0
A124: D121 | B124: 2/1.50 | C124: 850 | D124: Justice Williams | E124: Current | F124: Occupied | G124: 1199 | H124: 1225 | I124: 21.5 | J124: 45584 | K124: 46325 | L124: 45584 | N124: 0 | O124: 0 | P124: 4
A125: I255 | B125: 3/2.00 | C125: 1150 | D125: Michael Henderson | E125: Current | F125: Occupied | G125: 1399 | H125: 1280 | I125: 149.5 | J125: 43206 | K125: 46007 | L125: 43206 | N125: -1429.5 | O125: 0 | P125: 0
A126: I157 | B126: 3/2.00 | C126: 1150 | D126: Avery Kwame | E126: Current | F126: Occupied | G126: 1399 | H126: 1290 | I126: 118.5 | J126: 44136 | K126: 46053 | L126: 44136 | N126: -1408.5 | O126: 0 | P126: 0
A127: A103 | B127: 2/1.50 | C127: 850 | D127: Toniece Jenkins | E127: Current | F127: Occupied | G127: 1199 | H127: 1300 | I127: 121.5 | J127: 45608 | K127: 45972 | L127: 45608 | N127: 0 | O127: 0 | P127: 0
A128: A108 | B128: 2/1.50 | C128: 850 | D128: Esperanza Pereira | E128: Evict | F128: Vacant | G128: 1199 | H128: 1300 | I128: 123.5 | J128: 45726 | K128: 46120 | L128: 45726 | M128: 45964 | N128: 6694 | O128: 0 | P128: 4
A129: A205 | B129: 2/1.50 | C129: 850 | D129: Arifa Rezai | E129: Current | F129: Occupied | G129: 1199 | H129: 1300 | I129: 123.5 | J129: 45749 | K129: 46113 | L129: 45749 | N129: -1423.5 | O129: 0 | P129: 0
A130: A207 | B130: 2/1.50 | C130: 850 | D130: Agneli Herrera Ruz | E130: Current | F130: Occupied | G130: 1199 | H130: 1300 | I130: 121.5 | J130: 45505 | K130: 45868 | L130: 45505 | N130: 0 | O130: 0 | P130: 0
A131: A209 | B131: 2/1.50 | C131: 850 | D131: Alexi Lopez | E131: Current | F131: Occupied | G131: 1199 | H131: 1300 | I131: 123.5 | J131: 45721 | K131: 46116 | L131: 45721 | N131: 0 | O131: 0 | P131: 1
A132: G140 | B132: 2/1.50 | C132: 850 | D132: Tarsha Daise | E132: Current | F132: Occupied | G132: 1199 | H132: 1300 | I132: 113.5 | J132: 45717 | K132: 46081 | L132: 45717 | N132: -1051.5 | O132: 1 | P132: 3
A133: G239 | B133: 2/1.50 | C133: 850 | D133: Joshua Reed-Buck | E133: Current | F133: Occupied | G133: 1199 | H133: 1300 | I133: 168.5 | J133: 45772 | K133: 46142 | L133: 45772 | N133: 0 | O133: 0 | P133: 0
A134: G242 | B134: 2/1.50 | C134: 850 | D134: Yordan Montesino | E134: Current | F134: Occupied | G134: 1199 | H134: 1300 | I134: 123.5 | J134: 45717 | K134: 46142 | L134: 45717 | N134: 620.5 | O134: 0 | P134: 3
A135: I257 | B135: 3/2.00 | C135: 1150 | D135: Carlanika T. Brown | E135: Current | F135: Occupied | G135: 1399 | H135: 1399 | I135: -1399 | J135: 45930 | K135: 46295 | L135: 45930 | N135: 0 | O135: 0 | P135: 0
A136: I253 | B136: 3/2.00 | C136: 1150 | D136: Francisco Gonzales | E136: Evict | F136: Vacant | G136: 1399 | H136: 1425 | I136: 131.5 | J136: 45536 | K136: 45900 | L136: 45536 | M136: 45964 | N136: 1799.5 | O136: 0 | P136: 5
A137: I155 | B137: 3/2.00 | C137: 1150 | D137: Abdullah Hassan | E137: Current | F137: Occupied | G137: 1399 | H137: 1499 | I137: 131.5 | J137: 45551 | K137: 46295 | L137: 45551 | N137: -1570 | O137: 0 | P137: 2
A138: 127 Units | C138: 100950 | E138: 98.4% Occupied | G138: 142193 | H138: 135949 | I138: -2368.5 | N138: -33660.91 | O138: 11 | P138: 88
A140: Total 127 Units | C140: 100950 | E140: 98.4% Occupied | G140: 142193 | H140: 135949 | I140: -2368.5 | N140: -33660.91 | O140: 11 | P140: 88
...
