Workbook
Name xx: #REF!
Name DELME2: #REF!
Name DATA_01: #REF!
Name aq: #REF!
Name _Key2: #REF!
Name wrn.PropertyInformation.: #REF!
Name RentableFeet: #REF!
Name XXX: #REF!
Name wrn.CCC._.OPEX.: #REF!
Name wrn.CF_HISTORY.: #REF!
Name _Key1: #REF!
Name wrn.Historys.: #REF!
Name wrn.Submittal._.Reconciliation._.Schedule.: #REF!
Name wrn.AnnualRentRoll: #REF!
Name wrn.Rent._.Rolls.: #REF!
Name sadddddddd: #REF!
Name hope: #REF!
Name wrn.AnnualRentRoll: #REF!
Name wrn.CF_HISTORY.: #REF!
Name wrn.Rent._.Rolls.: #REF!
Name wrn.PK._.Variance.: #REF!
Name wrn.CCC.: #REF!
Name DELME4: #REF!
Name wrn.TANASBOURNE._.ONLY.: #REF!
Name wrn.Presentation.: #REF!
Name wrn.ExitAndSalesAssumptions.: #REF!
Name wrn.Presentation.: #REF!
Name xx: #REF!
Name wrn.PropertyInformation.: #REF!
Name sadddddddddd: #REF!
Name wrn.Month._.to._.Month.: #REF!
Name wrn.CF_HIS_Rent_Roll.: #REF!
Name saddddd: #REF!
Name wrn.FULL._.COMPARISON.: #REF!
Name wrn.Variance.: #REF!
Name saddddddddddddd: #REF!
Name DELME7: #REF!
Name wrn.Expense._.Detail.: #REF!
Name wrn.Expense._.Detail.: #REF!
Name sadddddddddd: #REF!
Name saddddddddddddd: #REF!
Name wrn.EXPENSE.: #REF!
Name DELME3: #REF!
Name hope: #REF!
Name XXX: #REF!
Name wrn.OperatingAssumtions.: #REF!
Name wrn.AnnualRentRoll: #REF!
Name wrn.OFFICE._.BUDGET.: #REF!
Name DELME7: #REF!
Name wrn.Rent._.Rolls.: #REF!
Name saddd: #REF!
Name wrn.Summary.: #REF!
Name hope: #REF!
Name saddddd: #REF!
Name _Sort: #REF!
Name DELM: #REF!
Name wrn.PRINT._.ALL.: #REF!
Name wrn.AnnualRentRoll: #REF!
Name wrn.AnnualRentRoll.: #REF!
Name DELME4: #REF!

Sheet DO NOT DELETE
A1: CATEGORY | B1: LINE ITEMS | C1: ELIGIBILITY FOR DEPOSITS/DOWN PAYMENTS/PAID INVOICES | D1: LIEN WAIVER FOR CONTRACTS > $10K | E1: NEED PROOF OF PAYMENT IN THE NEXT DRAW?
A2: Interior Renovations | B2: =+'CapEx Borrower Budget'!B16 -> Unit upgrades | C2: 1) 50% of the contract amount for Downpayment/Deposits | D2: Conditional Lien Waiver Submitted | E2: POP
A3: Exterior Renovations | B3: =+'CapEx Borrower Budget'!B17 -> Appliances | C3: 2) Advance for Unpaid Work | D3: Conditional Lien Waiver NOT Submitted | E3: n/a
A4: Deferred Maintenance | B4: =+'CapEx Borrower Budget'!B18 -> Flooring | C4: 3) Paid Invoice/Purchase Order
A5: Immediate Reparis | B5: =+'CapEx Borrower Budget'!B19 -> Fixtures
A6: Construction Management Fees | B6: =+'CapEx Borrower Budget'!B20 -> Cabinets
A7: Contingency | B7: =+'CapEx Borrower Budget'!B21 -> washer/dryer machines
B8: =+'CapEx Borrower Budget'!B22 -> New Units
B9: =+'CapEx Borrower Budget'!B23 -> Down Unit
B10: =+'CapEx Borrower Budget'!B44 -> Landscaping
B11: =+'CapEx Borrower Budget'!B45 -> Leasing office
B12: =+'CapEx Borrower Budget'!B46 -> Fitness center
B13: =+'CapEx Borrower Budget'!B47 -> Monument sign
B14: =+'CapEx Borrower Budget'!B48 -> Pool area
B15: =+'CapEx Borrower Budget'!B49 -> Grilling stations
B16: =+'CapEx Borrower Budget'!B50 -> Dog park
B17: =+'CapEx Borrower Budget'!B51 -> EV chargers
B18: =+'CapEx Borrower Budget'!B52 -> Playground
B19: =+'CapEx Borrower Budget'!B62 -> Roofs (seller credit)
B20: =+'CapEx Borrower Budget'!B63 -> Plumbing
B21: =+'CapEx Borrower Budget'!B64 -> Electrical
B22: =+'CapEx Borrower Budget'!B65 -> HVAC
B23: =+'CapEx Borrower Budget'!B75 -> Install and /or repair fencing and gates to comply with security plan.
B24: =+'CapEx Borrower Budget'!B76 -> Repair damaged pavement consisting of linear cracking, alligator cracking, potholes, and surface raveling throughout the Property.
B25: =+'CapEx Borrower Budget'!B77 -> Install security cameras to comply with security plan.
B26: =+'CapEx Borrower Budget'!B78 -> Repair and replace cracked and broken concrete stair treads.
B27: =+'CapEx Borrower Budget'!B79 -> Repair all trip hazards.
B28: =+'CapEx Borrower Budget'!B80 -> Reconfigure the ramp and access walk to provide a level landing at the leasing office entry door
B29: =+'CapEx Borrower Budget'!B81 -> Reconfigure the ADA accessible parking space to provide unobstructed access to aisle.
B30: =+'CapEx Borrower Budget'!B88 -> Interior Contingency
B31: =+'CapEx Borrower Budget'!B90 -> Def. Maintenance Contingency

Sheet CapEx Summary
B2: BLUE - Manual Input
B3: BLACK - Formula
B5: Capital Improvement Budget Summary
B6: Category | C6: Total Amount | D6: Per Unit
B7: Interior Renovations | C7: =SUM('CapEx Borrower Budget'!E41) -> 751200 | D7: =C7/'CapEx Borrower Budget'!$C$10 -> 5868.75
B8: Exterior Renovations | C8: ='CapEx Borrower Budget'!E59 -> 65000 | D8: =C8/'CapEx Borrower Budget'!$C$10 -> 507.8125
B9: Deferred Maintenance | C9: =+'CapEx Borrower Budget'!E72 -> 551270 | D9: =C9/'CapEx Borrower Budget'!$C$10 -> 4306.7969
B10: Immediate Repairs | C10: ='CapEx Borrower Budget'!E85 -> 87700 | D10: =C10/'CapEx Borrower Budget'!$C$10 -> 685.15625
B11: Construction Management Fees | C11: =+'CapEx Borrower Budget'!E91 -> 0 | D11: =C11/'CapEx Borrower Budget'!$C$10 -> 0
B12: Contingency | C12: =+SUM('CapEx Borrower Budget'!E88:E90) -> 36830 | D12: =C12/'CapEx Borrower Budget'!$C$10 -> 287.73438
B13: Total Capital Improvement Budget | C13: =SUM(C7:C12) -> 1492000 | D13: =C13/'CapEx Borrower Budget'!$C$10 -> 11656.25

Sheet Capex Detail
A1: What? | B1: Type | C1: How much | D1: Transfer | F1: Total spent so far: | G1: =SUM(C2:C1000) -> 214901.18
A2: Office Buildout | B2: Capex | C2: 8570.41 | D2: 45518 | F2: =MONTH(D2) -> 8
A3: Appliances | B3: Unit Renovations | C3: 10306 | D3: 45518 | F3: =MONTH(D3) -> 8
A4: HVAC A102 | B4: HVAC | C4: 3500 | D4: 45517 | F4: =MONTH(D4) -> 8 | H4: =SUMIF($F$2:$F$25,7,C2:C25) -> 28874
A5: HVAC I258 | B5: HVAC | C5: 3400 | D5: 45517 | F5: =MONTH(D5) -> 8
A6: HVAC G238 | B6: HVAC | C6: 1610 | D6: 45517 | F6: =MONTH(D6) -> 8
A7: HVAC G140 | B7: HVAC | C7: 3550 | D7: 45517 | F7: =MONTH(D7) -> 8
A8: HVAC G240 | B8: HVAC | C8: 3550 | D8: 45517 | F8: =MONTH(D8) -> 8
A9: HVAC A109 | B9: HVAC | C9: 3550 | D9: 45517 | F9: =MONTH(D9) -> 8
A10: HVAC C131 | B10: HVAC | C10: 3900 | D10: 45517 | F10: =MONTH(D10) -> 8
A11: Flooring A102, A207, A105 | B11: Unit Renovations | C11: 1050 | D11: 45517 | F11: =MONTH(D11) -> 8
A12: Optivo Ph 1 & 2 initial payment | B12: Unit Renovations | C12: 29542 | D12: 45517 | F12: =MONTH(D12) -> 8
A13: Fire Extinguishers | B13: Capex | C13: 5092.28 | D13: 45506 | F13: =MONTH(D13) -> 8
A14: Coastal Luxury | B14: Immediate Repairs | C14: 5724 | D14: 45503 | F14: =MONTH(D14) -> 7
A15: Cecilios Painting | B15: Capex | C15: 180 | D15: 45503 | F15: =MONTH(D15) -> 7
A16: Joel Flooring | B16: Capex | C16: 350 | D16: 45503 | F16: =MONTH(D16) -> 7
... A18: Coastal Luxury | B18: Immediate Repairs | C18: 16190 | D18: 45495 | F18: =MONTH(D18) -> 7
A19: Roofing???? | B19: Roofing | F19: =MONTH(D19) -> 12
A20: Jyrka for stair repair (Final payment | B20: Immediate Repairs | C20: 6430 | D20: 45533 | F20: =MONTH(D20) -> 8
A21: Joel Flooring | B21: Unit Renovations | C21: 1771 | D21: 45533 | F21: =MONTH(D21) -> 8
A22: Optivo Ph 1 & 2 final payment | B22: Unit Renovations | C22: 29542 | D22: 45533 | E22: Paid in full | F22: =MONTH(D22) -> 8
A23: ARJ Optivo Ph 4 initial payment | B23: Unit Renovations | C23: 28062.5 | D23: 45534 | E23: =C23*3 -> 84187.5 | F23: =MONTH(D23) -> 8
A24: Optivo Ph 3 | B24: unit Renovations | C24: 41562 | D24: 45601 | F24: =MONTH(D24) -> 11
A25: "ABSTRACT PAW" DOG PARK BUNDLE with BENCH | B25: unit Renovations | C25: 1038.99 | D25: 45558 | F25: =MONTH(D25) -> 9

Sheet CapEx Borrower Budget
B2: BLUE - Manual Input
B3: BLACK - Formula
B5: Borrowing Entity Name: | C5: Red Raider 45 LLC
B6: Property Name: | C6: The Park at Pottsburg Creek
B7: Property Address: | C7: 4800 Atlantic Blvd, Jacksonville, FL 32207
B8: Budget Created By: | C8: Edward Sittler, Vinnie Patel
B9: Date: | C9: 45212
B10: Total # Units: | C10: 128
B11: # Full Upgrades: | C11: 128
B12: # Partial Upgrades: | C12: 0
B14: Item/Description of Work | C14: # Units | D14: Unit Cost | E14: Total
B15: Interior Budget
B16: Unit upgrades | C16: 0 | D16: 0 | E16: =C16*D16 -> 0
B17: Appliances | C17: 128 | D17: 1500 | E17: =C17*D17 -> 192000
B18: Flooring | C18: 128 | D18: 1500 | E18: =C18*D18 -> 192000
B19: Fixtures | C19: 128 | D19: 1000 | E19: =C19*D19 -> 128000
B20: Cabinets | C20: 128 | D20: 900 | E20: =C20*D20 -> 115200
B21: washer/dryer machines | C21: 128 | D21: 500 | E21: =C21*D21 -> 64000
B22: New Units | C22: 2 | D22: 20000 | E22: =C22*D22 -> 40000
B23: Down Unit | C23: 1 | D23: 20000 | E23: =C23*D23 -> 20000
B24: [Enter] | C24: 0 | D24: 0 | E24: =C24*D24 -> 0
B25: [Enter] | C25: 0 | D25: 0 | E25: =C25*D25 -> 0
B26: [Enter] | C26: 0 | D26: 0 | E26: =C26*D26 -> 0
B27: [Enter] | C27: 0 | D27: 0 | E27: =C27*D27 -> 0
... B40: [Enter] | C40: 0 | D40: 0 | E40: =C40*D40 -> 0
B41: Interiors Subtotal | E41: =SUM(E16:E40) -> 751200
B43: Exterior Budget
B44: Landscaping | C44: 1 | D44: 20000 | E44: =C44*D44 -> 20000
B45: Leasing office | C45: 1 | D45: 10000 | E45: =C45*D45 -> 10000
B46: Fitness center | C46: 1 | D46: 5000 | E46: =C46*D46 -> 5000
B47: Monument sign | C47: 1 | D47: 10000 | E47: =C47*D47 -> 10000
B48: Pool area | C48: 1 | D48: 3000 | E48: =C48*D48 -> 3000
B49: Grilling stations | C49: 2 | D49: 2500 | E49: =C49*D49 -> 5000
B50: Dog park | C50: 1 | D50: 5000 | E50: =C50*D50 -> 5000
B51: EV chargers | C51: 2 | D51: 2500 | E51: =C51*D51 -> 5000
B52: Playground | C52: 1 | D52: 2000 | E52: =C52*D52 -> 2000
B53: [Enter] | C53: 0 | D53: 0 | E53: =C53*D53 -> 0
B54: [Enter] | C54: 0 | D54: 0 | E54: =C54*D54 -> 0
B55: [Enter] | C55: 0 | D55: 0 | E55: =C55*D55 -> 0
... B58: [Enter] | C58: 0 | D58: 0 | E58: =C58*D58 -> 0
B59: Exteriors Subtotal | E59: =SUM(E44:E58) -> 65000
B61: Deferred Maintenance
B62: Roofs (seller credit) | C62: 1 | D62: 272000 | E62: =C62*D62 -> 272000
B63: Plumbing | C63: 1 | D63: 179200 | E63: =C63*D63 -> 179200
B64: Electrical | C64: 128 | D64: 440 | E64: =C64*D64 -> 56320
B65: HVAC | C65: 35 | D65: 1250 | E65: =C65*D65 -> 43750
B66: [Enter] | C66: 0 | D66: 0 | E66: =C66*D66 -> 0
B67: [Enter] | C67: 0 | D67: 0 | E67: =C67*D67 -> 0
B68: [Enter] | C68: 0 | D68: 0 | E68: =C68*D68 -> 0
B69: [Enter] | C69: 0 | D69: 0 | E69: =C69*D69 -> 0
B70: [Enter] | C70: 0 | D70: 0 | E70: =C70*D70 -> 0
B71: [Enter] | C71: 0 | D71: 0 | E71: =C71*D71 -> 0
B72: Deferred Maintenance Subtotal | E72: =SUM(E62:E71) -> 551270
B74: Immediate Repairs
B75: Install and /or repair fencing and gates to comply with security plan. | C75: 1 | D75: 30000 | E75: =C75*D75 -> 30000
B76: Repair damaged pavement consisting of linear cracking, alligator cracking, potholes, and surface raveling throughout the Property. | C76: 1 | D76: 28000 | E76: =C76*D76 -> 28000
B77: Install security cameras to comply with security plan. | C77: 1 | D77: 20000 | E77: =C77*D77 -> 20000
B78: Repair and replace cracked and broken concrete stair treads. | C78: 1 | D78: 5000 | E78: =C78*D78 -> 5000
B79: Repair all trip hazards. | C79: 1 | D79: 3000 | E79: =C79*D79 -> 3000
B80: Reconfigure the ramp and access walk to provide a level landing at the leasing office entry door | C80: 1 | D80: 1200 | E80: =C80*D80 -> 1200
B81: Reconfigure the ADA accessible parking space to provide unobstructed access to aisle. | C81: 1 | D81: 500 | E81: =C81*D81 -> 500
B82: [Enter] | C82: 0 | D82: 0 | E82: =C82*D82 -> 0
B83: [Enter] | C83: 0 | D83: 0 | E83: =C83*D83 -> 0
B84: [Enter] | C84: 0 | D84: 0 | E84: =C84*D84 -> 0
B85: Immediate Repairs Subtotal | E85: =SUM(E75:E84) -> 87700
B87: Soft Costs
B88: Interior Contingency | D88: =E88/E41 -> 0.017039404 | E88: 12800
B89: Exterior Contingency | D89: =E89/E59 -> 0 | E89: 0
B90: Def. Maintenance Contingency | D90: =+E90/E72 -> 0.043590255 | E90: 24030
B91: Construction Management Fees | D91: =E91/(E94-E91) -> 0 | E91: 0
B92: Soft Costs Subtotal | E92: =SUM(E88:E91) -> 36830
B94: Total CapEx Budget | E94: =E41+E59+E72+E85+E92 -> 1492000
B96: Escrow Reserves
B97: [Enter] | C97: 0 | D97: 0 | E97: =C97*D97 -> 0
B98: Escrow Reserve Subtoatal | E98: =SUM(E94:E97) -> 1492000
B100: Description/Scope of Work
B101: [Enter any clarifying information here including descriptions of different levels of upgrades if not uniform (e.g., XX units to receive "Elite" upgrades with stainless steel appliances, granite countertops, etc.).]

Sheet New Capex Borrower Budget
A1: Borrowing Entity Name: | B1: Red Raider 45 LLC
A2: Property Name: | B2: The Park at Pottsburg Creek
A3: Property Address: | B3: 4800 Atlantic Blvd, Jacksonville, FL 32207
A4: Budget Created By: | B4: Edward Sittler, Vinnie Patel
A5: Date: | B5: 45212
A6: Total # Units: | B6: 128
A7: # Full Upgrades: | B7: 128
A8: # Partial Upgrades: | B8: 0
D9: =D80 -> 1492000 | E9: =E80 -> 1492000 | F9: =E9-D9 -> 0
A10: Item/Description of Work | B10: # Units | C10: Unit Cost | D10: Total | F10: Vendor | G10: Actual Amount | H10: Actual Cost | I10: Versus Budget | J10: Comments
A11: Interior Budget
A12: Unit upgrades | B12: 60 | C12: 5700 | D12: =B12*C12 -> 342000 | F12: Optivo & ARJ | G12: 0 | H12: =B12*G12 -> 0 | I12: =SUM(D12:D16)-H12 -> 636000 | J12: $10.6K per unit.
A13: Appliances | B13: 60 | C13: 1500 | D13: =B13*C13 -> 90000 | F13: Incl. in unit upgrades | G13: 0 | H13: 0
A14: Flooring | B14: 60 | C14: 1500 | D14: =B14*C14 -> 90000 | F14: Incl. in unit upgrades | G14: 0 | H14: 0
A15: Fixtures | B15: 60 | C15: 1000 | D15: =B15*C15 -> 60000 | F15: Incl. in unit upgrades | G15: 0 | H15: 0
A16: Cabinets | B16: 60 | C16: 900 | D16: =B16*C16 -> 54000 | F16: Incl. in unit upgrades | G16: 0 | H16: 0
A17: washer/dryer machines | B17: 0 | C17: 0 | D17: =B17*C17 -> 0 | G17: 0 | H17: 0
A18: New Units | B18: 0 | C18: 0 | D18: =B18*C18 -> 0 | G18: 0 | H18: 0
A19: Down Unit | B19: 1 | C19: 40000 | D19: =B19*C19 -> 40000 | E19: Fire damaged unit | G19: 40000 | H19: =B19*G19 -> 40000 | I19: =D19-H19 -> 0
A20: Laundry Room Improvements | B20: 1 | C20: =20000-4800 -> 15200 | D20: =B20*C20 -> 15200 | F20: OEM Laundry/Orexis | G20: 4000 | H20: =B20*G20 -> 4000 | I20: =C20-H20 -> 11200 | J20: Includes $3,000 investment from OEM. The extra can be re-assigned to another category
A21: [Enter] | B21: 0 | C21: 0 | D21: =B21*C21 -> 0
A22: [Enter] | B22: 0 | C22: 0 | D22: =B22*C22 -> 0
A23: Interiors Subtotal | D23: =SUM(D12:D22) -> 691200 | H23: =SUM(H12:H22) -> 44000 | I23: =SUM(I12:I22) -> 647200
E24: 751200
A25: Exterior Budget
A26: Landscaping | B26: 1 | C26: 50000 | D26: =B26*C26 -> 50000 | F26: TBD | G26: 50000 | H26: =B26*G26 -> 50000 | I26: =D26-H26 -> 0
A27: Leasing office | B27: 1 | C27: 10000 | D27: =B27*C27 -> 10000 | F27: ? | G27: 8570.41 | H27: =B27*G27 -> 8570.41 | I27: =D27-H27 -> 1429.59 | J27: Re-assign the left over to another category
A28: Fitness center | B28: 1 | C28: 0 | D28: =B28*C28 -> 0 | F28: N/A | G28: 0 | H28: =B28*G28 -> 0 | I28: =D28-H28 -> 0
A29: Monument sign | B29: 1 | C29: 10000 | D29: =B29*C29 -> 10000 | F29: TBD | G29: 10000 | H29: =B29*G29 -> 10000 | I29: =D29-H29 -> 0
A30: Pool area | B30: 1 | C30: 10000 | D30: =B30*C30 -> 10000 | F30: TBD | G30: 50000 | H30: =B30*G30 -> 50000 | I30: =D30-H30 -> -40000
A31: Grilling stations | B31: 2 | C31: 2500 | D31: =B31*C31 -> 5000 | F31: N/A | G31: 0 | H31: =B31*G31 -> 0 | I31: =D31-H31 -> 5000 | J31: Included in Pool Area
A32: Dog park | B32: 1 | C32: 5000 | D32: =B32*C32 -> 5000 | F32: TBD | G32: 2000 | H32: =B32*G32 -> 2000 | I32: =D32-H32 -> 3000
A33: EV chargers | B33: 2 | C33: 2500 | D33: =B33*C33 -> 5000 | F33: N/A | G33: 0 | H33: =B33*G33 -> 0 | I33: =D33-H33 -> 5000
A34: Playground | B34: 1 | C34: 2000 | D34: =B34*C34 -> 2000 | F34: N/A | G34: 1000 | H34: =B34*G34 -> 1000 | I34: =D34-H34 -> 1000 | J34: Wash the playground
A35: Shed | B35: 1 | C35: 0 | D35: =B35*C35 -> 0 | F35: TBD | G35: 10000 | H35: =B35*G35 -> 10000 | I35: =D35-H35 -> -10000
A36: Remaining signs | B36: 1 | C36: 0 | D36: =B36*C36 -> 0 | F36: TBD | G36: 20000 | H36: =B36*G36 -> 20000 | I36: =D36-H36 -> -20000
A37: [Enter] | B37: 0 | C37: 0 | D37: =B37*C37 -> 0
A38: [Enter] | B38: 0 | C38: 0 | D38: =B38*C38 -> 0
A39: [Enter] | B39: 0 | C39: 0 | D39: =B39*C39 -> 0
A40: [Enter] | B40: 0 | C40: 0 | D40: =B40*C40 -> 0
A41: Exteriors Subtotal | D41: =SUM(D26:D40) -> 97000 | H41: =SUM(H26:H40) -> 151570.41 | I41: =D41-H41 -> -54570.41
E42: 65000
A43: Deferred Maintenance
A44: Roofs (seller credit) | B44: 1 | C44: 300000 | D44: =B44*C44 -> 300000 | F44: Anthony | G44: 283496 | H44: =B44*G44 -> 283496 | I44: =D44-H44 -> 16504
A45: Plumbing | B45: 1 | C45: 179200 | D45: =B45*C45 -> 179200 | F45: MISC | G45: 50000 | H45: =B45*G45 -> 50000 | I45: =D45-H45 -> 129200 | J45: Estimated
A46: Electrical | B46: 128 | C46: 440 | D46: =B46*C46 -> 56320 | F46: MISC | G46: 200 | H46: =B46*G46 -> 25600 | I46: =D46-H46 -> 30720 | J46: Estimated | L46: General budget to address deffered maintenance on electric items. Validate with the bank if this can be used on-demand, as work is performed.
A47: HVAC | B47: 35 | C47: 1250 | D47: =B47*C47 -> 43750 | F47: MISC | G47: 3000 | H47: =B47*G47 -> 105000 | I47: =D47-H47 -> -61250 | J47: Estimated
A48: [Enter] | B48: 0 | C48: 0 | D48: =B48*C48 -> 0
A49: [Enter] | B49: 0 | C49: 0 | D49: =B49*C49 -> 0
A50: [Enter] | B50: 0 | C50: 0 | D50: =B50*C50 -> 0
A51: [Enter] | B51: 0 | C51: 0 | D51: =B51*C51 -> 0
A52: [Enter] | B52: 0 | C52: 0 | D52: =B52*C52 -> 0
A53: [Enter] | B53: 0 | C53: 0 | D53: =B53*C53 -> 0
A54: Deferred Maintenance Subtotal | D54: =SUM(D44:D53) -> 579270 | G54: =SUM(G44:G53) -> 336696 | H54: =SUM(H44:H53) -> 464096 | I54: =SUM(I44:I53) -> 115174
E55: 551270
A56: Immediate Repairs
A57: Install and /or repair fencing and gates to comply with security plan. | B57: 1 | C57: 30000 | D57: =B57*C57 -> 30000 | F57: Fence Pro Inc | G57: 0 | H57: =B57*G57 -> 0 | I57: =D57-G57 -> 30000 | J57: On hold
A58: Repair damaged pavement consisting of linear cracking, alligator cracking, potholes, and surface raveling throughout the Property. | B58: 1 | C58: 28000 | D58: =B58*C58 -> 28000 | F58: Pro Seal Asphalt | G58: 32300 | H58: =B58*G58 -> 32300 | I58: =D58-G58 -> -4300 | J58: Estimate
A59: Install security cameras to comply with security plan. | B59: 1 | C59: 20000 | D59: =B59*C59 -> 20000 | F59: TBD | G59: 50000 | H59: =B59*G59 -> 50000 | I59: =D59-G59 -> -30000 | J59: Estimate
A60: Repair and replace cracked and broken concrete stair treads | B60: 1 | C60: 5000 | D60: =B60*C60 -> 5000 | E60: ? | F60: TBD | G60: 25000 | H60: =B60*G60 -> 25000 | I60: =D60-G60 -> -20000 | J60: Estimate
A61: Repair all trip hazards. | B61: 1 | C61: 3000 | D61: =B61*C61 -> 3000 | E61: ? | F61: TBD | G61: 20000 | H61: =B61*G61 -> 20000 | I61: =D61-G61 -> -17000 | J61: Includes the money spent on Rob
A62: Reconfigure the ramp and access walk to provide a level landing at the leasing office entry door | B62: 1 | C62: 1200 | D62: =B62*C62 -> 1200 | F62: TBD | G62: 0 | H62: =B62*G62 -> 0 | I62: =D62-G62 -> 1200 | J62: Includes the money spent on Rob
A63: Reconfigure the ADA accessible parking space to provide unobstructed access to aisle. | B63: 1 | C63: 500 | D63: =B63*C63 -> 500 | F63: TBD | G63: 0 | H63: =B63*G63 -> 0 | I63: =D63-G63 -> 500 | J63: Part of PSA project
A64: Pool Repair | B64: 1 | C64: 0 | D64: =B64*C64 -> 0 | F64: Luxury Coastal | G64: =47617+5724 -> 53341 | H64: =B64*G64 -> 53341 | I64: =D64-G64 -> -53341
A65: [Enter] | B65: 0 | C65: 0 | D65: =B65*C65 -> 0
A66: [Enter] | B66: 0 | C66: 0 | D66: =B66*C66 -> 0
A67: Immediate Repairs Subtotal | D67: =SUM(D57:D66) -> 87700 | H67: =SUM(H57:H64) -> 180641 | I67: =SUM(I57:I64) -> -92941
E68: 87700
A69: Soft Costs
A70: Interior Contingency | B70: 1 | C70: =D70/D23 -> 0.018518519 | D70: 12800 | G70: 0 | H70: =B70*G70 -> 0 | I70: =D70-G70 -> 12800
A71: Exterior Contingency | B71: 1 | C71: =D71/D41 -> 0 | D71: 0 | G71: 0 | H71: =B71*G71 -> 0 | I71: =D71-G71 -> 0
A72: Def. Maintenance Contingency | B72: 1 | C72: =+D72/D54 -> 0.041483246 | D72: 24030 | G72: 0 | H72: =B72*G72 -> 0 | I72: =D72-G72 -> 24030
A73: Construction Management Fees | B73: 1 | C73: =D73/(D76-D73) -> 0 | D73: 0 | G73: 0 | H73: =B73*G73 -> 0 | I73: =D73-G73 -> 0
A74: Soft Costs Subtotal | D74: =SUM(D70:D73) -> 36830 | H74: =SUM(H70:H73) -> 0 | I74: =SUM(I70:I73) -> 36830
E75: 36830
A76: Total CapEx Budget | D76: =D23+D41+D54+D67+D74 -> 1492000 | H76: =H74+H67+H54+H41+H23 -> 840307.41 | I76: =I74+I67+I54+I41+I23 -> 651692.59
A78: Escrow Reserves
A79: [Enter] | B79: 0 | C79: 0 | D79: =B79*C79 -> 0
A80: Escrow Reserve Subtoatal | D80: =SUM(D76:D79) -> 1492000 | E80: 1492000
A81: Additional capital raise | D81: 272000 | G81: 0 | H81: 0 | I81: =D81-G81 -> 272000
A82: Total budget | D82: =D81+D80 -> 1764000 | H82: =H81+H76 -> 840307.41 | I82: =I81+I76 -> 923692.59
D84: 2100000
D85: =D84-D82 -> 336000

Sheet CapEx Tracker
B2: BLUE - Manual Input | G2: BLUE - Manual Input
B3: BLACK - Formula | G3: BLACK - Formula
B5: ='CapEx Borrower Budget'!B5 -> Borrowing Entity Name: | C5: ='CapEx Borrower Budget'!C5 -> Red Raider 45 LLC
B6: ='CapEx Borrower Budget'!B6 -> Property Name: | C6: ='CapEx Borrower Budget'!C6 -> The Park at Pottsburg Creek
B7: ='CapEx Borrower Budget'!B7 -> Property Address: | C7: ='CapEx Borrower Budget'!C7 -> 4800 Atlantic Blvd, Jacksonville, FL 32207 | G7: Property Address: | H7: =C7 -> 4800 Atlantic Blvd, Jacksonville, FL 32207
B8: ='CapEx Borrower Budget'!B8 -> Budget Created By: | C8: ='CapEx Borrower Budget'!C8 -> Edward Sittler, Vinnie Patel | G8: Budget Created By: | H8: =C8 -> Edward Sittler, Vinnie Patel
B9: ='CapEx Borrower Budget'!B9 -> Date: | C9: ='CapEx Borrower Budget'!C9 -> 45212 | G9: Date: | H9: =C9 -> 45212
B10: ='CapEx Borrower Budget'!B10 -> Total # Units: | C10: ='CapEx Borrower Budget'!C10 -> 128 | G10: Total # Units: | H10: =C10 -> 128
B11: ='CapEx Borrower Budget'!B11 -> # Full Upgrades: | C11: ='CapEx Borrower Budget'!C11 -> 128 | G11: # Full Upgrades: | H11: =C11 -> 128
B12: ='CapEx Borrower Budget'!B12 -> # Partial Upgrades: | C12: ='CapEx Borrower Budget'!C12 -> 0 | G12: # Partial Upgrades: | H12: =C12 -> 0
B14: ='CapEx Borrower Budget'!B14 -> Item/Description of Work | C14: ='CapEx Borrower Budget'!C14 -> # Units | D14: ='CapEx Borrower Budget'!D14 -> Unit Cost | E14: ='CapEx Borrower Budget'!E14 -> Total | G14: Item/Description of Work | H14: Original Budget | I14: Budget Reallocations | J14: Adjusted Current Budget | K14: 1 | L14: 2 | M14: 3 | N14: 4 | O14: 5 | P14: 6 | Q14: 7 | R14: 8 | S14: 9 | T14: 10 | U14: 11 | V14: 12 | W14: Total Completed and Stored to date | X14: % Complete | Y14: Balance To Finish the Project | Z14: Notes
B15: ='CapEx Borrower Budget'!B15 -> Interior Budget | G15: Interiors | H15: (A) | I15: (B) | J15: (A + B) | K15: (D) | L15: (D) | M15: (D) | N15: (D) | O15: (D) | P15: (D) | Q15: (D) | R15: (D) | S15: (D) | T15: (D) | U15: (D) | V15: (D) | W15: (D+D) | X15: (D+D) / (A+B) | Y15: (A+B)-(D+D)
B16: ='CapEx Borrower Budget'!B16 -> Unit upgrades | C16: ='CapEx Borrower Budget'!C16 -> 0 | D16: ='CapEx Borrower Budget'!D16 -> 0 | E16: ='CapEx Borrower Budget'!E16 -> 0 | G16: =+B16 -> Unit upgrades | H16: =+E16 -> 0 | I16: 627200 | J16: =H16+I16 -> 627200 | K16: 0 | L16: 0 | M16: 0 | N16: 0 | O16: 0 | P16: 0 | Q16: 0 | R16: 0 | S16: 0 | T16: 0 | U16: 0 | V16: 0 | W16: =SUM(K16:V16) -> 0 | X16: =IFERROR((W16)/J16,"0%") -> 0 | Y16: =J16-W16 -> 627200
B17: ='CapEx Borrower Budget'!B17 -> Appliances | C17: ='CapEx Borrower Budget'!C17 -> 128 | D17: ='CapEx Borrower Budget'!D17 -> 1500 | E17: ='CapEx Borrower Budget'!E17 -> 192000 | G17: =+B17 -> Appliances | H17: =+E17 -> 192000 | I17: -192000 | J17: =H17+I17 -> 0 | K17: 0 | L17: 0 | M17: 0 | N17: 0 | O17: 0 | P17: 0 | Q17: 0 | R17: 0 | S17: 0 | T17: 0 | U17: 0 | V17: 0 | W17: =SUM(K17:V17) -> 0 | X17: =IFERROR((W17)/J17,"0%") -> 0% | Y17: =J17-W17 -> 0
B18: ='CapEx Borrower Budget'!B18 -> Flooring | C18: ='CapEx Borrower Budget'!C18 -> 128 | D18: ='CapEx Borrower Budget'!D18 -> 1500 | E18: ='CapEx Borrower Budget'!E18 -> 192000 | G18: =+B18 -> Flooring | H18: =+E18 -> 192000 | I18: -192000 | J18: =H18+I18 -> 0 | K18: 0 | L18: 0 | M18: 0 | N18: 0 | O18: 0 | P18: 0 | Q18: 0 | R18: 0 | S18: 0 | T18: 0 | U18: 0 | V18: 0 | W18: =SUM(K18:V18) -> 0 | X18: =IFERROR((W18)/J18,"0%") -> 0% | Y18: =J18-W18 -> 0
B19: ='CapEx Borrower Budget'!B19 -> Fixtures | C19: ='CapEx Borrower Budget'!C19 -> 128 | D19: ='CapEx Borrower Budget'!D19 -> 1000 | E19: ='CapEx Borrower Budget'!E19 -> 128000 | G19: =+B19 -> Fixtures | H19: =+E19 -> 128000 | I19: =-H19 -> -128000 | J19: =H19+I19 -> 0 | K19: 0 | L19: 0 | M19: 0 | N19: 0 | O19: 0 | P19: 0 | Q19: 0 | R19: 0 | S19: 0 | T19: 0 | U19: 0 | V19: 0 | W19: =SUM(K19:V19) -> 0 | X19: =IFERROR((W19)/J19,"0%") -> 0% | Y19: =J19-W19 -> 0
B20: ='CapEx Borrower Budget'!B20 -> Cabinets | C20: ='CapEx Borrower Budget'!C20 -> 128 | D20: ='CapEx Borrower Budget'!D20 -> 900 | E20: ='CapEx Borrower Budget'!E20 -> 115200 | G20: =+B20 -> Cabinets | H20: =+E20 -> 115200 | I20: =-H20 -> -115200 | J20: =H20+I20 -> 0 | K20: 0 | L20: 0 | M20: 0 | N20: 0 | O20: 0 | P20: 0 | Q20: 0 | R20: 0 | S20: 0 | T20: 0 | U20: 0 | V20: 0 | W20: =SUM(K20:V20) -> 0 | X20: =IFERROR((W20)/J20,"0%") -> 0% | Y20: =J20-W20 -> 0
B21: ='CapEx Borrower Budget'!B21 -> washer/dryer machines | C21: ='CapEx Borrower Budget'!C21 -> 128 | D21: ='CapEx Borrower Budget'!D21 -> 500 | E21: ='CapEx Borrower Budget'!E21 -> 64000 | G21: =+B21 -> washer/dryer machines | H21: =+E21 -> 64000 | I21: 0 | J21: =H21+I21 -> 64000 | K21: 0 | L21: 0 | M21: 0 | N21: 0 | O21: 0 | P21: 0 | Q21: 0 | R21: 0 | S21: 0 | T21: 0 | U21: 0 | V21: 0 | W21: =SUM(K21:V21) -> 0 | X21: =IFERROR((W21)/J21,"0%") -> 0 | Y21: =J21-W21 -> 64000
B22: ='CapEx Borrower Budget'!B22 -> New Units | C22: ='CapEx Borrower Budget'!C22 -> 2 | D22: ='CapEx Borrower Budget'!D22 -> 20000 | E22: ='CapEx Borrower Budget'!E22 -> 40000 | G22: =+B22 -> New Units | H22: =+E22 -> 40000 | I22: 0 | J22: =H22+I22 -> 40000 | K22: 0 | L22: 0 | M22: 0 | N22: 0 | O22: 0 | P22: 0 | Q22: 0 | R22: 0 | S22: 0 | T22: 0 | U22: 0 | V22: 0 | W22: =SUM(K22:V22) -> 0 | X22: =IFERROR((W22)/J22,"0%") -> 0 | Y22: =J22-W22 -> 40000
B23: ='CapEx Borrower Budget'!B23 -> Down Unit | C23: ='CapEx Borrower Budget'!C23 -> 1 | D23: ='CapEx Borrower Budget'!D23 -> 20000 | E23: ='CapEx Borrower Budget'!E23 -> 20000 | G23: =+B23 -> Down Unit | H23: =+E23 -> 20000 | I23: 0 | J23: =H23+I23 -> 20000 | K23: 0 | L23: 0 | M23: 0 | N23: 0 | O23: 0 | P23: 0 | Q23: 0 | R23: 0 | S23: 0 | T23: 0 | U23: 0 | V23: 0 | W23: =SUM(K23:V23) -> 0 | X23: =IFERROR((W23)/J23,"0%") -> 0 | Y23: =J23-W23 -> 20000
B24: ='CapEx Borrower Budget'!B24 -> [Enter] | C24: ='CapEx Borrower Budget'!C24 -> 0 | D24: ='CapEx Borrower Budget'!D24 -> 0 | E24: ='CapEx Borrower Budget'!E24 -> 0 | G24: =+B24 -> [Enter] | H24: =+E24 -> 0 | I24: 0 | J24: =H24+I24 -> 0 | K24: 0 | L24: 0 | M24: 0 | N24: 0 | O24: 0 | P24: 0 | Q24: 0 | R24: 0 | S24: 0 | T24: 0 | U24: 0 | V24: 0 | W24: =SUM(K24:V24) -> 0 | X24: =IFERROR((W24)/J24,"0%") -> 0% | Y24: =J24-W24 -> 0
B25: ='CapEx Borrower Budget'!B25 -> [Enter] | C25: ='CapEx Borrower Budget'!C25 -> 0 | D25: ='CapEx Borrower Budget'!D25 -> 0 | E25: ='CapEx Borrower Budget'!E25 -> 0 | G25: =+B25 -> [Enter] | H25: =+E25 -> 0 | I25: 0 | J25: =H25+I25 -> 0 | K25: 0 | L25: 0 | M25: 0 | N25: 0 | O25: 0 | P25: 0 | Q25: 0 | R25: 0 | S25: 0 | T25: 0 | U25: 0 | V25: 0 | W25: =SUM(K25:V25) -> 0 | X25: =IFERROR((W25)/J25,"0%") -> 0% | Y25: =J25-W25 -> 0
B26: ='CapEx Borrower Budget'!B26 -> [Enter] | C26: ='CapEx Borrower Budget'!C26 -> 0 | D26: ='CapEx Borrower Budget'!D26 -> 0 | E26: ='CapEx Borrower Budget'!E26 -> 0 | G26: =+B26 -> [Enter] | H26: =+E26 -> 0 | I26: 0 | J26: =H26+I26 -> 0 | K26: 0 | L26: 0 | M26: 0 | N26: 0 | O26: 0 | P26: 0 | Q26: 0 | R26: 0 | S26: 0 | T26: 0 | U26: 0 | V26: 0 | W26: =SUM(K26:V26) -> 0 | X26: =IFERROR((W26)/J26,"0%") -> 0% | Y26: =J26-W26 -> 0
B27: ='CapEx Borrower Budget'!B27 -> [Enter] | C27: ='CapEx Borrower Budget'!C27 -> 0 | D27: ='CapEx Borrower Budget'!D27 -> 0 | E27: ='CapEx Borrower Budget'!E27 -> 0 | G27: =+B27 -> [Enter] | H27: =+E27 -> 0 | I27: 0 | J27: =H27+I27 -> 0 | K27: 0 | L27: 0 | M27: 0 | N27: 0 | O27: 0 | P27: 0 | Q27: 0 | R27: 0 | S27: 0 | T27: 0 | U27: 0 | V27: 0 | W27: =SUM(K27:V27) -> 0 | X27: =IFERROR((W27)/J27,"0%") -> 0% | Y27: =J27-W27 -> 0
B28: ='CapEx Borrower Budget'!B28 -> [Enter] | C28: ='CapEx Borrower Budget'!C28 -> 0 | D28: ='CapEx Borrower Budget'!D28 -> 0 | E28: ='CapEx Borrower Budget'!E28 -> 0 | G28: =+B28 -> [Enter] | H28: =+E28 -> 0 | I28: 0 | J28: =H28+I28 -> 0 | K28: 0 | L28: 0 | M28: 0 | N28: 0 | O28: 0 | P28: 0 | Q28: 0 | R28: 0 | S28: 0 | T28: 0 | U28: 0 | V28: 0 | W28: =SUM(K28:V28) -> 0 | X28: =IFERROR((W28)/J28,"0%") -> 0% | Y28: =J28-W28 -> 0
B29: ='CapEx Borrower Budget'!B29 -> [Enter] | C29: ='CapEx Borrower Budget'!C29 -> 0 | D29: ='CapEx Borrower Budget'!D29 -> 0 | E29: ='CapEx Borrower Budget'!E29 -> 0 | G29: =+B29 -> [Enter] | H29: =+E29 -> 0 | I29: 0 | J29: =H29+I29 -> 0 | K29: 0 | L29: 0 | M29: 0 | N29: 0 | O29: 0 | P29: 0 | Q29: 0 | R29: 0 | S29: 0 | T29: 0 | U29: 0 | V29: 0 | W29: =SUM(K29:V29) -> 0 | X29: =IFERROR((W29)/J29,"0%") -> 0% | Y29: =J29-W29 -> 0
B30: ='CapEx Borrower Budget'!B30 -> [Enter] | C30: ='CapEx Borrower Budget'!C30 -> 0 | D30: ='CapEx Borrower Budget'!D30 -> 0 | E30: ='CapEx Borrower Budget'!E30 -> 0 | G30: =+B30 -> [Enter] | H30: =+E30 -> 0 | I30: 0 | J30: =H30+I30 -> 0 | K30: 0 | L30: 0 | M30: 0 | N30: 0 | O30: 0 | P30: 0 | Q30: 0 | R30: 0 | S30: 0 | T30: 0 | U30: 0 | V30: 0 | W30: =SUM(K30:V30) -> 0 | X30: =IFERROR((W30)/J30,"0%") -> 0% | Y30: =J30-W30 -> 0
B31: ='CapEx Borrower Budget'!B31 -> [Enter] | C31: ='CapEx Borrower Budget'!C31 -> 0 | D31: ='CapEx Borrower Budget'!D31 -> 0 | E31: ='CapEx Borrower Budget'!E31 -> 0 | G31: =+B31 -> [Enter] | H31: =+E31 -> 0 | I31: 0 | J31: =H31+I31 -> 0 | K31: 0 | L31: 0 | M31: 0 | N31: 0 | O31: 0 | P31: 0 | Q31: 0 | R31: 0 | S31: 0 | T31: 0 | U31: 0 | V31: 0 | W31: =SUM(K31:V31) -> 0 | X31: =IFERROR((W31)/J31,"0%") -> 0% | Y31: =J31-W31 -> 0
B32: ='CapEx Borrower Budget'!B32 -> [Enter] | C32: ='CapEx Borrower Budget'!C32 -> 0 | D32: ='CapEx Borrower Budget'!D32 -> 0 | E32: ='CapEx Borrower Budget'!E32 -> 0 | G32: =+B32 -> [Enter] | H32: =+E32 -> 0 | I32: 0 | J32: =H32+I32 -> 0 | K32: 0 | L32: 0 | M32: 0 | N32: 0 | O32: 0 | P32: 0 | Q32: 0 | R32: 0 | S32: 0 | T32: 0 | U32: 0 | V32: 0 | W32: =SUM(K32:V32) -> 0 | X32: =IFERROR((W32)/J32,"0%") -> 0% | Y32: =J32-W32 -> 0
... B40: ='CapEx Borrower Budget'!B40 -> [Enter] | C40: ='CapEx Borrower Budget'!C40 -> 0 | D40: ='CapEx Borrower Budget'!D40 -> 0 | E40: ='CapEx Borrower Budget'!E40 -> 0 | G40: =+B40 -> [Enter] | H40: =+E40 -> 0 | I40: 0 | J40: =H40+I40 -> 0 | K40: 0 | L40: 0 | M40: 0 | N40: 0 | O40: 0 | P40: 0 | Q40: 0 | R40: 0 | S40: 0 | T40: 0 | U40: 0 | V40: 0 | W40: =SUM(K40:V40) -> 0 | X40: =IFERROR((W40)/J40,"0%") -> 0% | Y40: =J40-W40 -> 0
B41: ='CapEx Borrower Budget'!B41 -> Interiors Subtotal | E41: ='CapEx Borrower Budget'!E41 -> 751200 | G41: =B41 -> Interiors Subtotal | H41: =SUM(H16:H40) -> 751200 | I41: =SUM(I16:I40) -> 0 | J41: =SUM(J16:J40) -> 751200 | K41: =SUM(K16:K40) -> 0 | L41: =SUM(L16:L40) -> 0 | M41: =SUM(M16:M40) -> 0 | N41: =SUM(N16:N40) -> 0 | O41: =SUM(O16:O40) -> 0 | ... V41: =SUM(V16:V40) -> 0 | W41: =SUM(K41:V41) -> 0 | X41: =IFERROR((W41)/J41,"0%") -> 0 | Y41: =J41-W41 -> 751200
B43: ='CapEx Borrower Budget'!B43 -> Exterior Budget | G43: Exteriors
B44: ='CapEx Borrower Budget'!B44 -> Landscaping | C44: ='CapEx Borrower Budget'!C44 -> 1 | D44: ='CapEx Borrower Budget'!D44 -> 20000 | E44: ='CapEx Borrower Budget'!E44 -> 20000 | G44: =+B44 -> Landscaping | H44: =+E44 -> 20000 | I44: 0 | J44: =H44+I44 -> 20000 | K44: 0 | L44: 0 | M44: 0 | N44: 0 | O44: 0 | P44: 0 | Q44: 0 | R44: 0 | S44: 0 | T44: 0 | U44: 0 | V44: 0 | W44: =SUM(K44:V44) -> 0 | X44: =IFERROR((W44)/J44,"0%") -> 0 | Y44: =J44-W44 -> 20000
B45: ='CapEx Borrower Budget'!B45 -> Leasing office | C45: ='CapEx Borrower Budget'!C45 -> 1 | D45: ='CapEx Borrower Budget'!D45 -> 10000 | E45: ='CapEx Borrower Budget'!E45 -> 10000 | G45: =+B45 -> Leasing office | H45: =+E45 -> 10000 | I45: -1429.59 | J45: =H45+I45 -> 8570.41 | K45: 0 | L45: 0 | M45: 0 | N45: 0 | O45: 0 | P45: 0 | Q45: 0 | R45: 0 | S45: 0 | T45: 0 | U45: 0 | V45: 0 | W45: =SUM(K45:V45) -> 0 | X45: =IFERROR((W45)/J45,"0%") -> 0 | Y45: =J45-W45 -> 8570.41
B46: ='CapEx Borrower Budget'!B46 -> Fitness center | C46: ='CapEx Borrower Budget'!C46 -> 1 | D46: ='CapEx Borrower Budget'!D46 -> 5000 | E46: ='CapEx Borrower Budget'!E46 -> 5000 | G46: =+B46 -> Fitness center | H46: =+E46 -> 5000 | I46: -5000 | J46: =H46+I46 -> 0 | K46: 0 | L46: 0 | M46: 0 | N46: 0 | O46: 0 | P46: 0 | Q46: 0 | R46: 0 | S46: 0 | T46: 0 | U46: 0 | V46: 0 | W46: =SUM(K46:V46) -> 0 | X46: =IFERROR((W46)/J46,"0%") -> 0% | Y46: =J46-W46 -> 0
B47: ='CapEx Borrower Budget'!B47 -> Monument sign | C47: ='CapEx Borrower Budget'!C47 -> 1 | D47: ='CapEx Borrower Budget'!D47 -> 10000 | E47: ='CapEx Borrower Budget'!E47 -> 10000 | G47: =+B47 -> Monument sign | H47: =+E47 -> 10000 | I47: 0 | J47: =H47+I47 -> 10000 | K47: 0 | L47: 0 | M47: 0 | N47: 0 | O47: 0 | P47: 0 | Q47: 0 | R47: 0 | S47: 0 | T47: 0 | U47: 0 | V47: 0 | W47: =SUM(K47:V47) -> 0 | X47: =IFERROR((W47)/J47,"0%") -> 0 | Y47: =J47-W47 -> 10000
B48: ='CapEx Borrower Budget'!B48 -> Pool area | C48: ='CapEx Borrower Budget'!C48 -> 1 | D48: ='CapEx Borrower Budget'!D48 -> 3000 | E48: ='CapEx Borrower Budget'!E48 -> 3000 | G48: =+B48 -> Pool area | H48: =+E48 -> 3000 | I48: 8929.59 | J48: =H48+I48 -> 11929.59 | K48: 0 | L48: 0 | M48: 0 | N48: 0 | O48: 0 | P48: 0 | Q48: 0 | R48: 0 | S48: 0 | T48: 0 | U48: 0 | V48: 0 | W48: =SUM(K48:V48) -> 0 | X48: =IFERROR((W48)/J48,"0%") -> 0 | Y48: =J48-W48 -> 11929.59
B49: ='CapEx Borrower Budget'!B49 -> Grilling stations | C49: ='CapEx Borrower Budget'!C49 -> 2 | D49: ='CapEx Borrower Budget'!D49 -> 2500 | E49: ='CapEx Borrower Budget'!E49 -> 5000 | G49: =+B49 -> Grilling stations | H49: =+E49 -> 5000 | I49: -2500 | J49: =H49+I49 -> 2500 | K49: 0 | L49: 0 | M49: 0 | N49: 0 | O49: 0 | P49: 0 | Q49: 0 | R49: 0 | S49: 0 | T49: 0 | U49: 0 | V49: 0 | W49: =SUM(K49:V49) -> 0 | X49: =IFERROR((W49)/J49,"0%") -> 0 | Y49: =J49-W49 -> 2500
B50: ='CapEx Borrower Budget'!B50 -> Dog park | C50: ='CapEx Borrower Budget'!C50 -> 1 | D50: ='CapEx Borrower Budget'!D50 -> 5000 | E50: ='CapEx Borrower Budget'!E50 -> 5000 | G50: =+B50 -> Dog park | H50: =+E50 -> 5000 | I50: 0 | J50: =H50+I50 -> 5000 | K50: 0 | L50: 0 | M50: 0 | N50: 0 | O50: 0 | P50: 0 | Q50: 0 | R50: 0 | S50: 0 | T50: 0 | U50: 0 | V50: 0 | W50: =SUM(K50:V50) -> 0 | X50: =IFERROR((W50)/J50,"0%") -> 0 | Y50: =J50-W50 -> 5000
B51: ='CapEx Borrower Budget'!B52 -> Playground | C51: ='CapEx Borrower Budget'!C52 -> 1 | D51: ='CapEx Borrower Budget'!D52 -> 2000 | E51: ='CapEx Borrower Budget'!E52 -> 2000 | G51: =+B51 -> Playground | H51: =+E51 -> 2000 | I51: 0 | J51: =H51+I51 -> 2000 | K51: 0 | L51: 0 | M51: 0 | N51: 0 | O51: 0 | P51: 0 | Q51: 0 | R51: 0 | S51: 0 | T51: 0 | U51: 0 | V51: 0 | W51: =SUM(K51:V51) -> 0 | X51: =IFERROR((W51)/J51,"0%") -> 0 | Y51: =J51-W51 -> 2000
B52: ='CapEx Borrower Budget'!B53 -> [Enter] | C52: ='CapEx Borrower Budget'!C53 -> 0 | D52: ='CapEx Borrower Budget'!D53 -> 0 | E52: ='CapEx Borrower Budget'!E53 -> 0 | G52: =+B52 -> [Enter] | H52: =+E52 -> 0 | I52: 0 | J52: =H52+I52 -> 0 | K52: 0 | L52: 0 | M52: 0 | N52: 0 | O52: 0 | P52: 0 | Q52: 0 | R52: 0 | S52: 0 | T52: 0 | U52: 0 | V52: 0 | W52: =SUM(K52:V52) -> 0 | X52: =IFERROR((W52)/J52,"0%") -> 0% | Y52: =J52-W52 -> 0
B53: ='CapEx Borrower Budget'!B54 -> [Enter] | C53: ='CapEx Borrower Budget'!C54 -> 0 | D53: ='CapEx Borrower Budget'!D54 -> 0 | E53: ='CapEx Borrower Budget'!E54 -> 0 | G53: =+B53 -> [Enter] | H53: =+E53 -> 0 | I53: 0 | J53: =H53+I53 -> 0 | K53: 0 | L53: 0 | M53: 0 | N53: 0 | O53: 0 | P53: 0 | Q53: 0 | R53: 0 | S53: 0 | T53: 0 | U53: 0 | V53: 0 | W53: =SUM(K53:V53) -> 0 | X53: =IFERROR((W53)/J53,"0%") -> 0% | Y53: =J53-W53 -> 0
B54: ='CapEx Borrower Budget'!B55 -> [Enter] | C54: ='CapEx Borrower Budget'!C55 -> 0 | D54: ='CapEx Borrower Budget'!D55 -> 0 | E54: ='CapEx Borrower Budget'!E55 -> 0 | G54: =+B54 -> [Enter] | H54: =+E54 -> 0 | I54: 0 | J54: =H54+I54 -> 0 | K54: 0 | L54: 0 | M54: 0 | N54: 0 | O54: 0 | P54: 0 | Q54: 0 | R54: 0 | S54: 0 | T54: 0 | U54: 0 | V54: 0 | W54: =SUM(K54:V54) -> 0 | X54: =IFERROR((W54)/J54,"0%") -> 0% | Y54: =J54-W54 -> 0
B55: ='CapEx Borrower Budget'!B56 -> [Enter] | C55: ='CapEx Borrower Budget'!C56 -> 0 | D55: ='CapEx Borrower Budget'!D56 -> 0 | E55: ='CapEx Borrower Budget'!E56 -> 0 | G55: =+B55 -> [Enter] | H55: =+E55 -> 0 | I55: 0 | J55: =H55+I55 -> 0 | K55: 0 | L55: 0 | M55: 0 | N55: 0 | O55: 0 | P55: 0 | Q55: 0 | R55: 0 | S55: 0 | T55: 0 | U55: 0 | V55: 0 | W55: =SUM(K55:V55) -> 0 | X55: =IFERROR((W55)/J55,"0%") -> 0% | Y55: =J55-W55 -> 0
B56: ='CapEx Borrower Budget'!B57 -> [Enter] | C56: ='CapEx Borrower Budget'!C57 -> 0 | D56: ='CapEx Borrower Budget'!D57 -> 0 | E56: ='CapEx Borrower Budget'!E57 -> 0 | G56: =+B56 -> [Enter] | H56: =+E56 -> 0 | I56: 0 | J56: =H56+I56 -> 0 | K56: 0 | L56: 0 | M56: 0 | N56: 0 | O56: 0 | P56: 0 | Q56: 0 | R56: 0 | S56: 0 | T56: 0 | U56: 0 | V56: 0 | W56: =SUM(K56:V56) -> 0 | X56: =IFERROR((W56)/J56,"0%") -> 0% | Y56: =J56-W56 -> 0
B57: ='CapEx Borrower Budget'!B58 -> [Enter] | C57: ='CapEx Borrower Budget'!C58 -> 0 | D57: ='CapEx Borrower Budget'!D58 -> 0 | E57: ='CapEx Borrower Budget'!E58 -> 0 | G57: =+B57 -> [Enter] | H57: =+E57 -> 0 | I57: 0 | J57: =H57+I57 -> 0 | K57: 0 | L57: 0 | M57: 0 | N57: 0 | O57: 0 | P57: 0 | Q57: 0 | R57: 0 | S57: 0 | T57: 0 | U57: 0 | V57: 0 | W57: =SUM(K57:V57) -> 0 | X57: =IFERROR((W57)/J57,"0%") -> 0% | Y57: =J57-W57 -> 0
B58: ='CapEx Borrower Budget'!B59 -> Exteriors Subtotal | E58: ='CapEx Borrower Budget'!E59 -> 65000 | G58: =B58 -> Exteriors Subtotal | H58: =SUM(H44:H57) -> 60000 | I58: =SUM(I44:I57) -> 0 | J58: =SUM(J44:J57) -> 60000 | K58: =SUM(K44:K57) -> 0 | L58: =SUM(L44:L57) -> 0 | M58: =SUM(M44:M57) -> 0 | N58: =SUM(N44:N57) -> 0 | O58: =SUM(O44:O57) -> 0 | ... V58: =SUM(V44:V57) -> 0 | W58: =SUM(K58:V58) -> 0 | X58: =IFERROR((W58)/J58,"0%") -> 0 | Y58: =J58-W58 -> 60000
B60: ='CapEx Borrower Budget'!B61 -> Deferred Maintenance | G60: Deferred Maintenance
B61: ='CapEx Borrower Budget'!B62 -> Roofs (seller credit) | C61: ='CapEx Borrower Budget'!C62 -> 1 | D61: ='CapEx Borrower Budget'!D62 -> 272000 | E61: ='CapEx Borrower Budget'!E62 -> 272000 | G61: =+B61 -> Roofs (seller credit) | H61: =+E61 -> 272000 | I61: 0 | J61: =H61+I61 -> 272000 | K61: 79670 | L61: 79670 | M61: =79670+44486.72 -> 124156.72 | N61: 0 | O61: 0 | P61: 0 | Q61: 0 | R61: 0 | S61: 0 | T61: 0 | U61: 0 | V61: 0 | W61: =SUM(K61:V61) -> 283496.72 | X61: =IFERROR((W61)/J61,"0%") -> 1.0422674 | Y61: =J61-W61 -> -11496.72
B62: ='CapEx Borrower Budget'!B63 -> Plumbing | C62: ='CapEx Borrower Budget'!C63 -> 1 | D62: ='CapEx Borrower Budget'!D63 -> 179200 | E62: ='CapEx Borrower Budget'!E63 -> 179200 | G62: =+B62 -> Plumbing | H62: =+E62 -> 179200 | I62: 0 | J62: =H62+I62 -> 179200 | K62: 0 | L62: 0 | M62: 0 | N62: 0 | O62: 0 | P62: 0 | Q62: 0 | R62: 0 | S62: 0 | T62: 0 | U62: 0 | V62: 0 | W62: =SUM(K62:V62) -> 0 | X62: =IFERROR((W62)/J62,"0%") -> 0 | Y62: =J62-W62 -> 179200
B63: ='CapEx Borrower Budget'!B64 -> Electrical | C63: ='CapEx Borrower Budget'!C64 -> 128 | D63: ='CapEx Borrower Budget'!D64 -> 440 | E63: ='CapEx Borrower Budget'!E64 -> 56320 | G63: =+B63 -> Electrical | H63: =+E63 -> 56320 | I63: 0 | J63: =H63+I63 -> 56320 | K63: 0 | L63: 0 | M63: 0 | N63: 0 | O63: 0 | P63: 0 | Q63: 0 | R63: 0 | S63: 0 | T63: 0 | U63: 0 | V63: 0 | W63: =SUM(K63:V63) -> 0 | X63: =IFERROR((W63)/J63,"0%") -> 0 | Y63: =J63-W63 -> 56320
B64: ='CapEx Borrower Budget'!B65 -> HVAC | C64: ='CapEx Borrower Budget'!C65 -> 35 | D64: ='CapEx Borrower Budget'!D65 -> 1250 | E64: ='CapEx Borrower Budget'!E65 -> 43750 | G64: =+B64 -> HVAC | H64: =+E64 -> 43750 | I64: 0 | J64: =H64+I64 -> 43750 | K64: 0 | L64: 0 | M64: 0 | N64: 0 | O64: 0 | P64: 0 | Q64: 0 | R64: 0 | S64: 0 | T64: 0 | U64: 0 | V64: 0 | W64: =SUM(K64:V64) -> 0 | X64: =IFERROR((W64)/J64,"0%") -> 0 | Y64: =J64-W64 -> 43750
B65: ='CapEx Borrower Budget'!B66 -> [Enter] | C65: ='CapEx Borrower Budget'!C66 -> 0 | D65: ='CapEx Borrower Budget'!D66 -> 0 | E65: ='CapEx Borrower Budget'!E66 -> 0 | G65: =+B65 -> [Enter] | H65: =+E65 -> 0 | I65: 0 | J65: =H65+I65 -> 0 | K65: 0 | L65: 0 | M65: 0 | N65: 0 | O65: 0 | P65: 0 | Q65: 0 | R65: 0 | S65: 0 | T65: 0 | U65: 0 | V65: 0 | W65: =SUM(K65:V65) -> 0 | X65: =IFERROR((W65)/J65,"0%") -> 0% | Y65: =J65-W65 -> 0
B66: ='CapEx Borrower Budget'!B67 -> [Enter] | C66: ='CapEx Borrower Budget'!C67 -> 0 | D66: ='CapEx Borrower Budget'!D67 -> 0 | E66: ='CapEx Borrower Budget'!E67 -> 0 | G66: =+B66 -> [Enter] | H66: =+E66 -> 0 | I66: 0 | J66: =H66+I66 -> 0 | K66: 0 | L66: 0 | M66: 0 | N66: 0 | O66: 0 | P66: 0 | Q66: 0 | R66: 0 | S66: 0 | T66: 0 | U66: 0 | V66: 0 | W66: =SUM(K66:V66) -> 0 | X66: =IFERROR((W66)/J66,"0%") -> 0% | Y66: =J66-W66 -> 0
B67: ='CapEx Borrower Budget'!B68 -> [Enter] | C67: ='CapEx Borrower Budget'!C68 -> 0 | D67: ='CapEx Borrower Budget'!D68 -> 0 | E67: ='CapEx Borrower Budget'!E68 -> 0 | G67: =+B67 -> [Enter] | H67: =+E67 -> 0 | I67: 0 | J67: =H67+I67 -> 0 | K67: 0 | L67: 0 | M67: 0 | N67: 0 | O67: 0 | P67: 0 | Q67: 0 | R67: 0 | S67: 0 | T67: 0 | U67: 0 | V67: 0 | W67: =SUM(K67:V67) -> 0 | X67: =IFERROR((W67)/J67,"0%") -> 0% | Y67: =J67-W67 -> 0
B68: ='CapEx Borrower Budget'!B69 -> [Enter] | C68: ='CapEx Borrower Budget'!C69 -> 0 | D68: ='CapEx Borrower Budget'!D69 -> 0 | E68: ='CapEx Borrower Budget'!E69 -> 0 | G68: =+B68 -> [Enter] | H68: =+E68 -> 0 | I68: 0 | J68: =H68+I68 -> 0 | K68: 0 | L68: 0 | M68: 0 | N68: 0 | O68: 0 | P68: 0 | Q68: 0 | R68: 0 | S68: 0 | T68: 0 | U68: 0 | V68: 0 | W68: =SUM(K68:V68) -> 0 | X68: =IFERROR((W68)/J68,"0%") -> 0% | Y68: =J68-W68 -> 0
B69: ='CapEx Borrower Budget'!B70 -> [Enter] | C69: ='CapEx Borrower Budget'!C70 -> 0 | D69: ='CapEx Borrower Budget'!D70 -> 0 | E69: ='CapEx Borrower Budget'!E70 -> 0 | G69: =+B69 -> [Enter] | H69: =+E69 -> 0 | I69: 0 | J69: =H69+I69 -> 0 | K69: 0 | L69: 0 | M69: 0 | N69: 0 | O69: 0 | P69: 0 | Q69: 0 | R69: 0 | S69: 0 | T69: 0 | U69: 0 | V69: 0 | W69: =SUM(K69:V69) -> 0 | X69: =IFERROR((W69)/J69,"0%") -> 0% | Y69: =J69-W69 -> 0
B70: ='CapEx Borrower Budget'!B71 -> [Enter] | C70: ='CapEx Borrower Budget'!C71 -> 0 | D70: ='CapEx Borrower Budget'!D71 -> 0 | E70: ='CapEx Borrower Budget'!E71 -> 0 | G70: =+B70 -> [Enter] | H70: =+E70 -> 0 | I70: 0 | J70: =H70+I70 -> 0 | K70: 0 | L70: 0 | M70: 0 | N70: 0 | O70: 0 | P70: 0 | Q70: 0 | R70: 0 | S70: 0 | T70: 0 | U70: 0 | V70: 0 | W70: =SUM(K70:V70) -> 0 | X70: =IFERROR((W70)/J70,"0%") -> 0% | Y70: =J70-W70 -> 0
B71: ='CapEx Borrower Budget'!B72 -> Deferred Maintenance Subtotal | E71: ='CapEx Borrower Budget'!E72 -> 551270 | G71: =B71 -> Deferred Maintenance Subtotal | H71: =SUM(H61:H70) -> 551270 | I71: =SUM(I61:I70) -> 0 | J71: =SUM(J61:J70) -> 551270 | K71: =SUM(K61:K70) -> 79670 | L71: =SUM(L61:L70) -> 79670 | M71: =SUM(M61:M70) -> 124156.72 | N71: =SUM(N61:N70) -> 0 | O71: =SUM(O61:O70) -> 0 | ... V71: =SUM(V61:V70) -> 0 | W71: =SUM(K71:V71) -> 283496.72 | X71: =IFERROR((W71)/J71,"0%") -> 0.51426111 | Y71: =J71-W71 -> 267773.28
B73: ='CapEx Borrower Budget'!B74 -> Immediate Repairs | G73: Immediate Repairs | Z73: # Days to Complete | AA73: 45313
B74: ='CapEx Borrower Budget'!B75 -> Install and /or repair fencing and gates to comply with security plan. | C74: ='CapEx Borrower Budget'!C75 -> 1 | D74: ='CapEx Borrower Budget'!D75 -> 30000 | E74: ='CapEx Borrower Budget'!E75 -> 30000 | G74: =+B74 -> Install and /or repair fencing and gates to comply with security plan. | H74: =+E74 -> 30000 | I74: 0 | J74: =H74+I74 -> 30000 | K74: 0 | L74: 0 | M74: 0 | N74: 0 | O74: 0 | P74: 0 | Q74: 0 | R74: 0 | S74: 0 | T74: 0 | U74: 0 | V74: 0 | W74: =SUM(K74:V74) -> 0 | X74: =IFERROR((W74)/J74,"0%") -> 0 | Y74: =J74-W74 -> 30000 | Z74: =EOMONTH($AA$73,60/30) -> 45382
B75: ='CapEx Borrower Budget'!B76 -> Repair damaged pavement consisting of linear cracking, alligator cracking, potholes, and surface raveling throughout the Property. | C75: ='CapEx Borrower Budget'!C76 -> 1 | D75: ='CapEx Borrower Budget'!D76 -> 28000 | E75: ='CapEx Borrower Budget'!E76 -> 28000 | G75: =+B75 -> Repair damaged pavement consisting of linear cracking, alligator cracking, potholes, and surface raveling throughout the Property. | H75: =+E75 -> 28000 | I75: 0 | J75: =H75+I75 -> 28000 | K75: 0 | L75: 0 | M75: 0 | N75: 0 | O75: 0 | P75: 0 | Q75: 0 | R75: 0 | S75: 0 | T75: 0 | U75: 0 | V75: 0 | W75: =SUM(K75:V75) -> 0 | X75: =IFERROR((W75)/J75,"0%") -> 0 | Y75: =J75-W75 -> 28000 | Z75: =EOMONTH($AA$73,60/30) -> 45382
B76: ='CapEx Borrower Budget'!B77 -> Install security cameras to comply with security plan. | C76: ='CapEx Borrower Budget'!C77 -> 1 | D76: ='CapEx Borrower Budget'!D77 -> 20000 | E76: ='CapEx Borrower Budget'!E77 -> 20000 | G76: =+B76 -> Install security cameras to comply with security plan. | H76: =+E76 -> 20000 | I76: 0 | J76: =H76+I76 -> 20000 | K76: 0 | L76: 0 | M76: 0 | N76: 0 | O76: 0 | P76: 0 | Q76: 0 | R76: 0 | S76: 0 | T76: 0 | U76: 0 | V76: 0 | W76: =SUM(K76:V76) -> 0 | X76: =IFERROR((W76)/J76,"0%") -> 0 | Y76: =J76-W76 -> 20000 | Z76: =EOMONTH($AA$73,60/30) -> 45382
B77: ='CapEx Borrower Budget'!B78 -> Repair and replace cracked and broken concrete stair treads. | C77: ='CapEx Borrower Budget'!C78 -> 1 | D77: ='CapEx Borrower Budget'!D78 -> 5000 | E77: ='CapEx Borrower Budget'!E78 -> 5000 | G77: =+B77 -> Repair and replace cracked and broken concrete stair treads. | H77: =+E77 -> 5000 | I77: 0 | J77: =H77+I77 -> 5000 | K77: 0 | L77: 0 | M77: 0 | N77: 0 | O77: 0 | P77: 0 | Q77: 0 | R77: 0 | S77: 0 | T77: 0 | U77: 0 | V77: 0 | W77: =SUM(K77:V77) -> 0 | X77: =IFERROR((W77)/J77,"0%") -> 0 | Y77: =J77-W77 -> 5000 | Z77: =EOMONTH($AA$73,45/30) -> 45351
B78: ='CapEx Borrower Budget'!B79 -> Repair all trip hazards. | C78: ='CapEx Borrower Budget'!C79 -> 1 | D78: ='CapEx Borrower Budget'!D79 -> 3000 | E78: ='CapEx Borrower Budget'!E79 -> 3000 | G78: =+B78 -> Repair all trip hazards. | H78: =+E78 -> 3000 | I78: 0 | J78: =H78+I78 -> 3000 | K78: 0 | L78: 0 | M78: 0 | N78: 0 | O78: 0 | P78: 0 | Q78: 0 | R78: 0 | S78: 0 | T78: 0 | U78: 0 | V78: 0 | W78: =SUM(K78:V78) -> 0 | X78: =IFERROR((W78)/J78,"0%") -> 0 | Y78: =J78-W78 -> 3000 | Z78: =EOMONTH($AA$73,45/30) -> 45351
B79: ='CapEx Borrower Budget'!B80 -> Reconfigure the ramp and access walk to provide a level landing at the leasing office entry door | C79: ='CapEx Borrower Budget'!C80 -> 1 | D79: ='CapEx Borrower Budget'!D80 -> 1200 | E79: ='CapEx Borrower Budget'!E80 -> 1200 | G79: =+B79 -> Reconfigure the ramp and access walk to provide a level landing at the leasing office entry door | H79: =+E79 -> 1200 | I79: 0 | J79: =H79+I79 -> 1200 | K79: 0 | L79: 0 | M79: 0 | N79: 0 | O79: 0 | P79: 0 | Q79: 0 | R79: 0 | S79: 0 | T79: 0 | U79: 0 | V79: 0 | W79: =SUM(K79:V79) -> 0 | X79: =IFERROR((W79)/J79,"0%") -> 0 | Y79: =J79-W79 -> 1200 | Z79: =EOMONTH($AA$73,45/30) -> 45351
B80: ='CapEx Borrower Budget'!B81 -> Reconfigure the ADA accessible parking space to provide unobstructed access to aisle. | C80: ='CapEx Borrower Budget'!C81 -> 1 | D80: ='CapEx Borrower Budget'!D81 -> 500 | E80: ='CapEx Borrower Budget'!E81 -> 500 | G80: =+B80 -> Reconfigure the ADA accessible parking space to provide unobstructed access to aisle. | H80: =+E80 -> 500 | I80: 0 | J80: =H80+I80 -> 500 | K80: 0 | L80: 0 | M80: 0 | N80: 0 | O80: 0 | P80: 0 | Q80: 0 | R80: 0 | S80: 0 | T80: 0 | U80: 0 | V80: 0 | W80: =SUM(K80:V80) -> 0 | X80: =IFERROR((W80)/J80,"0%") -> 0 | Y80: =J80-W80 -> 500 | Z80: =EOMONTH($AA$73,45/30) -> 45351
B81: ='CapEx Borrower Budget'!B82 -> [Enter] | C81: ='CapEx Borrower Budget'!C82 -> 0 | D81: ='CapEx Borrower Budget'!D82 -> 0 | E81: ='CapEx Borrower Budget'!E82 -> 0 | G81: =+B81 -> [Enter] | H81: =+E81 -> 0 | I81: 0 | J81: =H81+I81 -> 0 | K81: 0 | L81: 0 | M81: 0 | N81: 0 | O81: 0 | P81: 0 | Q81: 0 | R81: 0 | S81: 0 | T81: 0 | U81: 0 | V81: 0 | W81: =SUM(K81:V81) -> 0 | X81: =IFERROR((W81)/J81,"0%") -> 0% | Y81: =J81-W81 -> 0 | Z81: =EOMONTH($AA$73,45/30) -> 45351
B82: ='CapEx Borrower Budget'!B83 -> [Enter] | C82: ='CapEx Borrower Budget'!C83 -> 0 | D82: ='CapEx Borrower Budget'!D83 -> 0 | E82: ='CapEx Borrower Budget'!E83 -> 0 | G82: =+B82 -> [Enter] | H82: =+E82 -> 0 | I82: 0 | J82: =H82+I82 -> 0 | K82: 0 | L82: 0 | M82: 0 | N82: 0 | O82: 0 | P82: 0 | Q82: 0 | R82: 0 | S82: 0 | T82: 0 | U82: 0 | V82: 0 | W82: =SUM(K82:V82) -> 0 | X82: =IFERROR((W82)/J82,"0%") -> 0% | Y82: =J82-W82 -> 0 | Z82: =EOMONTH($AA$73,45/30) -> 45351
B83: ='CapEx Borrower Budget'!B85 -> Immediate Repairs Subtotal | E83: ='CapEx Borrower Budget'!E85 -> 87700 | G83: =B83 -> Immediate Repairs Subtotal | H83: =SUM(H74:H82) -> 87700 | I83: =SUM(I74:I82) -> 0 | J83: =SUM(J74:J82) -> 87700 | K83: =SUM(K74:K82) -> 0 | L83: =SUM(L74:L82) -> 0 | M83: =SUM(M74:M82) -> 0 | N83: =SUM(N74:N82) -> 0 | O83: =SUM(O74:O82) -> 0 | ... V83: =SUM(V74:V82) -> 0 | W83: =SUM(K83:V83) -> 0 | X83: =IFERROR((W83)/J83,"0%") -> 0 | Y83: =J83-W83 -> 87700
B85: ='CapEx Borrower Budget'!B87 -> Soft Costs | G85: Soft Costs
B86: ='CapEx Borrower Budget'!B88 -> Interior Contingency | D86: ='CapEx Borrower Budget'!D88 -> 0.017039404 | E86: ='CapEx Borrower Budget'!E88 -> 12800 | G86: Interior Contingency | H86: =+E86 -> 12800 | I86: 0 | J86: =H86+I86 -> 12800 | K86: 0 | L86: 0 | M86: 0 | N86: 0 | O86: 0 | P86: 0 | Q86: 0 | R86: 0 | S86: 0 | T86: 0 | U86: 0 | V86: 0 | W86: =SUM(K86:V86) -> 0 | X86: =IFERROR((W86)/J86,"0%") -> 0 | Y86: =J86-W86 -> 12800
B87: ='CapEx Borrower Budget'!B89 -> Exterior Contingency | D87: ='CapEx Borrower Budget'!D89 -> 0 | E87: ='CapEx Borrower Budget'!E89 -> 0 | G87: Exterior Contingency | H87: =+E87 -> 0 | I87: 0 | J87: =H87+I87 -> 0 | K87: 0 | L87: 0 | M87: 0 | N87: 0 | O87: 0 | P87: 0 | Q87: 0 | R87: 0 | S87: 0 | T87: 0 | U87: 0 | V87: 0 | W87: =SUM(K87:V87) -> 0 | X87: =IFERROR((W87)/J87,"0%") -> 0% | Y87: =J87-W87 -> 0
B88: ='CapEx Borrower Budget'!B90 -> Def. Maintenance Contingency | D88: ='CapEx Borrower Budget'!D90 -> 0.043590255 | E88: ='CapEx Borrower Budget'!E90 -> 24030 | G88: Def. Maintenance Contingency | H88: =+E88 -> 24030 | I88: 0 | J88: =H88+I88 -> 24030 | K88: 0 | L88: 0 | M88: 0 | N88: 0 | O88: 0 | P88: 0 | Q88: 0 | R88: 0 | S88: 0 | T88: 0 | U88: 0 | V88: 0 | W88: =SUM(K88:V88) -> 0 | X88: =IFERROR((W88)/J88,"0%") -> 0 | Y88: =J88-W88 -> 24030
B89: ='CapEx Borrower Budget'!B91 -> Construction Management Fees | D89: ='CapEx Borrower Budget'!D91 -> 0 | E89: ='CapEx Borrower Budget'!E91 -> 0 | G89: Construction Management Fees | H89: =E89 -> 0 | I89: 0 | J89: =H89+I89 -> 0 | K89: 0 | L89: 0 | M89: 0 | N89: 0 | O89: 0 | P89: 0 | Q89: 0 | R89: 0 | S89: 0 | T89: 0 | U89: 0 | V89: 0 | W89: =SUM(K89:V89) -> 0 | X89: =IFERROR((W89)/J89,"0%") -> 0% | Y89: =J89-W89 -> 0
B90: ='CapEx Borrower Budget'!B92 -> Soft Costs Subtotal | E90: ='CapEx Borrower Budget'!E92 -> 36830 | G90: =B90 -> Soft Costs Subtotal | H90: =SUM(H86:H89) -> 36830 | I90: =SUM(I86:I89) -> 0 | J90: =SUM(J86:J89) -> 36830 | K90: =SUM(K86:K89) -> 0 | L90: =SUM(L86:L89) -> 0 | M90: =SUM(M86:M89) -> 0 | N90: =SUM(N86:N89) -> 0 | O90: =SUM(O86:O89) -> 0 | ... V90: =SUM(V86:V89) -> 0 | W90: =SUM(K90:V90) -> 0 | X90: =IFERROR((W90)/J90,"0%") -> 0 | Y90: =J90-W90 -> 36830
B91: ='CapEx Borrower Budget'!B93
B92: ='CapEx Borrower Budget'!B94 -> Total CapEx Budget | E92: ='CapEx Borrower Budget'!E94 -> 1492000 | G92: Total Bancorp Funded | H92: =H41+H58+H71+H83+H90 -> 1487000 | I92: =I41+I58+I71+I83+I90 -> 0 | J92: =J41+J58+J71+J83+J90 -> 1487000 | K92: =K41+K58+K71+K83+K90 -> 79670 | L92: =L41+L58+L71+L83+L90 -> 79670 | M92: =M41+M58+M71+M83+M90 -> 124156.72 | N92: =N41+N58+N71+N83+N90 -> 0 | O92: =O41+O58+O71+O83+O90 -> 0 | ... V92: =V41+V58+V71+V83+V90 -> 0 | W92: =SUM(K92:V92) -> 283496.72 | X92: =IFERROR((W92)/J92,"0%") -> 0.19065011 | Y92: =J92-W92 -> 1203503.3
B94: ='CapEx Borrower Budget'!B100 -> Description/Scope of Work | G94: Deductions | K94: 0 | L94: 0 | M94: 0 | N94: 0 | O94: 0 | P94: 0 | Q94: 0 | R94: 0 | S94: 0 | T94: 0 | U94: 0 | V94: 0 | W94: 0
B95: ='CapEx Borrower Budget'!B101:E110 -> #VALUE!
G96: Total Requested | K96: =K92-K94 -> 79670 | L96: =L92-L94 -> 79670 | M96: =M92-M94 -> 124156.72 | N96: =N92-N94 -> 0 | O96: =O92-O94 -> 0 | P96: =P92-P94 -> 0 | Q96: =Q92-Q94 -> 0 | R96: =R92-R94 -> 0 | ... W96: =W92-W94 -> 283496.72
G98: Escrows (If applicable)
G99: [Escrow 1] | H99: 0 | I99: 0 | J99: =H99+I99 -> 0 | K99: 0 | L99: 0 | M99: 0 | N99: 0 | O99: 0 | P99: 0 | Q99: 0 | R99: 0 | S99: 0 | T99: 0 | U99: 0 | V99: 0 | W99: =SUM(K99:V99) -> 0 | X99: =IFERROR((W99)/J99,"0%") -> 0% | Y99: =J99-W99 -> 0
G100: [Escrow 1] | H100: 0 | I100: 0 | J100: =H100+I100 -> 0 | K100: 0 | L100: 0 | M100: 0 | N100: 0 | O100: 0 | P100: 0 | Q100: 0 | R100: 0 | S100: 0 | T100: 0 | U100: 0 | V100: 0 | W100: =SUM(K100:V100) -> 0 | X100: =IFERROR((W100)/J100,"0%") -> 0% | Y100: =J100-W100 -> 0
G101: [Escrow 1] | H101: 0 | I101: 0 | J101: =H101+I101 -> 0 | K101: 0 | L101: 0 | M101: 0 | N101: 0 | O101: 0 | P101: 0 | Q101: 0 | R101: 0 | S101: 0 | T101: 0 | U101: 0 | V101: 0 | W101: =SUM(K101:V101) -> 0 | X101: =IFERROR((W101)/J101,"0%") -> 0% | Y101: =J101-W101 -> 0
G102: [Escrow 1] | H102: 0 | I102: 0 | J102: =H102+I102 -> 0 | K102: 0 | L102: 0 | M102: 0 | N102: 0 | O102: 0 | P102: 0 | Q102: 0 | R102: 0 | S102: 0 | T102: 0 | U102: 0 | V102: 0 | W102: =SUM(K102:V102) -> 0 | X102: =IFERROR((W102)/J102,"0%") -> 0% | Y102: =J102-W102 -> 0
G103: [Escrow 1] | H103: 0 | I103: 0 | J103: =H103+I103 -> 0 | K103: 0 | L103: 0 | M103: 0 | N103: 0 | O103: 0 | P103: 0 | Q103: 0 | R103: 0 | S103: 0 | T103: 0 | U103: 0 | V103: 0 | W103: =SUM(K103:V103) -> 0 | X103: =IFERROR((W103)/J103,"0%") -> 0% | Y103: =J103-W103 -> 0
G104: Total Bancorp Funded | H104: =SUM(H99) -> 0 | I104: =I99 -> 0 | J104: =H104+I104 -> 0 | K104: =K99 -> 0 | L104: =L99 -> 0 | M104: =SUM(M99) -> 0 | N104: =N99 -> 0 | O104: =O99 -> 0 | P104: =P99 -> 0 | Q104: =Q99 -> 0 | R104: =R99 -> 0 | S104: =S99 -> 0 | T104: =T99 -> 0 | U104: =U99 -> 0 | V104: =V99 -> 0 | W104: =SUM(K104:V104) -> 0 | X104: =IFERROR((W104)/J104,"0%") -> 0% | Y104: =J104-W104 -> 0

Sheet Unit Interior Tracker
A1: Borrowing Entity Name
A2: Property Name
A3: Property Address
A4: Date
A5: PLEASE FILL OUT ALL CELLS FOR EACH RENOVATED UNIT AND SUBMIT RENT ROLL
B6: Ex. 1 bd / 1 bd | D6: INCLUDE "X" IF THE UNIT IS RENOVATED AND AVAILABLE FOR LEASING | E6: INCLUDE "X" IF THE UNIT IS NOT FULLY RENOVATED, BUT UNDERGOING RENOVATION | F6: PLEASE FILL OUT DATE THE RENOVATION WAS COMPLETED | H6: PLEASE FILL OUT RENT FOR UNIT PRIOR TO RENOVATION | I6: PLEASE FILL OUT RENT UNIT IS LEASE AT. NOT THE MARKET UNIT FOR THE UNIT. LEASE MUST BE SUPPORTED BY RENT ROLL
A7: Unit # | B7: Unit Type | C7: SF | D7: Fully Renovated | E7: Undergoing Renovation | F7: Completion Date of Renovation | G7: Unit Leased? | H7: Prior Leased Rent | I7: New Leased Rent

Sheet Immediate Repairs
Q5: Immediate Repairs | T5: Status
Q6: Install and /or repair fencing and gates to comply with security plan. | R6: 1 | S6: 30000
Q7: Repair damaged pavement consisting of linear cracking, alligator cracking, potholes, and surface raveling throughout the Property. | R7: 1 | S7: 28000
Q8: Install security cameras to comply with security plan. | R8: 1 | S8: 20000
Q9: Repair and replace cracked and broken concrete stair treads. | R9: 1 | S9: 5000
Q10: Repair all trip hazards. | R10: 1 | S10: 3000
Q11: Reconfigure the ramp and access walk to provide a level landing at the leasing office entry door | R11: 1 | S11: 1200
Q12: Reconfigure the ADA accessible parking space to provide unobstructed access to aisle. | R12: 1 | S12: 500
Q13: [Enter] | R13: 0 | S13: 0
Q14: [Enter] | R14: 0 | S14: 0
Q15: [Enter] | R15: 0 | S15: 0
Q16: Immediate Repairs Subtotal

Sheet Closed& Approved Budget 

Sheet Appliance Details
A1: Appliances | C1: Rich Feller - LinkedIn | D1: Diamond Appl Group | E1: Diamond Appl Group | F1: Summit Appliance From Peak | G1: Amazon | H1: HD Supply | I1: Home Depot
C2: Single | D2: Single | E2: 10 Units | G2: Single
A3: FCFE3083AS | B3: Range | C3: 799
A4: F4000 Hood | B4: Hood | C4: 110
A5: FFTR1835VS | B5: Fridge | C5: 653 | D5: 670 | E5: 625 | G5: 680 | H5: 858.84 | I5: 598 | K5: FCFE3062AS | N5: FCFE3083AS | Q5: FFTR1835VS
A6: FCFE3062AS | B6: Range | D6: 785 | E6: 735 | G6: 780 | H6: 1220.84 | I6: 798
A7: Broan F403004 | B7: Hood | D7: 110 | E7: 99 | G7: 110 | I7: 60
A10: Total | C10: =SUM(C3:C9) -> 1562 | D10: =SUM(D3:D9) -> 1565 | E10: =SUM(E3:E9) -> 1459 | F10: =SUM(F3:F9) -> 0 | G10: =SUM(G3:G9) -> 1570 | H10: =SUM(H3:H9) -> 2079.68 | I10: =SUM(I3:I9) -> 1456
D16: appliances total | E16: 1403 | F16: 60 | G16: =F16*E16 -> 84180
D17: budget | E17: 1500 | F17: 128 | G17: =F17*E17 -> 192000
D18: budget reallocation | G18: =G17-G16 -> 107820
