Workbook

Sheet Worst Case
A1: Account Number | B1: Account Name | C1: Apr 2025 | D1: May 2025 | E1: Jun 2025 | F1: Total | I1: 45931 | J1: 45962 | K1: 45992 | L1: 46023 | M1: 46054 | N1: 46082 | O1: 46113 | P1: 46143 | Q1: 46174 | R1: 46204 | S1: 46235 | T1: 46235
H2: Avg units | I2: 17 | J2: 20 | K2: 20 | L2: 20 | M2: 30 | N2: 40 | O2: 60 | P2: 70 | Q2: 88 | R2: 88 | S2: 88 | T2: 88
H3: Avg Rent | I3: 1450 | J3: 1450 | K3: 1450 | L3: 1450 | M3: 1450 | N3: 1450 | O3: 1450 | P3: 1450 | Q3: 1450 | R3: 1450 | S3: 1450 | T3: 1450
A4: 3110 | B4: Rent | C4: 16436.71 | D4: 0 | E4: 505.72 | F4: 16942.43 | I4: =I2*I3 -> 24650 | J4: =J2*J3 -> 29000 | K4: =K2*K3 -> 29000 | L4: =L2*L3 -> 29000 | M4: =M2*M3 -> 43500 | N4: =N2*N3 -> 58000 | O4: =O2*O3 -> 87000 | P4: =P2*P3 -> 101500 | ... T4: =T2*T3 -> 127600 | U4: =SUM(I4:S4) -> 784450
A5: 3115 | B5: Late fee | C5: 0 | D5: 0 | E5: 280 | F5: 280
A6: 3124 | B6: Bad Debt Offset | C6: -17136.36 | D6: 0 | E6: 0 | F6: -17136.36
A7: 3130 | B7: Application Process | C7: 180 | D7: 210 | E7: 180 | F7: 570
A8: 3443 | B8: Pest Control | C8: 27 | D8: 0 | E8: 15 | F8: 42 | I8: =5*I2 -> 85 | J8: =5*J2 -> 100 | K8: =5*K2 -> 100 | L8: =5*L2 -> 100 | M8: =5*M2 -> 150 | N8: =5*N2 -> 200 | O8: =5*O2 -> 300 | P8: =5*P2 -> 350 | ... T8: =5*T2 -> 440
A9: 3712 | B9: Utility pass thru | C9: 609.65 | D9: 0 | E9: 284.28 | F9: 893.93 | I9: =85*I2 -> 1445 | J9: =85*J2 -> 1700 | K9: =85*K2 -> 1700 | L9: =85*L2 -> 1700 | M9: =85*M2 -> 2550 | N9: =85*N2 -> 3400 | O9: =85*O2 -> 5100 | P9: =85*P2 -> 5950 | ... T9: =85*T2 -> 7480
A10: 3719 | B10: Utility pass thru Trash | C10: 63 | D10: 0 | E10: 35 | F10: 98 | I10: =9*I2 -> 153 | J10: =9*J2 -> 180 | K10: =9*K2 -> 180 | L10: =9*L2 -> 180 | M10: =9*M2 -> 270 | N10: =9*N2 -> 360 | O10: =9*O2 -> 540 | P10: =9*P2 -> 630 | ... T10: =9*T2 -> 792
B11: Total Operating Income | C11: 180 | D11: 210 | E11: 1300 | F11: 1690 | I11: 18000 | J11: 20000 | K11: =SUM(K4:K10) -> 30980 | L11: =SUM(L4:L10) -> 30980 | M11: =SUM(M4:M10) -> 46470 | N11: =SUM(N4:N10) -> 61960 | O11: =SUM(O4:O10) -> 92940 | P11: =SUM(P4:P10) -> 108430 | Q11: =SUM(Q4:Q10) -> 136312 | R11: =SUM(R4:R10) -> 136312 | ... T11: =SUM(T4:T10) -> 136312 | U11: =SUM(I11:S11) -> 818696
B12: Expense | U12: =SUM(I12:S12) -> 0
B13: Maintenance Subtotal | U13: =SUM(I13:S13) -> 0
A14: 4416 | B14: Cleaning Supplies | C14: 28.5 | D14: 0 | E14: 0 | F14: 28.5 | U14: =SUM(I14:S14) -> 0
A15: 4433 | B15: Pest Control | C15: 958 | D15: 0 | E15: 0 | F15: 958 | U15: =SUM(I15:S15) -> 0
A16: 4455 | B16: Equipment Rep & Maint. | C16: 0 | D16: 729.14 | E16: 0 | F16: 729.14 | U16: =SUM(I16:S16) -> 0
A17: 4541 | B17: Turnover - Paint Labor | C17: 250 | D17: 0 | E17: 0 | F17: 250 | U17: =SUM(I17:S17) -> 0
B18: Total Maintenance Subtotal | C18: 1236.5 | D18: 729.14 | E18: 0 | F18: 1965.64 | I18: 1310.4267 | J18: 1310.4267 | K18: 1310.4267 | L18: 2000 | M18: 2000 | N18: 2000 | O18: 2000 | P18: 2000 | Q18: 2000 | R18: 2000 | S18: 2000 | T18: 2000 | U18: =SUM(I18:S18) -> 19931.28
B19: Utilities Subtotal | U19: =SUM(I19:S19) -> 0
A20: 4549 | B20: Turnover - Utility | C20: 624.34 | D20: 301.98 | E20: 402.87 | F20: 1329.19 | I20: 500 | J20: 500 | K20: 500 | L20: 500 | M20: 500 | N20: 500 | O20: 500 | P20: 500 | Q20: 500 | R20: 500 | S20: 500 | T20: 500 | U20: =SUM(I20:S20) -> 5500
A21: 4580 | B21: Electricity | C21: 2180.16 | D21: 1648.95 | E21: 1795.91 | F21: 5625.02 | I21: 2000 | J21: 2000 | K21: 2000 | L21: 2000 | M21: 2000 | N21: 2000 | O21: 2000 | P21: 2000 | Q21: 2000 | R21: 2000 | S21: 2000 | T21: 2000 | U21: =SUM(I21:S21) -> 22000
A22: 4606 | B22: Exp Reim - Cellphone | C22: 45.68 | D22: 45.68 | E22: 45.68 | F22: 137.04 | I22: 45.68 | J22: 45.68 | K22: 45.68 | L22: 45.68 | M22: 45.68 | N22: 45.68 | O22: 45.68 | P22: 45.68 | Q22: 45.68 | R22: 45.68 | S22: 45.68 | T22: 45.68 | U22: =SUM(I22:S22) -> 502.48
A23: 4610 | B23: Water & Sewer | C23: 0 | D23: 1985.53 | E23: 3848.66 | F23: 5834.19 | I23: 3500 | J23: 4500 | K23: 6000 | L23: 6000 | M23: 6000 | N23: 6000 | O23: 6000 | P23: 6000 | Q23: 6000 | R23: 6000 | S23: 6000 | T23: 6000 | U23: =SUM(I23:S23) -> 62000
A24: 4620 | B24: Trash | C24: 0 | D24: 0 | E24: 407.21 | F24: 407.21 | I24: 1000 | J24: 1000 | K24: 1000 | L24: 1000 | M24: 1000 | N24: 1000 | O24: 1000 | P24: 1000 | Q24: 1000 | R24: 1000 | S24: 1000 | T24: 1000 | U24: =SUM(I24:S24) -> 11000
A25: 4691 | B25: High Speed Internet Service | C25: 110 | D25: 110 | E25: 110 | F25: 330 | I25: 110 | J25: 110 | K25: 110 | L25: 110 | M25: 110 | N25: 110 | O25: 110 | P25: 110 | Q25: 110 | R25: 110 | S25: 110 | T25: 110 | U25: =SUM(I25:S25) -> 1210
A26: 4692 | B26: Telephone, Regular Service | C26: 85 | D26: 85 | E26: 85 | F26: 255 | I26: 85 | J26: 85 | K26: 85 | L26: 85 | M26: 85 | N26: 85 | O26: 85 | P26: 85 | Q26: 85 | R26: 85 | S26: 85 | T26: 85 | U26: =SUM(I26:S26) -> 935
B28: Utilities | C28: 3045.18 | D28: 4177.14 | E28: 6695.33 | F28: 13917.65 | I28: =SUM(I20:I26) -> 7240.68 | J28: =SUM(J20:J26) -> 8240.68 | K28: =SUM(K20:K26) -> 9740.68 | L28: =SUM(L20:L26) -> 9740.68 | M28: =SUM(M20:M26) -> 9740.68 | N28: =SUM(N20:N26) -> 9740.68 | O28: =SUM(O20:O26) -> 9740.68 | P28: =SUM(P20:P26) -> 9740.68 | ... T28: =SUM(T20:T26) -> 9740.68 | U28: =SUM(I28:S28) -> 103147.48
B29: Asset Management Subtotal | U29: =SUM(I29:S29) -> 0
A30: 4632 | B30: Offsite Services Fee | C30: 5000 | D30: 5000 | E30: 5000 | F30: 15000 | U30: =SUM(I30:S30) -> 0
B31: Total Property Management Subtotal | C31: 5000 | D31: 5000 | E31: 5000 | F31: 15000 | I31: 5000 | J31: 5000 | K31: 5000 | L31: 5000 | M31: 5000 | N31: 5000 | O31: 5000 | P31: 5000 | Q31: 5000 | R31: 5000 | S31: 5000 | T31: 5000 | U31: =SUM(I31:S31) -> 55000
B32: Advertising Subtotal | U32: =SUM(I32:S32) -> 0
A33: 4604 | B33: Exp Reim - Online Advertising | C33: 70.49 | D33: 69.5 | E33: 67.29 | F33: 207.28 | U33: =SUM(I33:S33) -> 0
A34: 4647 | B34: Print Advertising | C34: 204.83 | D34: 0 | E34: 0 | F34: 204.83 | U34: =SUM(I34:S34) -> 0
A35: 4649 | B35: Advertising Signs/Banners | C35: 0 | D35: 342.07 | E35: 0 | F35: 342.07 | U35: =SUM(I35:S35) -> 0
B36: Total Advertising Subtotal | C36: 275.32 | D36: 411.57 | E36: 67.29 | F36: 754.18 | I36: 4000 | J36: 4000 | K36: 4000 | L36: 4000 | M36: 2000 | N36: 2000 | O36: 2000 | P36: 2000 | Q36: 2000 | R36: 2000 | S36: 2000 | T36: 2000 | U36: =SUM(I36:S36) -> 30000
B37: Taxes & Licensing Subtotal | U37: =SUM(I37:S37) -> 0
A38: 4638 | B38: Annual Inspection - Fire | C38: 2008.18 | D38: 0 | E38: 0 | F38: 2008.18 | U38: =SUM(I38:S38) -> 0
A39: 4640 | B39: Taxes & Licenses | C39: 0 | D39: 0 | E39: 7293.74 | F39: 7293.74 | I39: 2431.2467 | J39: 2431.2467 | K39: 2431.2467 | L39: 2431.2467 | M39: 2431.2467 | N39: 2431.2467 | O39: 2431.2467 | P39: 2431.2467 | Q39: 2431.2467 | R39: 2431.2467 | S39: 2431.2467 | T39: 2431.2467 | U39: =SUM(I39:S39) -> 26743.713
A40: 4670 | B40: Property Tax | C40: 6004 | D40: 6004 | E40: 6004 | F40: 18012 | I40: 6004 | J40: 6004 | K40: 6004 | L40: 6004 | M40: 6004 | N40: 6004 | O40: 6004 | P40: 6004 | Q40: 6004 | R40: 6004 | S40: 6004 | T40: 6004 | U40: =SUM(I40:S40) -> 66044
B41: Total Taxes & Licensing Subtotal | C41: 8012.18 | D41: 6004 | E41: 13297.74 | F41: 27313.92 | I41: =SUM(I39:I40) -> 8435.2467 | J41: =SUM(J39:J40) -> 8435.2467 | K41: =SUM(K39:K40) -> 8435.2467 | L41: =SUM(L39:L40) -> 8435.2467 | M41: =SUM(M39:M40) -> 8435.2467 | N41: =SUM(N39:N40) -> 8435.2467 | O41: =SUM(O39:O40) -> 8435.2467 | P41: =SUM(P39:P40) -> 8435.2467 | ... T41: =SUM(T39:T40) -> 8435.2467 | U41: =SUM(I41:S41) -> 92787.713
B42: Security Subtotal | U42: =SUM(I42:S42) -> 0
A43: 4676 | B43: Security/Courtesy Officer | C43: 1138.5 | D43: 0 | E43: 0 | F43: 1138.5 | U43: =SUM(I43:S43) -> 0
A44: 4677 | B44: Monitored Security/Fire Alarm | C44: 0 | D44: 327.15 | E44: 0 | F44: 327.15 | I44: 0 | J44: 0 | K44: 0 | L44: 0 | M44: 0 | N44: 0 | O44: 0 | P44: 0 | Q44: 0 | R44: 0 | S44: 0 | T44: 0 | U44: =SUM(I44:S44) -> 0
B45: Total Security Subtotal | C45: 1138.5 | D45: 327.15 | E45: 0 | F45: 1465.65 | U45: =SUM(I45:S45) -> 0
B46: Office Admin Subtotal | U46: =SUM(I46:S46) -> 0
A47: 4600 | B47: Exp Reim - LISA | C47: 240.16 | D47: 222.9 | E47: 226.73 | F47: 689.79 | I47: 689.79 | J47: 689.79 | K47: 689.79 | L47: 689.79 | M47: 689.79 | N47: 689.79 | O47: 689.79 | P47: 689.79 | Q47: 689.79 | R47: 689.79 | S47: 689.79 | T47: 689.79 | U47: =SUM(I47:S47) -> 7587.69
A48: 4602 | B48: Exp Reim - Crd Crim Tenant Screening | C48: 15 | D48: 240 | E48: 225 | F48: 480 | I48: 480 | J48: 480 | K48: 480 | L48: 480 | M48: 480 | N48: 480 | O48: 480 | P48: 480 | Q48: 480 | R48: 480 | S48: 480 | T48: 480 | U48: =SUM(I48:S48) -> 5280
A49: 4605 | B49: Exp Reim - Postage & Shipping | C49: 79.53 | D49: 160.43 | E49: 146.38 | F49: 386.34 | I49: 386.34 | J49: 386.34 | K49: 386.34 | L49: 386.34 | M49: 386.34 | N49: 386.34 | O49: 386.34 | P49: 386.34 | Q49: 386.34 | R49: 386.34 | S49: 386.34 | T49: 386.34 | U49: =SUM(I49:S49) -> 4249.74
A50: 4609 | B50: Exp Reim - Mgmt Software | C50: 280.43 | D50: 227.22 | E50: 240.08 | F50: 747.73 | I50: 747.73 | J50: 747.73 | K50: 747.73 | L50: 747.73 | M50: 747.73 | N50: 747.73 | O50: 747.73 | P50: 747.73 | Q50: 747.73 | R50: 747.73 | S50: 747.73 | T50: 747.73 | U50: =SUM(I50:S50) -> 8225.03
A51: 4612 | B51: Exp Reim - Premium Leads | C51: 30 | D51: 0 | E51: 0 | F51: 30 | I51: 30 | J51: 30 | K51: 30 | L51: 30 | M51: 30 | N51: 30 | O51: 30 | P51: 30 | Q51: 30 | R51: 30 | S51: 30 | T51: 30 | U51: =SUM(I51:S51) -> 330
A52: 4613 | B52: Exp Reim - After Hours Answering Serv | C52: 12.6 | D52: 13.76 | E52: 9.53 | F52: 35.89 | I52: 35.89 | J52: 35.89 | K52: 35.89 | L52: 35.89 | M52: 35.89 | N52: 35.89 | O52: 35.89 | P52: 35.89 | Q52: 35.89 | R52: 35.89 | S52: 35.89 | T52: 35.89 | U52: =SUM(I52:S52) -> 394.79
A53: 4631 | B53: Eviction Fees | C53: 108 | D53: 0 | E53: 0 | F53: 108 | I53: 108 | J53: 108 | K53: 108 | L53: 108 | M53: 108 | N53: 108 | O53: 108 | P53: 108 | Q53: 108 | R53: 108 | S53: 108 | T53: 108 | U53: =SUM(I53:S53) -> 1188
A54: 4657 | B54: Recruitment Expense | C54: 16.43 | D54: 0 | E54: 60.86 | F54: 77.29 | I54: 77.29 | J54: 77.29 | K54: 77.29 | L54: 77.29 | M54: 77.29 | N54: 77.29 | O54: 77.29 | P54: 77.29 | Q54: 77.29 | R54: 77.29 | S54: 77.29 | T54: 77.29 | U54: =SUM(I54:S54) -> 850.19
A55: 4665 | B55: Bank Fees | C55: 137.4 | D55: 253.77 | E55: 102.28 | F55: 493.45 | I55: 493.45 | J55: 493.45 | K55: 493.45 | L55: 493.45 | M55: 493.45 | N55: 493.45 | O55: 493.45 | P55: 493.45 | Q55: 493.45 | R55: 493.45 | S55: 493.45 | T55: 493.45 | U55: =SUM(I55:S55) -> 5427.95
A56: 4672 | B56: Exp Reim - E Check Processing | C56: 30 | D56: 30 | E56: 15 | F56: 75 | I56: 75 | J56: 75 | K56: 75 | L56: 75 | M56: 75 | N56: 75 | O56: 75 | P56: 75 | Q56: 75 | R56: 75 | S56: 75 | T56: 75 | U56: =SUM(I56:S56) -> 825
A57: 4681 | B57: Training/Certification | C57: 32.64 | D57: 0 | E57: 0 | F57: 32.64 | I57: 32.64 | J57: 32.64 | K57: 32.64 | L57: 32.64 | M57: 32.64 | N57: 32.64 | O57: 32.64 | P57: 32.64 | Q57: 32.64 | R57: 32.64 | S57: 32.64 | T57: 32.64 | U57: =SUM(I57:S57) -> 359.04
A58: 4684 | B58: Software Subscription | C58: 167.8 | D58: 198.3 | E58: 201.45 | F58: 567.55 | I58: 567.55 | J58: 567.55 | K58: 567.55 | L58: 567.55 | M58: 567.55 | N58: 567.55 | O58: 567.55 | P58: 567.55 | Q58: 567.55 | R58: 567.55 | S58: 567.55 | T58: 567.55 | U58: =SUM(I58:S58) -> 6243.05
... A61: 4689 | B61: Legal and Professional | C61: 1520.5 | D61: 0 | E61: 52138 | F61: 53658.5 | I61: 4000 | J61: 4000 | K61: 4000 | L61: 4000 | M61: 4000 | N61: 4000 | O61: 4000 | P61: 4000 | Q61: 4000 | R61: 4000 | S61: 4000 | T61: 4000 | U61: =SUM(I61:S61) -> 44000
A62: 4708 | B62: Accounting Expense | C62: 6 | D62: 0 | E62: 0 | F62: 6 | U62: =SUM(I62:S62) -> 0
B63: Total Office Admin Subtotal | C63: 3030.47 | D63: 1512.31 | E63: 53365.31 | F63: 57908.09 | I63: =SUM(I47:I61) -> 8243.59 | J63: =SUM(J47:J61) -> 8243.59 | K63: =SUM(K47:K61) -> 8243.59 | L63: =SUM(L47:L61) -> 8243.59 | M63: =SUM(M47:M61) -> 8243.59 | N63: =SUM(N47:N61) -> 8243.59 | O63: =SUM(O47:O61) -> 8243.59 | P63: =SUM(P47:P61) -> 8243.59 | ... T63: =SUM(T47:T61) -> 8243.59 | U63: =SUM(I63:S63) -> 90679.49
B64: Insurance Subtotal | U64: =SUM(I64:S64) -> 0
A65: 4700 | B65: Property Insurance | C65: 3734 | D65: 3734 | E65: 3734 | F65: 11202 | I65: 3734 | J65: 3734 | K65: 3734 | L65: 3735 | M65: 3736 | N65: 3737 | O65: 3738 | P65: 3739 | Q65: 3740 | R65: 3741 | S65: 3742 | T65: 3742 | U65: =SUM(I65:S65) -> 41110
B66: Total Insurance Subtotal | C66: 3734 | D66: 3734 | E66: 3734 | F66: 11202 | U66: =SUM(I66:S66) -> 0
B67: Salaries and Related Subtotal | U67: =SUM(I67:S67) -> 0
A68: 4807 | B68: Traveling Property Operations Salary | C68: 444.29 | D68: 323.12 | E68: 80.78 | F68: 848.19 | U68: =SUM(I68:S68) -> 0
A69: 4810 | B69: Manager, salary | C69: 5000 | D69: 5000.29 | E69: 5000 | F69: 15000.29 | U69: =SUM(I69:S69) -> 0
A70: 4815 | B70: Leasing and Renewal Bonus | C70: 150 | D70: 150 | E70: 150 | F70: 450 | U70: =SUM(I70:S70) -> 0
A71: 4820 | B71: Maintenance, salary | C71: 1008 | D71: 2682 | E71: 864 | F71: 4554 | U71: =SUM(I71:S71) -> 0
A72: 4850 | B72: Payroll Taxes | C72: 665.56 | D72: 730.74 | E72: 540.4 | F72: 1936.7 | U72: =SUM(I72:S72) -> 0
A73: 4851 | B73: Payroll Processing Fees | C73: 1241.5 | D73: 264 | E73: 264 | F73: 1769.5 | U73: =SUM(I73:S73) -> 0
A74: 4861 | B74: 401k, Co. Contrb | C74: 150 | D74: 0 | E74: 0 | F74: 150 | U74: =SUM(I74:S74) -> 0
A75: 4862 | B75: Work Comp Insurance | C75: 55.64 | D75: 51.7 | E75: 39.69 | F75: 147.03 | U75: =SUM(I75:S75) -> 0
B76: Total Salaries and Related Subtotal | C76: 8714.99 | D76: 9201.85 | E76: 6938.87 | F76: 24855.71 | I76: =F76/3 -> 8285.2367 | J76: =I76 -> 8285.2367 | K76: =J76 -> 8285.2367 | L76: =K76 -> 8285.2367 | M76: =L76 -> 8285.2367 | N76: =M76 -> 8285.2367 | O76: =N76 -> 8285.2367 | P76: =O76 -> 8285.2367 | Q76: =P76 -> 8285.2367 | ... T76: =S76 -> 8285.2367 | U76: =SUM(I76:S76) -> 91137.603
B77: Total Operating Expense | C77: 34187.14 | D77: 31097.16 | E77: 89098.54 | F77: 154382.84 | I77: =I76+I65+I63+I44+I41+I36+I31+I28+I18+0 -> 46249.18 | J77: =J76+J65+J63+J44+J41+J36+J31+J28+J18+0 -> 47249.18 | K77: =K76+K65+K63+K44+K41+K36+K31+K28+K18+0 -> 48749.18 | L77: =L76+L65+L63+L44+L41+L36+L31+L28+L18+0 -> 49439.753 | M77: =M76+M65+M63+M44+M41+M36+M31+M28+M18+0 -> 47440.753 | N77: =N76+N65+N63+N44+N41+N36+N31+N28+N18+0 -> 47441.753 | O77: =O76+O65+O63+O44+O41+O36+O31+O28+O18+0 -> 47442.753 | P77: =P76+P65+P63+P44+P41+P36+P31+P28+P18+0 -> 47443.753 | ... T77: =T76+T65+T63+T44+T41+T36+T31+T28+T18+0 -> 47446.753 | U77: =SUM(I77:S77) -> 523793.57
U78: =SUM(I78:S78) -> 0
B79: NOI - Net Operating Income | C79: -34007.14 | D79: -30887.16 | E79: -87798.54 | F79: -152692.84 | I79: =I11-I77 -> -28249.18 | J79: =J11-J77 -> -27249.18 | K79: =K11-K77 -> -17769.18 | L79: =L11-L77 -> -18459.753 | M79: =M11-M77 -> -970.75333 | N79: =N11-N77 -> 14518.247 | O79: =O11-O77 -> 45497.247 | P79: =P11-P77 -> 60986.247 | ... T79: =T11-T77 -> 88865.247 | U79: =SUM(I79:S79) -> 294902.43
U80: =SUM(I80:S80) -> 0
B81: Other Income & Expense | U81: =SUM(I81:S81) -> 0
B82: Other Expense | U82: =SUM(I82:S82) -> 0
A83: 4710 | B83: 1st Mortgage, interest | C83: 20834.43 | D83: 51942.33 | E83: 57013.86 | F83: 129790.62 | I83: 60000 | J83: 60000 | K83: 60000 | L83: 62000 | M83: 62000 | N83: 62000 | O83: 65000 | P83: 65000 | Q83: 65000 | R83: 65000 | S83: 65001 | T83: 65001 | U83: =SUM(I83:S83) -> 691001
B84: FAS CAPEX Subtotal | U84: =SUM(I84:S84) -> 0
A85: 4212 | B85: FAS Capex-Electrical | C85: 3146 | D85: 0 | E85: 0 | F85: 3146 | U85: =SUM(I85:S85) -> 0
A86: 4216 | B86: FAS Capex-Entry Door - Exterior | C86: 0 | D86: 0 | E86: 5000 | F86: 5000 | U86: =SUM(I86:S86) -> 0
A87: 4228 | B87: FAS Capex-Insulation | C87: 9751 | D87: 0 | E87: 0 | F87: 9751 | U87: =SUM(I87:S87) -> 0
A88: 4236 | B88: FAS Capex-Painting - Exterior | C88: 0 | D88: 39204 | E88: 0 | F88: 39204 | U88: =SUM(I88:S88) -> 0
A89: 4242 | B89: FAS Capex-Plumbing/Boilers | C89: 3146.67 | D89: 84075 | E89: 0 | F89: 87221.67 | U89: =SUM(I89:S89) -> 0
A90: 4248 | B90: FAS Capex-Security Cameras/WiFi | C90: 0 | D90: 1904.31 | E90: 0 | F90: 1904.31 | U90: =SUM(I90:S90) -> 0
A91: 4262 | B91: FAS Capex-Unit Interiors - Vacant | C91: 33207.33 | D91: 32944.54 | E91: 0 | F91: 66151.87 | U91: =SUM(I91:S91) -> 0
A92: 4266 | B92: FAS Capex-Windows | C92: 0 | D92: 16174.9 | E92: 0 | F92: 16174.9 | U92: =SUM(I92:S92) -> 0
B93: Total FAS CAPEX Subtotal | C93: 49251 | D93: 174302.75 | E93: 5000 | F93: 228553.75 | U93: =SUM(I93:S93) -> 0
B94: Improvement Subtotal | U94: =SUM(I94:S94) -> 0
A95: 4368 | B95: IMP - Leasing Office Remodel | C95: 335.96 | D95: 2619.17 | E95: 0 | F95: 2955.13 | U95: =SUM(I95:S95) -> 0
A96: 4373 | B96: IMP - Sidewalk/Concrete | C96: 0 | D96: 0 | E96: 900 | F96: 900 | U96: =SUM(I96:S96) -> 0
A97: 4374 | B97: IMP - Exterior Paint/Repair | C97: 0 | D97: 0 | E97: 4950 | F97: 4950 | U97: =SUM(I97:S97) -> 0
A98: 4375 | B98: IMP - Interior Upgrades - Vacant | C98: 0 | D98: 9957.74 | E98: 0 | F98: 9957.74 | U98: =SUM(I98:S98) -> 0
A99: 4386 | B99: IMP - Landscaping/Common Areas | C99: 0 | D99: 0 | E99: 9077.43 | F99: 9077.43 | U99: =SUM(I99:S99) -> 0
A100: 4387 | B100: IMP - Security Camera System | C100: 4486.86 | D100: 0 | E100: 0 | F100: 4486.86 | U100: =SUM(I100:S100) -> 0
A101: 4388 | B101: IMP - Exterior Signage | C101: 212.19 | D101: 0 | E101: 0 | F101: 212.19 | U101: =SUM(I101:S101) -> 0
A102: 4389 | B102: IMP - Plumbing | C102: 15000 | D102: 0 | E102: 0 | F102: 15000 | U102: =SUM(I102:S102) -> 0
A103: 4390 | B103: IMP - Electrical Upgrades | C103: 0 | D103: 0 | E103: 28320 | F103: 28320 | U103: =SUM(I103:S103) -> 0
...

Sheet Calculator
A1: Month | B1: 45986
A3: Oasis at San Marco
A4: 4800 Atlantic Blvd, Jacksonville, FL 32207
A5: 127 Unit Multifamily
C6: Now | D6: Per unit | E6: PSF
A7: INCOME | D7: 127 | E7: =#REF! -> #REF!
A8: Gross Potential Rent | C8: =#REF! -> #REF! | D8: =C8/$D$7 -> #REF! | E8: =C8/$E$7 -> #REF!
A9: Utility Reimbursements | C9: 83600 | D9: =C9/$D$7 -> 658.26772 | E9: =C9/$E$7 -> #REF!
A10: Trash Fee | C10: 13600 | D10: =C10/$D$7 -> 107.08661 | E10: =C10/$E$7 -> #REF!
A11: Pet Monthly Fee | C11: 4000 | D11: =C11/$D$7 -> 31.496063 | E11: =C11/$E$7 -> #REF!
A12: Pest Control Fee | C12: 8000 | D12: =C12/$D$7 -> 62.992126 | E12: =C12/$E$7 -> #REF!
A13: Laundry Income | C13: 5000 | D13: =C13/$D$7 -> 39.370079 | E13: =C13/$E$7 -> #REF!
A14: App/Late/Admin Fee | C14: 57000 | D14: =C14/$D$7 -> 448.8189 | E14: =C14/$E$7 -> #REF!
A15: Less Market Vacancy @ | B15: 0.08 | C15: =-SUM(C8)*B15 -> #REF! | D15: =C15/$D$7 -> #REF! | E15: =C15/$E$7 -> #REF!
A16: Effective Gross Inc. | C16: =SUM(C8:C15) -> #REF! | D16: =C16/$D$7 -> #REF! | E16: =C16/$E$7 -> #REF! | G16: =C16/12 -> #REF!
A18: EXPENSES
A19: Insurance
A20: R&M + Contract Services
A21: Water & Sewer | C21: 40000 | D21: =C21/$D$7 -> 314.96063 | E21: =C21/$E$7 -> #REF!
A22: Electric
A23: Electric - Common | C23: 14000 | D23: =C23/$D$7 -> 110.23622 | E23: =C23/$E$7 -> #REF!
A24: Garbage & Recycling
A25: Gas | C25: 2000 | D25: =C25/$D$7 -> 15.748031 | E25: =C25/$E$7 -> #REF!
A26: Admin + Advertising
A28: Management | B28: 0.03 | C28: =C16*B28 -> #REF! | D28: =C28/$D$7 -> #REF! | E28: =C28/$E$7 -> #REF! | G28: RE Assessment
A30: TOTAL OPERATING EXP. | C30: =SUM(C19:C28) -> #REF! | D30: =C30/$D$7 -> #REF! | E30: =C30/$E$7 -> #REF! | I30: RE Tax
G31: Assessment | H31: 0.75 | I31: 11518443
A32: RE TAXES (In-Place 160,038) | C32: 165000 | D32: =C32/$D$7 -> 1299.2126 | E32: =C32/$E$7 -> #REF! | G32: Mill rate @ | H32: 0.017865 | I32: 205777
A33: Replacement Reserves
A34: Payroll | C34: =D34*D7 -> 127000 | D34: 1000 | E34: =C34/$E$7 -> #REF!
A36: TOTAL EXPENSES
A38: NET OPERATING INCOME
A40: Value
A41: Cap Rate
A42: Max Perm Debt
A43: Loan to Value
A45: Debt Service Coverage Ratio
A46: Amount
A47: Rate
A48: Amortization
A49: IO Monthly pymt
A50: Monthly pymt
... A52: DSCR

Sheet Budget Summary 2026
A1: Account Name | B1: 46023 | C1: =EDATE(B1, 1) -> 46054 | D1: =EDATE(C1, 1) -> 46082 | E1: =EDATE(D1, 1) -> 46113 | F1: =EDATE(E1, 1) -> 46143 | G1: =EDATE(F1, 1) -> 46174 | H1: =EDATE(G1, 1) -> 46204 | I1: =EDATE(H1, 1) -> 46235 | J1: =EDATE(I1, 1) -> 46266 | ... M1: =EDATE(L1, 1) -> 46357 | N1: Total
A2: Gross Potential Rent | B2: ='Worksheet - DO NOT DELETE'!B12 -> 159666 | C2: ='Worksheet - DO NOT DELETE'!C12 -> 159666 | D2: ='Worksheet - DO NOT DELETE'!D12 -> 159666 | E2: ='Worksheet - DO NOT DELETE'!E12 -> 159666 | F2: ='Worksheet - DO NOT DELETE'!F12 -> 159666 | G2: ='Worksheet - DO NOT DELETE'!G12 -> 159666 | H2: ='Worksheet - DO NOT DELETE'!H12 -> 159666 | I2: ='Worksheet - DO NOT DELETE'!I12 -> 159666 | ... M2: ='Worksheet - DO NOT DELETE'!M12 -> 159666 | N2: =SUM(B2:M2) -> 1915992
A3: Loss/Gain to Market | B3: ='Worksheet - DO NOT DELETE'!B16 -> -9750.12 | C3: ='Worksheet - DO NOT DELETE'!C16 -> -9750.12 | D3: ='Worksheet - DO NOT DELETE'!D16 -> -9375.3303 | E3: ='Worksheet - DO NOT DELETE'!E16 -> -9179.9524 | F3: ='Worksheet - DO NOT DELETE'!F16 -> -8984.3206 | G3: ='Worksheet - DO NOT DELETE'!G16 -> -8788.4344 | H3: ='Worksheet - DO NOT DELETE'!H16 -> -8516.8548 | I3: ='Worksheet - DO NOT DELETE'!I16 -> -8244.7863 | ... M3: ='Worksheet - DO NOT DELETE'!M16 -> -7699.0155 | N3: =SUM(B3:M3) -> -103932.52
A4: Concessions | B4: ='Worksheet - DO NOT DELETE'!B15-(B5+B6) -> 0 | C4: ='Worksheet - DO NOT DELETE'!C15-(C5+C6) -> -3541.32 | D4: ='Worksheet - DO NOT DELETE'!D15-(D5+D6) -> -9762.9766 | E4: ='Worksheet - DO NOT DELETE'!E15-(E5+E6) -> -1777.3943 | F4: ='Worksheet - DO NOT DELETE'!F15-(F5+F6) -> -2669.5573 | G4: ='Worksheet - DO NOT DELETE'!G15-(G5+G6) -> -2673.0277 | H4: ='Worksheet - DO NOT DELETE'!H15-(H5+H6) -> -1785.2261 | I4: ='Worksheet - DO NOT DELETE'!I15-(I5+I6) -> -1788.4395 | ... M4: ='Worksheet - DO NOT DELETE'!M15-(M5+M6) -> -897.44282 | N4: =SUM(B4:M4) -> -28480.315
A5: Concessions - Recurring | B5: -100 | C5: -100 | D5: -100 | E5: -100 | F5: -100 | G5: -100 | H5: -100 | I5: -100 | J5: -100 | K5: -100 | L5: -100 | M5: -100 | N5: =SUM(B5:M5) -> -1200
A6: Concessions - Employee Unit | B6: -210 | C6: -210 | D6: -210 | E6: -210 | F6: -210 | G6: -210 | H6: -210 | I6: -210 | J6: -210 | K6: -210 | L6: -210 | M6: -210 | N6: =SUM(B6:M6) -> -2520
A7: Vacancy | B7: ='Worksheet - DO NOT DELETE'!B13 -> -14165.28 | C7: ='Worksheet - DO NOT DELETE'!C13 -> -9443.52 | D7: ='Worksheet - DO NOT DELETE'!D13 -> -4733.5644 | E7: ='Worksheet - DO NOT DELETE'!E13 -> -4739.718 | F7: ='Worksheet - DO NOT DELETE'!F13 -> -4745.8797 | G7: ='Worksheet - DO NOT DELETE'!G13 -> -4752.0493 | H7: ='Worksheet - DO NOT DELETE'!H13 -> -4760.603 | I7: ='Worksheet - DO NOT DELETE'!I13 -> -4769.1721 | ... M7: ='Worksheet - DO NOT DELETE'!M13 -> -3589.7713 | N7: =SUM(B7:M7) -> -66455.961
A8: Bad Debt - Contra | B8: ='Worksheet - DO NOT DELETE'!B17 -> -11804.4 | C8: ='Worksheet - DO NOT DELETE'!C17 -> -11804.4 | D8: ='Worksheet - DO NOT DELETE'!D17 -> -15384.084 | E8: ='Worksheet - DO NOT DELETE'!E17 -> -1184.9295 | F8: ='Worksheet - DO NOT DELETE'!F17 -> -1186.4699 | G8: ='Worksheet - DO NOT DELETE'!G17 -> -1188.0123 | H8: ='Worksheet - DO NOT DELETE'!H17 -> -1190.1507 | I8: ='Worksheet - DO NOT DELETE'!I17 -> -1192.293 | ... M8: ='Worksheet - DO NOT DELETE'!M17 -> 0 | N8: =SUM(B8:M8) -> -48520.208
A9: Total Rental Income | B9: =SUM(B2:B8) -> 123636.2 | C9: =SUM(C2:C8) -> 124816.64 | D9: =SUM(D2:D8) -> 120100.04 | E9: =SUM(E2:E8) -> 142474.01 | F9: =SUM(F2:F8) -> 141769.77 | G9: =SUM(G2:G8) -> 141954.48 | H9: =SUM(H2:H8) -> 143103.17 | I9: =SUM(I2:I8) -> 143361.31 | ... M9: =SUM(M2:M8) -> 147169.77 | N9: =SUM(B9:M9) -> 1664883
A10: Other Income
A11: Lease Lock
A12: NSF Fees Collected | B12: 50 | C12: 50 | D12: 50 | E12: 50 | F12: 50 | G12: 50 | H12: 50 | I12: 50 | J12: 50 | K12: 50 | L12: 50 | M12: 50 | N12: =SUM(B12:M12) -> 600
A13: Late Fee | B13: 2100 | C13: 2100 | D13: 2100 | E13: 2100 | F13: 2100 | G13: 2100 | H13: 2100 | I13: 2100 | J13: 2100 | K13: 2100 | L13: 2100 | M13: 2100 | N13: =SUM(B13:M13) -> 25200
A14: Utility Income | N14: =SUM(B14:M14) -> 0
A15: Electricity Income | N15: =SUM(B15:M15) -> 0
A16: Utility Reimbursements | B16: 7360 | C16: 7360 | D16: 7360 | E16: 7360 | F16: 7360 | G16: 7360 | H16: 7360 | I16: 7360 | J16: 7360 | K16: 7360 | L16: 7360 | M16: 7360 | N16: =SUM(B16:M16) -> 88320
A17: Resident Liability & Contents Coverage | B17: 725 | C17: 725 | D17: 725 | E17: 725 | F17: 725 | G17: 725 | H17: 725 | I17: 725 | J17: 725 | K17: 725 | L17: 725 | M17: 725 | N17: =SUM(B17:M17) -> 8700
A18: 1st month - Resident Liability & Contents Coverage | N18: =SUM(B18:M18) -> 0
A19: AppFolio Insurance Admin Fee | B19: 185 | C19: 185 | D19: 185 | E19: 185 | F19: 185 | G19: 185 | H19: 185 | I19: 185 | J19: 185 | K19: 185 | L19: 185 | M19: 185 | N19: =SUM(B19:M19) -> 2220
A20: Pet Fee - Non Refundable | N20: =SUM(B20:M20) -> 0
A21: Bad Debt Recovery | N21: =SUM(B21:M21) -> 0
A22: Pet Application Fee | N22: =SUM(B22:M22) -> 0
A23: Monthly Pet Rent | B23: 480 | C23: 480 | D23: 480 | E23: 480 | F23: 480 | G23: 480 | H23: 480 | I23: 480 | J23: 480 | K23: 480 | L23: 480 | M23: 480 | N23: =SUM(B23:M23) -> 5760
A24: Admin Fee | B24: 150 | C24: 150 | D24: 150 | E24: 150 | F24: 150 | G24: 150 | H24: 150 | I24: 150 | J24: 150 | K24: 150 | L24: 150 | M24: 150 | N24: =SUM(B24:M24) -> 1800
A25: Early Lease Termination Fee | N25: =SUM(B25:M25) -> 0
A26: Application Fee Income | B26: 215 | C26: 215 | D26: 215 | E26: 215 | F26: 215 | G26: 215 | H26: 215 | I26: 215 | J26: 215 | K26: 215 | L26: 215 | M26: 215 | N26: =SUM(B26:M26) -> 2580
A27: Extended Month to Month Fee | B27: 200 | C27: 200 | D27: 200 | E27: 200 | F27: 200 | G27: 200 | H27: 200 | I27: 200 | J27: 200 | K27: 200 | L27: 200 | M27: 200 | N27: =SUM(B27:M27) -> 2400
A28: Move Out Charges | B28: 500 | C28: 500 | D28: 500 | E28: 500 | F28: 500 | G28: 500 | H28: 500 | I28: 500 | J28: 500 | K28: 500 | L28: 500 | M28: 500 | N28: =SUM(B28:M28) -> 6000
A29: Move In Charges - Misc | N29: =SUM(B29:M29) -> 0
A30: Resident Transfer fee | N30: =SUM(B30:M30) -> 0
A31: Laundry Income | B31: 500 | C31: 500 | D31: 500 | E31: 500 | F31: 500 | G31: 500 | H31: 500 | I31: 500 | J31: 500 | K31: 500 | L31: 500 | M31: 500 | N31: =SUM(B31:M31) -> 6000
A32: Miscellaneous Income | N32: =SUM(B32:M32) -> 0
A33: Misc Reimbursements | N33: =SUM(B33:M33) -> 0
A34: Damages | B34: 406 | C34: 406 | D34: 406 | E34: 406 | F34: 406 | G34: 406 | H34: 406 | I34: 406 | J34: 406 | K34: 406 | L34: 406 | M34: 406 | N34: =SUM(B34:M34) -> 4872
A35: Amenity Fee | B35: ='Worksheet - DO NOT DELETE'!B$5*15 -> 1575 | C35: ='Worksheet - DO NOT DELETE'!C$5*15 -> 1635 | D35: ='Worksheet - DO NOT DELETE'!D$5*15 -> 1650 | E35: ='Worksheet - DO NOT DELETE'!E$5*15 -> 1830 | F35: ='Worksheet - DO NOT DELETE'!F$5*15 -> 1830 | G35: ='Worksheet - DO NOT DELETE'!G$5*15 -> 1830 | H35: ='Worksheet - DO NOT DELETE'!H$5*15 -> 1830 | I35: ='Worksheet - DO NOT DELETE'!I$5*15 -> 1830 | ... M35: ='Worksheet - DO NOT DELETE'!M$5*15 -> 1860 | N35: =SUM(B35:M35) -> 21405
A36: Trash Fee | B36: ='Worksheet - DO NOT DELETE'!B$5*10 -> 1050 | C36: ='Worksheet - DO NOT DELETE'!C$5*10 -> 1090 | D36: ='Worksheet - DO NOT DELETE'!D$5*10 -> 1100 | E36: ='Worksheet - DO NOT DELETE'!E$5*10 -> 1220 | F36: ='Worksheet - DO NOT DELETE'!F$5*10 -> 1220 | G36: ='Worksheet - DO NOT DELETE'!G$5*10 -> 1220 | H36: ='Worksheet - DO NOT DELETE'!H$5*10 -> 1220 | I36: ='Worksheet - DO NOT DELETE'!I$5*10 -> 1220 | ... M36: ='Worksheet - DO NOT DELETE'!M$5*10 -> 1240 | N36: =SUM(B36:M36) -> 14270
A37: Pest Control Fee | B37: ='Worksheet - DO NOT DELETE'!B$5*5 -> 525 | C37: ='Worksheet - DO NOT DELETE'!C$5*5 -> 545 | D37: ='Worksheet - DO NOT DELETE'!D$5*5 -> 550 | E37: ='Worksheet - DO NOT DELETE'!E$5*5 -> 610 | F37: ='Worksheet - DO NOT DELETE'!F$5*5 -> 610 | G37: ='Worksheet - DO NOT DELETE'!G$5*5 -> 610 | H37: ='Worksheet - DO NOT DELETE'!H$5*5 -> 610 | I37: ='Worksheet - DO NOT DELETE'!I$5*5 -> 610 | ... M37: ='Worksheet - DO NOT DELETE'!M$5*5 -> 620 | N37: =SUM(B37:M37) -> 7135
A38: Maintenance Fee | N38: =SUM(B38:M38) -> 0
A39: Waiver Deposit Fee | B39: ='Worksheet - DO NOT DELETE'!B$5*28*0.35 -> 1029 | C39: ='Worksheet - DO NOT DELETE'!C$5*28*0.35 -> 1068.2 | D39: ='Worksheet - DO NOT DELETE'!D$5*28*0.35 -> 1078 | E39: ='Worksheet - DO NOT DELETE'!E$5*28*0.35 -> 1195.6 | F39: ='Worksheet - DO NOT DELETE'!F$5*28*0.35 -> 1195.6 | G39: ='Worksheet - DO NOT DELETE'!G$5*28*0.35 -> 1195.6 | H39: ='Worksheet - DO NOT DELETE'!H$5*28*0.35 -> 1195.6 | I39: ='Worksheet - DO NOT DELETE'!I$5*28*0.35 -> 1195.6 | ... M39: ='Worksheet - DO NOT DELETE'!M$5*28*0.35 -> 1215.2 | N39: =SUM(B39:M39) -> 13984.6
A40: PM Service Fee | B40: ='Worksheet - DO NOT DELETE'!B$5*3 -> 315 | C40: ='Worksheet - DO NOT DELETE'!C$5*3 -> 327 | D40: ='Worksheet - DO NOT DELETE'!D$5*3 -> 330 | E40: ='Worksheet - DO NOT DELETE'!E$5*3 -> 366 | F40: ='Worksheet - DO NOT DELETE'!F$5*3 -> 366 | G40: ='Worksheet - DO NOT DELETE'!G$5*3 -> 366 | H40: ='Worksheet - DO NOT DELETE'!H$5*3 -> 366 | I40: ='Worksheet - DO NOT DELETE'!I$5*3 -> 366 | ... M40: ='Worksheet - DO NOT DELETE'!M$5*3 -> 372 | N40: =SUM(B40:M40) -> 4281
A41: Utility - OW Service Fee | B41: ='Worksheet - DO NOT DELETE'!B$5*3 -> 315 | C41: ='Worksheet - DO NOT DELETE'!C$5*3 -> 327 | D41: ='Worksheet - DO NOT DELETE'!D$5*3 -> 330 | E41: ='Worksheet - DO NOT DELETE'!E$5*3 -> 366 | F41: ='Worksheet - DO NOT DELETE'!F$5*3 -> 366 | G41: ='Worksheet - DO NOT DELETE'!G$5*3 -> 366 | H41: ='Worksheet - DO NOT DELETE'!H$5*3 -> 366 | I41: ='Worksheet - DO NOT DELETE'!I$5*3 -> 366 | ... M41: ='Worksheet - DO NOT DELETE'!M$5*3 -> 372 | N41: =SUM(B41:M41) -> 4281
A42: Interest on Bank Accounts | N42: =SUM(B42:M42) -> 0
A43: Bad Debt - Contra Other Income | B43: ='Worksheet - DO NOT DELETE'!B6*-122 -> -1220 | C43: ='Worksheet - DO NOT DELETE'!C6*-122 -> -1220 | D43: ='Worksheet - DO NOT DELETE'!D6*-122 -> -1586 | E43: ='Worksheet - DO NOT DELETE'!E6*-122 -> -122 | F43: ='Worksheet - DO NOT DELETE'!F6*-122 -> -122 | G43: ='Worksheet - DO NOT DELETE'!G6*-122 -> -122 | H43: ='Worksheet - DO NOT DELETE'!H6*-122 -> -122 | I43: ='Worksheet - DO NOT DELETE'!I6*-122 -> -122 | ... M43: ='Worksheet - DO NOT DELETE'!M6*-122 -> 0 | N43: =SUM(B43:M43) -> -5002
A44: Total Other Income | B44: =SUM(B13:B43) -> 16410 | C44: =SUM(C13:C43) -> 16593.2 | D44: =SUM(D13:D43) -> 16273 | E44: =SUM(E13:E43) -> 18286.6 | F44: =SUM(F13:F43) -> 18286.6 | G44: =SUM(G13:G43) -> 18286.6 | H44: =SUM(H13:H43) -> 18286.6 | I44: =SUM(I13:I43) -> 18286.6 | ... M44: =SUM(M13:M43) -> 18500.2 | N44: =SUM(B44:M44) -> 214206.6
A45: Total Operating Income | B45: =B9+B44 -> 140046.2 | C45: =C9+C44 -> 141409.84 | D45: =D9+D44 -> 136373.04 | E45: =E9+E44 -> 160760.61 | F45: =F9+F44 -> 160056.37 | G45: =G9+G44 -> 160241.08 | H45: =H9+H44 -> 161389.77 | I45: =I9+I44 -> 161647.91 | ... M45: =M9+M44 -> 165669.97 | N45: =SUM(B45:M45) -> 1879089.6
A46: Expense
A47: Management Fee Expenses
A48: Management Fees
A49: Lease Renewal Fee
A50: Management Fee - Multifamily | B50: =MAX(B45*3%, 4500) -> 4500 | C50: =MAX(C45*3%, 4500) -> 4500 | D50: =MAX(D45*3%, 4500) -> 4500 | E50: =MAX(E45*3%, 4500) -> 4822.8182 | F50: =MAX(F45*3%, 4500) -> 4801.6912 | G50: =MAX(G45*3%, 4500) -> 4807.2323 | H50: =MAX(H45*3%, 4500) -> 4841.693 | I50: =MAX(I45*3%, 4500) -> 4849.4373 | ... M50: =MAX(M45*3%, 4500) -> 4970.0991 | N50: =SUM(B50:M50) -> 57337.816
A51: Total Management Fee Expenses | B51: =SUM(B48:B50) -> 4500 | C51: =SUM(C48:C50) -> 4500 | D51: =SUM(D48:D50) -> 4500 | E51: =SUM(E48:E50) -> 4822.8182 | F51: =SUM(F48:F50) -> 4801.6912 | G51: =SUM(G48:G50) -> 4807.2323 | H51: =SUM(H48:H50) -> 4841.693 | I51: =SUM(I48:I50) -> 4849.4373 | ... M51: =SUM(M48:M50) -> 4970.0991 | N51: =SUM(B51:M51) -> 57337.816
A52: Admin Expenses
A53: Property Inspections | B53: 45 | C53: $ - | D53: $ - | E53: $ - | F53: $ - | G53: $ - | H53: $ - | I53: $ - | J53: $ - | K53: $ - | L53: $ - | M53: $ - | N53: =SUM(B53:M53) -> 45
A54: Payment Processing Fees | B54: 0 | C54: 0 | D54: 0 | E54: 0 | F54: 0 | G54: 0 | H54: 0 | I54: 0 | J54: 0 | K54: 0 | L54: 0 | M54: 0 | N54: =SUM(B54:M54) -> 0
A55: Telephone Expense | B55: 138.36 | C55: 138.36 | D55: 138.36 | E55: 138.36 | F55: 138.36 | G55: 138.36 | H55: 138.36 | I55: 138.36 | J55: 138.36 | K55: 138.36 | L55: 138.36 | M55: 138.36 | N55: =SUM(B55:M55) -> 1660.32
A56: Memberships/Professional Organizations | B56: 439 | C56: $ - | D56: $ - | E56: $ - | F56: $ - | G56: $ - | I56: $ - | J56: $ - | K56: $ - | L56: $ - | M56: $ - | N56: =SUM(B56:M56) -> 439
A57: Uniforms | B57: $ - | C57: $ - | D57: $ - | E57: $ - | F57: $ - | G57: $ - | H57: $ - | I57: $ - | J57: $ - | K57: $ - | L57: $ - | M57: $ - | N57: =SUM(B57:M57) -> 0
A58: Legal Fees - Retail | B58: $ - | C58: $ - | D58: $ - | E58: $ - | F58: $ - | G58: $ - | H58: $ - | I58: $ - | J58: $ - | K58: $ - | L58: $ - | M58: $ - | N58: =SUM(B58:M58) -> 0
A59: Office Rent | B59: $ - | C59: $ - | D59: $ - | E59: $ - | F59: $ - | G59: $ - | H59: $ - | I59: $ - | J59: $ - | K59: $ - | L59: $ - | M59: $ - | N59: =SUM(B59:M59) -> 0
A60: Office Supplies | B60: 61.39 | C60: 61.39 | D60: 61.39 | E60: 61.39 | F60: 61.39 | G60: 61.39 | H60: 61.39 | I60: 61.39 | J60: 61.39 | K60: 61.39 | L60: 61.39 | M60: 61.39 | N60: =SUM(B60:M60) -> 736.68
A61: Marketing - Entertainment | B61: $ - | C61: $ - | D61: $ - | E61: $ - | F61: $ - | G61: $ - | H61: $ - | I61: $ - | J61: $ - | K61: $ - | L61: 277.36 | M61: $ - | N61: =SUM(B61:M61) -> 277.36
A62: Bank Fees | B62: 16.25 | C62: 16.25 | D62: 16.25 | E62: 16.25 | F62: 16.25 | G62: 16.25 | H62: 16.25 | I62: 16.25 | J62: 16.25 | K62: 16.25 | L62: 16.25 | M62: 16.25 | N62: =SUM(B62:M62) -> 195
A63: Office Miscellaneous Expenses | N63: =SUM(B63:M63) -> 0
A64: Legal Expenses | B64: 500 | C64: 500 | D64: 500 | E64: 500 | F64: 500 | G64: 500 | H64: 500 | I64: 500 | J64: 500 | K64: 500 | L64: 500 | M64: 500 | N64: =SUM(B64:M64) -> 6000
A65: Accounting Expenses | B65: 350 | C65: 350 | D65: 350 | E65: 350 | F65: 350 | G65: 350 | H65: 350 | I65: 350 | J65: 350 | K65: 350 | L65: 350 | M65: 350 | N65: =SUM(B65:M65) -> 4200
A66: Other Professional Fees | B66: $ - | C66: $ - | D66: $ - | E66: 5300 | F66: $ - | G66: $ - | H66: $ - | I66: $ - | J66: $ - | K66: $ - | L66: $ - | M66: $ - | N66: =SUM(B66:M66) -> 5300
A67: Postage and Shipping Expenses | B67: 17.33 | C67: 17.33 | D67: 17.33 | E67: 17.33 | F67: 17.33 | G67: 17.33 | H67: 17.33 | I67: 17.33 | J67: 17.33 | K67: 17.33 | L67: 17.33 | M67: 17.33 | N67: =SUM(B67:M67) -> 207.96
A68: License and Permits | B68: $ - | C68: 796.72 | D68: $ - | E68: $ - | F68: 700.35 | G68: $ - | H68: $ - | I68: $ - | J68: $ - | K68: $ - | L68: $ - | M68: $ - | N68: =SUM(B68:M68) -> 1497.07
A69: Education and Training | B69: $ - | C69: $ - | D69: $ - | E69: $ - | F69: $ - | G69: $ - | H69: $ - | I69: $ - | J69: $ - | K69: $ - | L69: $ - | M69: $ - | N69: =SUM(B69:M69) -> 0
A70: Computer Software | B70: 1107.22 | C70: 1107.22 | D70: 1107.22 | E70: 1107.22 | F70: 1107.22 | G70: 1107.22 | H70: 1107.22 | I70: 3307.22 | J70: 1407.22 | K70: 1107.22 | L70: 1107.22 | M70: 1107.22 | N70: =SUM(B70:M70) -> 15786.64
A71: After Hours Cell Phone | B71: $ - | C71: $ - | D71: $ - | E71: $ - | F71: $ - | G71: $ - | H71: $ - | I71: $ - | J71: $ - | K71: $ - | L71: $ - | M71: $ - | N71: =SUM(B71:M71) -> 0
A72: Property Setup Fee | B72: $ - | C72: $ - | D72: $ - | E72: $ - | F72: $ - | G72: $ - | H72: $ - | I72: $ - | J72: $ - | K72: $ - | L72: $ - | M72: $ - | N72: =SUM(B72:M72) -> 0
A73: Online Bill Pay | B73: $ - | C73: $ - | D73: $ - | E73: $ - | F73: $ - | G73: $ - | H73: $ - | I73: $ - | J73: $ - | K73: $ - | L73: $ - | M73: $ - | N73: =SUM(B73:M73) -> 0
A74: Recruiting Expense | B74: $ - | C74: $ - | D74: $ - | E74: $ - | F74: $ - | G74: $ - | H74: $ - | I74: $ - | J74: $ - | K74: $ - | L74: 148.74 | M74: $ - | N74: =SUM(B74:M74) -> 148.74
A75: Verifast | B75: 100 | C75: 100 | D75: 100 | E75: 100 | F75: 100 | G75: 100 | H75: 100 | I75: 100 | J75: 100 | K75: 100 | L75: 100 | M75: 100 | N75: =SUM(B75:M75) -> 1200
A76: Staff-Meals/Entertainment | B76: 6.5 | C76: 6.5 | D76: 6.5 | E76: 6.5 | F76: 6.5 | G76: 6.5 | H76: 6.5 | I76: 6.5 | J76: 6.5 | K76: 6.5 | L76: 6.5 | M76: 6.5 | N76: =SUM(B76:M76) -> 78
A77: Total Admin Expenses | B77: =SUM(B53:B76) -> 2781.05 | C77: =SUM(C53:C76) -> 3093.77 | D77: =SUM(D53:D76) -> 2297.05 | E77: =SUM(E53:E76) -> 7597.05 | F77: =SUM(F53:F76) -> 2997.4 | G77: =SUM(G53:G76) -> 2297.05 | H77: =SUM(H53:H76) -> 2297.05 | I77: =SUM(I53:I76) -> 4497.05 | ... M77: =SUM(M53:M76) -> 2297.05 | N77: =SUM(B77:M77) -> 37771.77
A78: Turn Costs
A79: Carpet/ Floor Replacement - Turns | B79: $ - | C79: $ - | D79: $ - | E79: $ - | F79: $ - | G79: $ - | H79: $ - | I79: $ - | J79: $ - | K79: $ - | L79: $ - | M79: $ -
A80: Painting Turn | B80: 400 | C80: 400 | D80: 400 | E80: 400 | F80: 400 | G80: 400 | H80: 400 | I80: 400 | J80: 400 | K80: 400 | L80: 400 | M80: 400 | N80: =SUM(B80:M80) -> 4800
A81: Cleaning/Janitorial Turn | B81: 400 | C81: 400 | D81: $ - | E81: 1000 | F81: 200 | G81: 200 | H81: 600 | I81: 2400 | J81: 800 | K81: 767 | L81: 600 | M81: 1000 | N81: =SUM(B81:M81) -> 8367
A82: Key/Lock Turn | B82: 50 | C82: 50 | D82: 50 | E82: 50 | F82: 50 | G82: 50 | H82: 50 | I82: 50 | J82: 50 | K82: 50 | L82: 50 | M82: 50 | N82: =SUM(B82:M82) -> 600
A83: Carpet/Tile Cleaning - Turns | B83: 300 | C83: 300 | D83: 300 | E83: 300 | F83: 300 | G83: 300 | H83: 300 | I83: 300 | J83: 300 | K83: 300 | L83: 300 | M83: 300 | N83: =SUM(B83:M83) -> 3600
A84: Turn Repairs R&M | B84: 200 | C84: 200 | D84: $ - | E84: 500 | F84: 100 | G84: 100 | H84: 300 | I84: 1200 | J84: 400 | K84: 383 | L84: 300 | M84: 500 | N84: =SUM(B84:M84) -> 4183
A85: Tub/Shower Resurfacing - Turns | B85: 860 | C85: 860 | D85: 860 | E85: 860 | F85: 860 | G85: 860 | H85: 860 | I85: 860 | J85: 860 | K85: 860 | L85: 860 | M85: 860 | N85: =SUM(B85:M85) -> 10320
A86: Total Turn Costs | B86: =SUM(B79:B85) -> 2210 | C86: =SUM(C79:C85) -> 2210 | D86: =SUM(D79:D85) -> 1610 | E86: =SUM(E79:E85) -> 3110 | F86: =SUM(F79:F85) -> 1910 | G86: =SUM(G79:G85) -> 1910 | H86: =SUM(H79:H85) -> 2510 | I86: =SUM(I79:I85) -> 5210 | ... M86: =SUM(M79:M85) -> 3110 | N86: =SUM(B86:M86) -> 31870
A87: Advertising
A88: Advertising - General | B88: 0 | C88: 0 | D88: 0 | E88: 0 | F88: 0 | G88: 0 | H88: 0 | I88: 0 | J88: 0 | K88: 0 | L88: 0 | M88: 0 | N88: =SUM(B88:M88) -> 0
A89: Website | B89: 0 | C89: 0 | D89: 0 | E89: 0 | F89: 0 | G89: 0 | H89: 0 | I89: 0 | J89: 0 | K89: 0 | L89: 0 | M89: 0 | N89: =SUM(B89:M89) -> 0
A90: Resident Referral Fees | B90: 0 | C90: 0 | D90: 0 | E90: 0 | F90: 0 | G90: 0 | H90: 0 | I90: 0 | J90: 0 | K90: 0 | L90: 0 | M90: 0 | N90: =SUM(B90:M90) -> 0
A91: Marketing / Promotions | B91: 0 | C91: 0 | D91: 0 | E91: 0 | F91: 0 | G91: 0 | H91: 0 | I91: 0 | J91: 0 | K91: 0 | L91: 0 | M91: 0 | N91: =SUM(B91:M91) -> 0
A92: Resident Refreshments and Events | B92: 0 | C92: 0 | D92: 0 | E92: 0 | F92: 0 | G92: 0 | H92: 0 | I92: 0 | J92: 0 | K92: 0 | L92: 0 | M92: 0 | N92: =SUM(B92:M92) -> 0
A93: Model Expense | B93: 0 | C93: 0 | D93: 0 | E93: 0 | F93: 0 | G93: 0 | H93: 0 | I93: 0 | J93: 0 | K93: 163.95 | L93: 0 | M93: 0 | N93: =SUM(B93:M93) -> 163.95
A94: Apartments.com | B94: 2832 | C94: 2832 | D94: 2832 | E94: 2832 | F94: 2832 | G94: 2832 | H94: 2832 | I94: 2832 | J94: 2832 | K94: 1300 | L94: 1300 | M94: 1300 | N94: =SUM(B94:M94) -> 29388 | O94: Will reduce Apts.com in Q4
A95: Zillow | B95: 730 | C95: 730 | D95: 730 | E95: 730 | F95: 730 | G95: 730 | H95: 730 | I95: 730 | J95: 730 | K95: 730 | L95: 730 | M95: 730 | N95: =SUM(B95:M95) -> 8760
A96: Total Advertising | B96: =SUM(B88:B95) -> 3562 | C96: =SUM(C88:C95) -> 3562 | D96: =SUM(D88:D95) -> 3562 | E96: =SUM(E88:E95) -> 3562 | F96: =SUM(F88:F95) -> 3562 | G96: =SUM(G88:G95) -> 3562 | H96: =SUM(H88:H95) -> 3562 | I96: =SUM(I88:I95) -> 3562 | ... M96: =SUM(M88:M95) -> 2030 | N96: =SUM(B96:M96) -> 38311.95
A97: Repairs and Maintenance
A98: HVAC (Heat, Ventilation, Air) R&M | B98: 900 | C98: 900 | D98: 900 | E98: 900 | F98: 900 | G98: 900 | H98: 900 | I98: 900 | J98: 900 | K98: 900 | L98: 900 | M98: 900 | N98: =SUM(B98:M98) -> 10800 | O98: We took the budget from Atrium.
A99: Plumbing R&M | B99: 900 | C99: 900 | D99: 900 | E99: 900 | F99: 900 | G99: 900 | H99: 900 | I99: 900 | J99: 900 | K99: 900 | L99: 900 | M99: 900 | N99: =SUM(B99:M99) -> 10800 | O99: We took the budget from Atrium.
A100: Electrical R&M | B100: 212 | C100: 212 | D100: 212 | E100: 212 | F100: 212 | G100: 212 | H100: 212 | I100: 212 | J100: 212 | K100: 212 | L100: 212 | M100: 212 | N100: =SUM(B100:M100) -> 2544 | O100: Ownership's discretion base on T-12 after takeover
...

Sheet Budget 2026
A1: Account Name | B1: 46023 | C1: =EDATE(B1, 1) -> 46054 | D1: =EDATE(C1, 1) -> 46082 | E1: =EDATE(D1, 1) -> 46113 | F1: =EDATE(E1, 1) -> 46143 | G1: =EDATE(F1, 1) -> 46174 | H1: =EDATE(G1, 1) -> 46204 | I1: =EDATE(H1, 1) -> 46235 | J1: =EDATE(I1, 1) -> 46266 | ... M1: =EDATE(L1, 1) -> 46357 | N1: Total
A2: Gross Potential Rent | B2: ='Worksheet - DO NOT DELETE'!B12 -> 159666 | C2: ='Worksheet - DO NOT DELETE'!C12 -> 159666 | D2: ='Worksheet - DO NOT DELETE'!D12 -> 159666 | E2: ='Worksheet - DO NOT DELETE'!E12 -> 159666 | F2: ='Worksheet - DO NOT DELETE'!F12 -> 159666 | G2: ='Worksheet - DO NOT DELETE'!G12 -> 159666 | H2: ='Worksheet - DO NOT DELETE'!H12 -> 159666 | I2: ='Worksheet - DO NOT DELETE'!I12 -> 159666 | ... M2: ='Worksheet - DO NOT DELETE'!M12 -> 159666 | N2: =SUM(B2:M2) -> 1915992
A3: Loss/Gain to Market | B3: ='Worksheet - DO NOT DELETE'!B16 -> -9750.12 | C3: ='Worksheet - DO NOT DELETE'!C16 -> -9750.12 | D3: ='Worksheet - DO NOT DELETE'!D16 -> -9375.3303 | E3: ='Worksheet - DO NOT DELETE'!E16 -> -9179.9524 | F3: ='Worksheet - DO NOT DELETE'!F16 -> -8984.3206 | G3: ='Worksheet - DO NOT DELETE'!G16 -> -8788.4344 | H3: ='Worksheet - DO NOT DELETE'!H16 -> -8516.8548 | I3: ='Worksheet - DO NOT DELETE'!I16 -> -8244.7863 | ... M3: ='Worksheet - DO NOT DELETE'!M16 -> -7699.0155 | N3: =SUM(B3:M3) -> -103932.52
A4: Concessions | B4: ='Worksheet - DO NOT DELETE'!B15-(B5+B6) -> 0 | C4: ='Worksheet - DO NOT DELETE'!C15-(C5+C6) -> -3541.32 | D4: ='Worksheet - DO NOT DELETE'!D15-(D5+D6) -> -9762.9766 | E4: ='Worksheet - DO NOT DELETE'!E15-(E5+E6) -> -1777.3943 | F4: ='Worksheet - DO NOT DELETE'!F15-(F5+F6) -> -2669.5573 | G4: ='Worksheet - DO NOT DELETE'!G15-(G5+G6) -> -2673.0277 | H4: ='Worksheet - DO NOT DELETE'!H15-(H5+H6) -> -1785.2261 | I4: ='Worksheet - DO NOT DELETE'!I15-(I5+I6) -> -1788.4395 | ... M4: ='Worksheet - DO NOT DELETE'!M15-(M5+M6) -> -897.44282 | N4: =SUM(B4:M4) -> -28480.315
A5: Concessions - Recurring | B5: -100 | C5: -100 | D5: -100 | E5: -100 | F5: -100 | G5: -100 | H5: -100 | I5: -100 | J5: -100 | K5: -100 | L5: -100 | M5: -100 | N5: =SUM(B5:M5) -> -1200
A6: Concessions - Employee Unit | B6: -210 | C6: -210 | D6: -210 | E6: -210 | F6: -210 | G6: -210 | H6: -210 | I6: -210 | J6: -210 | K6: -210 | L6: -210 | M6: -210 | N6: =SUM(B6:M6) -> -2520
A7: Vacancy | B7: ='Worksheet - DO NOT DELETE'!B13 -> -14165.28 | C7: ='Worksheet - DO NOT DELETE'!C13 -> -9443.52 | D7: ='Worksheet - DO NOT DELETE'!D13 -> -4733.5644 | E7: ='Worksheet - DO NOT DELETE'!E13 -> -4739.718 | F7: ='Worksheet - DO NOT DELETE'!F13 -> -4745.8797 | G7: ='Worksheet - DO NOT DELETE'!G13 -> -4752.0493 | H7: ='Worksheet - DO NOT DELETE'!H13 -> -4760.603 | I7: ='Worksheet - DO NOT DELETE'!I13 -> -4769.1721 | ... M7: ='Worksheet - DO NOT DELETE'!M13 -> -3589.7713 | N7: =SUM(B7:M7) -> -66455.961
A8: Bad Debt - Contra | B8: ='Worksheet - DO NOT DELETE'!B17 -> -11804.4 | C8: ='Worksheet - DO NOT DELETE'!C17 -> -11804.4 | D8: ='Worksheet - DO NOT DELETE'!D17 -> -15384.084 | E8: ='Worksheet - DO NOT DELETE'!E17 -> -1184.9295 | F8: ='Worksheet - DO NOT DELETE'!F17 -> -1186.4699 | G8: ='Worksheet - DO NOT DELETE'!G17 -> -1188.0123 | H8: ='Worksheet - DO NOT DELETE'!H17 -> -1190.1507 | I8: ='Worksheet - DO NOT DELETE'!I17 -> -1192.293 | ... M8: ='Worksheet - DO NOT DELETE'!M17 -> 0 | N8: =SUM(B8:M8) -> -48520.208
A9: Total Rental Income | B9: =SUM(B2:B8) -> 123636.2 | C9: =SUM(C2:C8) -> 124816.64 | D9: =SUM(D2:D8) -> 120100.04 | E9: =SUM(E2:E8) -> 142474.01 | F9: =SUM(F2:F8) -> 141769.77 | G9: =SUM(G2:G8) -> 141954.48 | H9: =SUM(H2:H8) -> 143103.17 | I9: =SUM(I2:I8) -> 143361.31 | ... M9: =SUM(M2:M8) -> 147169.77 | N9: =SUM(B9:M9) -> 1664883
A10: Other Income
A11: Lease Lock
A12: NSF Fees Collected | B12: 50 | C12: 50 | D12: 50 | E12: 50 | F12: 50 | G12: 50 | H12: 50 | I12: 50 | J12: 50 | K12: 50 | L12: 50 | M12: 50 | N12: =SUM(B12:M12) -> 600
A13: Late Fee | B13: 2100 | C13: 2100 | D13: 2100 | E13: 2100 | F13: 2100 | G13: 2100 | H13: 2100 | I13: 2100 | J13: 2100 | K13: 2100 | L13: 2100 | M13: 2100 | N13: =SUM(B13:M13) -> 25200
A14: Utility Income | N14: =SUM(B14:M14) -> 0
A15: Electricity Income | N15: =SUM(B15:M15) -> 0
A16: Utility Reimbursements | B16: 7360 | C16: 7360 | D16: 7360 | E16: 7360 | F16: 7360 | G16: 7360 | H16: 7360 | I16: 7360 | J16: 7360 | K16: 7360 | L16: 7360 | M16: 7360 | N16: =SUM(B16:M16) -> 88320
A17: Resident Liability & Contents Coverage | B17: 725 | C17: 725 | D17: 725 | E17: 725 | F17: 725 | G17: 725 | H17: 725 | I17: 725 | J17: 725 | K17: 725 | L17: 725 | M17: 725 | N17: =SUM(B17:M17) -> 8700
A18: 1st month - Resident Liability & Contents Coverage | N18: =SUM(B18:M18) -> 0
A19: AppFolio Insurance Admin Fee | B19: 185 | C19: 185 | D19: 185 | E19: 185 | F19: 185 | G19: 185 | H19: 185 | I19: 185 | J19: 185 | K19: 185 | L19: 185 | M19: 185 | N19: =SUM(B19:M19) -> 2220
A20: Pet Fee - Non Refundable | N20: =SUM(B20:M20) -> 0
A21: Bad Debt Recovery | N21: =SUM(B21:M21) -> 0
A22: Pet Application Fee | N22: =SUM(B22:M22) -> 0
A23: Monthly Pet Rent | B23: 480 | C23: 480 | D23: 480 | E23: 480 | F23: 480 | G23: 480 | H23: 480 | I23: 480 | J23: 480 | K23: 480 | L23: 480 | M23: 480 | N23: =SUM(B23:M23) -> 5760
A24: Admin Fee | B24: 150 | C24: 150 | D24: 150 | E24: 150 | F24: 150 | G24: 150 | H24: 150 | I24: 150 | J24: 150 | K24: 150 | L24: 150 | M24: 150 | N24: =SUM(B24:M24) -> 1800
A25: Early Lease Termination Fee | N25: =SUM(B25:M25) -> 0
A26: Application Fee Income | B26: 215 | C26: 215 | D26: 215 | E26: 215 | F26: 215 | G26: 215 | H26: 215 | I26: 215 | J26: 215 | K26: 215 | L26: 215 | M26: 215 | N26: =SUM(B26:M26) -> 2580
A27: Extended Month to Month Fee | B27: 200 | C27: 200 | D27: 200 | E27: 200 | F27: 200 | G27: 200 | H27: 200 | I27: 200 | J27: 200 | K27: 200 | L27: 200 | M27: 200 | N27: =SUM(B27:M27) -> 2400
A28: Move Out Charges | B28: 500 | C28: 500 | D28: 500 | E28: 500 | F28: 500 | G28: 500 | H28: 500 | I28: 500 | J28: 500 | K28: 500 | L28: 500 | M28: 500 | N28: =SUM(B28:M28) -> 6000
A29: Move In Charges - Misc | N29: =SUM(B29:M29) -> 0
A30: Resident Transfer fee | N30: =SUM(B30:M30) -> 0
A31: Laundry Income | B31: 500 | C31: 500 | D31: 500 | E31: 500 | F31: 500 | G31: 500 | H31: 500 | I31: 500 | J31: 500 | K31: 500 | L31: 500 | M31: 500 | N31: =SUM(B31:M31) -> 6000
A32: Miscellaneous Income | N32: =SUM(B32:M32) -> 0
A33: Misc Reimbursements | N33: =SUM(B33:M33) -> 0
A34: Damages | B34: 406 | C34: 406 | D34: 406 | E34: 406 | F34: 406 | G34: 406 | H34: 406 | I34: 406 | J34: 406 | K34: 406 | L34: 406 | M34: 406 | N34: =SUM(B34:M34) -> 4872
A35: Amenity Fee | B35: ='Worksheet - DO NOT DELETE'!B$5*15 -> 1575 | C35: ='Worksheet - DO NOT DELETE'!C$5*15 -> 1635 | D35: ='Worksheet - DO NOT DELETE'!D$5*15 -> 1650 | E35: ='Worksheet - DO NOT DELETE'!E$5*15 -> 1830 | F35: ='Worksheet - DO NOT DELETE'!F$5*15 -> 1830 | G35: ='Worksheet - DO NOT DELETE'!G$5*15 -> 1830 | H35: ='Worksheet - DO NOT DELETE'!H$5*15 -> 1830 | I35: ='Worksheet - DO NOT DELETE'!I$5*15 -> 1830 | ... M35: ='Worksheet - DO NOT DELETE'!M$5*15 -> 1860 | N35: =SUM(B35:M35) -> 21405
A36: Trash Fee | B36: ='Worksheet - DO NOT DELETE'!B$5*10 -> 1050 | C36: ='Worksheet - DO NOT DELETE'!C$5*10 -> 1090 | D36: ='Worksheet - DO NOT DELETE'!D$5*10 -> 1100 | E36: ='Worksheet - DO NOT DELETE'!E$5*10 -> 1220 | F36: ='Worksheet - DO NOT DELETE'!F$5*10 -> 1220 | G36: ='Worksheet - DO NOT DELETE'!G$5*10 -> 1220 | H36: ='Worksheet - DO NOT DELETE'!H$5*10 -> 1220 | I36: ='Worksheet - DO NOT DELETE'!I$5*10 -> 1220 | ... M36: ='Worksheet - DO NOT DELETE'!M$5*10 -> 1240 | N36: =SUM(B36:M36) -> 14270
A37: Pest Control Fee | B37: ='Worksheet - DO NOT DELETE'!B$5*5 -> 525 | C37: ='Worksheet - DO NOT DELETE'!C$5*5 -> 545 | D37: ='Worksheet - DO NOT DELETE'!D$5*5 -> 550 | E37: ='Worksheet - DO NOT DELETE'!E$5*5 -> 610 | F37: ='Worksheet - DO NOT DELETE'!F$5*5 -> 610 | G37: ='Worksheet - DO NOT DELETE'!G$5*5 -> 610 | H37: ='Worksheet - DO NOT DELETE'!H$5*5 -> 610 | I37: ='Worksheet - DO NOT DELETE'!I$5*5 -> 610 | ... M37: ='Worksheet - DO NOT DELETE'!M$5*5 -> 620 | N37: =SUM(B37:M37) -> 7135
A38: Maintenance Fee | N38: =SUM(B38:M38) -> 0
A39: Waiver Deposit Fee | B39: ='Worksheet - DO NOT DELETE'!B$5*28*0.35 -> 1029 | C39: ='Worksheet - DO NOT DELETE'!C$5*28*0.35 -> 1068.2 | D39: ='Worksheet - DO NOT DELETE'!D$5*28*0.35 -> 1078 | E39: ='Worksheet - DO NOT DELETE'!E$5*28*0.35 -> 1195.6 | F39: ='Worksheet - DO NOT DELETE'!F$5*28*0.35 -> 1195.6 | G39: ='Worksheet - DO NOT DELETE'!G$5*28*0.35 -> 1195.6 | H39: ='Worksheet - DO NOT DELETE'!H$5*28*0.35 -> 1195.6 | I39: ='Worksheet - DO NOT DELETE'!I$5*28*0.35 -> 1195.6 | ... M39: ='Worksheet - DO NOT DELETE'!M$5*28*0.35 -> 1215.2 | N39: =SUM(B39:M39) -> 13984.6
A40: PM Service Fee | B40: ='Worksheet - DO NOT DELETE'!B$5*3 -> 315 | C40: ='Worksheet - DO NOT DELETE'!C$5*3 -> 327 | D40: ='Worksheet - DO NOT DELETE'!D$5*3 -> 330 | E40: ='Worksheet - DO NOT DELETE'!E$5*3 -> 366 | F40: ='Worksheet - DO NOT DELETE'!F$5*3 -> 366 | G40: ='Worksheet - DO NOT DELETE'!G$5*3 -> 366 | H40: ='Worksheet - DO NOT DELETE'!H$5*3 -> 366 | I40: ='Worksheet - DO NOT DELETE'!I$5*3 -> 366 | ... M40: ='Worksheet - DO NOT DELETE'!M$5*3 -> 372 | N40: =SUM(B40:M40) -> 4281
A41: Utility - OW Service Fee | B41: ='Worksheet - DO NOT DELETE'!B$5*3 -> 315 | C41: ='Worksheet - DO NOT DELETE'!C$5*3 -> 327 | D41: ='Worksheet - DO NOT DELETE'!D$5*3 -> 330 | E41: ='Worksheet - DO NOT DELETE'!E$5*3 -> 366 | F41: ='Worksheet - DO NOT DELETE'!F$5*3 -> 366 | G41: ='Worksheet - DO NOT DELETE'!G$5*3 -> 366 | H41: ='Worksheet - DO NOT DELETE'!H$5*3 -> 366 | I41: ='Worksheet - DO NOT DELETE'!I$5*3 -> 366 | ... M41: ='Worksheet - DO NOT DELETE'!M$5*3 -> 372 | N41: =SUM(B41:M41) -> 4281
A42: Interest on Bank Accounts | N42: =SUM(B42:M42) -> 0
A43: Bad Debt - Contra Other Income | B43: ='Worksheet - DO NOT DELETE'!B6*-122 -> -1220 | C43: ='Worksheet - DO NOT DELETE'!C6*-122 -> -1220 | D43: ='Worksheet - DO NOT DELETE'!D6*-122 -> -1586 | E43: ='Worksheet - DO NOT DELETE'!E6*-122 -> -122 | F43: ='Worksheet - DO NOT DELETE'!F6*-122 -> -122 | G43: ='Worksheet - DO NOT DELETE'!G6*-122 -> -122 | H43: ='Worksheet - DO NOT DELETE'!H6*-122 -> -122 | I43: ='Worksheet - DO NOT DELETE'!I6*-122 -> -122 | ... M43: ='Worksheet - DO NOT DELETE'!M6*-122 -> 0 | N43: =SUM(B43:M43) -> -5002
A44: Total Other Income | B44: =SUM(B13:B43) -> 16410 | C44: =SUM(C13:C43) -> 16593.2 | D44: =SUM(D13:D43) -> 16273 | E44: =SUM(E13:E43) -> 18286.6 | F44: =SUM(F13:F43) -> 18286.6 | G44: =SUM(G13:G43) -> 18286.6 | H44: =SUM(H13:H43) -> 18286.6 | I44: =SUM(I13:I43) -> 18286.6 | ... M44: =SUM(M13:M43) -> 18500.2 | N44: =SUM(B44:M44) -> 214206.6
A45: Total Operating Income | B45: =B9+B44 -> 140046.2 | C45: =C9+C44 -> 141409.84 | D45: =D9+D44 -> 136373.04 | E45: =E9+E44 -> 160760.61 | F45: =F9+F44 -> 160056.37 | G45: =G9+G44 -> 160241.08 | H45: =H9+H44 -> 161389.77 | I45: =I9+I44 -> 161647.91 | ... M45: =M9+M44 -> 165669.97 | N45: =SUM(B45:M45) -> 1879089.6
A46: Expense
A47: Management Fee Expenses
A48: Management Fees
A49: Lease Renewal Fee
A50: Management Fee - Multifamily | B50: =MAX(B45*3%, 4500) -> 4500 | C50: =MAX(C45*3%, 4500) -> 4500 | D50: =MAX(D45*3%, 4500) -> 4500 | E50: =MAX(E45*3%, 4500) -> 4822.8182 | F50: =MAX(F45*3%, 4500) -> 4801.6912 | G50: =MAX(G45*3%, 4500) -> 4807.2323 | H50: =MAX(H45*3%, 4500) -> 4841.693 | I50: =MAX(I45*3%, 4500) -> 4849.4373 | ... M50: =MAX(M45*3%, 4500) -> 4970.0991 | N50: =SUM(B50:M50) -> 57337.816
A51: Total Management Fee Expenses | B51: =SUM(B48:B50) -> 4500 | C51: =SUM(C48:C50) -> 4500 | D51: =SUM(D48:D50) -> 4500 | E51: =SUM(E48:E50) -> 4822.8182 | F51: =SUM(F48:F50) -> 4801.6912 | G51: =SUM(G48:G50) -> 4807.2323 | H51: =SUM(H48:H50) -> 4841.693 | I51: =SUM(I48:I50) -> 4849.4373 | ... M51: =SUM(M48:M50) -> 4970.0991 | N51: =SUM(B51:M51) -> 57337.816
A52: Admin Expenses
A53: Property Inspections | B53: 45 | C53: $ - | D53: $ - | E53: $ - | F53: $ - | G53: $ - | H53: $ - | I53: $ - | J53: $ - | K53: $ - | L53: $ - | M53: $ - | N53: =SUM(B53:M53) -> 45
A54: Payment Processing Fees | B54: 0 | C54: 0 | D54: 0 | E54: 0 | F54: 0 | G54: 0 | H54: 0 | I54: 0 | J54: 0 | K54: 0 | L54: 0 | M54: 0 | N54: =SUM(B54:M54) -> 0
A55: Telephone Expense | B55: 138.36 | C55: 138.36 | D55: 138.36 | E55: 138.36 | F55: 138.36 | G55: 138.36 | H55: 138.36 | I55: 138.36 | J55: 138.36 | K55: 138.36 | L55: 138.36 | M55: 138.36 | N55: =SUM(B55:M55) -> 1660.32
A56: Memberships/Professional Organizations | B56: 439 | C56: $ - | D56: $ - | E56: $ - | F56: $ - | G56: $ - | I56: $ - | J56: $ - | K56: $ - | L56: $ - | M56: $ - | N56: =SUM(B56:M56) -> 439
A57: Uniforms | B57: $ - | C57: $ - | D57: $ - | E57: $ - | F57: $ - | G57: $ - | H57: $ - | I57: $ - | J57: $ - | K57: $ - | L57: $ - | M57: $ - | N57: =SUM(B57:M57) -> 0
A58: Legal Fees - Retail | B58: $ - | C58: $ - | D58: $ - | E58: $ - | F58: $ - | G58: $ - | H58: $ - | I58: $ - | J58: $ - | K58: $ - | L58: $ - | M58: $ - | N58: =SUM(B58:M58) -> 0
A59: Office Rent | B59: $ - | C59: $ - | D59: $ - | E59: $ - | F59: $ - | G59: $ - | H59: $ - | I59: $ - | J59: $ - | K59: $ - | L59: $ - | M59: $ - | N59: =SUM(B59:M59) -> 0
A60: Office Supplies | B60: 61.39 | C60: 61.39 | D60: 61.39 | E60: 61.39 | F60: 61.39 | G60: 61.39 | H60: 61.39 | I60: 61.39 | J60: 61.39 | K60: 61.39 | L60: 61.39 | M60: 61.39 | N60: =SUM(B60:M60) -> 736.68
A61: Marketing - Entertainment | B61: $ - | C61: $ - | D61: $ - | E61: $ - | F61: $ - | G61: $ - | H61: $ - | I61: $ - | J61: $ - | K61: $ - | L61: 277.36 | M61: $ - | N61: =SUM(B61:M61) -> 277.36
A62: Bank Fees | B62: 16.25 | C62: 16.25 | D62: 16.25 | E62: 16.25 | F62: 16.25 | G62: 16.25 | H62: 16.25 | I62: 16.25 | J62: 16.25 | K62: 16.25 | L62: 16.25 | M62: 16.25 | N62: =SUM(B62:M62) -> 195
A63: Office Miscellaneous Expenses | N63: =SUM(B63:M63) -> 0
A64: Legal Expenses | B64: 500 | C64: 500 | D64: 500 | E64: 500 | F64: 500 | G64: 500 | H64: 500 | I64: 500 | J64: 500 | K64: 500 | L64: 500 | M64: 500 | N64: =SUM(B64:M64) -> 6000
A65: Accounting Expenses | B65: 350 | C65: 350 | D65: 350 | E65: 350 | F65: 350 | G65: 350 | H65: 350 | I65: 350 | J65: 350 | K65: 350 | L65: 350 | M65: 350 | N65: =SUM(B65:M65) -> 4200
A66: Other Professional Fees | B66: $ - | C66: $ - | D66: $ - | E66: 5300 | F66: $ - | G66: $ - | H66: $ - | I66: $ - | J66: $ - | K66: $ - | L66: $ - | M66: $ - | N66: =SUM(B66:M66) -> 5300
A67: Postage and Shipping Expenses | B67: 17.33 | C67: 17.33 | D67: 17.33 | E67: 17.33 | F67: 17.33 | G67: 17.33 | H67: 17.33 | I67: 17.33 | J67: 17.33 | K67: 17.33 | L67: 17.33 | M67: 17.33 | N67: =SUM(B67:M67) -> 207.96
A68: License and Permits | B68: $ - | C68: 796.72 | D68: $ - | E68: $ - | F68: 700.35 | G68: $ - | H68: $ - | I68: $ - | J68: $ - | K68: $ - | L68: $ - | M68: $ - | N68: =SUM(B68:M68) -> 1497.07
A69: Education and Training | B69: $ - | C69: $ - | D69: $ - | E69: $ - | F69: $ - | G69: $ - | H69: $ - | I69: $ - | J69: $ - | K69: $ - | L69: $ - | M69: $ - | N69: =SUM(B69:M69) -> 0
A70: Computer Software | B70: 1107.22 | C70: 1107.22 | D70: 1107.22 | E70: 1107.22 | F70: 1107.22 | G70: 1107.22 | H70: 1107.22 | I70: 3307.22 | J70: 1407.22 | K70: 1107.22 | L70: 1107.22 | M70: 1107.22 | N70: =SUM(B70:M70) -> 15786.64
A71: After Hours Cell Phone | B71: $ - | C71: $ - | D71: $ - | E71: $ - | F71: $ - | G71: $ - | H71: $ - | I71: $ - | J71: $ - | K71: $ - | L71: $ - | M71: $ - | N71: =SUM(B71:M71) -> 0
A72: Property Setup Fee | B72: $ - | C72: $ - | D72: $ - | E72: $ - | F72: $ - | G72: $ - | H72: $ - | I72: $ - | J72: $ - | K72: $ - | L72: $ - | M72: $ - | N72: =SUM(B72:M72) -> 0
A73: Online Bill Pay | B73: $ - | C73: $ - | D73: $ - | E73: $ - | F73: $ - | G73: $ - | H73: $ - | I73: $ - | J73: $ - | K73: $ - | L73: $ - | M73: $ - | N73: =SUM(B73:M73) -> 0
A74: Recruiting Expense | B74: $ - | C74: $ - | D74: $ - | E74: $ - | F74: $ - | G74: $ - | H74: $ - | I74: $ - | J74: $ - | K74: $ - | L74: 148.74 | M74: $ - | N74: =SUM(B74:M74) -> 148.74
A75: Verifast | B75: 100 | C75: 100 | D75: 100 | E75: 100 | F75: 100 | G75: 100 | H75: 100 | I75: 100 | J75: 100 | K75: 100 | L75: 100 | M75: 100 | N75: =SUM(B75:M75) -> 1200
A76: Staff-Meals/Entertainment | B76: 6.5 | C76: 6.5 | D76: 6.5 | E76: 6.5 | F76: 6.5 | G76: 6.5 | H76: 6.5 | I76: 6.5 | J76: 6.5 | K76: 6.5 | L76: 6.5 | M76: 6.5 | N76: =SUM(B76:M76) -> 78
A77: Total Admin Expenses | B77: =SUM(B53:B76) -> 2781.05 | C77: =SUM(C53:C76) -> 3093.77 | D77: =SUM(D53:D76) -> 2297.05 | E77: =SUM(E53:E76) -> 7597.05 | F77: =SUM(F53:F76) -> 2997.4 | G77: =SUM(G53:G76) -> 2297.05 | H77: =SUM(H53:H76) -> 2297.05 | I77: =SUM(I53:I76) -> 4497.05 | ... M77: =SUM(M53:M76) -> 2297.05 | N77: =SUM(B77:M77) -> 37771.77
A78: Turn Costs
A79: Carpet/ Floor Replacement - Turns | B79: $ - | C79: $ - | D79: $ - | E79: $ - | F79: $ - | G79: $ - | H79: $ - | I79: $ - | J79: $ - | K79: $ - | L79: $ - | M79: $ -
A80: Painting Turn | B80: 400 | C80: 400 | D80: 400 | E80: 400 | F80: 400 | G80: 400 | H80: 400 | I80: 400 | J80: 400 | K80: 400 | L80: 400 | M80: 400 | N80: =SUM(B80:M80) -> 4800
A81: Cleaning/Janitorial Turn | B81: 400 | C81: 400 | D81: $ - | E81: 1000 | F81: 200 | G81: 200 | H81: 600 | I81: 2400 | J81: 800 | K81: 767 | L81: 600 | M81: 1000 | N81: =SUM(B81:M81) -> 8367
A82: Key/Lock Turn | B82: 50 | C82: 50 | D82: 50 | E82: 50 | F82: 50 | G82: 50 | H82: 50 | I82: 50 | J82: 50 | K82: 50 | L82: 50 | M82: 50 | N82: =SUM(B82:M82) -> 600
A83: Carpet/Tile Cleaning - Turns | B83: 300 | C83: 300 | D83: 300 | E83: 300 | F83: 300 | G83: 300 | H83: 300 | I83: 300 | J83: 300 | K83: 300 | L83: 300 | M83: 300 | N83: =SUM(B83:M83) -> 3600
A84: Turn Repairs R&M | B84: 200 | C84: 200 | D84: $ - | E84: 500 | F84: 100 | G84: 100 | H84: 300 | I84: 1200 | J84: 400 | K84: 383 | L84: 300 | M84: 500 | N84: =SUM(B84:M84) -> 4183
A85: Tub/Shower Resurfacing - Turns | B85: 860 | C85: 860 | D85: 860 | E85: 860 | F85: 860 | G85: 860 | H85: 860 | I85: 860 | J85: 860 | K85: 860 | L85: 860 | M85: 860 | N85: =SUM(B85:M85) -> 10320
A86: Total Turn Costs | B86: =SUM(B79:B85) -> 2210 | C86: =SUM(C79:C85) -> 2210 | D86: =SUM(D79:D85) -> 1610 | E86: =SUM(E79:E85) -> 3110 | F86: =SUM(F79:F85) -> 1910 | G86: =SUM(G79:G85) -> 1910 | H86: =SUM(H79:H85) -> 2510 | I86: =SUM(I79:I85) -> 5210 | ... M86: =SUM(M79:M85) -> 3110 | N86: =SUM(B86:M86) -> 31870
A87: Advertising
A88: Advertising - General | B88: 0 | C88: 0 | D88: 0 | E88: 0 | F88: 0 | G88: 0 | H88: 0 | I88: 0 | J88: 0 | K88: 0 | L88: 0 | M88: 0 | N88: =SUM(B88:M88) -> 0
A89: Website | B89: 0 | C89: 0 | D89: 0 | E89: 0 | F89: 0 | G89: 0 | H89: 0 | I89: 0 | J89: 0 | K89: 0 | L89: 0 | M89: 0 | N89: =SUM(B89:M89) -> 0
A90: Resident Referral Fees | B90: 0 | C90: 0 | D90: 0 | E90: 0 | F90: 0 | G90: 0 | H90: 0 | I90: 0 | J90: 0 | K90: 0 | L90: 0 | M90: 0 | N90: =SUM(B90:M90) -> 0
A91: Marketing / Promotions | B91: 0 | C91: 0 | D91: 0 | E91: 0 | F91: 0 | G91: 0 | H91: 0 | I91: 0 | J91: 0 | K91: 0 | L91: 0 | M91: 0 | N91: =SUM(B91:M91) -> 0
A92: Resident Refreshments and Events | B92: 0 | C92: 0 | D92: 0 | E92: 0 | F92: 0 | G92: 0 | H92: 0 | I92: 0 | J92: 0 | K92: 0 | L92: 0 | M92: 0 | N92: =SUM(B92:M92) -> 0
A93: Model Expense | B93: 0 | C93: 0 | D93: 0 | E93: 0 | F93: 0 | G93: 0 | H93: 0 | I93: 0 | J93: 0 | K93: 163.95 | L93: 0 | M93: 0 | N93: =SUM(B93:M93) -> 163.95
A94: Apartments.com | B94: 2832 | C94: 2832 | D94: 2832 | E94: 2832 | F94: 2832 | G94: 2832 | H94: 2832 | I94: 2832 | J94: 2832 | K94: 1300 | L94: 1300 | M94: 1300 | N94: =SUM(B94:M94) -> 29388 | O94: Will reduce Apts.com in Q4
A95: Zillow | B95: 730 | C95: 730 | D95: 730 | E95: 730 | F95: 730 | G95: 730 | H95: 730 | I95: 730 | J95: 730 | K95: 730 | L95: 730 | M95: 730 | N95: =SUM(B95:M95) -> 8760
A96: Total Advertising | B96: =SUM(B88:B95) -> 3562 | C96: =SUM(C88:C95) -> 3562 | D96: =SUM(D88:D95) -> 3562 | E96: =SUM(E88:E95) -> 3562 | F96: =SUM(F88:F95) -> 3562 | G96: =SUM(G88:G95) -> 3562 | H96: =SUM(H88:H95) -> 3562 | I96: =SUM(I88:I95) -> 3562 | ... M96: =SUM(M88:M95) -> 2030 | N96: =SUM(B96:M96) -> 38311.95
A97: Repairs and Maintenance
A98: HVAC (Heat, Ventilation, Air) R&M | B98: 900 | C98: 900 | D98: 900 | E98: 900 | F98: 900 | G98: 900 | H98: 900 | I98: 900 | J98: 900 | K98: 900 | L98: 900 | M98: 900 | N98: =SUM(B98:M98) -> 10800 | O98: We took the budget from Atrium.
A99: Plumbing R&M | B99: 900 | C99: 900 | D99: 900 | E99: 900 | F99: 900 | G99: 900 | H99: 900 | I99: 900 | J99: 900 | K99: 900 | L99: 900 | M99: 900 | N99: =SUM(B99:M99) -> 10800 | O99: We took the budget from Atrium.
A100: Electrical R&M | B100: 212 | C100: 212 | D100: 212 | E100: 212 | F100: 212 | G100: 212 | H100: 212 | I100: 212 | J100: 212 | K100: 212 | L100: 212 | M100: 212 | N100: =SUM(B100:M100) -> 2544 | O100: Ownership's discretion base on T-12 after takeover
...

Sheet 2026 Budget Analysis
A13: Income analysis and projection for 2026 Budget
F14: ATRIUM vs Ownership version of the budget
B15: 2026 Atrium Budget | C15: 2026 T-1 Expenses Baseline | D15: 2026 Ownership budget | E15: Reviewed and Final | F15: Diff ($) | G15: Diff (%) | H15: Rationale
A16: Rent | B16: 1488447 | C16: 38500 | D16: ='Budget Summary 2026'!N9 -> 1664883 | E16: Yes, by Claudio Sanchez | F16: =B16-D16 -> -176436 | G16: =F16/B16 -> -0.11853697 | H16: Atrium's income projections are equivalent to the asset being in the mid 80% ecc. Occupancy.
A17: Other Income | B17: 225656 | C17: 58248 | D17: ='Budget Summary 2026'!N44 -> 214206.6 | E17: Yes, by Claudio Sanchez | F17: =B17-D17 -> 11449.4 | G17: =F17/B17 -> 0.050738292 | H17: Atrium other income has a larger portion of Late fee, early termination fees
B18: =SUM(B16:B17) -> 1714103 | C18: 797178 | D18: =SUM(D16:D17) -> 1879089.6 | F18: =B18-D18 -> -164986.6 | G18: =F18/B18 -> -0.096252443
A25: Expense analysis and projection for 2026 Budget
F26: ATRIUM vs Ownership version of the budget
B27: 2026 Atrium Budget | C27: 2026 T-1 Expenses Baseline | D27: 2026 Ownership budget | E27: Reviewed and Final | F27: Diff ($) | G27: Diff (%) | H27: Rationale
A28: Advertising | B28: 16000 | C28: 38500 | D28: ='Budget 2026'!N96 -> 38311.95 | E28: Yes, by Claudio Sanchez | F28: =B28-D28 -> -22311.95 | G28: =F28/B28 -> -1.3944969 | H28: Elimited one-time expenses in T-12, left with only Apts.com and Zillow.com
A29: Contract Services | B29: 58248 | C29: 58248 | D29: ='Budget 2026'!N122 -> 63554.09 | E29: Yes, by Claudio Sanchez | F29: =B29-D29 -> -5306.09 | G29: =F29/B29 -> -0.091094802 | H29: More in-line with last 6 mo pattern
A30: Repair and Maintenance | B30: 52620 | C30: 52620 | D30: ='Budget 2026'!N110 -> 39924 | E30: Yes, by Claudio Sanchez | F30: =B30-D30 -> 12696 | G30: =F30/B30 -> 0.24127708 | H30: More in-line with last 6 mo pattern
A31: Turn Over | B31: 34528 | C31: 34528 | D31: ='Budget 2026'!N86 -> 31870 | E31: Yes, by Claudio Sanchez | F31: =B31-D31 -> 2658 | G31: =F31/B31 -> 0.076981001 | H31: Less turn over as we are estabilized
A32: Utilities | B32: 78420 | C32: 78420 | D32: ='Budget 2026'!N131 -> 60346.56 | E32: Yes, by Claudio Sanchez | F32: =B32-D32 -> 18073.44 | G32: =F32/B32 -> 0.23046978 | H32: Optivo's T-12 includes lots of irregular payments. They were always late paying bills
A33: General/Admin | B33: 29342 | C33: 29342 | D33: ='Budget 2026'!N77 -> 37771.77 | E33: Yes, by Claudio Sanchez | F33: =B33-D33 -> -8429.77 | G33: =F33/B33 -> -0.28729364
A34: Insurance | B34: 95000 | C34: 94100 | D34: ='Budget 2026'!N133 -> 102000 | E34: Yes, by Claudio Sanchez | F34: =B34-D34 -> -7000 | G34: =F34/B34 -> -0.073684211
A35: RE Taxes | B35: 165000 | C35: 165500 | D35: ='Budget 2026'!N134 -> 151680 | E35: Yes, by Claudio Sanchez | F35: =B35-D35 -> 13320 | G35: =F35/B35 -> 0.080727273
A36: Legal | B36: 3960 | C36: 3960 | D36: 0 | E36: Yes, by Claudio Sanchez | F36: =B36-D36 -> 3960 | G36: =F36/B36 -> 1 | H36: Legal is covered inside of Admin Expenses Already.
A37: Payroll | B37: 153837 | C37: 151960 | D37: ='Budget 2026'!N151 -> 152400.4 | E37: Yes, by Claudio Sanchez | F37: =B37-D37 -> 1436.6 | G37: =F37/B37 -> 0.0093384556 | H37: We need review this ENTIRE CATEGORY W/ ATRIUM
A38: PM Fees | B38: 54000 | C38: 54000 | D38: ='Budget 2026'!N51 -> 57337.816 | E38: Yes, by Claudio Sanchez | F38: =B38-D38 -> -3337.8155 | G38: =F38/B38 -> -0.061811398
A39: Deposit to Replacement Reserves | B39: 0 | E39: Yes, by Claudio Sanchez | F39: =B39-D39 -> 0
B40: =SUM(B28:B39) -> 740955 | C40: 797178 | D40: =SUM(D28:D39) -> 735196.59 | F40: =B40-D40 -> 5758.4145 | G40: =F40/B40 -> 0.0077716116
A41: Expense to Income | B41: =B40/B18 -> 0.43226982 | D41: =D40/D18 -> 0.39125148
A42: NOI | B42: =B18-B40 -> 973148 | C42: =C18-C40 -> 0 | D42: =D18-D40 -> 1143893
A43: Valuation at 6.5% Cap rate | B43: =B42/6.5% -> 14971508 | D43: =D42/6.5% -> 17598354
A44: Impact to Valuation | B44: =B43-D43 -> -2626846.4
A50: Average EGI per Unit (Annual) | B50: =(B16/127)/12 -> 976.67126 | D50: =(D16/127)/12 -> 1092.4429
A51: Other Income Per Unit (Annual) | B51: =B17/127 -> 1776.8189 | C51: =C17/127 -> 458.64567 | D51: =D17/127 -> 1686.6661
A52: Other Income Per Unit (in relation to EGI) | B52: =B17/B16 -> 0.151605 | D52: =D17/D16 -> 0.12866165
A53: Vacancy (Annualized)

Sheet Agency vs HUD
A2: Agency Debt Modeling | D2: HUD 223(f) | AB2: SALE
D3: HUD Note Rate | E3: 0.0625 | H3: 2026 | V3: 2027 | X3: 2028 | Z3: 2029 | AB3: 2030
D4: Amortization (Years) | E4: 35 | H4: ='Budget 2026'!B1 -> 46023 | I4: ='Budget 2026'!C1 -> 46054 | J4: ='Budget 2026'!D1 -> 46082 | K4: ='Budget 2026'!E1 -> 46113 | L4: ='Budget 2026'!F1 -> 46143 | M4: ='Budget 2026'!G1 -> 46174 | N4: ='Budget 2026'!H1 -> 46204 | O4: ='Budget 2026'!I1 -> 46235 | ... S4: ='Budget 2026'!M1 -> 46357 | T4: Year 3 | V4: Year 4 | X4: Year 5 | Z4: Year 6 | AB4: Year 7 | AE4: EXIT at Year 7
A5: T-5 Treasury | B5: 0.0372 | D5: HUD Min DSCR | E5: 1.176 | G5: Financial Assumptions | O5: REFINANCE | AT5: Source | AU5: Source | AV5: Source | AW5: Source | AX5: Source | AY5: Source | AZ5: Source | BA5: Source | BB5: Source
A6: Spread | B6: 0.0155 | D6: HUD Max LTV | E6: 0.85 | G6: Annual Rent Escalator | V6: 0.04 | X6: 0.03 | Z6: 0.03 | AB6: 0.03 | AE6: Sale | AT6: T-12 | AU6: T-12 | AV6: T-12 | AW6: T-12
A7: Interest Rate | B7: =SUM(B5:B6) -> 0.0527 | D7: RR $/Unit/Yr (PCA placeholder) | E7: 350 | G7: Annual Expense Escalator | V7: 0.02 | X7: 0.02 | Z7: 0.02 | AB7: 0.02 | AE7: Net Operating Income | AF7: =Z34 -> 1525849.7 | AH7: Capital Invested | AL7: =AG37 -> 6047500 | AT7: Sept-25 | AU7: 46320 | AV7: 46351 | AW7: DEC | AX7: JAN | AY7: FEB | AZ7: MAR | BA7: APR | BB7: MAY
D8: Initial RR Deposit (Months) | E8: 12 | AE8: Exit Cap Rate | AF8: 0.07 | AH8: Limited Partner Returns | AS8: Gross Potential Rent (GPR) | AT8: 136185.3 | AU8: 139780.78 | AV8: 143362 | AW8: =AV8 -> 143362 | AX8: =AW8 -> 143362 | AY8: =AX8 -> 143362 | AZ8: =AY8 -> 143362 | BA8: =AZ8 -> 143362 | BB8: =BA8 -> 143362
A9: Refinance - Agency | D9: HUD Financing Costs % (all-in) | E9: 0.04 | G9: INCOME | T9: In-Place Rent | V9: In-Place Rent | X9: In-Place Rent | Z9: In-Place Rent | AB9: In-Place Rent | AE9: Insurance/Tax/Lender Escrows | AF9: 0 | AH9: Return of Capital | AL9: =AG37 -> 6047500 | AS9: - Vacancy | AT9: -17406.1 | AU9: -5336.53 | AV9: -8718.07 | AW9: -6599.14 | AX9: -3377 | AY9: -3377 | AZ9: -3377 | BA9: -3377 | BB9: -3377
A10: Units | B10: 127 | G10: Average In-Place Rent | T10: =(T17/$B$10)/12 -> 1092.4429 | V10: =(V17/$B$10)/12 -> 1242.126 | X10: =(X17/$B$10)/12 -> 1279.3898 | Z10: =(Z17/$B$10)/12 -> 1317.7715 | AB10: =(AB17/$B$10)/12 -> 1357.3047 | AE10: Total Equity Outstanding | AF10: =-AF30-AG32 -> 3568460.5 | AH10: Preferred returns | AL10: =AH37 -> 0 | AS10: - Concessions, Loss to Lease, Bad Debt | AT10: =SUM(AT11:AT13) -> -33231 | AU10: =SUM(AU11:AU13) -> -31462.9 | AV10: =SUM(AV11:AV13) -> -13600 | AW10: =SUM(AW11:AW13) -> -20106.11 | AX10: =SUM(AX11:AX13) -> -13412 | AY10: =SUM(AY11:AY13) -> -13412 | AZ10: =SUM(AZ11:AZ13) -> -11412 | BA10: =SUM(BA11:BA13) -> -8412 | BB10: =SUM(BB11:BB13) -> -6412
A11: Min DSCR | B11: 1.25 | D11: Amourt Months | E11: =E4*12 -> 420 | G11: Gross Potential Rent (GPR) | H11: ='Budget 2026'!B2 -> 159666 | I11: ='Budget 2026'!C2 -> 159666 | J11: ='Budget 2026'!D2 -> 159666 | K11: ='Budget 2026'!E2 -> 159666 | L11: ='Budget 2026'!F2 -> 159666 | M11: ='Budget 2026'!G2 -> 159666 | N11: ='Budget 2026'!H2 -> 159666 | O11: ='Budget 2026'!I2 -> 159666 | ... S11: ='Budget 2026'!M2 -> 159666 | T11: =SUM(H11:S11) -> 1915992 | V11: =T11*(1+V6) -> 1992631.7 | X11: =V11*(1+X6) -> 2052410.6 | Z11: =X11*(1+Z6) -> 2113982.9 | AB11: =Z11*(1+AB6) -> 2177402.4 | AH11: From Cash Flow | AL11: =AI37 -> 1621350.2 | AS11: Consessions | AT11: -17426 | AU11: =-(19220+410) -> -19630 | AV11: =-(11590+310) -> -11900 | AW11: -919 | AX11: -1712 | AY11: -1712 | AZ11: -1712 | BA11: -1712 | BB11: -1712
A12: Max LTV | B12: 0.75 | G12: - Vacancy | H12: ='Budget 2026'!B7 -> -14165.28 | I12: ='Budget 2026'!C7 -> -9443.52 | J12: ='Budget 2026'!D7 -> -4733.5644 | K12: ='Budget 2026'!E7 -> -4739.718 | L12: ='Budget 2026'!F7 -> -4745.8797 | M12: ='Budget 2026'!G7 -> -4752.0493 | N12: ='Budget 2026'!H7 -> -4760.603 | O12: ='Budget 2026'!I7 -> -4769.1721 | ... S12: ='Budget 2026'!M7 -> -3589.7713 | T12: =SUM(H12:S12) -> -66455.961 | U12: =ABS(T12/$T$11) -> 0.034684885 | V12: =-V11*W12 -> -19926.317 | W12: 0.01 | X12: =-X11*Y12 -> -41048.213 | Y12: 0.02 | Z12: =-Z11*AA12 -> -42279.659 | AA12: 0.02 | AB12: =-AB11*AC12 -> -43548.049 | AC12: 0.02 | AE12: Sales Price | AF12: =AF7/AF8 -> 21797854 | AG12: =AF12/B10 -> 171636.64 | AH12: From Sales Proceeds | AL12: =AK36 -> 2136890.7 | AS12: Loss To Lease | AT12: =856 -> 856 | AU12: -158.9 | AV12: -1700 | AW12: -4847.11 | AX12: -1700 | AY12: -1700 | AZ12: -1700 | BA12: -1700 | BB12: -1700
A13: Interest rate | B13: =B7 -> 0.0527 | G13: - Concessions, Loss to Lease, Bad Debt | T13: =SUM(H13:S13) -> 0 | V13: =-V11*W13 -> -79705.267 | W13: 0.04 | X13: =-X11*Y13 -> -61572.319 | Y13: 0.03 | Z13: =-Z11*AA13 -> -63419.488 | AA13: 0.03 | AB13: =-AB11*AC13 -> -65322.073 | AC13: 0.03 | AE13: Operating Reserves Remaining | AF13: =SUM(T45:AB45) -> 180000 | AG13: =AF13/B10 -> 1417.3228 | AH13: Total Distributions | AL13: =SUM(AL9:AL12) -> 9805740.9 | AS13: Bad Debt | AT13: -16661 | AU13: -11674 | AV13: 0 | AW13: -14340 | AX13: -10000 | AY13: -10000 | AZ13: -8000 | BA13: -5000 | BB13: -3000
A14: Cap rate | B14: 0.065 | G14: Consessions | H14: =SUM('Budget 2026'!B4:B6) -> -310 | I14: =SUM('Budget 2026'!C4:C6) -> -3851.32 | J14: =SUM('Budget 2026'!D4:D6) -> -10072.977 | K14: =SUM('Budget 2026'!E4:E6) -> -2087.3943 | L14: =SUM('Budget 2026'!F4:F6) -> -2979.5573 | M14: =SUM('Budget 2026'!G4:G6) -> -2983.0277 | N14: =SUM('Budget 2026'!H4:H6) -> -2095.2261 | O14: =SUM('Budget 2026'!I4:I6) -> -2098.4395 | ... S14: =SUM('Budget 2026'!M4:M6) -> -1207.4428 | T14: =SUM(H14:S14) -> -32200.315 | U14: =ABS(T14/$T$11) -> 0.01680608 | AE14: Pref/Mezz Principal Payoff | AF14: =-B62 -> 0 | AS14: Gross Potential Income (GPI) | AT14: =SUM(AT8:AT10) -> 85548.2 | AU14: =SUM(AU8:AU10) -> 102981.35 | AV14: =SUM(AV8:AV10) -> 121043.93 | AW14: =SUM(AW8:AW10) -> 116656.75 | AX14: =SUM(AX8:AX10) -> 126573 | AY14: =SUM(AY8:AY10) -> 126573 | AZ14: =SUM(AZ8:AZ10) -> 128573 | BA14: =SUM(BA8:BA10) -> 131573 | BB14: =SUM(BB8:BB10) -> 133573
A15: Income (MAY-JUL '26) | B15: =SUM(L19:N19)*4 -> 1926748.9 | D15: Income (MAY-JUL '26) | E15: =T19 -> 1879089.6 | G15: Loss To Lease | H15: ='Budget 2026'!B3 -> -9750.12 | I15: ='Budget 2026'!C3 -> -9750.12 | J15: ='Budget 2026'!D3 -> -9375.3303 | K15: ='Budget 2026'!E3 -> -9179.9524 | L15: ='Budget 2026'!F3 -> -8984.3206 | M15: ='Budget 2026'!G3 -> -8788.4344 | N15: ='Budget 2026'!H3 -> -8516.8548 | O15: ='Budget 2026'!I3 -> -8244.7863 | ... S15: ='Budget 2026'!M3 -> -7699.0155 | T15: =SUM(H15:S15) -> -103932.52 | U15: =ABS(T15/$T$11) -> 0.054244754 | AE15: Defferred Interest Pref/Mezz Payoff | AF15: =-B68*3 -> 0 | AH15: LP Metrics | AS15: Other Income | AT15: 13112.8 | AU15: 13988.72 | AV15: 17456.19 | AW15: 13773.1 | AX15: 14839 | AY15: 14839 | AZ15: 14839 | BA15: 14839 | BB15: 14839
A16: Expenses (MAY-JUL '26) | B16: =SUM(L32:N32)*4 -> 709184.39 | D16: Expenses (MAY-JUL '26) | E16: =T32 -> 734656.41 | G16: Bad Debt | H16: ='Budget 2026'!B8 -> -11804.4 | I16: ='Budget 2026'!C8 -> -11804.4 | J16: ='Budget 2026'!D8 -> -15384.084 | K16: ='Budget 2026'!E8 -> -1184.9295 | L16: ='Budget 2026'!F8 -> -1186.4699 | M16: ='Budget 2026'!G8 -> -1188.0123 | N16: ='Budget 2026'!H8 -> -1190.1507 | O16: ='Budget 2026'!I8 -> -1192.293 | ... S16: ='Budget 2026'!M8 -> 0 | T16: =SUM(H16:S16) -> -48520.208 | U16: =ABS(T16/$T$11) -> 0.025323805 | AE16: Sales Cost at 4% | AF16: =-AF12*4% -> -871914.14 | AG16: =AF16/B10 -> -6865.4657 | AH16: Equity Multiple | AL16: =(AL13/AL7) -> 1.6214536 | AS16: Effective Gross Income | AT16: =SUM(AT14:AT15) -> 98661 | AU16: =SUM(AU14:AU15) -> 116970.07 | AV16: =SUM(AV14:AV15) -> 138500.12 | AW16: =SUM(AW14:AW15) -> 130429.85 | AX16: =SUM(AX14:AX15) -> 141412 | AY16: =SUM(AY14:AY15) -> 141412 | AZ16: =SUM(AZ14:AZ15) -> 143412 | BA16: =SUM(BA14:BA15) -> 146412 | BB16: =SUM(BB14:BB15) -> 148412
A17: NOI | B17: =B15-B16 -> 1217564.5 | D17: NOI | E17: =E15-E16 -> 1144433.2 | G17: Gross Potential Income (GPI) | H17: =SUM(H11:H16) -> 123636.2 | I17: =SUM(I11:I16) -> 124816.64 | J17: =SUM(J11:J16) -> 120100.04 | K17: =SUM(K11:K16) -> 142474.01 | L17: =SUM(L11:L16) -> 141769.77 | M17: =SUM(M11:M16) -> 141954.48 | N17: =SUM(N11:N16) -> 143103.17 | O17: =SUM(O11:O16) -> 143361.31 | ... S17: =SUM(S11:S16) -> 147169.77 | T17: =SUM(H17:S17) -> 1664883 | U17: =ABS(T17/$T$11) -> 0.86894048 | V17: =SUM(V11:V13) -> 1893000.1 | W17: =V17/V11 -> 0.95 | X17: =SUM(X11:X13) -> 1949790.1 | Y17: =X17/X11 -> 0.95 | Z17: =SUM(Z11:Z13) -> 2008283.8 | AA17: =Z17/Z11 -> 0.95 | AB17: =SUM(AB11:AB13) -> 2068532.3 | AC17: =AB17/AB11 -> 0.95 | AE17: Outstanding Loan Balance | AF17: =-B20 -> -14048821 | AG17: =AF17/B10 -> -110620.64 | AH17: Cash On Cash | AL17: =AJ37 -> 0.038300364 | AT17: Source
A18: Income to Expense Ratio | B18: =B16/B15 -> 0.36807308 | G18: Other Income | H18: ='Budget 2026'!B44 -> 16410 | I18: ='Budget 2026'!C44 -> 16593.2 | J18: ='Budget 2026'!D44 -> 16273 | K18: ='Budget 2026'!E44 -> 18286.6 | L18: ='Budget 2026'!F44 -> 18286.6 | M18: ='Budget 2026'!G44 -> 18286.6 | N18: ='Budget 2026'!H44 -> 18286.6 | O18: ='Budget 2026'!I44 -> 18286.6 | ... S18: ='Budget 2026'!M44 -> 18500.2 | T18: =SUM(H18:S18) -> 214206.6 | U18: =ABS(T18/$T$11) -> 0.11179932 | V18: =T18*(1+V6) -> 222774.86 | W18: =V18/V11 -> 0.11179932 | X18: =V18*(1+X6) -> 229458.11 | Y18: =X18/X11 -> 0.11179932 | Z18: =X18*(1+Z6) -> 236341.85 | AA18: =Z18/Z11 -> 0.11179932 | AB18: =Z18*(1+AB6) -> 243432.11 | AC18: =AB18/AB11 -> 0.11179932 | AE18: Return of Member Capital | AF18: =-AF10 -> -3568460.5 | AH18: ARR | AL18: =(AL13/AL7)/7 -> 0.23163623 | AT18: T-12
A19: Appraised Value | B19: =B17/B14 -> 18731761 | G19: Effective Gross Income | H19: =SUM(H17:H18) -> 140046.2 | I19: =SUM(I17:I18) -> 141409.84 | J19: =SUM(J17:J18) -> 136373.04 | K19: =SUM(K17:K18) -> 160760.61 | L19: =SUM(L17:L18) -> 160056.37 | M19: =SUM(M17:M18) -> 160241.08 | N19: =SUM(N17:N18) -> 161389.77 | O19: =SUM(O17:O18) -> 161647.91 | ... S19: =SUM(S17:S18) -> 165669.97 | T19: =SUM(H19:S19) -> 1879089.6 | V19: =SUM(V17:V18) -> 2115775 | X19: =SUM(X17:X18) -> 2179248.2 | Z19: =SUM(Z17:Z18) -> 2244625.7 | AB19: =SUM(AB17:AB18) -> 2311964.4 | AE19: Members Preferred Return Deficiency | AF19: =-X51 -> 0 | AH19: IRR | AL19: =AL38 -> 0.11192712 | AS19: EXPENSES | AT19: T-12 Expenses
A20: Refi proceeds | B20: =MIN( B19*B12, PV(B13/12,30*12,-(B17/B11)/12) ) -> 14048821 | D20: HUD Refi Proceeds | E20: =MIN( PV($E$3/12,$E$11,-($B$17/$E$5)/12), $B$19*$E$6 ) -> 14696324 | AE20: Residual Cash After LP Capital + Pref | AF20: =SUM(AF12:AF19) -> 3488658.1 | AS20: Advertising | AT20: 31392.72
A21: Closing Charges | G21: EXPENSES | AE21: Exit Fee @ 2%of Sales price | AF21: =-AF12*2% -> -435957.07 | AS21: Contract Services | AT21: 66947.02
A22: Existing loan payoff | B22: -10899999 | D22: =A22 -> Existing loan payoff | E22: =$B$22 -> -10899999 | G22: PM Fees | H22: ='Budget 2026'!B51 -> 4500 | I22: ='Budget 2026'!C51 -> 4500 | J22: ='Budget 2026'!D51 -> 4500 | K22: ='Budget 2026'!E51 -> 4822.8182 | L22: ='Budget 2026'!F51 -> 4801.6912 | M22: ='Budget 2026'!G51 -> 4807.2323 | N22: ='Budget 2026'!H51 -> 4841.693 | O22: ='Budget 2026'!I51 -> 4849.4373 | ... T22: ='Budget 2026'!N51 -> 57337.816 | U22: =T22/$T$19 -> 0.030513614 | V22: =V19*3% -> 63473.249 | W22: =V22/V$17 -> 0.033530505 | X22: =V22*(1+$X$7) -> 64742.714 | Y22: =X22/X$17 -> 0.033204966 | Z22: =X22*(1+$X$7) -> 66037.568 | AA22: =Z22/Z$17 -> 0.032882588 | AB22: =Z22*(1+$X$7) -> 67358.319 | AC22: =AB22/AB$17 -> 0.032563339 | AE22: Net Proceeds to be distributed | AF22: =SUM(AF20:AF21) -> 3052701 | AS22: Repair and Maintenance | AT22: 66031.47
A23: Closing costs @ 1.5% | B23: =-B20*1.5% -> -210732.31 | D23: Hud Financing Costs | E23: =-$E$20*$E$9 -> -587852.96 | G23: Advertising | H23: ='Budget 2026'!B96 -> 3562 | I23: ='Budget 2026'!C77 -> 3093.77 | J23: ='Budget 2026'!D77 -> 2297.05 | K23: ='Budget 2026'!E77 -> 7597.05 | L23: ='Budget 2026'!F77 -> 2997.4 | M23: ='Budget 2026'!G77 -> 2297.05 | N23: ='Budget 2026'!H77 -> 2297.05 | O23: ='Budget 2026'!I77 -> 4497.05 | P23: ='Budget 2026'!J77 -> 2597.05 | ... T23: ='Budget 2026'!N77 -> 37771.77 | U23: =T23/$T$19 -> 0.020101101 | V23: =T23*(1+V$7) -> 38527.205 | W23: =V23/V$17 -> 0.020352458 | X23: =V23*(1+$X$7) -> 39297.75 | Y23: =X23/X$17 -> 0.020154862 | Z23: =X23*(1+$X$7) -> 40083.704 | AA23: =Z23/Z$17 -> 0.019959183 | AB23: =Z23*(1+$X$7) -> 40885.379 | AC23: =AB23/AB$17 -> 0.019765405 | AE23: Net Proceeds paid to Members (70%) | AF23: =SUM(AF20:AF21)*70% -> 2136890.7 | AS23: Turn Over | AT23: 40300.19
A24: Initial Replacement Reserves | B24: =-(B10*300)/2 -> -19050 | D24: initial replacement reserves deposit | E24: =-( $B$10 * $E$7 * $E$8 / 12 ) -> -44450 | G24: Contract Services | H24: ='Budget 2026'!B122 -> 5573.66 | I24: ='Budget 2026'!C122 -> 4898.04 | J24: ='Budget 2026'!D122 -> 4898.04 | K24: ='Budget 2026'!E122 -> 5573.66 | L24: ='Budget 2026'!F122 -> 4898.04 | M24: ='Budget 2026'!G122 -> 4898.04 | N24: ='Budget 2026'!H122 -> 5573.66 | O24: ='Budget 2026'!I122 -> 4898.04 | ... S24: ='Budget 2026'!M122 -> 4898.04 | T24: =SUM(H24:S24) -> 63554.09 | U24: =T24/$T$19 -> 0.033821745 | V24: =T24*(1+V$7) -> 64825.172 | W24: =V24/V$17 -> 0.034244674 | X24: =V24*(1+$X$7) -> 66121.675 | Y24: =X24/X$17 -> 0.033912202 | Z24: =X24*(1+$X$7) -> 67444.109 | AA24: =Z24/Z$17 -> 0.033582957 | AB24: =Z24*(1+$X$7) -> 68792.991 | AC24: =AB24/AB$17 -> 0.033256909 | AE24: Net Proceeds paid to Manager (30%) | AF24: =SUM(AF20:AF21)*30% -> 915810.31 | AS24: Utilities
G25: Repair and Maintenance | H25: ='Budget 2026'!B110 -> 3327 | I25: ='Budget 2026'!C110 -> 3327 | J25: ='Budget 2026'!D110 -> 3327 | K25: ='Budget 2026'!E110 -> 3327 | L25: ='Budget 2026'!F110 -> 3327 | M25: ='Budget 2026'!G110 -> 3327 | N25: ='Budget 2026'!H110 -> 3327 | O25: ='Budget 2026'!I110 -> 3327 | ... S25: ='Budget 2026'!M110 -> 3327 | T25: =SUM(H25:S25) -> 39924 | U25: =T25/$T$19 -> 0.021246459 | V25: =T25*(1+V$7) -> 40722.48 | W25: =V25/V$17 -> 0.021512138 | X25: =V25*(1+$X$7) -> 41536.93 | Y25: =X25/X$17 -> 0.021303283 | Z25: =X25*(1+$X$7) -> 42367.668 | AA25: =Z25/Z$17 -> 0.021096455 | AB25: =Z25*(1+$X$7) -> 43215.022 | AC25: =AB25/AB$17 -> 0.020891635 | AS25: Gas & Electric | AT25: 34323.46
G26: Turn Over | H26: ='Budget 2026'!B86 -> 2210 | I26: ='Budget 2026'!C86 -> 2210 | J26: ='Budget 2026'!D86 -> 1610 | K26: ='Budget 2026'!E86 -> 3110 | L26: ='Budget 2026'!F86 -> 1910 | M26: ='Budget 2026'!G86 -> 1910 | N26: ='Budget 2026'!H86 -> 2510 | O26: ='Budget 2026'!I86 -> 5210 | ... S26: ='Budget 2026'!M86 -> 3110 | T26: =SUM(H26:S26) -> 31870 | U26: =T26/$T$19 -> 0.016960341 | V26: =T26*(1+V$7) -> 32507.4 | W26: =V26/V$17 -> 0.017172424 | X26: =V26*(1+$X$7) -> 33157.548 | Y26: =X26/X$17 -> 0.017005701 | Z26: =X26*(1+$X$7) -> 33820.699 | AA26: =Z26/Z$17 -> 0.016840597 | AB26: =Z26*(1+$X$7) -> 34497.113 | AC26: =AB26/AB$17 -> 0.016677096 | AS26: Trash Removal
G27: Utilities | H27: ='Budget 2026'!B131 -> 5028.88 | I27: ='Budget 2026'!C131 -> 5028.88 | J27: ='Budget 2026'!D131 -> 5028.88 | K27: ='Budget 2026'!E131 -> 5028.88 | L27: ='Budget 2026'!F131 -> 5028.88 | M27: ='Budget 2026'!G131 -> 5028.88 | N27: ='Budget 2026'!H131 -> 5028.88 | O27: ='Budget 2026'!I131 -> 5028.88 | ... S27: ='Budget 2026'!M131 -> 5028.88 | T27: =SUM(H27:S27) -> 60346.56 | U27: =T27/$T$19 -> 0.032114786 | V27: =T27*(1+V$7) -> 61553.491 | W27: =V27/V$17 -> 0.03251637 | X27: =V27*(1+$X$7) -> 62784.561 | Y27: =X27/X$17 -> 0.032200677 | Z27: =X27*(1+$X$7) -> 64040.252 | AA27: =Z27/Z$17 -> 0.031888049 | AB27: =Z27*(1+$X$7) -> 65321.057 | AC27: =AB27/AB$17 -> 0.031578456 | AS27: Water and Sewer | AT27: 41380.97
A28: Total Charges | B28: =SUM(B22:B26) -> -11129781 | D28: Total Charges | E28: =SUM($E$22:$E$24) -> -11532302 | G28: General/Admin | H28: ='Budget 2026'!B77 -> 2781.05 | I28: ='Budget 2026'!C77 -> 3093.77 | J28: ='Budget 2026'!D77 -> 2297.05 | K28: ='Budget 2026'!E77 -> 7597.05 | L28: ='Budget 2026'!F77 -> 2997.4 | M28: ='Budget 2026'!G77 -> 2297.05 | N28: ='Budget 2026'!H77 -> 2297.05 | O28: ='Budget 2026'!I77 -> 4497.05 | ... S28: ='Budget 2026'!M77 -> 2297.05 | T28: =SUM(H28:S28) -> 37771.77 | U28: =T28/$T$19 -> 0.020101101 | V28: =T28*(1+V$7) -> 38527.205 | W28: =V28/V$17 -> 0.020352458 | X28: =V28*(1+$X$7) -> 39297.75 | Y28: =X28/X$17 -> 0.020154862 | Z28: =X28*(1+$X$7) -> 40083.704 | AA28: =Z28/Z$17 -> 0.019959183 | AB28: =Z28*(1+$X$7) -> 40885.379 | AC28: =AB28/AB$17 -> 0.019765405 | AS28: General/Admin | AT28: 52530.16
A29: B. Cash out (in) | B29: =SUM(B20:B26) -> 2919039.5 | D29: Cash Out | E29: =$E$20+$E$28 -> 3164022 | G29: Insurance | H29: ='Budget 2026'!B133 -> 8500 | I29: ='Budget 2026'!C133 -> 8500 | J29: ='Budget 2026'!D133 -> 8500 | K29: ='Budget 2026'!E133 -> 8500 | L29: ='Budget 2026'!F133 -> 8500 | M29: ='Budget 2026'!G133 -> 8500 | N29: ='Budget 2026'!H133 -> 8500 | O29: ='Budget 2026'!I133 -> 8500 | ... S29: ='Budget 2026'!M133 -> 8500 | T29: =SUM(H29:S29) -> 102000 | U29: =T29/$T$19 -> 0.054281605 | V29: =T29*(1+V$7) -> 104040 | W29: =V29/V$17 -> 0.054960378 | X29: =V29*(1+$X$7) -> 106120.8 | Y29: =X29/X$17 -> 0.054426782 | Z29: =X29*(1+$X$7) -> 108243.22 | AA29: =Z29/Z$17 -> 0.053898366 | AB29: =Z29*(1+$X$7) -> 110408.08 | AC29: =AB29/AB$17 -> 0.053375081 | AE29: Year | AF29: Contributions | AG29: Return of Capital | AH29: Pref. Returns | AI29: Cash Flow | AJ29: Cash On Cash | AK29: Sale Proceeds | AL29: Total | AS29: Insurance | AT29: 206902.04
A30: New Debt Service | G30: RE Taxes | H30: ='Budget 2026'!B134 -> 12640 | I30: ='Budget 2026'!C134 -> 12640 | J30: ='Budget 2026'!D134 -> 12640 | K30: ='Budget 2026'!E134 -> 12640 | L30: ='Budget 2026'!F134 -> 12640 | M30: ='Budget 2026'!G134 -> 12640 | N30: ='Budget 2026'!H134 -> 12640 | O30: ='Budget 2026'!I134 -> 12640 | ... S30: ='Budget 2026'!M134 -> 12640 | T30: =SUM(H30:S30) -> 151680 | U30: =T30/$T$19 -> 0.08071994 | V30: =T30*(1+V$7) -> 154713.6 | W30: =V30/V$17 -> 0.081729314 | X30: =V30*(1+$X$7) -> 157807.87 | Y30: =X30/X$17 -> 0.080935826 | Z30: =X30*(1+$X$7) -> 160964.03 | AA30: =Z30/Z$17 -> 0.080150041 | AB30: =Z30*(1+$X$7) -> 164183.31 | AC30: =AB30/AB$17 -> 0.079371885 | AE30: 45292 | AF30: -6047500 | AG30: 0 | AH30: 0 | AI30: 0 | AJ30: 0 | AL30: =AF30 -> -6047500 | AS30: RE Taxes | AT30: 164042.76
A31: Amortized Per Annum | B31: =PMT(B13/12,30*12,B20)*12 -> -933026.77 | D31: Amortized Per Annum | E31: =PMT($E$3/12,$E$11,$E$20)*12 -> -1035343.9 | G31: Payroll | H31: ='Budget 2026'!B151 -> 12241.7 | I31: ='Budget 2026'!C151 -> 12241.7 | J31: ='Budget 2026'!D151 -> 12991.7 | K31: ='Budget 2026'!E151 -> 12241.7 | L31: ='Budget 2026'!F151 -> 12241.7 | M31: ='Budget 2026'!G151 -> 12991.7 | N31: ='Budget 2026'!H151 -> 12241.7 | O31: ='Budget 2026'!I151 -> 12241.7 | ... S31: ='Budget 2026'!M151 -> 15491.7 | T31: =SUM(H31:S31) -> 152400.4 | U31: =T31/$T$19 -> 0.081103317 | V31: =T31*(1+V$7) -> 155448.41 | W31: =V31/V$17 -> 0.082117486 | X31: =V31*(1+$X$7) -> 158557.38 | Y31: =X31/X$17 -> 0.081320228 | Z31: =X31*(1+$X$7) -> 161728.52 | AA31: =Z31/Z$17 -> 0.080530712 | AB31: =Z31*(1+$X$7) -> 164963.09 | AC31: =AB31/AB$17 -> 0.07974886 | AE31: 45658 | AG31: 0 | AH31: 0 | AI31: 0 | AJ31: 0 | AL31: 0 | AS31: Legal | AT31: 3951.5
A32: Monthly Debt Service | B32: =B31/12 -> -77752.231 | D32: =A32 -> Monthly Debt Service | E32: =PMT($E$3/12,$E$11,$E$20) -> -86278.661 | G32: Total Expenses | H32: =SUM(H22:H31) -> 60364.29 | I32: =SUM(I22:I31) -> 59533.16 | J32: =SUM(J22:J31) -> 58089.72 | K32: =SUM(K22:K31) -> 70438.158 | L32: =SUM(L22:L31) -> 59342.111 | M32: =SUM(M22:M31) -> 58696.952 | N32: =SUM(N22:N31) -> 59257.033 | O32: =SUM(O22:O31) -> 65689.157 | ... T32: =SUM(T22:T31) -> 734656.41 | U32: =T32/$T$19 -> 0.39096401 | V32: =SUM(V23:V31) -> 690864.96 | W32: =V32/V19 -> 0.32653046 | X32: =SUM(X23:X31) -> 704682.26 | Y32: =X32/X$17 -> 0.36141442 | Z32: =SUM(Z23:Z31) -> 718775.91 | AA32: =Z32/Z$17 -> 0.35790554 | AB32: =SUM(AB23:AB31) -> 733151.42 | AC32: =AB32/AB$17 -> 0.35443073 | AE32: 46023 | AG32: =B58 -> 2479039.5 | AH32: 0 | AI32: =T57 -> 136219.65 | AJ32: =AI32/$AG$37 -> 0.022524953 | AL32: =SUM(AG32:AI32) -> 2615259.2 | AS32: Payroll | AT32: 96128.71
A33: Effective LTV | B33: =B20/B19 -> 0.75 | D33: =A33 -> Effective LTV | E33: =$E$20/$B$19 -> 0.78456713 | AE33: 46388 | AG33: 0 | AH33: =V52 -> 0 | AI33: =V57 -> 319355.15 | AJ33: =AI33/$AG$37 -> 0.052807797 | AL33: =SUM(AG33:AI33) -> 319355.15 | AS33: PM Fees | AT33: 126907.18
A34: Debt Yield | B34: =B17/B20 -> 0.086666667 | D34: =A34 -> Debt Yield | E34: =$B$17/$E$20 -> 0.082848233 | G34: Net Operating Income | H34: =H19-H32 -> 79681.91 | I34: =I19-I32 -> 81876.68 | J34: =J19-J32 -> 78283.324 | K34: =K19-K32 -> 90322.448 | L34: =L19-L32 -> 100714.26 | M34: =M19-M32 -> 101544.12 | N34: =N19-N32 -> 102132.73 | O34: =O19-O32 -> 95958.752 | ... T34: =T19-T32 -> 1144433.2 | U34: =T34/T19 -> 0.60903599 | V34: =V19-V32 -> 1424910 | W34: =V34/V19 -> 0.67346954 | X34: =X19-X32 -> 1474565.9 | Y34: =X34/X19 -> 0.67663974 | Z34: =Z19-Z32 -> 1525849.7 | AA34: =Z34/Z19 -> 0.67977916 | AB34: =AB19-AB32 -> 1578813 | AC34: =AB34/AB19 -> 0.6828881 | AE34: 46753 | AG34: 0 | AH34: =X52 -> 0 | AI34: =X57 -> 353225.69 | AJ34: =AI34/$AG$37 -> 0.058408547 | AL34: =SUM(AG34:AI34) -> 353225.69 | AS34: Deposit to Replacement Reserves | AT34: 0
A35: DSCR | B35: =B17/ABS(B31) -> 1.304962 | C35: =IF(B35>=B11,"OK","DSCR FAIL") -> OK | D35: =A35 -> DSCR | E35: =$B$17/ABS($E$31) -> 1.176 | AE35: 47119 | AG35: 0 | AH35: 0 | AI35: =Z57 -> 388209.07 | AJ35: =AI35/$AG$37 -> 0.064193314 | AL35: =AG35+AI35+AK35 -> 388209.07
G36: Debt Service | AE36: 47484 | AG36: =AF10 -> 3568460.5 | AH36: 0 | AI36: =AB57 -> 424340.6 | AJ36: =AI36/$AG$37 -> 0.070167937 | AK36: =AF23 -> 2136890.7 | AL36: =AG36+AI36+AK36 -> 6129691.8
A37: Interest Only Period | G37: Senior Loan Principal | AG37: =SUM(AG30:AG36) -> 6047500 | AH37: =SUM(AH30:AH35) -> 0 | AI37: =SUM(AI30:AI36) -> 1621350.2 | AJ37: =AVERAGE(AJ30:AJ36) -> 0.038300364 | AL37: =AG37+AH37+AK37 -> 6047500
A38: Interest Only | B38: =-B20*B13 -> -740372.86 | G38: Senior Loan Interest | H38: 78585 | I38: 78585 | J38: 78585 | K38: 78585 | L38: 78585 | M38: 78585 | N38: 78585 | O38: 78585 | P38: =-$B$39 -> 61697.738 | Q38: =-$B$39 -> 61697.738 | R38: =-$B$39 -> 61697.738 | S38: =-$B$39 -> 61697.738 | T38: =SUM(H38:S38) -> 875470.95 | V38: =-B39*12 -> 740372.86 | X38: =V38 -> 740372.86 | Z38: =X38 -> 740372.86 | AB38: =Z38 -> 740372.86 | AK38: IRR | AL38: =XIRR(AL30:AL36, AE30:AE36) -> 0.11192712 | AS38: Advertising | AT38: 3631 | AU38: 3812 | AV38: 2936.62
A39: Monthly I/O | B39: =B38/12 -> -61697.738 | G39: Short term Mezz Debt Interest | H39: =B67 -> 0 | I39: =D67 -> 0 | J39: =G67 -> 0 | K39: =H67 -> 0 | L39: =I67 -> 0 | M39: =J67 -> 0 | N39: =K67 -> 0 | O39: =L67 -> 0 | P39: =M67 -> 0 | Q39: =N67 -> 0 | ... S39: =P67 -> 0 | T39: =SUM(H39:S39) -> 0 | V39: =-B67 -> 0 | X39: =-B67 -> 0 | Z39: =-G61 -> 0 | AB39: =-I61 -> 0 | AS39: Contract Services | AT39: 0 | AU39: 0 | AV39: 0
AS40: Repair and Maintenance | AT40: 10385.34 | AU40: 9136.84 | AV40: 12365.79
G41: Total Debt Service | H41: =SUM(H37:H40) -> 78585 | I41: =SUM(I37:I40) -> 78585 | J41: =SUM(J37:J40) -> 78585 | K41: =SUM(K37:K40) -> 78585 | L41: =SUM(L37:L40) -> 78585 | M41: =SUM(M37:M40) -> 78585 | N41: =SUM(N37:N40) -> 78585 | O41: =SUM(O37:O40) -> 78585 | ... T41: =SUM(T37:T40) -> 875470.95 | V41: =SUM(V37:V40) -> 740372.86 | X41: =SUM(X37:X40) -> 740372.86 | Z41: =SUM(Z37:Z40) -> 740372.86 | AB41: =SUM(AB37:AB40) -> 740372.86 | AS41: Turn Over | AT41: 0 | AU41: 0 | AV41: 0
A42: Souces and Uses | D42: Souces and Uses | AS42: Utilities | AT42: 8844.79 | AU42: 7754.52 | AV42: 7885.53
A43: Source(s) | D43: Source(s) | G43: Asset Management Fee @ 2% | H43: =H19*0.02 -> 2800.924 | I43: =I19*0.02 -> 2828.1968 | J43: =J19*0.02 -> 2727.4609 | K43: =K19*0.02 -> 3215.2121 | L43: =L19*0.02 -> 3201.1275 | M43: =M19*0.02 -> 3204.8215 | N43: =N19*0.02 -> 3227.7953 | O43: =O19*0.02 -> 3232.9582 | ... S43: =S19*0.02 -> 3313.3994 | T43: =SUM((H43:S43)) -> 37581.792 | V43: =V19*2% -> 42315.499 | X43: =X19*2% -> 43584.964 | Z43: =Z19*2% -> 44892.513 | AB43: =AB19*2% -> 46239.288 | AS43: General / Admin | AT43: 2899.94 | AU43: 1765.76 | AV43: 1965.88
G44: Capex Expenses | I44: 0 | J44: 0 | K44: 0 | L44: 0 | M44: 0 | N44: 0 | O44: 0 | P44: 0 | Q44: 0 | R44: 0 | S44: 0 | T44: =SUM((H44:S44)) -> 0 | V44: 150000 | X44: 150000 | Z44: 150000 | AB44: 150000 | AS44: Insurance + RE Taxes | AT44: 8137.21 | AU44: 5762.21 | AV44: 28312.52
A45: Senior Loan Proceeds | B45: =B20 -> 14048821 | D45: Senior Loan Proceeds | E45: =E20 -> 14696324 | G45: Replace Reserve Deposits | H45: 3000 | I45: 3000 | J45: 3000 | K45: 3000 | L45: 3000 | M45: 3000 | N45: 3000 | O45: 3000 | P45: 3000 | Q45: 3000 | R45: 3000 | S45: 3000 | T45: =SUM((H45:S45)) -> 36000 | V45: =T45 -> 36000 | X45: =T45 -> 36000 | Z45: =V45 -> 36000 | AB45: =X45 -> 36000 | AS45: Legal | AT45: 0 | AU45: 0 | AV45: 0
A46: Mezz/HML | B46: =B62 -> 0 | D46: Mezz/HML | E46: =E62 -> 0 | G46: Cash Flow available for Distribution | H46: =H34-(H41+SUM(H43:H45)) -> -4704.014 | I46: =I34-(I41+SUM(I43:I45)) -> -2536.5168 | J46: =J34-(J41+SUM(J43:J45)) -> -6029.1365 | K46: =K34-(K41+SUM(K43:K45)) -> 5522.2355 | L46: =L34-(L41+SUM(L43:L45)) -> 15928.134 | M46: =M34-(M41+SUM(M43:M45)) -> 16754.302 | N46: =N34-(N41+SUM(N43:N45)) -> 17319.937 | O46: =O34-(O41+SUM(O43:O45)) -> 11140.794 | ... S46: =S34-(S41+SUM(S43:S45)) -> 35099.014 | T46: =SUM(H46:S46) -> 194599.5 | V46: =V34-(V41+SUM(V43:V45)) -> 456221.64 | X46: =X34-(X41+SUM(X43:X45)) -> 504608.13 | Z46: =Z34-(Z41+SUM(Z43:Z45)) -> 554584.38 | AB46: =AB34-(AB41+SUM(AB43:AB45)) -> 606200.85 | AS46: Payroll | AT46: 40279.51 | AU46: 33188.81 | AV46: 20662.99
A47: Total Sources | B47: =SUM(B45:B46) -> 14048821 | D47: Total Sources | E47: =SUM(E45:E46) -> 14696324 | AS47: PM Fees | AT47: 4500 | AU47: 4500 | AV47: 4500
A48: Uses | D48: Uses | G48: Distributions from Cash Flow | H48: =IF(H46>0, H46,0) -> 0 | I48: =IF(I46>0, I46,0) -> 0 | J48: =IF(J46>0, J46,0) -> 0 | K48: =IF(K46>0, K46,0) -> 5522.2355 | L48: =IF(L46>0, L46,0) -> 15928.134 | M48: =IF(M46>0, M46,0) -> 16754.302 | N48: =IF(N46>0, N46,0) -> 17319.937 | O48: =IF(O46>0, O46,0) -> 11140.794 | ... T48: =IF(T46>0, T46,0) -> 194599.5 | AS48: Deposit to Replacement Reserves | AT48: 0 | AU48: 0 | AV48: 0
A49: Existing Loan Payoff | B49: =B22 -> -10899999 | D49: Existing Loan Payoff | E49: =E22 -> -10899999
A50: =A21 -> Closing Charges | B50: =B23+B24 -> -229782.31 | D50: Closing Charges | E50: =E23+E24 -> -632302.96 | G50: Members Preferred Return Due | H50: 0 | I50: 0 | J50: 0 | K50: 0 | L50: 0 | M50: 0 | N50: 0 | O50: 0 | P50: 0 | Q50: 0 | R50: 0 | S50: 0 | T50: =SUM(H50:S50) -> 0 | V50: 0 | X50: 0 | Z50: 0 | AB50: 0
A51: D. Existing GP Loans | B51: -150000 | D51: D. Existing GP Loans | E51: -150000 | G51: Members Preferred Return Deficiency | H51: 0 | I51: 0 | J51: 0 | K51: 0 | L51: 0 | M51: 0 | N51: 0 | O51: 0 | P51: 0 | Q51: 0 | R51: 0 | S51: 0 | T51: =SUM(H51:S51) -> 0 | V51: 0 | X51: 0 | Z51: 0 | AB51: 0
A52: E. Accrued AM Fees | B52: -90000 | D52: E. Accrued AM Fees | E52: -90000 | G52: Members Prefered Return Paid | H52: 0 | I52: 0 | J52: 0 | K52: 0 | L52: 0 | M52: 0 | N52: 0 | O52: 0 | P52: 0 | Q52: 0 | R52: 0 | S52: 0 | T52: =SUM(H52:S52) -> 0 | V52: 0 | X52: 0 | Z52: 0 | AB52: 0
A53: F. LP's Unpaid pref (Class A at 10%) | B53: 0 | D53: F. LP's Unpaid pref (Class A at 10%) | E53: 0 | G53: Members Prefered Return Deffered | H53: 0 | I53: 0 | J53: 0 | K53: 0 | L53: 0 | M53: 0 | N53: 0 | O53: 0 | P53: 0 | Q53: 0 | R53: 0 | S53: 0 | T53: =SUM(H53:S53) -> 0 | V53: 0 | X53: 0 | Z53: 0 | AB53: 0
A54: G. Operating Reserves | B54: 0 | D54: G. Operating Reserves | E54: 0
A55: K. Capex | B55: -200000 | D55: K. Capex | E55: -200000
A56: Total Uses | B56: =SUM(B49:B55) -> -11569781 | D56: Total Uses | E56: =SUM(E49:E55) -> -11972302 | G56: Excess Cash Flow | H56: =H46 -> -4704.014 | I56: =I46 -> -2536.5168 | J56: =J46 -> -6029.1365 | K56: =K46 -> 5522.2355 | L56: =L46 -> 15928.134 | M56: =M46 -> 16754.302 | N56: =N46 -> 17319.937 | O56: =O46 -> 11140.794 | ... T56: =T46 -> 194599.5 | V56: =V46 -> 456221.64 | X56: =X46 -> 504608.13 | Z56: =Z46 -> 554584.38 | AB56: =AB46 -> 606200.85
G57: Distributed to Members (70%) | H57: =IF(H$46>0, H$46*0.7, 0) -> 0 | I57: =IF(I$46>0, I$46*0.7, 0) -> 0 | J57: =IF(J$46>0, J$46*0.7, 0) -> 0 | K57: =IF(K$46>0, K$46*0.7, 0) -> 3865.5648 | L57: =IF(L$46>0, L$46*0.7, 0) -> 11149.694 | M57: =IF(M$46>0, M$46*0.7, 0) -> 11728.012 | N57: =IF(N$46>0, N$46*0.7, 0) -> 12123.956 | O57: =IF(O$46>0, O$46*0.7, 0) -> 7798.5555 | ... T57: =IF(T$46>0, T$46*0.7, 0) -> 136219.65 | V57: =IF(V$46>0, V$46*0.7, 0) -> 319355.15 | X57: =IF(X$46>0, X$46*0.7, 0) -> 353225.69 | Z57: =IF(Z$46>0, Z$46*0.7, 0) -> 388209.07 | AB57: =IF(AB$46>0, AB$46*0.7, 0) -> 424340.6
A58: Return of Capital to Members | B58: =IF(B47>B56, B47+B56, 0) -> 2479039.5 | D58: Return of Capital to Members | E58: =IF(E47>E56, E47+E56, 0) -> 2724022 | G58: Distributed to Manager (30%) | H58: =IF(H$46>0, H$46*0.3, 0) -> 0 | I58: =IF(I$46>0, I$46*0.3, 0) -> 0 | J58: =IF(J$46>0, J$46*0.3, 0) -> 0 | K58: =IF(K$46>0, K$46*0.3, 0) -> 1656.6706 | L58: =IF(L$46>0, L$46*0.3, 0) -> 4778.4402 | M58: =IF(M$46>0, M$46*0.3, 0) -> 5026.2907 | N58: =IF(N$46>0, N$46*0.3, 0) -> 5195.9811 | O58: =IF(O$46>0, O$46*0.3, 0) -> 3342.2381 | ... T58: =IF(T$46>0, T$46*0.3, 0) -> 58379.85 | V58: =IF(V$46>0, V$46*0.3, 0) -> 136866.49 | X58: =IF(X$46>0, X$46*0.3, 0) -> 151382.44 | Z58: =IF(Z$46>0, Z$46*0.3, 0) -> 166375.31 | AB58: =IF(AB$46>0, AB$46*0.3, 0) -> 181860.26
A60: Short term Pref/Mezz Debt
A61: Sources
A62: Loan | B62: =IF(ABS(B56)>B45, ABS(B56+B45), 0) -> 0
A63: Origination @ 2.5% | B63: =B62*2.5% -> 0
A64: Legal and Closing @ 1% | B64: =B62*1% -> 0
A65: Current Interest Rate | B65: 0.08
A66: Defferred Interest Rate | B66: 0.06
A67: Annual Current Interest | B67: =B62*B65 -> 0
A68: Annual Deferred Interest | B68: =B62*B66 -> 0

Sheet Proforma FOR BUDGET 2026
A2: Debt Sizing Tool | Y2: SALE
E3: Year 3 | S3: 2027 | U3: 2028 | W3: 2029 | Y3: 2030
E4: ='Budget 2026'!B1 -> 46023 | F4: ='Budget 2026'!C1 -> 46054 | G4: ='Budget 2026'!D1 -> 46082 | H4: ='Budget 2026'!E1 -> 46113 | I4: ='Budget 2026'!F1 -> 46143 | J4: ='Budget 2026'!G1 -> 46174 | K4: ='Budget 2026'!H1 -> 46204 | L4: ='Budget 2026'!I1 -> 46235 | ... P4: ='Budget 2026'!M1 -> 46357 | Q4: Total | S4: Year 4 | U4: Year 5 | W4: Year 6 | Y4: Year 7 | AB4: EXIT at Year 7
A5: T-5 Treasury | B5: 0.0372 | D5: Financial Assumptions | L5: REFINANCE | AO5: Source | AP5: Source | AQ5: Source | AR5: Source | AS5: Source | AT5: Source | AU5: Source | AV5: Source | AW5: Source
A6: Spread | B6: 0.0155 | D6: Annual Rent Escalator | S6: 0.04 | U6: 0.03 | W6: 0.03 | Y6: 0.03 | AB6: Sale | AO6: T-12 | AP6: T-12 | AQ6: T-12 | AR6: T-12
B7: =SUM(B5:B6) -> 0.0527 | D7: Annual Expense Escalator | S7: 0.02 | U7: 0.02 | W7: 0.02 | Y7: 0.02 | AB7: Net Operating Income | AC7: =W34 -> 1525849.7 | AE7: Capital Invested | AI7: =AD37 -> 6047500 | AO7: Sept-25 | AP7: 46320 | AQ7: 46351 | AR7: DEC | AS7: JAN | AT7: FEB | AU7: MAR | AV7: APR | AW7: MAY
AB8: Exit Cap Rate | AC8: 0.07 | AE8: Limited Partner Returns
A9: Refinance - Agency | D9: INCOME | Q9: In-Place Rent | S9: In-Place Rent | U9: In-Place Rent | W9: In-Place Rent | Y9: In-Place Rent | AB9: Insurance/Tax/Lender Escrows | AC9: 0 | AE9: Return of Capital | AI9: =AD37 -> 6047500
A10: Units | B10: 127 | D10: Average In-Place Rent | Q10: =(Q17/$B$10)/12 -> 1092.4429 | S10: =(S17/$B$10)/12 -> 1242.126 | U10: =(U17/$B$10)/12 -> 1279.3898 | W10: =(W17/$B$10)/12 -> 1317.7715 | Y10: =(Y17/$B$10)/12 -> 1357.3047 | AB10: Total Equity Outstanding | AC10: =-AC30-AD32 -> 5230711 | AE10: Preferred returns | AI10: =AE37 -> 0
A11: Min DSCR | B11: 1.25 | D11: Gross Potential Rent (GPR) | E11: ='Budget 2026'!B2 -> 159666 | F11: ='Budget 2026'!C2 -> 159666 | G11: ='Budget 2026'!D2 -> 159666 | H11: ='Budget 2026'!E2 -> 159666 | I11: ='Budget 2026'!F2 -> 159666 | J11: ='Budget 2026'!G2 -> 159666 | K11: ='Budget 2026'!H2 -> 159666 | L11: ='Budget 2026'!I2 -> 159666 | ... P11: ='Budget 2026'!M2 -> 159666 | Q11: =SUM(E11:P11) -> 1915992 | S11: =Q11*(1+S6) -> 1992631.7 | U11: =S11*(1+U6) -> 2052410.6 | W11: =U11*(1+W6) -> 2113982.9 | Y11: =W11*(1+Y6) -> 2177402.4 | AE11: From Cash Flow | AI11: =AF37 -> 1806307.1
A12: Max LTV | B12: 0.75 | D12: - Vacancy | E12: ='Budget 2026'!B7 -> -14165.28 | F12: ='Budget 2026'!C7 -> -9443.52 | G12: ='Budget 2026'!D7 -> -4733.5644 | H12: ='Budget 2026'!E7 -> -4739.718 | I12: ='Budget 2026'!F7 -> -4745.8797 | J12: ='Budget 2026'!G7 -> -4752.0493 | K12: ='Budget 2026'!H7 -> -4760.603 | L12: ='Budget 2026'!I7 -> -4769.1721 | ... P12: ='Budget 2026'!M7 -> -3589.7713 | Q12: =SUM(E12:P12) -> -66455.961 | R12: =ABS(Q12/$Q$11) -> 0.034684885 | S12: =-S11*T12 -> -19926.317 | T12: 0.01 | U12: =-U11*V12 -> -41048.213 | V12: 0.02 | W12: =-W11*X12 -> -42279.659 | X12: 0.02 | Y12: =-Y11*Z12 -> -43548.049 | Z12: 0.02 | AB12: Sales Price | AC12: =AC7/AC8 -> 21797854 | AD12: =AC12/B10 -> 171636.64 | AE12: From Sales Proceeds | AI12: =AH36 -> 2151056.8 | AO12: Source | AP12: Source | AQ12: Source | AR12: Source | AS12: Source | AT12: Source | AU12: Source | AV12: Source | AW12: Source
A13: Interest rate | B13: =B7 -> 0.0527 | D13: - Concessions, Loss to Lease, Bad Debt | Q13: =SUM(E13:P13) -> 0 | S13: =-S11*T13 -> -79705.267 | T13: 0.04 | U13: =-U11*V13 -> -61572.319 | V13: 0.03 | W13: =-W11*X13 -> -63419.488 | X13: 0.03 | Y13: =-Y11*Z13 -> -65322.073 | Z13: 0.03 | AB13: Operating Reserves Remaining | AC13: =SUM(Q45:Y45) -> 180000 | AD13: =AC13/B10 -> 1417.3228 | AE13: Total Distributions | AI13: =SUM(AI9:AI12) -> 10004864 | AO13: T-12 | AP13: T-12 | AQ13: T-12 | AR13: T-12
A14: Cap rate | B14: 0.065 | D14: Consessions | E14: =SUM('Budget 2026'!B4:B6) -> -310 | F14: =SUM('Budget 2026'!C4:C6) -> -3851.32 | G14: =SUM('Budget 2026'!D4:D6) -> -10072.977 | H14: =SUM('Budget 2026'!E4:E6) -> -2087.3943 | I14: =SUM('Budget 2026'!F4:F6) -> -2979.5573 | J14: =SUM('Budget 2026'!G4:G6) -> -2983.0277 | K14: =SUM('Budget 2026'!H4:H6) -> -2095.2261 | L14: =SUM('Budget 2026'!I4:I6) -> -2098.4395 | ... P14: =SUM('Budget 2026'!M4:M6) -> -1207.4428 | Q14: =SUM(E14:P14) -> -32200.315 | R14: =ABS(Q14/$Q$11) -> 0.01680608 | AB14: Pref/Mezz Principal Payoff | AC14: =-B62 -> 0 | AO14: Sept-25 | AP14: 46320 | AQ14: 46351 | AR14: DEC | AS14: JAN | AT14: FEB | AU14: MAR | AV14: APR | AW14: MAY
A15: Income (MAY-JUL '26) | B15: =SUM(I19:K19)*4 -> 1926748.9 | D15: Loss To Lease | E15: ='Budget 2026'!B3 -> -9750.12 | F15: ='Budget 2026'!C3 -> -9750.12 | G15: ='Budget 2026'!D3 -> -9375.3303 | H15: ='Budget 2026'!E3 -> -9179.9524 | I15: ='Budget 2026'!F3 -> -8984.3206 | J15: ='Budget 2026'!G3 -> -8788.4344 | K15: ='Budget 2026'!H3 -> -8516.8548 | L15: ='Budget 2026'!I3 -> -8244.7863 | ... P15: ='Budget 2026'!M3 -> -7699.0155 | Q15: =SUM(E15:P15) -> -103932.52 | R15: =ABS(Q15/$Q$11) -> 0.054244754 | AB15: Defferred Interest Pref/Mezz Payoff | AC15: =-B68*3 -> 0 | AE15: LP Metrics | AN15: Gross Potential Rent (GPR) | AO15: 136185.3 | AP15: 139780.78 | AQ15: 143362 | AR15: =AQ15 -> 143362 | AS15: =AR15 -> 143362 | AT15: =AS15 -> 143362 | AU15: =AT15 -> 143362 | AV15: =AU15 -> 143362 | AW15: =AV15 -> 143362
A16: Expenses (MAY-JUL '26) | B16: 855000 | D16: Bad Debt | E16: ='Budget 2026'!B8 -> -11804.4 | F16: ='Budget 2026'!C8 -> -11804.4 | G16: ='Budget 2026'!D8 -> -15384.084 | H16: ='Budget 2026'!E8 -> -1184.9295 | I16: ='Budget 2026'!F8 -> -1186.4699 | J16: ='Budget 2026'!G8 -> -1188.0123 | K16: ='Budget 2026'!H8 -> -1190.1507 | L16: ='Budget 2026'!I8 -> -1192.293 | ... P16: ='Budget 2026'!M8 -> 0 | Q16: =SUM(E16:P16) -> -48520.208 | R16: =ABS(Q16/$Q$11) -> 0.025323805 | AB16: Sales Cost at 4% | AC16: =-AC12*4% -> -871914.14 | AD16: =AC16/B10 -> -6865.4657 | AE16: Equity Multiple | AI16: =(AI13/AI7) -> 1.6543801 | AN16: - Vacancy | AO16: -17406.1 | AP16: -5336.53 | AQ16: -8718.07 | AR16: -6599.14 | AS16: -3377 | AT16: -3377 | AU16: -3377 | AV16: -3377 | AW16: -3377
A17: NOI | B17: =B15-B16 -> 1071748.9 | D17: Gross Potential Income (GPI) | E17: =SUM(E11:E16) -> 123636.2 | F17: =SUM(F11:F16) -> 124816.64 | G17: =SUM(G11:G16) -> 120100.04 | H17: =SUM(H11:H16) -> 142474.01 | I17: =SUM(I11:I16) -> 141769.77 | J17: =SUM(J11:J16) -> 141954.48 | K17: =SUM(K11:K16) -> 143103.17 | L17: =SUM(L11:L16) -> 143361.31 | ... P17: =SUM(P11:P16) -> 147169.77 | Q17: =SUM(E17:P17) -> 1664883 | R17: =ABS(Q17/$Q$11) -> 0.86894048 | S17: =SUM(S11:S13) -> 1893000.1 | T17: =S17/S11 -> 0.95 | U17: =SUM(U11:U13) -> 1949790.1 | V17: =U17/U11 -> 0.95 | W17: =SUM(W11:W13) -> 2008283.8 | X17: =W17/W11 -> 0.95 | Y17: =SUM(Y11:Y13) -> 2068532.3 | Z17: =Y17/Y11 -> 0.95 | AB17: Outstanding Loan Balance | AC17: =-B20 -> -12366333 | AD17: =AC17/B10 -> -97372.7 | AE17: Cash On Cash | AI17: =AG37 -> 0.04266951 | AN17: - Concessions, Loss to Lease, Bad Debt | AO17: =SUM(AO18:AO20) -> -33231 | AP17: =SUM(AP18:AP20) -> -31462.9 | AQ17: =SUM(AQ18:AQ20) -> -13600 | AR17: =SUM(AR18:AR20) -> -20106.11 | AS17: =SUM(AS18:AS20) -> -13412 | AT17: =SUM(AT18:AT20) -> -13412 | AU17: =SUM(AU18:AU20) -> -11412 | AV17: =SUM(AV18:AV20) -> -8412 | AW17: =SUM(AW18:AW20) -> -6412
A18: Income to Expense Ratio | B18: =B16/B15 -> 0.4437527 | D18: Other Income | E18: ='Budget 2026'!B44 -> 16410 | F18: ='Budget 2026'!C44 -> 16593.2 | G18: ='Budget 2026'!D44 -> 16273 | H18: ='Budget 2026'!E44 -> 18286.6 | I18: ='Budget 2026'!F44 -> 18286.6 | J18: ='Budget 2026'!G44 -> 18286.6 | K18: ='Budget 2026'!H44 -> 18286.6 | L18: ='Budget 2026'!I44 -> 18286.6 | ... P18: ='Budget 2026'!M44 -> 18500.2 | Q18: =SUM(E18:P18) -> 214206.6 | R18: =ABS(Q18/$Q$11) -> 0.11179932 | S18: =Q18*(1+S6) -> 222774.86 | T18: =S18/S11 -> 0.11179932 | U18: =S18*(1+U6) -> 229458.11 | V18: =U18/U11 -> 0.11179932 | W18: =U18*(1+W6) -> 236341.85 | X18: =W18/W11 -> 0.11179932 | Y18: =W18*(1+Y6) -> 243432.11 | Z18: =Y18/Y11 -> 0.11179932 | AB18: Return of Member Capital | AC18: =-AC10 -> -5230711 | AE18: ARR | AI18: =(AI13/AI7)/7 -> 0.23634002 | AN18: Consessions | AO18: -17426 | AP18: =-(19220+410) -> -19630 | AQ18: =-(11590+310) -> -11900 | AR18: -919 | AS18: -1712 | AT18: -1712 | AU18: -1712 | AV18: -1712 | AW18: -1712
A19: Appraised Value | B19: =B17/B14 -> 16488444 | D19: Effective Gross Income | E19: =SUM(E17:E18) -> 140046.2 | F19: =SUM(F17:F18) -> 141409.84 | G19: =SUM(G17:G18) -> 136373.04 | H19: =SUM(H17:H18) -> 160760.61 | I19: =SUM(I17:I18) -> 160056.37 | J19: =SUM(J17:J18) -> 160241.08 | K19: =SUM(K17:K18) -> 161389.77 | L19: =SUM(L17:L18) -> 161647.91 | ... P19: =SUM(P17:P18) -> 165669.97 | Q19: =SUM(E19:P19) -> 1879089.6 | S19: =SUM(S17:S18) -> 2115775 | U19: =SUM(U17:U18) -> 2179248.2 | W19: =SUM(W17:W18) -> 2244625.7 | Y19: =SUM(Y17:Y18) -> 2311964.4 | AB19: Members Preferred Return Deficiency | AC19: =-U51 -> 0 | AE19: IRR | AI19: =AI38 -> 0.09917044 | AN19: Loss To Lease | AO19: =856 -> 856 | AP19: -158.9 | AQ19: -1700 | AR19: -4847.11 | AS19: -1700 | AT19: -1700 | AU19: -1700 | AV19: -1700 | AW19: -1700
A20: Refi proceeds | B20: =MIN( B19*B12, PV(B13/12,30*12,-(B17/B11)/12) ) -> 12366333 | AB20: Residual Cash After LP Capital + Pref | AC20: =SUM(AC12:AC19) -> 3508895.4 | AN20: Bad Debt | AO20: -16661 | AP20: -11674 | AQ20: 0 | AR20: -14340 | AS20: -10000 | AT20: -10000 | AU20: -8000 | AV20: -5000 | AW20: -3000
A21: Closing Charges | D21: EXPENSES | AB21: Exit Fee @ 2%of Sales price | AC21: =-AC12*2% -> -435957.07 | AN21: Gross Potential Income (GPI) | AO21: =SUM(AO15:AO17) -> 85548.2 | AP21: =SUM(AP15:AP17) -> 102981.35 | AQ21: =SUM(AQ15:AQ17) -> 121043.93 | AR21: =SUM(AR15:AR17) -> 116656.75 | AS21: =SUM(AS15:AS17) -> 126573 | AT21: =SUM(AT15:AT17) -> 126573 | AU21: =SUM(AU15:AU17) -> 128573 | AV21: =SUM(AV15:AV17) -> 131573 | AW21: =SUM(AW15:AW17) -> 133573
A22: Existing loan payoff | B22: -10899999 | D22: PM Fees | E22: ='Budget 2026'!B51 -> 4500 | F22: ='Budget 2026'!C51 -> 4500 | G22: ='Budget 2026'!D51 -> 4500 | H22: ='Budget 2026'!E51 -> 4822.8182 | I22: ='Budget 2026'!F51 -> 4801.6912 | J22: ='Budget 2026'!G51 -> 4807.2323 | K22: ='Budget 2026'!H51 -> 4841.693 | L22: ='Budget 2026'!I51 -> 4849.4373 | ... Q22: ='Budget 2026'!N51 -> 57337.816 | R22: =Q22/$Q$19 -> 0.030513614 | S22: =S19*3% -> 63473.249 | T22: =S22/S$17 -> 0.033530505 | U22: =S22*(1+$U$7) -> 64742.714 | V22: =U22/U$17 -> 0.033204966 | W22: =U22*(1+$U$7) -> 66037.568 | X22: =W22/W$17 -> 0.032882588 | Y22: =W22*(1+$U$7) -> 67358.319 | Z22: =Y22/Y$17 -> 0.032563339 | AB22: Net Proceeds to be distributed | AC22: =SUM(AC20:AC21) -> 3072938.3 | AN22: Other Income | AO22: 13112.8 | AP22: 13988.72 | AQ22: 17456.19 | AR22: 13773.1 | AS22: 14839 | AT22: 14839 | AU22: 14839 | AV22: 14839 | AW22: 14839
A23: Closing costs @ 1.5% | B23: =-B20*1.5% -> -185494.99 | D23: Advertising | E23: ='Budget 2026'!B96 -> 3562 | F23: ='Budget 2026'!C77 -> 3093.77 | G23: ='Budget 2026'!D77 -> 2297.05 | H23: ='Budget 2026'!E77 -> 7597.05 | I23: ='Budget 2026'!F77 -> 2997.4 | J23: ='Budget 2026'!G77 -> 2297.05 | K23: ='Budget 2026'!H77 -> 2297.05 | L23: ='Budget 2026'!I77 -> 4497.05 | M23: ='Budget 2026'!J77 -> 2597.05 | ... Q23: ='Budget 2026'!N77 -> 37771.77 | R23: =Q23/$Q$19 -> 0.020101101 | S23: =Q23*(1+S$7) -> 38527.205 | T23: =S23/S$17 -> 0.020352458 | U23: =S23*(1+$U$7) -> 39297.75 | V23: =U23/U$17 -> 0.020154862 | W23: =U23*(1+$U$7) -> 40083.704 | X23: =W23/W$17 -> 0.019959183 | Y23: =W23*(1+$U$7) -> 40885.379 | Z23: =Y23/Y$17 -> 0.019765405 | AB23: Net Proceeds paid to Members (70%) | AC23: =SUM(AC20:AC21)*70% -> 2151056.8 | AN23: Effective Gross Income | AO23: =SUM(AO21:AO22) -> 98661 | AP23: =SUM(AP21:AP22) -> 116970.07 | AQ23: =SUM(AQ21:AQ22) -> 138500.12 | AR23: =SUM(AR21:AR22) -> 130429.85 | AS23: =SUM(AS21:AS22) -> 141412 | AT23: =SUM(AT21:AT22) -> 141412 | AU23: =SUM(AU21:AU22) -> 143412 | AV23: =SUM(AV21:AV22) -> 146412 | AW23: =SUM(AW21:AW22) -> 148412
A24: Initial Replacement Reserves | B24: =-(B10*300)/2 -> -19050 | D24: Contract Services | E24: ='Budget 2026'!B122 -> 5573.66 | F24: ='Budget 2026'!C122 -> 4898.04 | G24: ='Budget 2026'!D122 -> 4898.04 | H24: ='Budget 2026'!E122 -> 5573.66 | I24: ='Budget 2026'!F122 -> 4898.04 | J24: ='Budget 2026'!G122 -> 4898.04 | K24: ='Budget 2026'!H122 -> 5573.66 | L24: ='Budget 2026'!I122 -> 4898.04 | ... P24: ='Budget 2026'!M122 -> 4898.04 | Q24: =SUM(E24:P24) -> 63554.09 | R24: =Q24/$Q$19 -> 0.033821745 | S24: =Q24*(1+S$7) -> 64825.172 | T24: =S24/S$17 -> 0.034244674 | U24: =S24*(1+$U$7) -> 66121.675 | V24: =U24/U$17 -> 0.033912202 | W24: =U24*(1+$U$7) -> 67444.109 | X24: =W24/W$17 -> 0.033582957 | Y24: =W24*(1+$U$7) -> 68792.991 | Z24: =Y24/Y$17 -> 0.033256909 | AB24: Net Proceeds paid to Manager (30%) | AC24: =SUM(AC20:AC21)*30% -> 921881.5 | AO24: Source
D25: Repair and Maintenance | E25: ='Budget 2026'!B110 -> 3327 | F25: ='Budget 2026'!C110 -> 3327 | G25: ='Budget 2026'!D110 -> 3327 | H25: ='Budget 2026'!E110 -> 3327 | I25: ='Budget 2026'!F110 -> 3327 | J25: ='Budget 2026'!G110 -> 3327 | K25: ='Budget 2026'!H110 -> 3327 | L25: ='Budget 2026'!I110 -> 3327 | ... P25: ='Budget 2026'!M110 -> 3327 | Q25: =SUM(E25:P25) -> 39924 | R25: =Q25/$Q$19 -> 0.021246459 | S25: =Q25*(1+S$7) -> 40722.48 | T25: =S25/S$17 -> 0.021512138 | U25: =S25*(1+$U$7) -> 41536.93 | V25: =U25/U$17 -> 0.021303283 | W25: =U25*(1+$U$7) -> 42367.668 | X25: =W25/W$17 -> 0.021096455 | Y25: =W25*(1+$U$7) -> 43215.022 | Z25: =Y25/Y$17 -> 0.020891635 | AO25: T-12
D26: Turn Over | E26: ='Budget 2026'!B86 -> 2210 | F26: ='Budget 2026'!C86 -> 2210 | G26: ='Budget 2026'!D86 -> 1610 | H26: ='Budget 2026'!E86 -> 3110 | I26: ='Budget 2026'!F86 -> 1910 | J26: ='Budget 2026'!G86 -> 1910 | K26: ='Budget 2026'!H86 -> 2510 | L26: ='Budget 2026'!I86 -> 5210 | ... P26: ='Budget 2026'!M86 -> 3110 | Q26: =SUM(E26:P26) -> 31870 | R26: =Q26/$Q$19 -> 0.016960341 | S26: =Q26*(1+S$7) -> 32507.4 | T26: =S26/S$17 -> 0.017172424 | U26: =S26*(1+$U$7) -> 33157.548 | V26: =U26/U$17 -> 0.017005701 | W26: =U26*(1+$U$7) -> 33820.699 | X26: =W26/W$17 -> 0.016840597 | Y26: =W26*(1+$U$7) -> 34497.113 | Z26: =Y26/Y$17 -> 0.016677096 | AN26: EXPENSES | AO26: T-12 Expenses
D27: Utilities | E27: ='Budget 2026'!B131 -> 5028.88 | F27: ='Budget 2026'!C131 -> 5028.88 | G27: ='Budget 2026'!D131 -> 5028.88 | H27: ='Budget 2026'!E131 -> 5028.88 | I27: ='Budget 2026'!F131 -> 5028.88 | J27: ='Budget 2026'!G131 -> 5028.88 | K27: ='Budget 2026'!H131 -> 5028.88 | L27: ='Budget 2026'!I131 -> 5028.88 | ... P27: ='Budget 2026'!M131 -> 5028.88 | Q27: =SUM(E27:P27) -> 60346.56 | R27: =Q27/$Q$19 -> 0.032114786 | S27: =Q27*(1+S$7) -> 61553.491 | T27: =S27/S$17 -> 0.03251637 | U27: =S27*(1+$U$7) -> 62784.561 | V27: =U27/U$17 -> 0.032200677 | W27: =U27*(1+$U$7) -> 64040.252 | X27: =W27/W$17 -> 0.031888049 | Y27: =W27*(1+$U$7) -> 65321.057 | Z27: =Y27/Y$17 -> 0.031578456 | AN27: Advertising | AO27: 31392.72
A28: Total Charges | B28: =SUM(B22:B26) -> -11104544 | D28: General/Admin | E28: ='Budget 2026'!B77 -> 2781.05 | F28: ='Budget 2026'!C77 -> 3093.77 | G28: ='Budget 2026'!D77 -> 2297.05 | H28: ='Budget 2026'!E77 -> 7597.05 | I28: ='Budget 2026'!F77 -> 2997.4 | J28: ='Budget 2026'!G77 -> 2297.05 | K28: ='Budget 2026'!H77 -> 2297.05 | L28: ='Budget 2026'!I77 -> 4497.05 | ... P28: ='Budget 2026'!M77 -> 2297.05 | Q28: =SUM(E28:P28) -> 37771.77 | R28: =Q28/$Q$19 -> 0.020101101 | S28: =Q28*(1+S$7) -> 38527.205 | T28: =S28/S$17 -> 0.020352458 | U28: =S28*(1+$U$7) -> 39297.75 | V28: =U28/U$17 -> 0.020154862 | W28: =U28*(1+$U$7) -> 40083.704 | X28: =W28/W$17 -> 0.019959183 | Y28: =W28*(1+$U$7) -> 40885.379 | Z28: =Y28/Y$17 -> 0.019765405 | AN28: Contract Services | AO28: 66947.02
A29: B. Cash out (in) | B29: =SUM(B20:B26) -> 1261789 | D29: Insurance | E29: ='Budget 2026'!B133 -> 8500 | F29: ='Budget 2026'!C133 -> 8500 | G29: ='Budget 2026'!D133 -> 8500 | H29: ='Budget 2026'!E133 -> 8500 | I29: ='Budget 2026'!F133 -> 8500 | J29: ='Budget 2026'!G133 -> 8500 | K29: ='Budget 2026'!H133 -> 8500 | L29: ='Budget 2026'!I133 -> 8500 | ... P29: ='Budget 2026'!M133 -> 8500 | Q29: =SUM(E29:P29) -> 102000 | R29: =Q29/$Q$19 -> 0.054281605 | S29: =Q29*(1+S$7) -> 104040 | T29: =S29/S$17 -> 0.054960378 | U29: =S29*(1+$U$7) -> 106120.8 | V29: =U29/U$17 -> 0.054426782 | W29: =U29*(1+$U$7) -> 108243.22 | X29: =W29/W$17 -> 0.053898366 | Y29: =W29*(1+$U$7) -> 110408.08 | Z29: =Y29/Y$17 -> 0.053375081 | AB29: Year | AC29: Contributions | AD29: Return of Capital | AE29: Pref. Returns | AF29: Cash Flow | AG29: Cash On Cash | AH29: Sale Proceeds | AI29: Total | AN29: Repair and Maintenance | AO29: 66031.47
A30: New Debt Service | C30: =IF(B35>=B11,"OK","DSCR FAIL") -> OK | D30: RE Taxes | E30: ='Budget 2026'!B134 -> 12640 | F30: ='Budget 2026'!C134 -> 12640 | G30: ='Budget 2026'!D134 -> 12640 | H30: ='Budget 2026'!E134 -> 12640 | I30: ='Budget 2026'!F134 -> 12640 | J30: ='Budget 2026'!G134 -> 12640 | K30: ='Budget 2026'!H134 -> 12640 | L30: ='Budget 2026'!I134 -> 12640 | ... P30: ='Budget 2026'!M134 -> 12640 | Q30: =SUM(E30:P30) -> 151680 | R30: =Q30/$Q$19 -> 0.08071994 | S30: =Q30*(1+S$7) -> 154713.6 | T30: =S30/S$17 -> 0.081729314 | U30: =S30*(1+$U$7) -> 157807.87 | V30: =U30/U$17 -> 0.080935826 | W30: =U30*(1+$U$7) -> 160964.03 | X30: =W30/W$17 -> 0.080150041 | Y30: =W30*(1+$U$7) -> 164183.31 | Z30: =Y30/Y$17 -> 0.079371885 | AB30: 45292 | AC30: -6047500 | AD30: 0 | AE30: 0 | AF30: 0 | AG30: 0 | AI30: =AC30 -> -6047500 | AN30: Turn Over | AO30: 40300.19
A31: Amortized Per Annum | B31: =PMT(B13/12,30*12,B20)*12 -> -821287.41 | D31: Payroll | E31: ='Budget 2026'!B151 -> 12241.7 | F31: ='Budget 2026'!C151 -> 12241.7 | G31: ='Budget 2026'!D151 -> 12991.7 | H31: ='Budget 2026'!E151 -> 12241.7 | I31: ='Budget 2026'!F151 -> 12241.7 | J31: ='Budget 2026'!G151 -> 12991.7 | K31: ='Budget 2026'!H151 -> 12241.7 | L31: ='Budget 2026'!I151 -> 12241.7 | ... P31: ='Budget 2026'!M151 -> 15491.7 | Q31: =SUM(E31:P31) -> 152400.4 | R31: =Q31/$Q$19 -> 0.081103317 | S31: =Q31*(1+S$7) -> 155448.41 | T31: =S31/S$17 -> 0.082117486 | U31: =S31*(1+$U$7) -> 158557.38 | V31: =U31/U$17 -> 0.081320228 | W31: =U31*(1+$U$7) -> 161728.52 | X31: =W31/W$17 -> 0.080530712 | Y31: =W31*(1+$U$7) -> 164963.09 | Z31: =Y31/Y$17 -> 0.07974886 | AB31: 45658 | AD31: 0 | AE31: 0 | AF31: 0 | AG31: 0 | AI31: 0 | AN31: Utilities
A32: Monthly Debt Service | B32: =B31/12 -> -68440.618 | D32: Total Expenses | E32: =SUM(E22:E31) -> 60364.29 | F32: =SUM(F22:F31) -> 59533.16 | G32: =SUM(G22:G31) -> 58089.72 | H32: =SUM(H22:H31) -> 70438.158 | I32: =SUM(I22:I31) -> 59342.111 | J32: =SUM(J22:J31) -> 58696.952 | K32: =SUM(K22:K31) -> 59257.033 | L32: =SUM(L22:L31) -> 65689.157 | ... Q32: =SUM(Q22:Q31) -> 734656.41 | R32: =Q32/$Q$19 -> 0.39096401 | S32: =SUM(S23:S31) -> 690864.96 | T32: =S32/S19 -> 0.32653046 | U32: =SUM(U23:U31) -> 704682.26 | V32: =U32/U$17 -> 0.36141442 | W32: =SUM(W23:W31) -> 718775.91 | X32: =W32/W$17 -> 0.35790554 | Y32: =SUM(Y23:Y31) -> 733151.42 | Z32: =Y32/Y$17 -> 0.35443073 | AB32: 46023 | AD32: =B58 -> 816788.97 | AE32: 0 | AF32: =Q57 -> 72908.643 | AG32: =AF32/$AD$37 -> 0.012055997 | AI32: =SUM(AD32:AF32) -> 889697.61 | AN32: Gas & Electric | AO32: 34323.46
A33: Effective LTV | B33: =B20/B19 -> 0.75 | AB33: 46388 | AD33: 0 | AE33: =S52 -> 0 | AF33: =S57 -> 381422.13 | AG33: =AF33/$AD$37 -> 0.063071042 | AI33: =SUM(AD33:AF33) -> 381422.13 | AN33: Trash Removal
A34: Debt Yield | B34: =B17/B20 -> 0.086666667 | D34: Net Operating Income | E34: =E19-E32 -> 79681.91 | F34: =F19-F32 -> 81876.68 | G34: =G19-G32 -> 78283.324 | H34: =H19-H32 -> 90322.448 | I34: =I19-I32 -> 100714.26 | J34: =J19-J32 -> 101544.12 | K34: =K19-K32 -> 102132.73 | L34: =L19-L32 -> 95958.752 | ... Q34: =Q19-Q32 -> 1144433.2 | R34: =Q34/Q19 -> 0.60903599 | S34: =S19-S32 -> 1424910 | T34: =S34/S19 -> 0.67346954 | U34: =U19-U32 -> 1474565.9 | V34: =U34/U19 -> 0.67663974 | W34: =W19-W32 -> 1525849.7 | X34: =W34/W19 -> 0.67977916 | Y34: =Y19-Y32 -> 1578813 | Z34: =Y34/Y19 -> 0.6828881 | AB34: 46753 | AD34: 0 | AE34: =U52 -> 0 | AF34: =U57 -> 415292.67 | AG34: =AF34/$AD$37 -> 0.068671793 | AI34: =SUM(AD34:AF34) -> 415292.67 | AN34: Water and Sewer | AO34: 41380.97
A35: DSCR | B35: =B17/ABS(B31) -> 1.304962 | AB35: 47119 | AD35: 0 | AE35: 0 | AF35: =W57 -> 450276.04 | AG35: =AF35/$AD$37 -> 0.074456559 | AI35: =AD35+AF35+AH35 -> 450276.04 | AN35: General/Admin | AO35: 52530.16
D36: Debt Service | AB36: 47484 | AD36: =AC10 -> 5230711 | AE36: 0 | AF36: =Y57 -> 486407.58 | AG36: =AF36/$AD$37 -> 0.080431182 | AH36: =AC23 -> 2151056.8 | AI36: =AD36+AF36+AH36 -> 7868175.5 | AN36: Insurance | AO36: 206902.04
A37: Interest Only Period | D37: Senior Loan Principal | AD37: =SUM(AD30:AD36) -> 6047500 | AE37: =SUM(AE30:AE35) -> 0 | AF37: =SUM(AF30:AF36) -> 1806307.1 | AG37: =AVERAGE(AG30:AG36) -> 0.04266951 | AI37: =AD37+AE37+AH37 -> 6047500 | AN37: RE Taxes | AO37: 164042.76
A38: Interest Only | B38: =-B20*B13 -> -651705.75 | D38: Senior Loan Interest | E38: 78585 | F38: 78585 | G38: 78585 | H38: 78585 | I38: 78585 | J38: 78585 | K38: 78585 | L38: 78585 | M38: =-$B$39 -> 54308.812 | N38: =-$B$39 -> 54308.812 | O38: =-$B$39 -> 54308.812 | P38: =-$B$39 -> 54308.812 | Q38: =SUM(E38:P38) -> 845915.25 | S38: =-B39*12 -> 651705.75 | U38: =S38 -> 651705.75 | W38: =U38 -> 651705.75 | Y38: =W38 -> 651705.75 | AH38: IRR | AI38: =XIRR(AI30:AI36, AB30:AB36) -> 0.09917044 | AN38: Legal | AO38: 3951.5
A39: Monthly I/O | B39: =B38/12 -> -54308.812 | D39: Short term Mezz Debt Interest | E39: =B67 -> 0 | F39: =C67 -> 0 | G39: =D67 -> 0 | H39: =E67 -> 0 | I39: =F67 -> 0 | J39: =G67 -> 0 | K39: =H67 -> 0 | L39: =I67 -> 0 | ... P39: =M67 -> 0 | Q39: =SUM(E39:P39) -> 0 | S39: =-B67 -> 0 | U39: =-B67 -> 0 | W39: =-D61 -> 0 | Y39: =-F61 -> 0 | AN39: Payroll | AO39: 96128.71
AN40: PM Fees | AO40: 126907.18
D41: Total Debt Service | E41: =SUM(E37:E40) -> 78585 | F41: =SUM(F37:F40) -> 78585 | G41: =SUM(G37:G40) -> 78585 | H41: =SUM(H37:H40) -> 78585 | I41: =SUM(I37:I40) -> 78585 | J41: =SUM(J37:J40) -> 78585 | K41: =SUM(K37:K40) -> 78585 | L41: =SUM(L37:L40) -> 78585 | ... Q41: =SUM(Q37:Q40) -> 845915.25 | S41: =SUM(S37:S40) -> 651705.75 | U41: =SUM(U37:U40) -> 651705.75 | W41: =SUM(W37:W40) -> 651705.75 | Y41: =SUM(Y37:Y40) -> 651705.75 | AN41: Deposit to Replacement Reserves | AO41: 0
A42: Souces and Uses
A43: Source(s) | D43: Asset Management Fee @ 2% | E43: =E19*0.02 -> 2800.924 | F43: =F19*0.02 -> 2828.1968 | G43: =G19*0.02 -> 2727.4609 | H43: =H19*0.02 -> 3215.2121 | I43: =I19*0.02 -> 3201.1275 | J43: =J19*0.02 -> 3204.8215 | K43: =K19*0.02 -> 3227.7953 | L43: =L19*0.02 -> 3232.9582 | ... P43: =P19*0.02 -> 3313.3994 | Q43: =SUM((E43:P43)) -> 37581.792 | S43: =S19*2% -> 42315.499 | U43: =U19*2% -> 43584.964 | W43: =W19*2% -> 44892.513 | Y43: =Y19*2% -> 46239.288
D44: Capex Expenses | E44: 10000 | F44: 10000 | G44: 10000 | H44: 10000 | I44: 10000 | J44: 10000 | K44: 10000 | L44: 10000 | M44: 10000 | N44: 10000 | O44: 10000 | P44: 10000 | Q44: =SUM((E44:P44)) -> 120000 | S44: 150000 | U44: 150000 | W44: 150000 | Y44: 150000
A45: Senior Loan Proceeds | B45: =B20 -> 12366333 | D45: Replace Reserve Deposits | E45: 3000 | F45: 3000 | G45: 3000 | H45: 3000 | I45: 3000 | J45: 3000 | K45: 3000 | L45: 3000 | M45: 3000 | N45: 3000 | O45: 3000 | P45: 3000 | Q45: =SUM((E45:P45)) -> 36000 | S45: =Q45 -> 36000 | U45: =Q45 -> 36000 | W45: =S45 -> 36000 | Y45: =U45 -> 36000 | AN45: Advertising | AO45: 3631 | AP45: 3812 | AQ45: 2936.62
A46: Mezz/HML | B46: =B62 -> 0 | D46: Cash Flow available for Distribution | E46: =E34-(E41+SUM(E43:E45)) -> -14704.014 | F46: =F34-(F41+SUM(F43:F45)) -> -12536.517 | G46: =G34-(G41+SUM(G43:G45)) -> -16029.136 | H46: =H34-(H41+SUM(H43:H45)) -> -4477.7645 | I46: =I34-(I41+SUM(I43:I45)) -> 5928.1339 | J46: =J34-(J41+SUM(J43:J45)) -> 6754.3024 | K46: =K34-(K41+SUM(K43:K45)) -> 7319.9371 | L46: =L34-(L41+SUM(L43:L45)) -> 1140.7936 | ... P46: =P34-(P41+SUM(P43:P45)) -> 32487.94 | Q46: =SUM(E46:P46) -> 104155.2 | S46: =S34-(S41+SUM(S43:S45)) -> 544888.75 | U46: =U34-(U41+SUM(U43:U45)) -> 593275.24 | W46: =W34-(W41+SUM(W43:W45)) -> 643251.49 | Y46: =Y34-(Y41+SUM(Y43:Y45)) -> 694867.96 | AN46: Contract Services | AO46: 0 | AP46: 0 | AQ46: 0
A47: Total Sources | B47: =SUM(B45:B46) -> 12366333 | AN47: Repair and Maintenance | AO47: 10385.34 | AP47: 9136.84 | AQ47: 12365.79
A48: Uses | D48: Distributions from Cash Flow | E48: =IF(E46>0, E46,0) -> 0 | F48: =IF(F46>0, F46,0) -> 0 | G48: =IF(G46>0, G46,0) -> 0 | H48: =IF(H46>0, H46,0) -> 0 | I48: =IF(I46>0, I46,0) -> 5928.1339 | J48: =IF(J46>0, J46,0) -> 6754.3024 | K48: =IF(K46>0, K46,0) -> 7319.9371 | L48: =IF(L46>0, L46,0) -> 1140.7936 | ... Q48: =IF(Q46>0, Q46,0) -> 104155.2 | AN48: Turn Over | AO48: 0 | AP48: 0 | AQ48: 0
A49: Existing Loan Payoff | B49: =B22 -> -10899999 | AN49: Utilities | AO49: 8844.79 | AP49: 7754.52 | AQ49: 7885.53
A50: =A21 -> Closing Charges | B50: =B23+B24 -> -204544.99 | D50: Members Preferred Return Due | E50: 0 | F50: 0 | G50: 0 | H50: 0 | I50: 0 | J50: 0 | K50: 0 | L50: 0 | M50: 0 | N50: 0 | O50: 0 | P50: 0 | Q50: =SUM(E50:P50) -> 0 | S50: 0 | U50: 0 | W50: 0 | Y50: 0 | AN50: General / Admin | AO50: 2899.94 | AP50: 1765.76 | AQ50: 1965.88
A51: D. Existing GP Loans | B51: -150000 | D51: Members Preferred Return Deficiency | E51: 0 | F51: 0 | G51: 0 | H51: 0 | I51: 0 | J51: 0 | K51: 0 | L51: 0 | M51: 0 | N51: 0 | O51: 0 | P51: 0 | Q51: =SUM(E51:P51) -> 0 | S51: 0 | U51: 0 | W51: 0 | Y51: 0 | AN51: Insurance + RE Taxes | AO51: 8137.21 | AP51: 5762.21 | AQ51: 28312.52
A52: E. Accrued AM Fees | B52: -45000 | D52: Members Prefered Return Paid | E52: 0 | F52: 0 | G52: 0 | H52: 0 | I52: 0 | J52: 0 | K52: 0 | L52: 0 | M52: 0 | N52: 0 | O52: 0 | P52: 0 | Q52: =SUM(E52:P52) -> 0 | S52: 0 | U52: 0 | W52: 0 | Y52: 0 | AN52: Legal | AO52: 0 | AP52: 0 | AQ52: 0
A53: F. LP's Unpaid pref (Class A at 10%) | B53: 0 | D53: Members Prefered Return Deffered | E53: 0 | F53: 0 | G53: 0 | H53: 0 | I53: 0 | J53: 0 | K53: 0 | L53: 0 | M53: 0 | N53: 0 | O53: 0 | P53: 0 | Q53: =SUM(E53:P53) -> 0 | S53: 0 | U53: 0 | W53: 0 | Y53: 0 | AN53: Payroll | AO53: 40279.51 | AP53: 33188.81 | AQ53: 20662.99
A54: G. Operating Reserves | B54: 0 | AN54: PM Fees | AO54: 4500 | AP54: 4500 | AQ54: 4500
A55: K. Capex | B55: -250000 | AN55: Deposit to Replacement Reserves | AO55: 0 | AP55: 0 | AQ55: 0
A56: Total Uses | B56: =SUM(B49:B55) -> -11549544 | D56: Excess Cash Flow | E56: =E46 -> -14704.014 | F56: =F46 -> -12536.517 | G56: =G46 -> -16029.136 | H56: =H46 -> -4477.7645 | I56: =I46 -> 5928.1339 | J56: =J46 -> 6754.3024 | K56: =K46 -> 7319.9371 | L56: =L46 -> 1140.7936 | ... Q56: =Q46 -> 104155.2 | S56: =S46 -> 544888.75 | U56: =U46 -> 593275.24 | W56: =W46 -> 643251.49 | Y56: =Y46 -> 694867.96
D57: Distributed to Members (70%) | E57: =IF(E$46>0, E$46*0.7, 0) -> 0 | F57: =IF(F$46>0, F$46*0.7, 0) -> 0 | G57: =IF(G$46>0, G$46*0.7, 0) -> 0 | H57: =IF(H$46>0, H$46*0.7, 0) -> 0 | I57: =IF(I$46>0, I$46*0.7, 0) -> 4149.6937 | J57: =IF(J$46>0, J$46*0.7, 0) -> 4728.0117 | K57: =IF(K$46>0, K$46*0.7, 0) -> 5123.956 | L57: =IF(L$46>0, L$46*0.7, 0) -> 798.55552 | ... Q57: =IF(Q$46>0, Q$46*0.7, 0) -> 72908.643 | S57: =IF(S$46>0, S$46*0.7, 0) -> 381422.13 | U57: =IF(U$46>0, U$46*0.7, 0) -> 415292.67 | W57: =IF(W$46>0, W$46*0.7, 0) -> 450276.04 | Y57: =IF(Y$46>0, Y$46*0.7, 0) -> 486407.58
A58: Return of Capital to Members | B58: =IF(B47>B56, B47+B56, 0) -> 816788.97 | D58: Distributed to Manager (30%) | E58: =IF(E$46>0, E$46*0.3, 0) -> 0 | F58: =IF(F$46>0, F$46*0.3, 0) -> 0 | G58: =IF(G$46>0, G$46*0.3, 0) -> 0 | H58: =IF(H$46>0, H$46*0.3, 0) -> 0 | I58: =IF(I$46>0, I$46*0.3, 0) -> 1778.4402 | J58: =IF(J$46>0, J$46*0.3, 0) -> 2026.2907 | K58: =IF(K$46>0, K$46*0.3, 0) -> 2195.9811 | L58: =IF(L$46>0, L$46*0.3, 0) -> 342.23808 | ... Q58: =IF(Q$46>0, Q$46*0.3, 0) -> 31246.561 | S58: =IF(S$46>0, S$46*0.3, 0) -> 163466.63 | U58: =IF(U$46>0, U$46*0.3, 0) -> 177982.57 | W58: =IF(W$46>0, W$46*0.3, 0) -> 192975.45 | Y58: =IF(Y$46>0, Y$46*0.3, 0) -> 208460.39
A60: Short term Pref/Mezz Debt
A61: Sources
A62: Loan | B62: =IF(ABS(B56)>B45, ABS(B56+B45), 0) -> 0
A63: Origination @ 2.5% | B63: =B62*2.5% -> 0
A64: Legal and Closing @ 1% | B64: =B62*1% -> 0
A65: Current Interest Rate | B65: 0.08
A66: Defferred Interest Rate | B66: 0.06
A67: Annual Current Interest | B67: =B62*B65 -> 0
A68: Annual Deferred Interest | B68: =B62*B66 -> 0

Sheet Financials
I7: Account Name | J7: 45809 | K7: 45839 | L7: 45870 | M7: 45901 | N7: 45931 | O7: 45962 | P7: Dec 2025 | Q7: 46023 | R7: 46054 | S7: 46082 | T7: 46113 | U7: 46143 | V7: 46174 | W7: 46204 | X7: 46235 | Y7: 46266 | Z7: 46296 | AA7: 46327 | AB7: 46357 | AC7: T-12 | AD7: Jun 2025 - MAy 2026 | AE7: JUL 25 - JUL 26 | AF7: AUG 25- AUG 26 | AG7: SEPT 25 - SEPT 26 | AH7: OCT - OCT | AI7: NOV-NOV | AJ7: DEC-DEC
I8: Total Rental Income | J8: 106694.97 | K8: 108561.68 | L8: 100393.75 | M8: 85547.93 | N8: 102980.78 | O8: 121043.54 | P8: 116656.75 | Q8: 123636.2 | R8: 124816.64 | S8: 131933.96 | T8: 142474.01 | U8: 141769.77 | V8: 141954.48 | W8: 143103.17 | X8: 143361.31 | Y8: 144814.36 | Z8: 145797.8 | AA8: 145885.46 | AB8: 147169.77 | AC8: =SUM(P8:AB8) -> 1793373.7
I9: Total Other Income | J9: 16538.85 | K9: 11410.24 | L9: 14422.98 | M9: 13112.8 | N9: 13988.72 | O9: 17456.19 | P9: 13773.1 | Q9: 16410 | R9: 16593.2 | S9: 18195 | T9: 18286.6 | U9: 18286.6 | V9: 18286.6 | W9: 18286.6 | X9: 18286.6 | Y9: 18332.4 | Z9: 18332.4 | AA9: 18332.4 | AB9: 18500.2 | AC9: =SUM(P9:AB9) -> 229901.7
I10: Total Operating Income | J10: 123233.82 | K10: 119971.92 | L10: 114816.73 | M10: 98660.73 | N10: 116969.5 | O10: 138499.73 | P10: 130429.85 | Q10: 140046.2 | R10: 141409.84 | S10: 150128.96 | T10: 160760.61 | U10: 160056.37 | V10: =SUM(V8:V9) -> 160241.08 | W10: 161389.77 | X10: 161647.91 | Y10: 163146.76 | Z10: 164130.2 | AA10: 164217.86 | AB10: 165669.97 | AC10: =SUM(P10:AB10) -> 2023275.4
I11: Expense
I12: Total Management Fee Expenses | J12: 4500 | K12: 4500 | L12: 4500 | M12: 4500 | N12: 4500 | O12: 4500 | P12: 4500 | Q12: 4500 | R12: 4500 | S12: 4503.8687 | T12: 4822.8182 | U12: 4801.6912 | V12: 4807.2323 | W12: 4841.693 | X12: 4849.4373 | Y12: 4894.4027 | Z12: 4923.9059 | AA12: 4926.5359 | AB12: 4970.0991 | AC12: =SUM(P12:AB12) -> 61841.684 | AD12: =SUM(J12:U12) -> 54628.378 | AE12: =SUM(K12:V12) -> 54935.61 | AF12: =SUM(L12:W12) -> 55277.303 | AG12: =SUM(M12:X12) -> 55626.741 | AH12: =SUM(N12:Y12) -> 56021.143 | AI12: =SUM(O12:Z12) -> 56445.049 | AJ12: =SUM(P12:AA12) -> 56871.585
I13: Total Admin Expenses | J13: 1458.99 | K13: 9822.95 | L13: 3470.28 | M13: 1775.6 | N13: 2899.94 | O13: 1765.76 | P13: 1965.88 | Q13: 2781.05 | R13: 3093.77 | S13: 2297.05 | T13: 7597.05 | U13: 2997.4 | V13: 2297.05 | W13: 2297.05 | X13: 4497.05 | Y13: 2597.05 | Z13: 2297.05 | AA13: 2723.15 | AB13: 2297.05 | AC13: =SUM(P13:AB13) -> 39737.65 | AD13: =SUM(J13:U13) -> 41925.72 | AE13: =SUM(K13:V13) -> 42763.78 | AF13: =SUM(L13:W13) -> 35237.88 | AG13: =SUM(M13:X13) -> 36264.65 | AH13: =SUM(N13:Y13) -> 37086.1 | AI13: =SUM(O13:Z13) -> 36483.21 | AJ13: =SUM(P13:AA13) -> 37440.6
I14: Total Turn Costs | J14: 0 | K14: 0 | L14: 3303.8 | M14: 8685.78 | N14: 2766.2 | O14: 1258.46 | P14: 1460.93 | Q14: 2210 | R14: 2210 | S14: 1610 | T14: 3110 | U14: 1910 | V14: 4898.04 | W14: 2510 | X14: 5210 | Y14: 2810 | Z14: 2760 | AA14: 2510 | AB14: 3110 | AC14: =SUM(P14:AB14) -> 36318.97 | AD14: =SUM(J14:U14) -> 28525.17 | AE14: =SUM(K14:V14) -> 33423.21 | AF14: =SUM(L14:W14) -> 35933.21 | AG14: =SUM(M14:X14) -> 37839.41 | AH14: =SUM(N14:Y14) -> 31963.63 | AI14: =SUM(O14:Z14) -> 31957.43 | AJ14: =SUM(P14:AA14) -> 33208.97
I15: Total Advertising | J15: 5691.04 | K15: 3691.38 | L15: 4535.23 | M15: 4396.92 | N15: 3631 | O15: 3812 | P15: 2936.62 | Q15: 3562 | R15: 3562 | S15: 3562 | T15: 3562 | U15: 3562 | V15: 3327 | W15: 3562 | X15: 3562 | Y15: 3562 | Z15: 2193.95 | AA15: 2030 | AB15: 2030 | AC15: =SUM(P15:AB15) -> 41013.57 | AD15: =SUM(J15:U15) -> 46504.19 | AE15: =SUM(K15:V15) -> 44140.15 | AF15: =SUM(L15:W15) -> 44010.77 | AG15: =SUM(M15:X15) -> 43037.54 | AH15: =SUM(N15:Y15) -> 42202.62 | AI15: =SUM(O15:Z15) -> 40765.57 | AJ15: =SUM(P15:AA15) -> 38983.57
I16: Total Repairs and Maintenance | J16: 5700.66 | K16: 702.97 | L16: 5245.66 | M16: 5314.97 | N16: 5026.4 | O16: 6685.8 | P16: 10229.92 | Q16: 3327 | R16: 3327 | S16: 3327 | T16: 3327 | U16: 3327 | V16: 1910 | W16: 3327 | X16: 3327 | Y16: 3327 | Z16: 3327 | AA16: 3327 | AB16: 3327 | AC16: =SUM(P16:AB16) -> 48736.92 | AD16: =SUM(J16:U16) -> 55541.38 | AE16: =SUM(K16:V16) -> 51750.72 | AF16: =SUM(L16:W16) -> 54374.75 | AG16: =SUM(M16:X16) -> 52456.09 | AH16: =SUM(N16:Y16) -> 50468.12 | AI16: =SUM(O16:Z16) -> 48768.72 | AJ16: =SUM(P16:AA16) -> 45409.92
I17: Total Contract Services | J17: 5013.05 | K17: 3890.75 | L17: 5456.68 | M17: 4976.36 | N17: 5351.97 | O17: 7348.6 | P17: 4528.6 | Q17: 5573.66 | R17: 4898.04 | S17: 4898.04 | T17: 5573.66 | U17: 4898.04 | V17: 5028.88 | W17: 5573.66 | X17: 4898.04 | Y17: 4898.04 | Z17: 5573.66 | AA17: 6973.17 | AB17: 4898.04 | AC17: =SUM(P17:AB17) -> 68213.53 | AD17: =SUM(J17:U17) -> 62407.45 | AE17: =SUM(K17:V17) -> 62423.28 | AF17: =SUM(L17:W17) -> 64106.19 | AG17: =SUM(M17:X17) -> 63547.55 | AH17: =SUM(N17:Y17) -> 63469.23 | AI17: =SUM(O17:Z17) -> 63690.92 | AJ17: =SUM(P17:AA17) -> 63315.49
I18: Total Utilities | J18: 6743.78 | K18: 6410.55 | L18: 7404.19 | M18: 6924.26 | N18: 5967.88 | O18: 6320.12 | P18: 6240.74 | Q18: 5028.88 | R18: 5028.88 | S18: 5028.88 | T18: 5028.88 | U18: 5028.88 | V18: 2297.05 | W18: 5028.88 | X18: 5028.88 | Y18: 5028.88 | Z18: 5028.88 | AA18: 5028.88 | AB18: 5028.88 | AC18: =SUM(P18:AB18) -> 63855.47 | AD18: =SUM(J18:U18) -> 71155.92 | AE18: =SUM(K18:V18) -> 66709.19 | AF18: =SUM(L18:W18) -> 65327.52 | AG18: =SUM(M18:X18) -> 62952.21 | AH18: =SUM(N18:Y18) -> 61056.83 | AI18: =SUM(O18:Z18) -> 60117.83 | AJ18: =SUM(P18:AA18) -> 58826.59
I19: Total Taxes and Insurance | J19: 30149.1 | K19: 30149.1 | L19: 36042 | M19: 36042 | N19: 36042 | O19: 28518.86 | P19: 44207.66 | Q19: 0 | R19: 21140 | S19: 21140 | T19: 21140 | U19: 21140 | V19: 21140 | W19: 21140 | X19: 21140 | Y19: 21140 | Z19: 21140 | AA19: 21140 | AB19: 21140 | AC19: =SUM(P19:AB19) -> 276747.66 | AD19: =SUM(J19:U19) -> 325710.72 | AE19: =SUM(K19:V19) -> 316701.62 | AF19: =SUM(L19:W19) -> 307692.52 | AG19: =SUM(M19:X19) -> 292790.52 | AH19: =SUM(N19:Y19) -> 277888.52 | AI19: =SUM(O19:Z19) -> 262986.52 | AJ19: =SUM(P19:AA19) -> 255607.66
I20: Total Payroll Expenses | J20: 14595.66 | K20: 20007.3 | L20: 18746.52 | M20: 12406.7 | N20: 15143.6 | O20: 12182.34 | P20: 14019.56 | Q20: 12241.7 | R20: 12241.7 | S20: 12991.7 | T20: 12241.7 | U20: 12241.7 | V20: 12241.7 | W20: 12241.7 | X20: 12241.7 | Y20: 12991.7 | Z20: 12241.7 | AA20: 12241.7 | AB20: 15491.7 | AC20: =SUM(P20:AB20) -> 165669.96 | AD20: =SUM(J20:U20) -> 169060.18 | AE20: =SUM(K20:V20) -> 166706.22 | AF20: =SUM(L20:W20) -> 158940.62 | AG20: =SUM(M20:X20) -> 152435.8 | AH20: =SUM(N20:Y20) -> 153020.8 | AI20: =SUM(O20:Z20) -> 150118.9 | AJ20: =SUM(P20:AA20) -> 150178.26
I21: Total Operating Expense | J21: =SUM(J12:J20) -> 73852.28 | K21: =SUM(K12:K20) -> 79175 | L21: =SUM(L12:L20) -> 88704.36 | M21: =SUM(M12:M20) -> 85022.59 | N21: =SUM(N12:N20) -> 81328.99 | O21: =SUM(O12:O20) -> 72391.94 | P21: 90089.91 | Q21: 60364.29 | R21: 60001.39 | S21: 59358.539 | T21: 66403.108 | U21: 59906.711 | V21: =SUM(V12:V20) -> 57946.952 | W21: 60521.983 | X21: 64754.107 | Y21: 61249.073 | Z21: 59486.146 | AA21: 60900.436 | AB21: 62292.769 | AC21: =SUM(P21:AB21) -> 823275.41 | AD21: =SUM(AD12:AD20) -> 855459.11 | AE21: =SUM(AE12:AE20) -> 839553.78 | AF21: =SUM(AF12:AF20) -> 820900.76 | AG21: =SUM(AG12:AG20) -> 796950.51 | AH21: =SUM(AH12:AH20) -> 773176.99 | AI21: =SUM(AI12:AI20) -> 751334.15 | AJ21: =SUM(AJ12:AJ20) -> 739842.65
I23: NOI - Net Operating Income | J23: =J10-J21 -> 49381.54 | K23: =K10-K21 -> 40796.92 | L23: =L10-L21 -> 26112.37 | M23: =M10-M21 -> 13638.14 | N23: =N10-N21 -> 35640.51 | O23: =O10-O21 -> 66107.79 | P23: =P10-P21 -> 40339.94 | Q23: 79681.91 | R23: 81408.45 | S23: 90770.417 | T23: 94357.498 | U23: 100149.66 | V23: =V10-V21 -> 102294.12 | W23: 100867.78 | X23: 96893.802 | Y23: 101897.68 | Z23: 104644.05 | AA23: 103317.43 | AB23: 103377.2 | AC23: =SUM(P23:AB23) -> 1199999.9
AB1048567: =SUM(J1048567:U1048576) -> 0

Sheet Worksheet - DO NOT DELETE
A1: Starting Avg. Market Rent | B1: 1180.44
A2: Units | B2: 127
A3: New Leases with consessions (75% off 1st Month) | B3: 0 | C3: 4 | D3: 11 | E3: 2 | F3: 3 | G3: 3 | H3: 2 | I3: 2 | J3: 2 | K3: 1 | L3: 1 | M3: 1
A4: Vacant Units | B4: 12 | C4: 8 | D4: 4 | E4: 4 | F4: 4 | G4: 4 | H4: 4 | I4: 4 | J4: 3 | K4: 3 | L4: 3 | M4: 3
A5: Units Economically occupied | B5: 105 | C5: 109 | D5: 110 | E5: 122 | F5: 122 | G5: 122 | H5: 122 | I5: 122 | J5: 123 | K5: 123 | L5: 123 | M5: 124
A6: Eviction Units | B6: =ABS(SUM(B4:B5)-$B$2) -> 10 | C6: =ABS(SUM(C4:C5)-$B$2) -> 10 | D6: =ABS(SUM(D4:D5)-$B$2) -> 13 | E6: =ABS(SUM(E4:E5)-$B$2) -> 1 | F6: =ABS(SUM(F4:F5)-$B$2) -> 1 | G6: =ABS(SUM(G4:G5)-$B$2) -> 1 | H6: =ABS(SUM(H4:H5)-$B$2) -> 1 | I6: =ABS(SUM(I4:I5)-$B$2) -> 1 | ... M6: =ABS(SUM(M4:M5)-$B$2) -> 0
A7: Increase | C7: 0 | D7: 0.0025 | E7: 0.0013 | F7: 0.0013 | G7: 0.0013 | H7: 0.0018 | I7: 0.0018 | J7: 0.0018 | K7: 0.0006 | L7: 0.0006 | M7: 0.0006
B8: =B1 -> 1180.44 | C8: =B8*(1+C7) -> 1180.44 | D8: =C8*(1+D7) -> 1183.3911 | E8: =D8*(1+E7) -> 1184.9295 | F8: =E8*(1+F7) -> 1186.4699 | G8: =F8*(1+G7) -> 1188.0123 | H8: =G8*(1+H7) -> 1190.1507 | I8: =H8*(1+I7) -> 1192.293 | J8: =I8*(1+J7) -> 1194.4391 | ... M8: =L8*(1+M7) -> 1196.5904
A10: In-place Average Rent | B10: =(B18+B15)/B5 -> 1174.5352
B11: 1 | C11: =B11+1 -> 2 | D11: =C11+1 -> 3 | E11: =D11+1 -> 4 | F11: =E11+1 -> 5 | G11: =F11+1 -> 6 | H11: =G11+1 -> 7 | I11: =H11+1 -> 8 | J11: =I11+1 -> 9 | ... M11: =L11+1 -> 12 | N11: TOTAL | O11: TOTAL (%)
A12: Gross Potential Rent (GPR) | B12: ='2026 Rent Strategy'!$N$12 -> 159666 | C12: ='2026 Rent Strategy'!$N$12 -> 159666 | D12: ='2026 Rent Strategy'!$N$12 -> 159666 | E12: ='2026 Rent Strategy'!$N$12 -> 159666 | F12: ='2026 Rent Strategy'!$N$12 -> 159666 | G12: ='2026 Rent Strategy'!$N$12 -> 159666 | H12: ='2026 Rent Strategy'!$N$12 -> 159666 | I12: ='2026 Rent Strategy'!$N$12 -> 159666 | ... M12: ='2026 Rent Strategy'!$N$12 -> 159666 | N12: =SUM(B12:M12) -> 1915992
A13: - Vacancy | B13: =-B8*B4 -> -14165.28 | C13: =-C8*C4 -> -9443.52 | D13: =-D8*D4 -> -4733.5644 | E13: =-E8*E4 -> -4739.718 | F13: =-F8*F4 -> -4745.8797 | G13: =-G8*G4 -> -4752.0493 | H13: =-H8*H4 -> -4760.603 | I13: =-I8*I4 -> -4769.1721 | ... M13: =-M8*M4 -> -3589.7713 | N13: =SUM(B13:M13) -> -66455.961 | O13: =ABS(N13/$N$12) -> 0.034684885
A14: - Concessions, Loss to Lease, Bad Debt
A15: Consessions | B15: =(-B3*B8*0.75)-310 -> -310 | C15: =(-C3*C8*0.75)-310 -> -3851.32 | D15: =(-D3*D8*0.75)-310 -> -10072.977 | E15: =(-E3*E8*0.75)-310 -> -2087.3943 | F15: =(-F3*F8*0.75)-310 -> -2979.5573 | G15: =(-G3*G8*0.75)-310 -> -2983.0277 | H15: =(-H3*H8*0.75)-310 -> -2095.2261 | I15: =(-I3*I8*0.75)-310 -> -2098.4395 | ... M15: =(-M3*M8*0.75)-310 -> -1207.4428 | N15: =SUM(B15:M15) -> -32200.315 | O15: =ABS(N15/$N$12) -> 0.01680608
A16: Loss To Lease | B16: =(B8-(B12/$B$2))*$B$2 -> -9750.12 | C16: =(C8-(C12/$B$2))*$B$2 -> -9750.12 | D16: =(D8-(D12/$B$2))*$B$2 -> -9375.3303 | E16: =(E8-(E12/$B$2))*$B$2 -> -9179.9524 | F16: =(F8-(F12/$B$2))*$B$2 -> -8984.3206 | G16: =(G8-(G12/$B$2))*$B$2 -> -8788.4344 | H16: =(H8-(H12/$B$2))*$B$2 -> -8516.8548 | I16: =(I8-(I12/$B$2))*$B$2 -> -8244.7863 | ... M16: =(M8-(M12/$B$2))*$B$2 -> -7699.0155 | N16: =SUM(B16:M16) -> -103932.52 | O16: =ABS(N16/$N$12) -> 0.054244754
A17: Bad Debt | B17: =($B$2-(B5+B4))*-B8 -> -11804.4 | C17: =($B$2-(C5+C4))*-C8 -> -11804.4 | D17: =(SUM(D4:D5)-$B$2)*D8 -> -15384.084 | E17: =(SUM(E4:E5)-$B$2)*E8 -> -1184.9295 | F17: =(SUM(F4:F5)-$B$2)*F8 -> -1186.4699 | G17: =(SUM(G4:G5)-$B$2)*G8 -> -1188.0123 | H17: =(SUM(H4:H5)-$B$2)*H8 -> -1190.1507 | I17: =(SUM(I4:I5)-$B$2)*I8 -> -1192.293 | J17: =(SUM(J4:J5)-$B$2)*J8 -> -1194.4391 | K17: =(SUM(K4:K5)-$B$2)*K8 -> -1195.1558 | ... M17: =(SUM(M4:M5)-$B$2)*M8 -> 0 | N17: =SUM(B17:M17) -> -48520.208 | O17: =ABS(N17/$N$12) -> 0.025323805
A18: Gross Potential Income (GPI) | B18: =SUM(B12:B17) -> 123636.2 | C18: =SUM(C12:C17) -> 124816.64 | D18: =SUM(D12:D17) -> 120100.04 | E18: =SUM(E12:E17) -> 142474.01 | F18: =SUM(F12:F17) -> 141769.77 | G18: =SUM(G12:G17) -> 141954.48 | H18: =SUM(H12:H17) -> 143103.17 | I18: =SUM(I12:I17) -> 143361.31 | ... M18: =SUM(M12:M17) -> 147169.77 | N18: =SUM(B18:M18) -> 1664883 | O18: =ABS(N18/$N$12) -> 0.86894048
A19: Other Income | B19: ='Budget 2026'!B44 -> 16410 | C19: ='Budget 2026'!C44 -> 16593.2 | D19: ='Budget 2026'!D44 -> 16273 | E19: ='Budget 2026'!E44 -> 18286.6 | F19: ='Budget 2026'!F44 -> 18286.6 | G19: ='Budget 2026'!G44 -> 18286.6 | H19: ='Budget 2026'!H44 -> 18286.6 | I19: ='Budget 2026'!I44 -> 18286.6 | ... M19: ='Budget 2026'!M44 -> 18500.2 | N19: =SUM(B19:M19) -> 214206.6 | O19: =ABS(N19/$N$12) -> 0.11179932
A20: Effective Gross Income | B20: =B18+B19 -> 140046.2 | C20: =C18+C19 -> 141409.84 | D20: =D18+D19 -> 136373.04 | E20: =E18+E19 -> 160760.61 | F20: =F18+F19 -> 160056.37 | G20: =G18+G19 -> 160241.08 | H20: =H18+H19 -> 161389.77 | I20: =I18+I19 -> 161647.91 | ... M20: =M18+M19 -> 165669.97 | N20: =SUM(B20:M20) -> 1879089.6
A22: EXPENSES | N22: T-12 Expenses
A23: Advertising | B23: ='Budget 2026'!B96 -> 3562 | C23: ='Budget 2026'!C96 -> 3562 | D23: ='Budget 2026'!D96 -> 3562 | E23: ='Budget 2026'!E96 -> 3562 | F23: ='Budget 2026'!F96 -> 3562 | G23: ='Budget 2026'!G96 -> 3562 | H23: ='Budget 2026'!H96 -> 3562 | I23: ='Budget 2026'!I96 -> 3562 | ... M23: ='Budget 2026'!M96 -> 2030 | N23: =SUM(B23:M23) -> 38311.95
A24: Contract Services | B24: ='Budget 2026'!B122 -> 5573.66 | C24: ='Budget 2026'!C122 -> 4898.04 | D24: ='Budget 2026'!D122 -> 4898.04 | E24: ='Budget 2026'!E122 -> 5573.66 | F24: ='Budget 2026'!F122 -> 4898.04 | G24: ='Budget 2026'!G122 -> 4898.04 | H24: ='Budget 2026'!H122 -> 5573.66 | I24: ='Budget 2026'!I122 -> 4898.04 | ... M24: ='Budget 2026'!M122 -> 4898.04 | N24: =SUM(B24:M24) -> 63554.09
A25: Repair and Maintenance | B25: ='Budget 2026'!B110 -> 3327 | C25: ='Budget 2026'!C110 -> 3327 | D25: ='Budget 2026'!D110 -> 3327 | E25: ='Budget 2026'!E110 -> 3327 | F25: ='Budget 2026'!F110 -> 3327 | G25: ='Budget 2026'!G110 -> 3327 | H25: ='Budget 2026'!H110 -> 3327 | I25: ='Budget 2026'!I110 -> 3327 | ... K25: ='Budget 2026'!K110 -> 3327 | L25: 3327 | M25: 3327 | N25: =SUM(B25:M25) -> 39924
A26: Turn Over | B26: ='Budget 2026'!B86 -> 2210 | C26: ='Budget 2026'!C86 -> 2210 | D26: ='Budget 2026'!D86 -> 1610 | E26: ='Budget 2026'!E86 -> 3110 | F26: ='Budget 2026'!F86 -> 1910 | G26: ='Budget 2026'!G86 -> 1910 | H26: ='Budget 2026'!H86 -> 2510 | I26: ='Budget 2026'!I86 -> 5210 | ... M26: ='Budget 2026'!M86 -> 3110 | N26: =SUM(B26:M26) -> 31870
A27: Utilities | B27: ='Budget 2026'!B131 -> 5028.88 | C27: ='Budget 2026'!C131 -> 5028.88 | D27: ='Budget 2026'!D131 -> 5028.88 | E27: ='Budget 2026'!E131 -> 5028.88 | F27: ='Budget 2026'!F131 -> 5028.88 | G27: ='Budget 2026'!G131 -> 5028.88 | H27: ='Budget 2026'!H131 -> 5028.88 | I27: ='Budget 2026'!I131 -> 5028.88 | ... M27: ='Budget 2026'!M131 -> 5028.88 | N27: =SUM(B27:M27) -> 60346.56 | XEV27: =-XEV24*XEV21 -> 0
A28: Gas & Electric | N28: =SUM(B28:M28) -> 0
A29: Trash Removal | N29: =SUM(B29:M29) -> 0
A30: Water and Sewer | N30: =SUM(B30:M30) -> 0
A31: General/Admin | B31: ='Budget 2026'!B77 -> 2781.05 | C31: ='Budget 2026'!C77 -> 3093.77 | D31: ='Budget 2026'!D77 -> 2297.05 | E31: ='Budget 2026'!E77 -> 7597.05 | F31: ='Budget 2026'!F77 -> 2997.4 | G31: ='Budget 2026'!G77 -> 2297.05 | H31: ='Budget 2026'!H77 -> 2297.05 | I31: ='Budget 2026'!I77 -> 4497.05 | ... M31: ='Budget 2026'!M77 -> 2297.05 | N31: =SUM(B31:M31) -> 37771.77
A32: Insurance | B32: ='Budget 2026'!B133 -> 8500 | C32: ='Budget 2026'!C133 -> 8500 | D32: ='Budget 2026'!D133 -> 8500 | E32: ='Budget 2026'!E133 -> 8500 | F32: ='Budget 2026'!F133 -> 8500 | G32: ='Budget 2026'!G133 -> 8500 | H32: ='Budget 2026'!H133 -> 8500 | I32: ='Budget 2026'!I133 -> 8500 | ... M32: ='Budget 2026'!M133 -> 8500 | N32: =SUM(B32:M32) -> 102000 | XEV32: =XEV24*XEV22 -> 0
A33: RE Taxes | B33: ='Budget 2026'!B134 -> 12640 | C33: ='Budget 2026'!C134 -> 12640 | D33: ='Budget 2026'!D134 -> 12640 | E33: ='Budget 2026'!E134 -> 12640 | F33: ='Budget 2026'!F134 -> 12640 | G33: ='Budget 2026'!G134 -> 12640 | H33: ='Budget 2026'!H134 -> 12640 | I33: ='Budget 2026'!I134 -> 12640 | ... M33: ='Budget 2026'!M134 -> 12640 | N33: =SUM(B33:M33) -> 151680
A34: Legal | B34: 0 | C34: 0 | D34: 0 | E34: 0 | F34: 0 | G34: 0 | H34: 0 | I34: 0 | J34: 0 | K34: 0 | L34: 0 | M34: 0 | N34: =SUM(B34:M34) -> 0
A35: Payroll | B35: ='Budget 2026'!B151 -> 12241.7 | C35: ='Budget 2026'!C151 -> 12241.7 | D35: ='Budget 2026'!D151 -> 12991.7 | E35: ='Budget 2026'!E151 -> 12241.7 | F35: ='Budget 2026'!F151 -> 12241.7 | G35: ='Budget 2026'!G151 -> 12991.7 | H35: ='Budget 2026'!H151 -> 12241.7 | I35: ='Budget 2026'!I151 -> 12241.7 | ... M35: ='Budget 2026'!M151 -> 15491.7 | N35: =SUM(B35:M35) -> 152400.4
A36: PM Fees | B36: ='Budget 2026'!B51 -> 4500 | C36: ='Budget 2026'!C51 -> 4500 | D36: ='Budget 2026'!D51 -> 4500 | E36: ='Budget 2026'!E51 -> 4822.8182 | F36: ='Budget 2026'!F51 -> 4801.6912 | G36: ='Budget 2026'!G51 -> 4807.2323 | H36: ='Budget 2026'!H51 -> 4841.693 | I36: ='Budget 2026'!I51 -> 4849.4373 | ... M36: ='Budget 2026'!M51 -> 4970.0991 | N36: =SUM(B36:M36) -> 57337.816
A37: Total Expenses | B37: =SUM(B23:B36) -> 60364.29 | C37: =SUM(C23:C36) -> 60001.39 | D37: =SUM(D23:D36) -> 59354.67 | E37: =SUM(E23:E36) -> 66403.108 | F37: =SUM(F23:F36) -> 59906.711 | G37: =SUM(G23:G36) -> 59961.902 | H37: =SUM(H23:H36) -> 60521.983 | I37: =SUM(I23:I36) -> 64754.107 | ... N37: =SUM(N23:N36) -> 735196.59
A39: Expense to Income Ratio | B39: =B37/B20 -> 0.43103126 | C39: =C37/C20 -> 0.42430845 | D39: =D37/D20 -> 0.43523755 | E39: =E37/E20 -> 0.41305585 | F39: =F37/F20 -> 0.37428507 | G39: =G37/G20 -> 0.37419808 | H39: =H37/H20 -> 0.37500509 | I39: =I37/I20 -> 0.40058735 | ... N39: =N37/N20 -> 0.39125148
A40: NOI | B40: =B20-B37 -> 79681.91 | C40: =C20-C37 -> 81408.45 | D40: =D20-D37 -> 77018.374 | E40: =E20-E37 -> 94357.498 | F40: =F20-F37 -> 100149.66 | G40: =G20-G37 -> 100279.17 | H40: =H20-H37 -> 100867.78 | I40: =I20-I37 -> 96893.802 | ... M40: =M20-M37 -> 103377.2 | N40: =SUM(B40:M40) -> 1143893

Sheet 2026 Rent Strategy
A3: 2026 Proforma
A4: Unit Mix | I4: Advertised Rents | L4: 2026 Market Rents
F5: Current Rent | I5: Advertised Rents - Dec 2025 | O5: Target Rent - Y5
A6: Type | B6: # Units | D6: Avg Sq Ft | E6: Total | F6: $/SqFt | G6: Average | H6: Total | I6: $/SqFt | J6: Average | K6: Total | L6: $/SqFt | M6: Average | N6: Total | O6: Average | P6: Total
A7: 1/1 Classic | B7: 39 | D7: 650 | E7: =IF(B7>0,D7*B7,0) -> 25350 | F7: =G7/D7 -> 1.4960308 | G7: 972.42 | H7: =B7*G7 -> 37924.38 | I7: =J7/D7 -> 1.6538462 | J7: 1075 | K7: =J7*B7 -> 41925 | L7: =M7/D7 -> 1.7538462 | M7: 1140 | N7: =M7*B7 -> 44460 | O7: 1199 | P7: =O7*B7 -> 46761
A8: 2/1 Classic | B8: 20 | D8: 800 | E8: =IF(B8>0,D8*B8,0) -> 16000 | F8: =G8/D8 -> 1.3185 | G8: 1054.8 | H8: =B8*G8 -> 21096 | I8: =J8/D8 -> 1.36875 | J8: 1095 | K8: =J8*B8 -> 21900 | L8: =M8/D8 -> 1.51875 | M8: 1215 | N8: =M8*B8 -> 24300 | O8: 1350 | P8: =O8*B8 -> 27000
A9: 2/1.5 Classic | B9: 33 | D9: 850 | E9: =IF(B9>0,D9*B9,0) -> 28050 | F9: =G9/D9 -> 1.3087294 | G9: 1112.42 | H9: =B9*G9 -> 36709.86 | I9: =J9/D9 -> 1.3529412 | J9: 1150 | K9: =J9*B9 -> 37950 | L9: =M9/D9 -> 1.4882353 | M9: 1265 | N9: =M9*B9 -> 41745 | O9: 1399 | P9: =O9*B9 -> 46167
A10: 2/1.5 Signature | B10: 29 | D10: 850 | E10: =IF(B10>0,D10*B10,0) -> 24650 | F10: =G10/D10 -> 1.3758353 | G10: 1169.46 | H10: =B10*G10 -> 33914.34 | I10: =J10/D10 -> 1.5294118 | J10: 1300 | K10: =J10*B10 -> 37700 | L10: =M10/D10 -> 1.5988235 | M10: 1359 | N10: =M10*B10 -> 39411 | O10: 1550 | P10: =O10*B10 -> 44950
A11: 3/2 Classic | B11: 6 | D11: 1150 | E11: =IF(B11>0,D11*B11,0) -> 6900 | F11: =G11/D11 -> 1.149913 | G11: 1322.4 | H11: =B11*G11 -> 7934.4 | I11: =J11/D11 -> 1.2391304 | J11: 1425 | K11: =J11*B11 -> 8550 | L11: =M11/D11 -> 1.4130435 | M11: 1625 | N11: =M11*B11 -> 9750 | O11: 1799 | P11: =O11*B11 -> 10794
A12: Total / Average | B12: =SUM(B7:B11) -> 127 | E12: =SUM(E7:E11) -> 100950 | F12: =AVERAGEIF(F7:F11, "<>0") -> 1.3298017 | G12: =H12/B12 -> 1083.2991 | H12: =SUM(H7:H11) -> 137578.98 | I12: =AVERAGEIF(I7:I11, "<>0") -> 1.4288159 | J12: =$K$12/B12 -> 1165.5512 | K12: =SUM(K7:K11) -> 148025 | L12: =AVERAGEIF(L7:L11, "<>0") -> 1.5545397 | M12: =N12/B12 -> 1257.2126 | N12: =SUM(N7:N11) -> 159666 | O12: =P12/B12 -> 1383.2441 | P12: =SUM(P7:P11) -> 175672
G13: GPR | H13: =H12*12 -> 1650947.8 | J13: GPR | K13: =K12*12 -> 1776300 | M13: GPR | N13: =N12*12 -> 1915992 | O13: GPR | P13: =P12*12 -> 2108064
D17: Oasis at San Marco, Advertised 2026 Rent Strategy | U17: Increase | V17: 0.06 | X17: Increase | Y17: 0.0445
A18: Unit Type | B18: # | C18: Q4 2025 | E18: Q1 | H18: Q2 | K18: Q3 | N18: Q4 | Q18: 2026 MARKET | U18: 2027 MARKET RENT | X18: 2028 MARKET RENT
C19: PSF | D19: Rent | E19: Psf | F19: Advt. Rent | G19: Increase | H19: Psf | I19: Advt. Rent | J19: Increase | K19: Psf | L19: Advt. Rent | M19: Increase | N19: Psf | O19: Advt. Rent | P19: Increase | Q19: Psf | R19: Target | S19: Total Income/Month | T19: Total Income | U19: Target | V19: Total Income/Month | W19: Total Income | X19: Target | Y19: Total Income/Month | Z19: Total Income
A20: 1/1 Classic | B20: 39 | C20: =D20/D7 -> 1.5369231 | D20: 999 | E20: =F20/D7 -> 1.6138462 | F20: 1049 | G20: =1-(D20/F20) -> 0.047664442 | H20: =I20/D7 -> 1.66 | I20: 1079 | J20: =1-(F20/I20) -> 0.027803522 | K20: =L20/D7 -> 1.7215385 | L20: 1119 | M20: =1-(I20/L20) -> 0.035746202 | N20: =O20/D7 -> 1.7538462 | O20: 1140 | P20: =1-(L20/O20) -> 0.018421053 | Q20: =R20/D7 -> 1.7538462 | R20: =M7 -> 1140 | S20: =R20*B20 -> 44460 | T20: =S20*12 -> 533520 | U20: =R20*(1+$V$17) -> 1208.4 | V20: =U20*B20 -> 47127.6 | W20: =V20*12 -> 565531.2 | X20: =U20*(1+$Y$17) -> 1262.1738 | Y20: =X20*B20 -> 49224.778 | Z20: =Y20*12 -> 590697.34
A21: 2/1 Classic | B21: 20 | C21: =D21/D8 -> 1.34875 | D21: 1079 | E21: =F21/D8 -> 1.39875 | F21: 1119 | G21: =(F21/D21)-1 -> 0.037071362 | H21: =I21/D8 -> 1.41875 | I21: 1135 | J21: =1-(F21/I21) -> 0.014096916 | K21: =L21/D8 -> 1.46875 | L21: 1175 | M21: =1-(I21/L21) -> 0.034042553 | N21: =O21/D8 -> 1.51875 | O21: 1215 | P21: =1-(L21/O21) -> 0.032921811 | Q21: =R21/D8 -> 1.51875 | R21: =M8 -> 1215 | S21: =R21*B21 -> 24300 | T21: =S21*12 -> 291600 | U21: =R21*(1+$V$17) -> 1287.9 | V21: =U21*B21 -> 25758 | W21: =V21*12 -> 309096 | X21: =U21*(1+$Y$17) -> 1345.2115 | Y21: =X21*B21 -> 26904.231 | Z21: =Y21*12 -> 322850.77
A22: 2/1.5 Classic | B22: 33 | C22: =D22/D9 -> 1.2929412 | D22: 1099 | E22: =F22/D9 -> 1.3517647 | F22: 1149 | G22: =(F22/D22)-1 -> 0.045495905 | H22: =I22/D9 -> 1.3870588 | I22: 1179 | J22: =1-(F22/I22) -> 0.025445293 | K22: =L22/D9 -> 1.4341176 | L22: 1219 | M22: =1-(I22/L22) -> 0.032813782 | N22: =O22/G9 -> 1.1407562 | O22: 1269 | P22: =1-(L22/O22) -> 0.039401103 | Q22: =R22/D9 -> 1.4882353 | R22: =M9 -> 1265 | S22: =R22*B22 -> 41745 | T22: =S22*12 -> 500940 | U22: =R22*(1+$V$17) -> 1340.9 | V22: =U22*B22 -> 44249.7 | W22: =V22*12 -> 530996.4 | X22: =U22*(1+$Y$17) -> 1400.5701 | Y22: =X22*B22 -> 46218.812 | Z22: =Y22*12 -> 554625.74
A23: 2/1.5 Signature | B23: 29 | C23: =D23/D10 -> 1.4341176 | D23: 1219 | E23: =F23/D10 -> 1.5294118 | F23: 1300 | G23: =(F23/D23)-1 -> 0.066447908 | H23: =I23/D10 -> 1.5635294 | I23: 1329 | J23: =1-(F23/I23) -> 0.021820918 | K23: =L23/D10 -> 1.5752941 | L23: 1339 | M23: =1-(I23/L23) -> 0.0074682599 | N23: =O23/G10 -> 1.1620748 | O23: 1359 | P23: =1-(L23/O23) -> 0.014716703 | Q23: =R23/D10 -> 1.5988235 | R23: 1359 | S23: =R23*B23 -> 39411 | T23: =S23*12 -> 472932 | U23: =R23*(1+$V$17) -> 1440.54 | V23: =U23*B23 -> 41775.66 | W23: =V23*12 -> 501307.92 | X23: =U23*(1+$Y$17) -> 1504.644 | Y23: =X23*B23 -> 43634.677 | Z23: =Y23*12 -> 523616.12
A24: 3/2 Classic | B24: 6 | C24: =D24/D11 -> 1.3034783 | D24: 1499 | E24: =F24/D11 -> 1.3295652 | F24: 1529 | G24: =(F24/D24)-1 -> 0.020013342 | H24: =I24/G11 -> 1.1864791 | I24: 1569 | J24: =1-(F24/I24) -> 0.025493945 | K24: =L24/J11 -> 1.1221053 | L24: 1599 | M24: =1-(I24/L24) -> 0.018761726 | N24: =O24/M11 -> 1 | O24: 1625 | P24: =1-(L24/O24) -> 0.016 | Q24: =R24/D11 -> 1.4130435 | R24: 1625 | S24: =R24*B24 -> 9750 | T24: =S24*12 -> 117000 | U24: =R24*(1+$V$17) -> 1722.5 | V24: =U24*B24 -> 10335 | W24: =V24*12 -> 124020 | X24: =U24*(1+$Y$17) -> 1799.1512 | Y24: =X24*B24 -> 10794.907 | Z24: =Y24*12 -> 129538.89
B25: =SUM(B20:B24) -> 127 | D25: =($B$20*D20+$B$21*D21+$B$22*D22+$B$23*D23+$B$24*D24)/127 -> 1111.4409 | F25: =($B$20*F20+$B$21*F21+$B$22*F22+$B$23*F23+$B$24*F24)/127 -> 1166 | I25: =($B$20*I20+$B$21*I21+$B$22*I22+$B$23*I23+$B$24*I24)/127 -> 1194.0394 | L25: =($B$20*L20+$B$21*L21+$B$22*L22+$B$23*L23+$B$24*L24)/127 -> 1226.7165 | O25: =($B$20*O20+$B$21*O21+$B$22*O22+$B$23*O23+$B$24*O24)/127 -> 1258.252 | R25: =($B$20*R20+$B$21*R21+$B$22*R22+$B$23*R23+$B$24*R24)/127 -> 1257.2126 | S25: =SUM(S20:S24) -> 159666 | T25: =S25*12 -> 1915992 | U25: =($B$20*U20+$B$21*U21+$B$22*U22+$B$23*U23+$B$24*U24)/127 -> 1332.6454 | V25: =SUM(V20:V24) -> 169245.96 | W25: =V25*12 -> 2030951.5 | X25: =($B$20*X20+$B$21*X21+$B$22*X22+$B$23*X23+$B$24*X24)/127 -> 1391.9481 | Y25: =SUM(Y20:Y24) -> 176777.41 | Z25: =SUM(Z20:Z24) -> 2121328.9
A28: Unit Type | B28: # | C28: Q1 Rent | D28: Q2 Rent | E28: Q3 Rent | F28: Q4 Rent | G28: 2026 Market | H28: 2027 Market | I28: 2028 Market
A29: 1/1 Classic | B29: 39 | C29: =F20 -> 1049 | D29: =I20 -> 1079 | E29: =L20 -> 1119 | F29: =O20 -> 1140 | G29: =R20 -> 1140 | H29: =G29*1.05 -> 1197 | I29: =H29*1.05 -> 1256.85
A30: 2/1 Classic | B30: 20 | C30: =F21 -> 1119 | D30: =I21 -> 1135 | E30: =L21 -> 1175 | F30: =O21 -> 1215 | G30: =R21 -> 1215 | H30: =G30*1.05 -> 1275.75 | I30: =H30*1.05 -> 1339.5375
A31: 2/1.5 Classic | B31: 33 | C31: =F22 -> 1149 | D31: =I22 -> 1179 | E31: =L22 -> 1219 | F31: =O22 -> 1269 | G31: 1269 | H31: =G31*1.05 -> 1332.45 | I31: =H31*1.05 -> 1399.0725
A32: 2/1.5 Signature | B32: 29 | C32: =F23 -> 1300 | D32: =I23 -> 1329 | E32: =L23 -> 1339 | F32: =O23 -> 1359 | G32: 1359 | H32: =G32*1.05 -> 1426.95 | I32: =H32*1.05 -> 1498.2975
A33: 3/2 Classic | B33: 6 | C33: =F24 -> 1529 | D33: =I24 -> 1569 | E33: =L24 -> 1599 | F33: =O24 -> 1625 | G33: =R24 -> 1625 | H33: =G33*1.05 -> 1706.25 | I33: =H33*1.05 -> 1791.5625
B37: Bonus Structure for New Leases/Renewals
A39: Bonus | B39: 50
A40: Increase | C40: BONUS | D40: 75 | E40: 70 | F40: 60 | G40: 50
A41: Min | B41: Max | C41: Factor | D41: Q1 Bonus | E41: Q2 Bonus | F41: Q3 Rent | G41: Q4 Rent
A42: 0 | B42: 0.3 | C42: 0.1 | D42: =$C42*D$40 -> 7.5 | E42: =$C42*E$40 -> 7 | F42: =$C42*F$40 -> 6 | G42: =$C42*G$40 -> 5
A43: 0.3 | B43: 0.5 | C43: 0.4 | D43: =C43*D$40 -> 30 | E43: =$C43*E$40 -> 28 | F43: =$C43*F$40 -> 24 | G43: =$C43*G$40 -> 20
A44: 0.5 | B44: 0.8 | C44: 0.6 | D44: =C44*D$40 -> 45 | E44: =$C44*E$40 -> 42 | F44: =$C44*F$40 -> 36 | G44: =$C44*G$40 -> 30
A45: 0.8 | B45: 1 | C45: 1 | D45: =C45*D$40 -> 75 | E45: =$C45*E$40 -> 70 | F45: =$C45*F$40 -> 60 | G45: =$C45*G$40 -> 50
B48: RENEWAL SIMULATOR
B49: Quarter | C49: Q2
B50: Quarter Bonus Max | C50: 70
B51: Unit | C51: B1111 | D51: Tenant Increase
B52: Advertised Rent | C52: 1329 | D52: =ABS(C53-C52)/C53 -> 0.022307692
B53: Current Rent | C53: 1300
B54: Achieved Rent | C54: 1320 | D54: =(C54-C53)/C53 -> 0.015384615
B56: Factor Achieved | C56: =_xlfn.XLOOKUP(MIN(($C$54/$C$53-1)/D52,1),$A$42:$A$45,$C$42:$C$45,0,-1) -> 0.6
B57: Bonus Achieved | C57: =C50*_xlfn.XLOOKUP(MIN(($C$54/$C$53-1)/D52,1),$A$42:$A$45,$C$42:$C$45,0,-1) -> 42
B58: ="Congratulations! You achieved a rent increase for Unit of $" & TEXT(C54-C53,"#,##0.00") & ", representing a " & TEXT((C54-C53)/C52,"0.0%") & " lease trade-out versus advertised rent." -> Congratulations! You achieved a rent increase for Unit of $20.00, representing a 1.5% lease trade-out versus advertised rent.
B60: EXAMPLE REPORT TO BE PROVIDED BY PM TO CALCULATE PAYOUT
B61: Unit | C61: Prior Rent | D61: New Rent | E61: Advertised Rent | F61: Lease Trade Out ($) | G61: Lease Trade Out (%) | H61: Quarter | I61: Factor | J61: Bonus Max | K61: Bonus Achieved
B62: =C51 -> B1111 | C62: =C53 -> 1300 | D62: =C54 -> 1320 | E62: =C52 -> 1329 | F62: =D62-C62 -> 20 | G62: =D54 -> 0.015384615 | H62: =C49 -> Q2 | I62: =C56 -> 0.6 | J62: =C50 -> 70 | K62: =C57 -> 42

Sheet Rent Comps
A3: Rent Comps - Dec 30, 2025
E5: 1Bd/1bth - Classic | H5: 2bd/1bth - Classic | K5: 2bd/1.5bth - Classic | N5: 2bd/1.5bth - Signature | Q5: 3bd/2bth
A6: Vintage | B6: Units | C6: Property Name | D6: Rating | E6: Rent | F6: Sqft | G6: Price/Sqft | H6: Rent | I6: Sqft | J6: Price/Sqft | K6: Rent | L6: Sqft | M6: Price/Sqft | N6: Rent | O6: Sqft | P6: Price/Sqft | Q6: Rent | R6: Sqft | S6: Price/Sqft
A7: 1963 | B7: 127 | C7: Oasis at San Marco | D7: 45787 | E7: 999 | F7: 650 | G7: =E7/F7 -> 1.5369231 | H7: 1079 | I7: 800 | J7: =H7/I7 -> 1.34875 | K7: 1150 | L7: 850 | M7: =K7/L7 -> 1.3529412 | N7: 1300 | O7: 850 | P7: =N7/O7 -> 1.5294118 | Q7: 1499 | R7: 1150 | S7: =Q7/R7 -> 1.3034783
A8: 1973 | B8: 207 | C8: The Landings at San Marco | D8: 45818 | E8: 1030 | F8: 680 | G8: =E8/F8 -> 1.5147059 | H8: 1208 | I8: 900 | J8: =H8/I8 -> 1.3422222 | N8: 1589 | O8: 900 | P8: =N8/O8 -> 1.7655556
A9: 1963 | B9: 89 | C9: Prospect Heights | D9: 45787 | E9: 999 | F9: 650 | G9: =E9/F9 -> 1.5369231 | K9: 1135 | L9: 850 | M9: =K9/L9 -> 1.3352941 | N9: 1250 | O9: 850 | P9: =N9/O9 -> 1.4705882
A10: 1969 | B10: 133 | C10: Park Place Apts | D10: 45726 | E10: 825 | F10: 850 | G10: =E10/F10 -> 0.97058824 | K10: 1019 | L10: 1050 | M10: =K10/L10 -> 0.97047619
A11: 1975 | B11: 176 | C11: Marco Meadows | D11: 45787 | E11: 999 | F11: 750 | G11: =E11/F11 -> 1.332 | H11: 1299 | I11: 1050 | J11: =H11/I11 -> 1.2371429
A12: 1985 | B12: 78 | C12: Manchester Apartments | D12: 45757 | E12: 1020 | F12: 576 | G12: =E12/F12 -> 1.7708333 | K12: 1200 | L12: 864 | M12: =K12/L12 -> 1.3888889
A16: Rent Comps - Jan 12, 2025
E18: 1Bd/1bth - Classic | H18: 2bd/1bth - Classic | K18: 2bd/1.5bth - Classic | N18: 2bd/1.5bth - Signature | Q18: 3bd/2bth
A19: Vintage | B19: Units | C19: Property Name | D19: Rating | E19: Rent | F19: Sqft | G19: Price/Sqft | H19: Rent | I19: Sqft | J19: Price/Sqft | K19: Rent | L19: Sqft | M19: Price/Sqft | N19: Rent | O19: Sqft | P19: Price/Sqft | Q19: Rent | R19: Sqft | S19: Price/Sqft
A20: 1963 | B20: 127 | C20: Oasis at San Marco | D20: 45787 | E20: 1049 | F20: 650 | G20: =E20/F20 -> 1.6138462 | H20: 1149 | I20: 800 | J20: =H20/I20 -> 1.43625 | K20: 1119 | L20: 850 | M20: =K20/L20 -> 1.3164706 | N20: 1300 | O20: 850 | P20: =N20/O20 -> 1.5294118 | Q20: 1529 | R20: 1150 | S20: =Q20/R20 -> 1.3295652
A21: 1973 | B21: 207 | C21: The Landings at San Marco | D21: 45818 | E21: 1030 | F21: 680 | G21: =E21/F21 -> 1.5147059 | H21: 1208 | I21: 900 | J21: =H21/I21 -> 1.3422222 | N21: 1589 | O21: 900 | P21: =N21/O21 -> 1.7655556
A22: 1963 | B22: 89 | C22: Prospect Heights | D22: 45787 | E22: 999 | F22: 650 | G22: =E22/F22 -> 1.5369231 | K22: 1135 | L22: 850 | M22: =K22/L22 -> 1.3352941 | N22: 1250 | O22: 850 | P22: =N22/O22 -> 1.4705882
A23: 1969 | B23: 133 | C23: Park Place Apts | D23: 45726 | E23: 825 | F23: 850 | G23: =E23/F23 -> 0.97058824 | K23: 1019 | L23: 1050 | M23: =K23/L23 -> 0.97047619
A24: 1975 | B24: 176 | C24: Marco Meadows | D24: 45787 | E24: 999 | F24: 750 | G24: =E24/F24 -> 1.332 | H24: 1299 | I24: 1050 | J24: =H24/I24 -> 1.2371429
A25: 1985 | B25: 78 | C25: Manchester Apartments | D25: 45757 | E25: 1020 | F25: 576 | G25: =E25/F25 -> 1.7708333 | K25: 1200 | L25: 864 | M25: =K25/L25 -> 1.3888889

Sheet T12 - Nov
V1: 45931 | W1: 45962 | X1: T-12 | Y1: T-1 NOV
U2: Advertising | V2: =L104+L105+L106+L107+L108+L109+L110+L111 -> 3631 | W2: =(M104+M105+M106+M107+M108+M109+M110+M111) -> 3812 | X2: =O104+O105+O106+O107+O108+O109+O110+O111 -> 31392.72 | Y2: =W2*12 -> 45744
U3: Contract Services | V3: =L129+L131+L132+L133+L134+L135+L136+L137+L123+L124 -> 6251.97 | W3: =M129+M131+M132+M133+M134+M135+M136+M137+M123+M124 -> 7348.6 | X3: =O129+O131+O132+O133+O134+O135+O136+O137+O123+O124 -> 66947.02 | Y3: =W3*12 -> 88183.2
U4: Repair and Maintenance | V4: =L100+L114+L115+L116+L117+L118+L119+L120+L121+L122+L125+L128+L130 -> 4187.59 | W4: =M100+M114+M115+M116+M117+M118+M119+M120+M121+M122+M125+M128+M130 -> 6685.8 | X4: =O100+O114+O115+O116+O117+O118+O119+O120+O121+O122+O125+O128+O130 -> 66031.47 | Y4: =W4*12 -> 80229.6
A5: Income Statement - 12 Month | U5: Turn Over | V5: =L95+L96+L97+L98+L99+L101 -> 2705.01 | W5: =M95+M96+M97+M98+M99+M101 -> 1258.46 | X5: =O95+O96+O97+O98+O99+O101 -> 40300.19 | Y5: =W5*12 -> 15101.52
A6: Exported On: 12/10/2025 03:27 PM | U6: Utilities
U7: Gas & Electric | V7: =L140+L141+L144+L145 -> 2316.8 | W7: =M140+M141+M144+M145 -> 2070.33 | X7: =O140+O141+O144+O145 -> 34323.46 | Y7: =W7*12 -> 24843.96
A8: Atrium Management Company | U8: Trash Removal
A9: Properties: Oasis at San Marco - 4800 Atlantic Blvd Jacksonville, FL 32207 | U9: Water and Sewer | V9: =L142+L143+L146 -> 3651.08 | W9: =M142+M143+M146 -> 4249.79 | X9: =O142+O143+O146 -> 41380.97 | Y9: =W9*12 -> 50997.48
A10: Fund Type: All | U10: General/Admin | V10: =L70+L71+L72+L73+L75+L76+L77+L78+L79+L81+L82+L83+L84+L85+L86+L87+L89+L90+L91+L92+L160 -> 2867.27 | W10: =M70+M71+M72+M73+M75+M76+M77+M78+M79+M81+M82+M83+M84+M85+M86+M87+M89+M90+M91+M92+M160 -> 1811.02 | X10: =O70+O71+O72+O73+O75+O76+O77+O78+O79+O81+O82+O83+O84+O85+O86+O87+O89+O90+O91+O92+O160 -> 52530.16 | Y10: =W10*12 -> 21732.24
A11: Period Range: Dec 2024 to Nov 2025 (Trailing 12 Months) | U11: Insurance | V11: =L149 -> 20353.19 | W11: =M149 -> 20353.19 | X11: =O149 -> 206902.04 | Y11: =W11*12 -> 244238.28
A12: Accounting Basis: Accrual | U12: RE Taxes | V12: =L150 -> 15688.81 | W12: =M150 -> 8165.67 | X12: =O150 -> 164042.76 | Y12: =W12*12 -> 97988.04
A13: GL Account Map: None - use master chart of accounts | U13: Legal | V13: =L74+L80 -> 102 | W13: =M74+M80 -> 0 | X13: =O74+O80 -> 3951.5 | Y13: =W13*12 -> 0
A14: Level of Detail: Detail View | U14: Payroll | V14: =L154+L155+L156+L157+L158+L159+L161+L162+L163+L164+L165+L166+L153 -> 15074.27 | W14: =M154+M155+M156+M157+M158+M159+M161+M162+M163+M164+M165+M166+M153 -> 12137.08 | X14: =O154+O155+O156+O157+O158+O159+O161+O162+O163+O164+O165+O166+O153 -> 96128.71 | Y14: =W14*12 -> 145644.96
A15: Include Zero Balance GL Accounts: No | U15: PM Fees | V15: =L64+L65+L66+L69+L88 -> 4500 | W15: =M64+M65+M66+M69+M88 -> 4500 | X15: =O64+O65+O66+O69+O88 -> 126907.18 | Y15: =W15*12 -> 54000
U16: Deposit to Replacement Reserves | V16: 0 | W16: 0 | X16: 0 | Y16: =W16*12 -> 0
A17: Account Name | B17: 45627 | C17: 45658 | D17: 45689 | E17: 45717 | F17: 45748 | G17: 45778 | H17: 45809 | I17: 45839 | J17: 45870 | K17: 45901 | L17: 45931 | M17: 45962 | N17: December | O17: Total | P17: T-3 | Q17: T-6 | R17: Category | S17: Subcategory | U17: Total T12 operating expenses | V17: =SUM(V2:V16) -> 81328.99 | W17: =SUM(W2:W16) -> 72391.94 | X17: =SUM(X2:X16) -> 930838.18 | Y17: =SUM(Y2:Y16) -> 868703.28
A18: Gross Potential Rent | B18: 144721.55 | C18: 146896.53 | D18: 147357.5 | E18: 147078 | F18: 147078 | G18: 147078 | H18: 154421 | I18: 155067.12 | J18: 142265.39 | K18: 136185.3 | L18: 139780.78 | M18: 143362 | N18: 143362 | O18: 1751291.2 | P18: =SUM(K18:M18)*4 -> 1677312.3 | Q18: =SUM(H18:M18)*2 -> 1742163.2
A19: Loss/Gain to Market | B19: -7553.26 | C19: -9302.88 | D19: -7219.92 | E19: -11409.39 | F19: -7196.23 | G19: -8458.77 | H19: -15965.57 | I19: -3498.54 | J19: -1535.7 | K19: 856.42 | L19: -158.9 | M19: -1700.4 | N19: -4847.11 | O19: -73143.14 | P19: =SUM(K19:M19)*4 -> -4011.52 | Q19: =SUM(I19:M19)*2 -> -12074.24
A20: Concessions | B20: -100 | C20: -700 | D20: -1200 | E20: -320 | F20: -200 | G20: -1849 | H20: -1659 | I20: -1409 | J20: -5855 | K20: -17016.5 | L20: -19220.5 | M20: -11589.99 | N20: -609 | O20: -61118.99 | P20: =SUM(K20:M20)*4 -> -191307.96 | Q20: =SUM(I20:M20)*2 -> -110181.98
A21: Concessions - Recurring | B21: 0 | C21: 0 | D21: 0 | E21: 0 | F21: 0 | G21: 0 | H21: -200 | I21: -200 | J21: -200 | K21: -200 | L21: -200 | M21: -100 | N21: -100 | O21: -1100 | P21: =SUM(K21:M21)*4 -> -2000 | Q21: =SUM(I21:M21)*2 -> -1800
A22: Concessions - Employee Unit | B22: 0 | C22: 0 | D22: 0 | E22: 0 | F22: 0 | G22: 0 | H22: 0 | I22: 0 | J22: 0 | K22: -210 | L22: -210 | M22: -210 | N22: -210 | O22: -630 | P22: =SUM(K22:M22)*4 -> -2520 | Q22: =SUM(I22:M22)*2 -> -1260
A23: Vacancy | B23: -29499.93 | C23: -25913.5 | D23: -24560.58 | E23: -19223.61 | F23: -25112.77 | G23: -26229.23 | H23: -29901.46 | I23: -37429.9 | J23: -34280.94 | K23: -17406.1 | L23: -5336.53 | M23: -8718.07 | N23: -6599.14 | O23: -283612.62 | P23: =SUM(K23:M23)*4 -> -125842.8 | Q23: =SUM(I23:M23)*2 -> -206343.08
A24: Bad Debt - Contra | B24: -400 | C24: -22098.2 | D24: -1006 | E24: -20742.65 | F24: -26539.02 | G24: 0 | H24: 0 | I24: -3968 | J24: 0 | K24: -16661.19 | L24: -11674.07 | M24: 0 | N24: -14340 | O24: -103089.13 | P24: =SUM(K24:M24)*4 -> -113341.04 | Q24: =SUM(I24:M24)*2 -> -64606.52
A25: Total Rental Income | B25: 107168.36 | C25: 88881.95 | D25: 113371 | E25: 95382.35 | F25: 88029.98 | G25: 110541 | H25: 106694.97 | I25: 108561.68 | J25: 100393.75 | K25: 85547.93 | L25: 102980.78 | M25: 121043.54 | N25: 116656.75 | O25: 1228597.3 | P25: =SUM(P18:P24) -> 1238289 | Q25: =SUM(I25:M25)*2 -> 1037055.4
A26: Other Income
A27: Lease Lock | B27: 1274 | C27: 1218 | D27: 0 | E27: 0 | F27: 0 | G27: 0 | H27: 0 | I27: 0 | J27: 0 | K27: 0 | L27: 0 | M27: 0 | N27: 0 | O27: 2492 | P27: =SUM(K27:M27)*4 -> 0 | Q27: =SUM(I27:M27)*2 -> 0
A28: NSF Fees Collected | B28: 0 | C28: 165 | D28: 275 | E28: 385 | F28: 55 | G28: 55 | H28: 0 | I28: 150 | J28: 0 | K28: -75 | L28: -75 | M28: 80 | N28: 80 | O28: 1015 | P28: =SUM(K28:M28)*4 -> -280 | Q28: =SUM(I28:M28)*2 -> 160
A29: Late Fee | B29: 2414.8 | C29: 2981 | D29: 3381.7 | E29: 3761.8 | F29: 3081.7 | G29: 3111.8 | H29: 4980.4 | I29: 250 | J29: 2429.16 | K29: 1850.19 | L29: 2271.56 | M29: 2299.95 | N29: 3416.55 | O29: 32814.06 | P29: =SUM(K29:M29)*4 -> 25686.8 | Q29: =SUM(I29:M29)*2 -> 18201.72
A30: Utility Income | B30: 0 | C30: 0 | D30: 0 | E30: 0 | F30: 0 | G30: 0 | H30: 0 | I30: 0 | J30: 9.03 | K30: -9.03 | L30: 0 | M30: 0 | N30: 0 | O30: 0 | P30: =SUM(K30:M30)*4 -> -36.12 | Q30: =SUM(I30:M30)*2 -> 0
A31: Electricity Income | B31: 95 | C31: 95 | D31: 95 | E31: 95 | F31: 95 | G31: 95 | H31: 0 | I31: 0 | J31: 0 | K31: 0 | L31: 0 | M31: 0 | N31: 0 | O31: 570 | P31: =SUM(K31:M31)*4 -> 0 | Q31: =SUM(I31:M31)*2 -> 0
A32: Pet Application Fee | B32: 6794 | C32: 7216 | D32: 7099 | E32: 7482 | F32: 7122 | G32: 7077 | H32: 6398.33 | I32: 6302.77 | J32: 5980.56 | K32: 7009.03 | L32: 7576.96 | M32: 7558.96 | N32: 7534.23 | O32: 83616.61 | P32: =SUM(K32:M32)*4 -> 88579.8 | Q32: =SUM(I32:M32)*2 -> 68856.56
A33: Pet Application Fee | B33: 588 | C33: 661.5 | D33: 735 | E33: 756 | F33: 766.5 | G33: 724.5 | H33: -15.5 | I33: 258.5 | J33: 161 | K33: -107.92 | L33: -58.08 | M33: 263.22 | N33: -109.22 | O33: 4732.72 | P33: =SUM(K33:M33)*4 -> 388.88 | Q33: =SUM(I33:M33)*2 -> 1033.44
A34: Pet Application Fee | B34: 0 | C34: 0 | D34: 0 | E34: 0 | F34: 0 | G34: 0 | H34: 26.52 | I34: -13.52 | J34: -13 | K34: -13 | L34: 0 | M34: 0 | N34: 0 | O34: -13 | P34: =SUM(K34:M34)*4 -> -52 | Q34: =SUM(I34:M34)*2 -> -79.04
A35: Pet Application Fee | B35: -382.5 | C35: -428 | D35: -505 | E35: -563 | F35: -581.5 | G35: -1366 | H35: 0 | I35: 0 | J35: 0 | K35: 0 | L35: 0 | M35: 0 | N35: 0 | O35: -3826 | P35: =SUM(K35:M35)*4 -> 0 | Q35: =SUM(I35:M35)*2 -> 0
A36: Pet Application Fee | B36: 0 | C36: 0 | D36: 0 | E36: 0 | F36: 300 | G36: 0 | H36: 0 | I36: 0 | J36: 0 | K36: 0 | L36: 0 | M36: 0 | N36: 0 | O36: 300 | P36: =SUM(K36:M36)*4 -> 0 | Q36: =SUM(I36:M36)*2 -> 0
A37: Pet Application Fee | B37: 0 | C37: 0 | D37: 0 | E37: 0 | F37: 162.71 | G37: 14.55 | H37: 0 | I37: 0 | J37: 0 | K37: 0 | L37: 0 | M37: 0 | N37: 0 | O37: 177.26 | P37: =SUM(K37:M37)*4 -> 0 | Q37: =SUM(I37:M37)*2 -> 0
A38: Pet Application Fee | B38: 0 | C38: 0 | D38: 0 | E38: 0 | F38: 0 | G38: 222 | H38: 0 | I38: 0 | J38: 0 | K38: 0 | L38: 0 | M38: 0 | N38: 0 | O38: 222 | P38: =SUM(K38:M38)*4 -> 0 | Q38: =SUM(I38:M38)*2 -> 0
... A61: Total Operating Income | B61: 124662.16 | C61: 107988.75 | D61: 128515.7 | E61: 116661.26 | F61: 115786.39 | G61: 128679.44 | H61: 123233.82 | I61: 119971.92 | J61: 114816.73 | K61: 98660.73 | L61: 116969.5 | M61: 138499.73 | N61: 13773.1 | O61: 1434446.1 | P61: =SUM(K61:M61)*4 -> 1416519.8 | Q61: =SUM(I61:M61)*2 -> 1177837.2
A62: Expense | N62: 130429.85
A63: Management Fee Expenses
A64: Management Fees | B64: 15433 | C64: 16178 | D64: 16327 | E64: 16625 | F64: 16923 | G64: 13046.18 | H64: 0 | I64: 0 | J64: 0 | K64: 0 | L64: 0 | M64: 0 | O64: 94532.18 | Q64: =SUM(I64:M64)*2 -> 0 | R64: PM Fees
A65: Lease Renewal Fee | B65: 450 | C65: 900 | D65: 1200 | E65: 450 | F65: 0 | G65: 1050 | H65: 0 | I65: 0 | J65: 0 | K65: 0 | L65: 0 | M65: 0 | O65: 4050 | Q65: =SUM(I65:M65)*2 -> 0 | R65: PM Fees
A66: Management Fee - Multifamily | B66: 0 | C66: 0 | D66: 0 | E66: 0 | F66: 0 | G66: 0 | H66: 4500 | I66: 4500 | J66: 4500 | K66: 4500 | L66: 4500 | M66: 4500 | O66: 27000 | Q66: =SUM(I66:M66)*2 -> 45000 | R66: PM Fees
A67: Total Management Fee Expenses | B67: 15883 | C67: 17078 | D67: 17527 | E67: 17075 | F67: 16923 | G67: 14096.18 | H67: 4500 | I67: 4500 | J67: 4500 | K67: 4500 | L67: 4500 | M67: 4500 | O67: 125582.18
A68: Admin Expenses
A69: Property Inspections | B69: 45 | C69: 0 | D69: 0 | E69: 0 | F69: 0 | G69: 0 | H69: 0 | I69: 0 | J69: 0 | K69: 0 | L69: 0 | M69: 0 | O69: 45 | Q69: =SUM(I69:M69)*2 -> 0 | R69: PM Fees
A70: Payment Processing Fees | B70: 0 | C70: 0 | D70: 0 | E70: 0 | F70: 0 | G70: 0 | H70: 0 | I70: 1430.6 | J70: 0 | K70: 0 | L70: 0 | M70: 0 | O70: 1430.6 | Q70: =SUM(I70:M70)*2 -> 2861.2 | R70: General/Admin
A71: Telephone Expense | B71: 133.84 | C71: 398.15 | D71: 138.15 | E71: 138.15 | F71: 138.01 | G71: 138 | H71: 138.01 | I71: 133 | J71: 158.07 | K71: 145.58 | L71: 138.36 | M71: 138.36 | O71: 1935.68 | Q71: =SUM(I71:M71)*2 -> 1426.74 | R71: General/Admin
A72: Memberships/Professional Organizations | B72: 0 | C72: 0 | D72: 0 | E72: 0 | F72: 0 | G72: 0 | H72: 264.32 | I72: 0 | J72: 0 | K72: 0 | L72: 0 | M72: 0 | O72: 264.32 | Q72: =SUM(I72:M72)*2 -> 0 | R72: General/Admin
A73: Uniforms | B73: 0 | C73: 0 | D73: 0 | E73: 0 | F73: 0 | G73: 0 | H73: 0 | I73: 300 | J73: 0 | K73: 0 | L73: 0 | M73: 0 | O73: 300 | Q73: =SUM(I73:M73)*2 -> 600 | R73: General/Admin
A74: Legal Fees - Retail | B74: 438.5 | C74: 354 | D74: 0 | E74: 0 | F74: 0 | G74: 926 | H74: 0 | I74: 0 | J74: 0 | K74: 0 | L74: 0 | M74: 0 | O74: 1718.5 | Q74: =SUM(I74:M74)*2 -> 0 | R74: Legal
A75: Office Rent | B75: 0 | C75: 0 | D75: 0 | E75: 0 | F75: 0 | G75: 0 | H75: 0 | I75: 0 | J75: 0 | K75: 0 | L75: 32.87 | M75: 0 | O75: 32.87 | Q75: =SUM(I75:M75)*2 -> 65.74 | R75: General/Admin
A76: Office Supplies | B76: 200 | C76: 0 | D76: 0 | E76: 0 | F76: 80.6 | G76: 0 | H76: 253.43 | I76: 47.92 | J76: 64.49 | K76: 0 | L76: 90.33 | M76: 0 | O76: 736.77 | Q76: =SUM(I76:M76)*2 -> 405.48 | R76: General/Admin
A77: Marketing - Entertainment | B77: 0 | C77: 0 | D77: 0 | E77: 0 | F77: 0 | G77: 0 | H77: 0 | I77: 0 | J77: 0 | K77: 0 | L77: 277.36 | M77: 0 | O77: 277.36 | Q77: =SUM(I77:M77)*2 -> 554.72 | R77: General/Admin
A78: Bank Fees | B78: 0 | C78: 0 | D78: 195 | E78: 0 | F78: 0 | G78: 0 | H78: 0 | I78: 0 | J78: 0 | K78: 0 | L78: 0 | M78: 0 | O78: 195 | Q78: =SUM(I78:M78)*2 -> 0 | R78: General/Admin
A79: Office Miscellaneous Expenses | B79: 0 | C79: 0 | D79: 0 | E79: 0 | F79: 0 | G79: 0 | H79: 0 | I79: 483.64 | J79: 0 | K79: 0 | L79: 0 | M79: 48.58 | O79: 532.22 | Q79: =SUM(I79:M79)*2 -> 1064.44 | R79: General/Admin
A80: Legal Expenses | B80: 0 | C80: 0 | D80: 0 | E80: 0 | F80: 0 | G80: 0 | H80: 204 | I80: 926 | J80: 1001 | K80: 0 | L80: 102 | M80: 0 | O80: 2233 | Q80: =SUM(I80:M80)*2 -> 4058 | R80: Legal
A81: Accounting Expenses | B81: 0 | C81: 0 | D81: 0 | E81: 150 | F81: 0 | G81: 5633.42 | H81: 0 | I81: 500 | J81: 350 | K81: 350 | L81: 350 | M81: 350 | O81: 7683.42 | Q81: =SUM(I81:M81)*2 -> 3800 | R81: General/Admin
A82: Other Professional Fees | B82: 14300 | C82: 150 | D82: 2350 | E82: -520.5 | G82: 5300 | H82: 0 | I82: 0 | J82: 0 | K82: 0 | L82: 0 | M82: 0 | O82: 21579.5 | Q82: =SUM(I82:M82)*2 -> 0 | R82: General/Admin
A83: Postage and Shipping Expenses | B83: 0 | C83: 0 | D83: 0 | E83: 0 | F83: 0 | G83: 0 | H83: 0 | I83: 0 | J83: 0 | K83: 0 | L83: 208.06 | M83: 0 | O83: 208.06 | Q83: =SUM(I83:M83)*2 -> 416.12 | R83: General/Admin
A84: License and Permits | B84: 256 | C84: 796.72 | D84: 0 | E84: 0 | F84: 700.35 | G84: 0 | H84: 0 | I84: 0 | J84: 0 | K84: 0 | L84: 0 | M84: 0 | O84: 1753.07 | Q84: =SUM(I84:M84)*2 -> 0 | R84: General/Admin
A85: Education and Training | B85: 0 | C85: 0 | D85: 0 | E85: 0 | F85: 0 | G85: 0 | H85: 0 | I85: 0 | J85: 350 | K85: 0 | L85: 0 | M85: 0 | O85: 350 | Q85: =SUM(I85:M85)*2 -> 700 | R85: General/Admin
A86: Computer Software | B86: 0 | C86: 256 | D86: 256 | E86: 256 | F86: 256 | G86: 206.45 | H86: 300 | I86: 4622.79 | J86: 1407.22 | K86: 1107.22 | L86: 1107.22 | M86: 1107.22 | O86: 10882.12 | Q86: =SUM(I86:M86)*2 -> 18703.34 | R86: General/Admin
A87: After Hours Cell Phone | B87: 99 | C87: 99 | D87: 99 | E87: 99 | F87: 99 | G87: 99 | H87: 99 | I87: 99 | J87: 128 | K87: 99 | L87: 397 | M87: 0 | O87: 1416 | Q87: =SUM(I87:M87)*2 -> 1446 | R87: General/Admin
A88: Property Setup Fee | B88: 0 | C88: 0 | D88: 0 | G88: 0 | H88: 0 | I88: 1280 | J88: 0 | K88: 0 | L88: 0 | M88: 0 | O88: 1280 | Q88: =SUM(I88:M88)*2 -> 2560 | R88: PM Fees
A89: Online Bill Pay | B89: 0 | C89: 0 | D89: 0 | E89: 0 | F89: 0 | G89: 0 | H89: 0 | I89: 0 | J89: 11.5 | K89: 73.8 | L89: 48 | M89: 21.6 | O89: 154.9 | Q89: =SUM(I89:M89)*2 -> 309.8 | R89: General/Admin
A90: Recruiting Expense | B90: 0 | C90: 0 | D90: 0 | E90: 0 | F90: 0 | G90: 0 | H90: 0 | I90: 0 | J90: 0 | K90: 0 | L90: 148.74 | M90: 0 | O90: 148.74 | Q90: =SUM(I90:M90)*2 -> 297.48 | R90: General/Admin
A91: Verifast | B91: 0 | C91: 0 | D91: 45 | E91: 1080 | F91: 225 | G91: 540 | H91: 125 | I91: 0 | J91: 0 | K91: 0 | L91: 0 | M91: 100 | O91: 2115 | Q91: =SUM(I91:M91)*2 -> 200 | R91: General/Admin
A92: Staff-Meals/Entertainment | B92: 2.84 | C92: 0 | D92: 0 | E92: 0 | F92: 0 | G92: 0 | H92: 75.23 | I92: 0 | J92: 0 | K92: 0 | L92: 0 | M92: 0 | O92: 78.07 | Q92: =SUM(I92:M92)*2 -> 0 | R92: General/Admin
A93: Total Admin Expenses | B93: 15475.18 | C93: 2053.87 | D93: 3083.15 | E93: 1202.65 | F93: 6798.96 | G93: 7542.87 | H93: 1458.99 | I93: 9822.95 | J93: 3470.28 | K93: 1775.6 | L93: 2899.94 | M93: 1765.76 | O93: 57350.2
A94: Turn Costs
A95: Carpet/ Floor Replacement - Turns | B95: 0 | C95: 0 | D95: 0 | E95: 0 | F95: 0 | G95: 0 | H95: 0 | I95: 0 | J95: 0 | K95: 1715.42 | L95: 0 | M95: 514.16 | O95: 2229.58 | R95: Turn Over
A96: Painting Turn | B96: 1720.67 | C96: 4650 | D96: 1333.7 | E96: 1558.63 | F96: 0 | G96: 0 | H96: 0 | I96: 0 | J96: 670.77 | K96: 290 | L96: 0 | M96: 509.3 | O96: 10733.07 | R96: Turn Over
A97: Cleaning/Janitorial Turn | B97: 1160 | C97: 1261.33 | D97: 386.54 | E97: 985 | F97: 1870 | G97: 2420 | H97: 0 | I97: 0 | J97: 236.03 | K97: 1540.36 | L97: 2190.01 | M97: 235 | O97: 12284.27 | R97: Turn Over
A98: Key/Lock Turn | B98: 19.95 | C98: 0 | D98: 80.3 | E98: 0 | F98: 0 | G98: -31.98 | H98: 0 | I98: 0 | J98: 0 | K98: 0 | L98: 0 | M98: 0 | O98: 68.27 | R98: Turn Over
A99: Carpet/Tile Cleaning - Turns | B99: 200 | C99: 0 | D99: 0 | E99: 0 | F99: 125 | G99: 980 | H99: 0 | I99: 0 | J99: 0 | K99: 0 | L99: 515 | M99: 0 | O99: 1820 | R99: Turn Over
A100: Turn Repairs R&M | B100: 0 | C100: 0 | D100: 0 | E100: 0 | F100: 0 | G100: 0 | H100: 0 | I100: 0 | J100: 152 | K100: 5140 | L100: 61.19 | M100: 0 | O100: 5353.19 | R100: Repair and Maintenance
A101: Tub/Shower Resurfacing - Turns | B101: 0 | C101: 0 | D101: 560 | E101: 4100 | F101: 0 | G101: 6260 | H101: 0 | I101: 0 | J101: 2245 | K101: 0 | L101: 0 | M101: 0 | O101: 13165 | R101: Turn Over
A102: Total Turn Costs | B102: 3100.62 | C102: 5911.33 | D102: 2360.54 | E102: 6643.63 | F102: 1995 | G102: 9628.02 | H102: 0 | I102: 0 | J102: 3303.8 | K102: 8685.78 | L102: 2766.2 | M102: 1258.46 | O102: 45653.38
A103: Advertising
A104: Advertising - General | B104: 645 | C104: 645 | D104: 667.17 | E104: 682.98 | F104: 1175 | G104: 1820 | H104: 0 | I104: 0 | J104: 0 | K104: 0 | L104: 0 | M104: 0 | O104: 5635.15 | R104: Advertising
A105: Website | B105: 0 | C105: 0 | D105: 0 | E105: 0 | F105: 0 | G105: 0 | H105: 1950 | I105: 0 | J105: 0 | K105: 0 | L105: 0 | M105: 0 | O105: 1950 | R105: Advertising
A106: Resident Referral Fees | B106: 0 | C106: 0 | D106: 0 | E106: 0 | F106: 0 | G106: 0 | H106: 0 | I106: 0 | J106: 600 | K106: 750 | L106: 0 | M106: 250 | O106: 1600 | R106: Advertising
A107: Marketing / Promotions | B107: 0 | C107: 0 | D107: 0 | E107: 0 | F107: 0 | G107: 0 | H107: 0 | I107: 429.38 | J107: 0 | K107: -79.03 | L107: 69 | M107: 0 | O107: 419.35 | R107: Advertising
A108: Resident Refreshments and Events | B108: 0 | C108: 0 | D108: 0 | E108: 0 | F108: 0 | G108: 0 | H108: 0 | I108: 0 | J108: 373.23 | K108: 0 | L108: 0 | M108: 0 | O108: 373.23 | R108: Advertising
A109: Model Expense | B109: 0 | C109: 0 | D109: 0 | E109: 0 | F109: 0 | G109: 0 | H109: 0 | I109: 0 | J109: 0 | K109: 163.95 | L109: 0 | M109: 0 | O109: 163.95 | R109: Advertising
A110: Apartments.com | B110: 0 | C110: 0 | D110: 0 | E110: 0 | F110: 0 | G110: 0 | H110: 2940.39 | I110: 2532 | J110: 2832 | K110: 2832 | L110: 2832 | M110: 2832 | O110: 16800.39 | R110: Advertising
A111: Zillow | B111: 0 | C111: 0 | D111: 0 | E111: 0 | F111: 0 | G111: 0 | H111: 800.65 | I111: 730 | J111: 730 | K111: 730 | L111: 730 | M111: 730 | O111: 4450.65 | R111: Advertising
A112: Total Advertising | B112: 645 | C112: 645 | D112: 667.17 | E112: 682.98 | F112: 1175 | G112: 1820 | H112: 5691.04 | I112: 3691.38 | J112: 4535.23 | K112: 4396.92 | L112: 3631 | M112: 3812 | O112: 31392.72
A113: Repairs and Maintenance
A114: HVAC (Heat, Ventilation, Air) R&M | B114: 776.97 | C114: 704.69 | D114: 234.76 | E114: 960 | F114: 0 | G114: 1475.28 | H114: 1205.79 | I114: 502.98 | J114: 2330 | K114: 818.79 | L114: 2001.93 | M114: 45.12 | O114: 11056.31 | R114: Repair and Maintenance
A115: Plumbing R&M | B115: 3414.03 | C115: 532.35 | D115: 511.46 | E115: 2075.99 | F115: 0 | G115: 861.56 | H115: 2205.25 | I115: 0 | J115: 1872.8 | K115: 2179.47 | L115: 601.88 | M115: 3883.34 | O115: 18138.13 | R115: Repair and Maintenance
A116: Electrical R&M | B116: 610 | C116: 775 | D116: 205.3 | E116: 0 | F116: 650 | G116: 0 | H116: 309.3 | I116: 0 | J116: 0 | K116: 0 | L116: 0 | M116: 0 | O116: 2549.6 | R116: Repair and Maintenance
A117: Roof R&M | B117: 1500 | C117: 1500 | D117: 750 | E117: 0 | F117: 0 | G117: 800 | H117: 0 | I117: 0 | J117: 645 | K117: 0 | L117: 396.41 | M117: 0 | O117: 5591.41 | R117: Repair and Maintenance
A118: Supplies R&M | B118: 1009.81 | C118: 510.19 | D118: 1369.28 | E118: 1819.9 | F118: 674.13 | G118: 4162.29 | H118: 857 | I118: 0 | J118: 0 | K118: 0 | L118: 0 | M118: 209.99 | O118: 10612.59 | R118: Repair and Maintenance
A119: Window and Screen R&M | B119: 0 | C119: 0 | D119: 0 | E119: 0 | F119: 1405 | G119: 954.6 | H119: 0 | I119: 0 | J119: 0 | K119: 633.25 | L119: 0 | M119: 1225 | O119: 4217.85 | R119: Repair and Maintenance
A120: Repair R&M | B120: 266.61 | C120: 0 | D120: 125 | E120: -105 | F120: 0 | G120: 0 | H120: 1123.32 | I120: 161.49 | J120: 397.86 | K120: 953.46 | L120: 1018.7 | M120: 1322.35 | O120: 5263.79 | R120: Repair and Maintenance
A121: Equipment/Tools R&M | B121: 0 | C121: 0 | D121: -118 | E121: 0 | F121: 0 | G121: 128.99 | H121: 0 | I121: 0 | J121: 0 | K121: 0 | L121: 107.48 | M121: 0 | O121: 118.47 | R121: Repair and Maintenance
A122: Maintenance Services Request | B122: 0 | C122: 75 | D122: 0 | E122: 50 | F122: 50 | G122: 25 | H122: 0 | I122: 0 | J122: 0 | K122: 0 | L122: 0 | M122: 0 | O122: 200 | R122: Repair and Maintenance
...

Sheet T-12 Summarized - Nov
B4: Account Name | C4: 45627 | D4: 45658 | E4: 45689 | F4: 45717 | G4: 45748 | H4: 45778 | I4: 45809 | J4: 45839 | K4: 45870 | L4: 45901 | M4: 45931 | N4: 45962 | O4: TOTAL | P4: T-6 | Q4: T-3 | R4: T-1
B5: Rental Income | C5: 107168.36 | D5: 88881.95 | E5: 113371 | F5: 95382.35 | G5: 88029.98 | H5: 110541 | I5: 106694.97 | J5: 108561.68 | K5: 100393.75 | L5: 85547.93 | M5: 102980.78 | N5: 121043.54 | O5: =SUM(C5:N5) -> 1228597.3 | P5: =SUM(I5:N5)*2 -> 1250445.3 | Q5: =SUM(L5:N5)*4 -> 1238289 | R5: =N5*12 -> 1452522.5
B6: Other Income | C6: 17493.8 | D6: 19106.8 | E6: 15144.7 | F6: 21278.91 | G6: 27756.41 | H6: 18138.44 | I6: 16538.85 | J6: 11410.24 | K6: 14422.98 | L6: 13112.8 | M6: 13988.72 | N6: 17456.19 | O6: =SUM(C6:N6) -> 205848.84 | P6: =SUM(I6:N6)*2 -> 173859.56 | Q6: =SUM(L6:N6)*4 -> 178230.84 | R6: =N6*12 -> 209474.28
B7: Total Operating Income | C7: 124662.16 | D7: 107988.75 | E7: 128515.7 | F7: 116661.26 | G7: 115786.39 | H7: 128679.44 | I7: 123233.82 | J7: 119971.92 | K7: 114816.73 | L7: 98660.73 | M7: 116969.5 | N7: 138499.73 | O7: =SUM(C7:N7) -> 1434446.1 | P7: =SUM(I7:N7)*2 -> 1424304.9 | Q7: =SUM(L7:N7)*4 -> 1416519.8 | R7: =N7*12 -> 1661996.8
B9: Management Fee Expenses | C9: 15883 | D9: 17078 | E9: 17527 | F9: 17075 | G9: 16923 | H9: 14096.18 | I9: 4500 | J9: 4500 | K9: 4500 | L9: 4500 | M9: 4500 | N9: 4500 | R9: =N9*12 -> 54000
B10: Admin Expenses | C10: 15475.18 | D10: 2053.87 | E10: 3083.15 | F10: 1202.65 | G10: 6798.96 | H10: 7542.87 | I10: 1458.99 | J10: 9822.95 | K10: 3470.28 | L10: 1775.6 | M10: 2899.94 | N10: 1765.76 | R10: =N10*12 -> 21189.12
B11: Turn Costs | C11: 3100.62 | D11: 5911.33 | E11: 2360.54 | F11: 6643.63 | G11: 1995 | H11: 9628.02 | I11: 0 | J11: 0 | K11: 3303.8 | L11: 8685.78 | M11: 2766.2 | N11: 1258.46 | R11: =N11*12 -> 15101.52
B12: Advertising | C12: 645 | D12: 645 | E12: 667.17 | F12: 682.98 | G12: 1175 | H12: 1820 | I12: 5691.04 | J12: 3691.38 | K12: 4535.23 | L12: 4396.92 | M12: 3631 | N12: 3812 | R12: =N12*12 -> 45744
B13: Repairs and Maintenance | C13: 7577.42 | D13: 4542.23 | E13: 3077.8 | F13: 5270.89 | G13: 4609.13 | H13: 9282.4 | I13: 5700.66 | J13: 702.97 | K13: 5245.66 | L13: 5314.97 | M13: 5026.4 | N13: 6685.8 | R13: =N13*12 -> 80229.6
B14: Contract Services | C14: 5951.14 | D14: 3180.09 | E14: 4322.42 | F14: 4875.68 | G14: 5150.68 | H14: 9071.55 | I14: 5013.05 | J14: 3890.75 | K14: 5456.68 | L14: 4976.36 | M14: 5351.97 | N14: 7348.6 | R14: =N14*12 -> 88183.2
B15: Utilities | C15: 5268.91 | D15: 8163.11 | E15: 5740.67 | F15: 4829.93 | G15: 5597.64 | H15: 6333.39 | I15: 6743.78 | J15: 6410.55 | K15: 7404.19 | L15: 6924.26 | M15: 5967.88 | N15: 6320.12 | R15: =N15*12 -> 75841.44
B16: Taxes and Insurance | C16: 32302.9 | D16: 21102.44 | E16: 30149.1 | F16: 30149.1 | G16: 30149.1 | H16: 30149.1 | I16: 30149.1 | J16: 30149.1 | K16: 36042 | L16: 36042 | M16: 36042 | N16: 28518.86 | R16: =N16*12 -> 342226.32
B17: Payroll Expenses | C17: 1200 | D17: 0 | E17: 0 | F17: 0 | G17: 0 | H17: 2303.05 | I17: 14595.66 | J17: 20007.3 | K17: 18746.52 | L17: 12406.7 | M17: 15143.6 | N17: 12182.34 | R17: =N17*12 -> 146188.08
B18: TOTAL | C18: =SUM(C9:C17) -> 87404.17 | D18: =SUM(D9:D17) -> 62676.07 | E18: =SUM(E9:E17) -> 66927.85 | F18: =SUM(F9:F17) -> 70729.86 | G18: =SUM(G9:G17) -> 72398.51 | H18: =SUM(H9:H17) -> 90226.56 | I18: =SUM(I9:I17) -> 73852.28 | J18: =SUM(J9:J17) -> 79175 | ... N18: =SUM(N9:N17) -> 72391.94 | R18: =SUM(R9:R17) -> 868703.28
C20: 45627 | D20: 45658 | E20: 45689 | F20: 45717 | G20: 45748 | H20: 45778 | I20: 45809 | J20: 45839 | K20: 45870 | L20: 45901 | M20: 45931 | N20: 45962
B21: Management Fee Expenses | C21: 15883 | D21: 17078 | E21: 17527 | F21: 17075 | G21: 16923 | H21: 14096.18 | I21: 4500 | J21: 4500 | K21: 4500 | L21: 4500 | M21: 4500 | N21: 4500
B22: Admin Expenses | C22: 15475.18 | D22: 2053.87 | E22: 3083.15 | F22: 1202.65 | G22: 6798.96 | H22: 7542.87 | I22: 1458.99 | J22: 9822.95 | K22: 3470.28 | L22: 1775.6 | M22: 2899.94 | N22: 1765.76
B23: Turn Costs | C23: 3100.62 | D23: 5911.33 | E23: 2360.54 | F23: 6643.63 | G23: 1995 | H23: 9628.02 | I23: 0 | J23: 0 | K23: 3303.8 | L23: 8685.78 | M23: 2766.2 | N23: 1258.46
B24: Advertising | C24: 645 | D24: 645 | E24: 667.17 | F24: 682.98 | G24: 1175 | H24: 1820 | I24: 5691.04 | J24: 3691.38 | K24: 4535.23 | L24: 4396.92 | M24: 3631 | N24: 3812
B25: Repairs and Maintenance | C25: 7577.42 | D25: 4542.23 | E25: 3077.8 | F25: 5270.89 | G25: 4609.13 | H25: 9282.4 | I25: 5700.66 | J25: 702.97 | K25: 5245.66 | L25: 5314.97 | M25: 5026.4 | N25: 6685.8
B26: Contract Services | C26: 5951.14 | D26: 3180.09 | E26: 4322.42 | F26: 4875.68 | G26: 5150.68 | H26: 9071.55 | I26: 5013.05 | J26: 3890.75 | K26: 5456.68 | L26: 4976.36 | M26: 5351.97 | N26: 7348.6
B27: Utilities | C27: 5268.91 | D27: 8163.11 | E27: 5740.67 | F27: 4829.93 | G27: 5597.64 | H27: 6333.39 | I27: 6743.78 | J27: 6410.55 | K27: 7404.19 | L27: 6924.26 | M27: 5967.88 | N27: 6320.12
B28: Taxes and Insurance | C28: 32302.9 | D28: 21102.44 | E28: 30149.1 | F28: 30149.1 | G28: 30149.1 | H28: 30149.1 | I28: 30149.1 | J28: 30149.1 | K28: 36042 | L28: 36042 | M28: 36042 | N28: 28518.86
B29: Payroll Expenses | C29: 1200 | D29: 0 | E29: 0 | F29: 0 | G29: 0 | H29: 2303.05 | I29: 14595.66 | J29: 20007.3 | K29: T-12 | L29: 12406.7 | M29: 15143.6 | N29: 12182.34
B30: TOTAL | C30: =SUM(C21:C29) -> 87404.17 | D30: =SUM(D21:D29) -> 62676.07 | E30: =SUM(E21:E29) -> 66927.85 | F30: =SUM(F21:F29) -> 70729.86 | G30: =SUM(G21:G29) -> 72398.51 | H30: =SUM(H21:H29) -> 90226.56 | I30: =SUM(I21:I29) -> 73852.28 | J30: =SUM(J21:J29) -> 79175 | ... N30: =SUM(N21:N29) -> 72391.94

Sheet Sheet2
A1: December 2025 Rent Roll Analysis
A3: Row Labels | B3: Count of Unit | C3: Sum of Rent | D3: Sum of Recurring Charges
A4: Current | B4: 106 | C4: 113554 | D4: 11921.5
A5: Notice-Rented | B5: 2 | C5: 2004 | D5: 361
A6: Notice-Unrented | B6: 5 | C6: 5541 | D6: 656
A7: Grand Total | B7: 113 | C7: 121099 | D7: 12938.5

Sheet Rent Roll - Dec25
A1: Unit Type | B1: Sqft | C1: Unit | D1: Tenant | E1: Status | F1: Market Rent | G1: Rent | H1: Recurring Charges | I1: Lease From | J1: Lease To | K1: Move-in | L1: Move-out | M1: Past Due | N1: Advertised Rent
A2: 2/1.5 Classic | B2: 850 | C2: A106 | E2: Vacant-Rented | F2: 1149 | H2: 0 | N2: 1149
A3: 2/1.5 Classic | B3: 850 | C3: A107 | E3: Vacant-Unrented | F3: 1149 | H3: 0 | N3: 1149
A4: 1/1 Classic | B4: 650 | C4: B137 | E4: Vacant-Rented | F4: 1029 | H4: 0 | N4: 999
A5: 2/1.5 Signature | B5: 850 | C5: G138 | E5: Vacant-Unrented | F5: 1199 | H5: 0 | N5: 1199
A6: 2/1.5 Classic | B6: 850 | C6: G240 | E6: Vacant-Unrented | F6: 1149 | H6: 0 | N6: 1149
A7: 3 Bed 2 Bath | B7: 1150 | C7: I253 | E7: Vacant-Rented | F7: 1399 | H7: 0 | N7: 1499
A8: 3 Bed 2 Bath | B8: 1150 | C8: I255 | D8: Maria E. Henderson | E8: Current | F8: 1399 | G8: 0 | H8: 149.5 | I8: 43206 | J8: 46372 | K8: 43206 | M8: -1449.5 | N8: 1399
A9: 1/1 Classic | B9: 650 | C9: B132 | D9: Vivian Jenkins | E9: Evict | F9: 1029 | G9: 620 | H9: 120.5 | I9: 41694 | J9: 45838 | K9: 41694 | M9: 3868.1 | N9: 1029
A10: 1/1 Classic | B10: 650 | C10: B236 | D10: Persharon Jennings | E10: Current | F10: 1029 | G10: 632 | H10: 45 | I10: 42307 | J10: 45470 | K10: 42307 | M10: -179 | N10: 1029
A11: 1/1 Classic | B11: 650 | C11: B136 | D11: Arlene Marcellus-Summers | E11: Notice-Rented | F11: 1029 | G11: 905 | H11: 239.5 | I11: 43483 | J11: 45912 | K11: 43483 | L11: 46022 | M11: 0 | N11: 1029
A12: 1/1 Classic | B12: 650 | C12: F213 | D12: Doris Blake | E12: Current | F12: 1029 | G12: 925 | H12: 96.5 | I12: 43203 | J12: 46356 | K12: 43203 | M12: 0 | N12: 1029
A13: 1/1 Classic | B13: 650 | C13: F113 | D13: Lisa Colon | E13: Current | F13: 1029 | G13: 943 | H13: 113.5 | I13: 40764 | J13: 46147 | K13: 40764 | M13: 1661.5 | N13: 1029
A14: 1/1 Classic | B14: 650 | C14: B134 | D14: Myia M. Natson-Green | E14: Current | F14: 1029 | G14: 949 | H14: 121.5 | I14: 45930 | J14: 46294 | K14: 45930 | M14: 0 | N14: 1029
A15: 1/1 Classic | B15: 650 | C15: B232 | D15: Jemuel A. Derla | E15: Current | F15: 1029 | G15: 949 | H15: 121.5 | I15: 45891 | J15: 46265 | K15: 45891 | M15: 0 | N15: 1029
A16: 1/1 Classic | B16: 650 | C16: B234 | D16: Tavish D. Reynolds | E16: Current | F16: 1029 | G16: 949 | H16: 121.5 | I16: 45899 | J16: 46265 | K16: 45899 | M16: 0 | N16: 1029
A17: 1/1 Classic | B17: 650 | C17: F111 | D17: Asia R. Lincoln | E17: Current | F17: 1029 | G17: 949 | H17: 121.5 | I17: 45910 | J17: 46295 | K17: 45910 | M17: -1070.5 | N17: 1029
A18: 1/1 Classic | B18: 650 | C18: F115 | D18: Donnalyn A. Montgomery | E18: Current | F18: 1029 | G18: 949 | H18: 106 | I18: 45930 | J18: 46294 | K18: 45930 | M18: 0 | N18: 1029
A19: 1/1 Classic | B19: 650 | C19: I156 | D19: Carlos A. Garcia | E19: Current | F19: 1029 | G19: 949 | H19: 121.5 | I19: 45910 | J19: 46274 | K19: 45910 | M19: -1070.5 | N19: 1029
A20: 1/1 Classic | B20: 650 | C20: I254 | D20: Adriana Pedroso | E20: Current | F20: 1029 | G20: 949 | H20: 121.5 | I20: 45912 | J20: 46276 | K20: 45912 | M20: 0 | N20: 1029
A21: 1/1 Classic | B21: 650 | C21: B233 | D21: Vanness White | E21: Current | F21: 1029 | G21: 950 | H21: 124.5 | I21: 44901 | J21: 46387 | K21: 44901 | M21: -549 | N21: 1029
A22: 1/1 Classic | B22: 650 | C22: B133 | D22: Allison Jones | E22: Current | F22: 1029 | G22: 975 | H22: 76 | I22: 40185 | J22: 46067 | K22: 40185 | M22: -250 | N22: 1029
A23: 1/1 Classic | B23: 650 | C23: I258 | D23: Burton Martinez | E23: Current | F23: 1029 | G23: 975 | H23: 123.5 | I23: 43615 | J23: 46142 | K23: 43615 | M23: 0 | N23: 1029
... A31: 2/1 Classic | B31: 800 | C31: E119 | D31: Michael Hays | E31: Current | F31: 1049 | G31: 999 | H31: 106 | I31: 45899 | J31: 46263 | K31: 45899 | M31: -1105 | N31: 1049
A32: 1/1 Classic | B32: 650 | C32: F110 | D32: Alfredo Raudez Ramos | E32: Notice-Unrented | F32: 1029 | G32: 999 | H32: 113.5 | I32: 45772 | J32: 46142 | K32: 45772 | L32: 46024 | M32: 0 | N32: 1029
A33: 1/1 Classic | B33: 650 | C33: F112 | D33: Frantzso Etienne | E33: Current | F33: 1029 | G33: 999 | H33: 105.5 | I33: 45710 | J33: 46074 | K33: 45710 | M33: 0 | N33: 1029
A34: 1/1 Classic | B34: 650 | C34: F114 | D34: Yerili Rodriguez Chong | E34: Current | F34: 1029 | G34: 999 | H34: 118 | I34: 44228 | J34: 46418 | K34: 44228 | M34: -1117 | N34: 1029
A35: 1/1 Classic | B35: 650 | C35: F210 | D35: Jose Morles Hernandez | E35: Current | F35: 1029 | G35: 999 | H35: 141.5 | I35: 45659 | J35: 46388 | K35: 45659 | M35: -1140.5 | N35: 1029
A36: 1/1 Classic | B36: 650 | C36: F212 | D36: Shawn Geddes | E36: Evict | F36: 1029 | G36: 999 | H36: 111.5 | I36: 45582 | J36: 46295 | K36: 45582 | M36: 1721 | N36: 1029
A37: 1/1 Classic | B37: 650 | C37: F214 | D37: Wayne Wicker | E37: Current | F37: 1029 | G37: 999 | H37: 96.5 | J37: 46326 | K37: 41979 | M37: 0 | N37: 1029
A38: 1/1 Classic | B38: 650 | C38: I158 | D38: Kassidy King | E38: Current | F38: 1029 | G38: 999 | H38: 113.5 | I38: 45778 | J38: 46142 | K38: 45778 | M38: 0 | N38: 1029
A39: 1/1 Classic | B39: 650 | C39: I256 | D39: Nelson Perdomo Alvarez | E39: Current | F39: 1029 | G39: 999 | H39: 113.5 | I39: 45383 | J39: 46112 | K39: 45383 | M39: 0 | N39: 1029
A40: 2/1 Classic | B40: 800 | C40: J246 | D40: Pashent Robinson | E40: Current | F40: 1049 | G40: 999 | I40: 45900 | J40: 46264 | K40: 45900 | M40: 0 | N40: 1049
A41: 2/1 Classic | B41: 800 | C41: J247 | D41: Shelly Diallo | E41: Evict | F41: 1049 | G41: 999 | H41: 118.5 | I41: 45880 | J41: 46244 | K41: 45880 | M41: 2465.9 | N41: 1049
A42: 2/1 Classic | B42: 800 | C42: J249 | D42: Aaliyah K. Myers | E42: Current | F42: 1049 | G42: 999 | H42: 122 | I42: 45891 | J42: 46265 | K42: 45891 | M42: -1121 | N42: 1049
A43: 2/1 Classic | B43: 800 | C43: E118 | D43: Miguel Munoz Alvarado | E43: Current | F43: 1049 | G43: 1000 | H43: 158.5 | I43: 45055 | J43: 46142 | K43: 45055 | M43: 0 | N43: 1049
A44: 1/1 Classic | B44: 650 | C44: C228 | D44: Ability Housing, Inc. | E44: Current | F44: 1029 | G44: 1025 | H44: 111.5 | I44: 45618 | J44: 46349 | K44: 45618 | M44: -598 | N44: 1029
A45: 1/1 Classic | B45: 650 | C45: C230 | D45: Yanely Gomez | E45: Current | F45: 1029 | G45: 1025 | H45: 111.5 | I45: 45601 | J45: 46326 | K45: 45601 | M45: -1136.5 | N45: 1029
A46: 1/1 Classic | B46: 650 | C46: F215 | D46: Presbyterian Social Ministries | E46: Current | F46: 1029 | G46: 1025 | H46: 111.5 | I46: 45595 | J46: 46326 | K46: 45595 | M46: 0 | N46: 1029
A47: 2/1.5 Classic | B47: 850 | C47: D225 | D47: Omega A. Johnson | E47: Current | F47: 1149 | G47: 1029 | H47: 121.5 | I47: 45982 | J47: 46339 | K47: 45975 | M47: 40.5 | N47: 1029
A48: 2/1 Classic | B48: 800 | C48: J150 | D48: Lacoria S. Glover | E48: Current | F48: 1049 | G48: 1029 | H48: 121.5 | I48: 46003 | J48: 46367 | K48: 46003 | M48: -1150.5 | N48: 1049
A49: 2/1.5 Classic | B49: 850 | C49: D226 | D49: Lisandro Matos | E49: Current | F49: 1149 | G49: 1030 | H49: 106.5 | I49: 42620 | J49: 46326 | K49: 42620 | M49: -1136.5 | N49: 1149
A50: 1/1 Classic | B50: 650 | C50: C229 | D50: Beryl Davis III | E50: Notice-Unrented | F50: 1029 | G50: 1040 | H50: 133.5 | I50: 44968 | K50: 44968 | L50: 46035 | M50: -1173.5 | N50: 1029
A51: 1/1 Classic | B51: 650 | C51: B235 | D51: Andre Outlaw | E51: Notice-Unrented | F51: 1029 | G51: 1045 | H51: 153 | I51: 45313 | J51: 46053 | K51: 45313 | L51: 46053 | M51: -1198 | N51: 1029
A52: 2/1.5 Signature | B52: 850 | C52: A103 | D52: Nicole J. Rhodes | E52: Current | F52: 1199 | G52: 1049 | H52: 121.5 | I52: 45992 | J52: 46356 | K52: 45992 | M52: -1170.5 | N52: 1199
A53: 2/1.5 Classic | B53: 850 | C53: D126 | D53: SanTonio M. Davis | E53: Current | F53: 1149 | G53: 1049 | H53: 121.5 | I53: 45947 | J53: 46326 | K53: 45947 | M53: 0 | N53: 1149
A54: 2/1.5 Classic | B54: 850 | C54: D127 | D54: Genesis Badnegas | E54: Current | F54: 1149 | G54: 1049 | H54: 121.5 | I54: 45902 | J54: 46266 | K54: 45902 | M54: 0 | N54: 1149
A55: 2/1 Classic | B55: 800 | C55: E116 | D55: Nicole A. Cunningham | E55: Current | F55: 1049 | G55: 1049 | H55: 121.5 | I55: 45899 | J55: 46263 | K55: 45899 | M55: 0 | N55: 1049
A56: 1/1 Classic | B56: 650 | C56: F211 | D56: Erick Torres Escalera | E56: Current | F56: 1029 | G56: 1049 | H56: 133.5 | I56: 45065 | J56: 45748 | K56: 45065 | M56: 100 | N56: 1029
A57: 2/1.5 Classic | B57: 850 | C57: G143 | D57: Temeka R. Stanley | E57: Current | F57: 1149 | G57: 1049 | H57: 121.5 | I57: 45897 | J57: 46261 | K57: 45897 | M57: 121.5 | N57: 1149
A58: 2/1.5 Classic | B58: 850 | C58: G145 | D58: wilfrido sanchez martinez | E58: Current | F58: 1149 | G58: 1049 | H58: 121.5 | I58: 45897 | J58: 46265 | K58: 45897 | M58: -92 | N58: 1149
A59: 2/1.5 Classic | B59: 850 | C59: H262 | D59: Thomas Cortes | E59: Current | F59: 1149 | G59: 1049 | H59: 106.5 | I59: 45931 | J59: 46295 | K59: 41508 | M59: 0 | N59: 1149
A60: 2/1.5 Classic | B60: 850 | C60: H263 | D60: Seifelyazal H. Ali | E60: Current | F60: 1149 | G60: 1049 | H60: -378.5 | I60: 45931 | J60: 46295 | K60: 45931 | M60: -1170.5 | N60: 1149
A61: 2/1.5 Classic | B61: 850 | C61: H264 | D61: Dennis M. Simanovich | E61: Current | F61: 1149 | G61: 1049 | H61: 121.5 | I61: 45926 | J61: 46295 | K61: 45926 | M61: 0 | N61: 1149
A62: 2/1.5 Classic | B62: 850 | C62: I152 | D62: Daniel P. Ellison | E62: Current | F62: 1149 | G62: 1049 | H62: 121.5 | I62: 45920 | J62: 46295 | K62: 45920 | M62: -1170.5 | N62: 1149
A63: 2/1 Classic | B63: 800 | C63: E117 | D63: Carlos Sardinas | E63: Current | F63: 1049 | G63: 1050 | H63: 153.5 | I63: 45708 | J63: 46072 | K63: 45708 | M63: 0 | N63: 1049
... A87: 2/1.5 Signature | B87: 850 | C87: G245 | D87: Harry J. Black | E87: Current | F87: 1199 | G87: 1099 | H87: 121.5 | I87: 45897 | J87: 46261 | K87: 45897 | M87: 0 | N87: 1199
A88: 2/1.5 Signature | B88: 850 | C88: H163 | D88: Dajanae Brown | E88: Notice-Rented | F88: 1199 | G88: 1099 | H88: 121.5 | I88: 45899 | J88: 46265 | K88: 45899 | L88: 46044 | M88: 3110.14 | N88: 1199
A89: 2/1.5 Signature | B89: 850 | C89: H260 | D89: Janell A. Joyce | E89: Current | F89: 1199 | G89: 1099 | H89: 121.5 | I89: 45898 | J89: 46262 | K89: 45898 | M89: -1220.5 | N89: 1199
A90: 2/1.5 Signature | B90: 850 | C90: H265 | D90: Ezekiel L. Anderson | E90: Current | F90: 1199 | G90: 1099 | H90: 121.5 | I90: 45910 | J90: 46295 | K90: 45919 | M90: 0 | N90: 1199
A91: 2/1.5 Classic | B91: 850 | C91: A204 | D91: Yenisel Fernandez | E91: Current | F91: 1149 | G91: 1100 | H91: 130.5 | I91: 45748 | J91: 46102 | K91: 45383 | M91: -1230.5 | N91: 1149
A92: 2/1.5 Classic | B92: 850 | C92: G142 | D92: Danier Delagado Sanchez | E92: Current | F92: 1149 | G92: 1100 | H92: 119 | I92: 45272 | J92: 46022 | K92: 45272 | M92: 0 | N92: 1149
A93: 1/1 Classic | B93: 650 | C93: D120 | D93: Najah Mayo | E93: Current | F93: 1029 | G93: 1101 | H93: 91 | I93: 43686 | J93: 46265 | K93: 43686 | M93: 0 | N93: 1029
A94: 1/1 Classic | B94: 650 | C94: I154 | D94: Cecilio O. Orta-Martinez | E94: Current | F94: 1029 | G94: 1108 | H94: -1 | I94: 45809 | J94: 46173 | K94: 45809 | M94: 0 | N94: 1029
A95: 2/1.5 Classic | B95: 850 | C95: G241 | D95: Delia Eslavon | E95: Current | F95: 1149 | G95: 1128 | H95: 98.5 | I95: 40634 | J95: 46409 | K95: 40634 | M95: 0 | N95: 1149
A96: 2/1.5 Classic | B96: 850 | C96: A104 | D96: Yisen Montalvo | E96: Current | F96: 1149 | G96: 1130 | H96: 139.5 | I96: 45931 | J96: 46295 | K96: 45110 | M96: 0 | N96: 1149
A97: 2/1.5 Signature | B97: 850 | C97: D222 | D97: Ameer Hamza | E97: Evict | F97: 1199 | G97: 1149 | H97: 121.5 | I97: 45930 | J97: 46295 | K97: 45930 | M97: 1270.5 | N97: 1199
A98: 2/1.5 Signature | B98: 850 | C98: H165 | D98: Deborah L. Anderson | E98: Current | F98: 1199 | G98: 1149 | H98: 121.5 | I98: 45941 | J98: 46305 | K98: 45941 | M98: -10.05 | N98: 1199
A99: 2/1.5 Classic | B99: 850 | C99: A109 | D99: Adams Ghaji | E99: Current | F99: 1149 | G99: 1150 | H99: 134.5 | I99: 45164 | J99: 46259 | K99: 45164 | M99: -1284.5 | N99: 1149
A100: 2/1.5 Classic | B100: 850 | C100: D122 | D100: Moises Francisco | E100: Current | F100: 1149 | G100: 1150 | H100: 179.5 | I100: 45113 | J100: 45869 | K100: 45113 | M100: -1329.5 | N100: 1149
... A102: 2/1 Classic | B102: 800 | C102: J250 | D102: Angel Moya | E102: Current | F102: 1049 | G102: 1150 | H102: 149.5 | I102: 45288 | J102: 46383 | K102: 45288 | M102: -50.5 | N102: 1049
A103: 2/1.5 Classic | B103: 850 | C103: G243 | D103: Tilor Correll | E103: Notice-Unrented | F103: 1149 | G103: 1157 | H103: 142.5 | I103: 44938 | J103: 46033 | K103: 44938 | L103: 46033 | M103: 0 | N103: 1149
A104: 2/1.5 Classic | B104: 850 | C104: G141 | D104: Phylicia Carter | E104: Evict | F104: 1149 | G104: 1175 | H104: 134.5 | I104: 45084 | J104: 46234 | K104: 45084 | M104: 4678.5 | N104: 1149
A105: 2/1.5 Classic | B105: 850 | C105: A203 | D105: Scheila Chagas | E105: Current | F105: 1149 | G105: 1199 | H105: 151.5 | I105: 45017 | J105: 45747 | K105: 45017 | M105: 0 | N105: 1149
A106: 2/1 Classic | B106: 800 | C106: G139 | D106: Alexander Lucas Zapata | E106: Current | F106: 1049 | G106: 1199 | H106: 131.5 | I106: 45562 | J106: 46295 | K106: 45562 | M106: 0 | N106: 1049
A107: 2/1.5 Classic | B107: 850 | C107: H261 | D107: Latif Nedimovic | E107: Current | F107: 1149 | G107: 1199 | H107: 142.5 | I107: 42749 | J107: 46297 | K107: 42749 | M107: 0 | N107: 1149
A108: 3 Bed 2 Bath | B108: 1150 | C108: I153 | D108: Jaw M. Hay | E108: Current | F108: 1399 | G108: 1199 | H108: 121.5 | I108: 45971 | J108: 46335 | K108: 45971 | M108: 0 | N108: 1199
A109: 2/1.5 Classic | B109: 850 | C109: I159 | D109: Tantania Burkett | E109: Current | F109: 1149 | G109: 1199 | H109: 158.5 | I109: 44778 | J109: 46053 | K109: 44778 | M109: 0 | N109: 1149
A110: 2/1.5 Classic | B110: 850 | C110: I252 | D110: Ana Rodriguez De Garcia | E110: Current | F110: 1149 | G110: 1199 | H110: 121.5 | I110: 45536 | J110: 46263 | K110: 45534 | M110: 0 | N110: 1149
A111: 2/1.5 Signature | B111: 850 | C111: D221 | D111: Dinia Banegas | E111: Current | F111: 1199 | G111: 1200 | H111: 121.5 | I111: 45579 | J111: 46387 | K111: 45579 | M111: 0 | N111: 1199
A112: 2/1.5 Classic | B112: 850 | C112: D224 | D112: Jose Ramos | E112: Current | F112: 1149 | G112: 1200 | H112: 121.5 | I112: 45630 | J112: 46359 | K112: 45630 | M112: -1321.5 | N112: 1149
A113: 2/1.5 Signature | B113: 850 | C113: H160 | D113: Billenia Smith | E113: Current | F113: 1199 | G113: 1200 | H113: 121.5 | I113: 45638 | J113: 46002 | K113: 45638 | M113: 1321.5 | N113: 1099
A114: 2/1.5 Signature | B114: 850 | C114: H161 | D114: Yosainer Rodriguez | E114: Current | F114: 1199 | G114: 1200 | H114: 108.5 | I114: 45681 | J114: 46045 | K114: 45681 | M114: 0 | N114: 1199
A115: 2/1.5 Signature | B115: 850 | C115: H162 | D115: Andreina Carmen | E115: Current | F115: 1199 | G115: 1200 | H115: 138.5 | I115: 45677 | J115: 46406 | K115: 45673 | M115: 0 | N115: 1199
... A123: 2/1.5 Signature | B123: 850 | C123: A209 | D123: Alexi Lopez | E123: Current | F123: 1199 | G123: 1300 | H123: 123.5 | I123: 45721 | J123: 46116 | K123: 45721 | M123: 0 | N123: 1199
A124: 2/1.5 Signature | B124: 850 | C124: G140 | D124: Tarsha Daise | E124: Notice-Unrented | F124: 1199 | G124: 1300 | H124: 113.5 | I124: 45717 | J124: 46081 | K124: 45717 | L124: 46041 | M124: 0 | N124: 1199
A125: 2/1.5 Signature | B125: 850 | C125: G239 | D125: Joshua Reed-Buck | E125: Current | F125: 1199 | G125: 1300 | H125: 168.5 | I125: 45772 | J125: 46142 | K125: 45772 | M125: -1468.5 | N125: 1199
A126: 2/1.5 Signature | B126: 850 | C126: G242 | D126: Yordan Montesino | E126: Evict | F126: 1199 | G126: 1300 | H126: 123.5 | I126: 45717 | J126: 46142 | K126: 45717 | M126: 0 | N126: 1199
A127: 3 Bed 2 Bath | B127: 1150 | C127: I257 | D127: Carlanika T. Brown | E127: Current | F127: 1399 | G127: 1399 | H127: 121.5 | I127: 45930 | J127: 46295 | K127: 45930 | M127: 0 | N127: 1399
A128: 3 Bed 2 Bath | B128: 1150 | C128: I155 | D128: Abdullah Hassan | E128: Current | F128: 1399 | G128: 1425 | H128: 121.5 | I128: 45551 | J128: 46332 | K128: 45551 | M128: 107 | N128: 1399
